Workbook
Name _Hlk99922360: SubclassAspects!$BE$65

Sheet Sheet1
C1: Name: | D1: Scout
C2: Tier: | D2: 1
C3: Base: | D3: Archer
C4: Code: | D4: 2
C5: Requirements:
C6: =IF(SubclassAspects!C13>0,"Dexterity ", "") -> Dexterity | D6: =IF(SubclassAspects!C13>0,SubclassAspects!C13) -> 58 | E6: =IF(SubclassAspects!C17>0,"Charisma ", "") -> Charisma | F6: =IF(SubclassAspects!C17>0,SubclassAspects!C17, "") -> 58
C7: =IF(SubclassAspects!C14>0,"Dexterity ","") | D7: =IF(SubclassAspects!C14>0,SubclassAspects!C14, "") | E7: =IF(SubclassAspects!C18>0,"Endurance ", "") -> Endurance | F7: =IF(SubclassAspects!C18>0,SubclassAspects!C18, "") -> 53
C8: =IF(SubclassAspects!C15>0,"Strength ","") -> Strength | D8: =IF(SubclassAspects!C15>0,SubclassAspects!C15, "") -> 54 | E8: =IF(SubclassAspects!C19>0,"Luck ", "") | F8: =IF(SubclassAspects!C19>0,SubclassAspects!C19, "")
C9: =IF(SubclassAspects!C16>0,"Wisdom ","") -> Wisdom | D9: =IF(SubclassAspects!C16>0,SubclassAspects!C16, "") -> 61 | E9: =IF(SubclassAspects!C20>0,"Will ", "") -> Will | F9: =IF(SubclassAspects!C20>0,SubclassAspects!C20, "") -> 54
A11: Overview
A13: Quote: | B13: “With proper preparations, the fighting is merely a formality.”
A14: The Scout is an archer-based class that can act early and effectively. He uses preliminary actions to take control of the battlefield, attacks enemies at full health, and quickens himself readily. He is hard to destroy before his turn.
A15: World Notes: Scouts are an essential part of enemy army, as only with knowledge of the enemy can success be found. The scouts prepare the battlefield to best support their army’s success.
A16: Appearance: The scout is lightly armored because he is constantly on the move.
A17: Defining Mechanic: The Scout can implement scouted abilities. These abilities, which come in all three strengths, can only be used as the first action of battle, after which they turn into a related, but lesser, ability.
A19: Equipment
A20: Default Weapon: | C20: Short Bow
A21: Default Armor:
A41: Major Abilities
A42: Adroit Momentum – Ranged attack with pinpoint and momentum enhancing accuracy (Scout)
A43: Aimed Momentum – Ranged attack that generates extra aim based on momentum (Scout)
A44: Coordinated Shot – Ranged attack with quick preparation that grants increased accuracy and damage to next attack versus target (Scout)
A45: Delaying Jolt – Ranged attack with delay against stunned target (Scout)
A46: Flanking Shot – Ranged attack that causes flanked (Scout)
A47: Lay of the Land – Ranged attack that enhances dodge of team based on aim (Scout)
A48: Quickening Aim – Ranged attack against single target that consumes aim to quicken self (Scout)
A49: Rapid Vow – Prepared ranged attack that determines target on preparation. Quickens scout on preparation and on use (Scout)
A50: Scouted Arrow Burst – Ranged attack against all enemies. Deals less damage and requires aim if not first turn (Scout)
A51: Scouted Chink – Full penetration ranged attack if first attack of battle. Can proc full penetration with ranged attack after (Scout)
... A71: Share Momentum – Quicken all allies based on momentum (Scout)

Sheet SubclassAspects
D1: Hunter | P1: Wrestler | AO1: Siege Engineer | AV1: Rager | BR1: Black Knight | CD1: Sword Magus | EQ1: Winter Witch | ES1: Witch Doctor
A2: Name | B2: =COUNTA(C2:FF2)/1.6 -> 100 | C2: Scout | D2: Huntsman | E2: Crossbowman | F2: Marksman | G2: Falconer | H2: Bounty Hunter | I2: Stalker | J2: Poacher | K2: Sharpshooter | L2: Toxophilite | M2: Initiate | N2: Pugilist | O2: Skirmisher | P2: Vajra | Q2: Stonefist | R2: Infiltrator | S2: Viper Fang | T2: Ascetic | U2: Thunderfist | V2: Drunken Master | W2: Bandit | X2: Cutthroat | Y2: Burglar | Z2: Thief | AA2: Acrobat | AB2: Assassin | AC2: Brigand | AD2: Smuggler | AE2: Skulk | AF2: Ninja | AG2: Scavenger | AH2: Alchemist | AI2: Artificer | AJ2: Tinker | AK2: Engineer | AL2: Bomber | AM2: Gunslinger | AN2: Savant | AO2: Machinist | AP2: Reliquarian | AQ2: Brute | AR2: Raider | AS2: Berserker | AT2: Marauder | AU2: Viking | AV2: Vandal | AW2: Fury | AX2: Cannibal | AY2: Destroyer | AZ2: Beastlord | BA2: Gladiator | BB2: Duelist | BC2: Phalanx | BD2: Dervish | BE2: Fencer | BF2: Lancer | BG2: Samurai | BH2: Dreadnaught | BI2: Swashbuckler | BJ2: Warlord | BK2: Bodyguard | BL2: Champion | BM2: Hospitaler | BN2: Cavalier | BO2: Sentinel | BP2: Dragoon | BQ2: Paragon | BR2: Blackguard | BS2: Crusader | BT2: Templar | BU2: Blitzknecht | BV2: Feuerknecht | BW2: Trinknecht | BX2: Drecknecht | BY2: Mercenary | BZ2: Transmuter | CA2: Force Weaver | CB2: Myrmidon | CC2: Nightblade | CD2: Sword Saint | CE2: Minstrel | CF2: Jester | CG2: Dirge Singer | CH2: Balladeer | CI2: Drummer | CJ2: Spy | CK2: Mountebank | CL2: Diva | CM2: Muse | CN2: Lantern Bearer | CO2: Conjurer | CP2: Occultist | CQ2: Shaman | CR2: Medium | CS2: Animist | CT2: Spiritualist | CU2: Astrologer | CV2: Vizier | CW2: Alienist | CX2: Pact Master | CY2: Acolyte | CZ2: Healer | DA2: Disciple | DB2: Priest | DC2: Combat Medic | DD2: Exorcist | DE2: Preacher | DF2: Zealot | DG2: Plague Doctor | DH2: Oracle | DI2: Buccaneer | DJ2: Executioner | DK2: Gravedigger | DL2: Hangman | DM2: Harbinger | DN2: Sin Eater | DO2: Sandman | DP2: Whisperer | DQ2: Mercy Bringer | DR2: Gaslighter | DS2: Telepath | DT2: Kinetic | DU2: Amnesiac | DV2: Hypnotist | DW2: Diviner | DX2: Haunted | DY2: Mastermind | DZ2: Mindbleeder | EA2: Chronomancer | EB2: Puppet Master | EC2: Abjurer | ED2: Symbolist | EE2: Cabalist | EF2: Hermit | EG2: Disenchanter | EH2: Scrivener | EI2: Sage | EJ2: Glyphic | EK2: Cryptic | EL2: Sorcerer | EM2: Cultist | EN2: Warlock | EO2: Effigist | EP2: Dustbringer | EQ2: Crone | ER2: Hedgemage | ES2: Mambo | ET2: Bokor | EU2: Hag | EV2: Malefax | EW2: Elementalist | EX2: Necromancer | EY2: Hydromancer | EZ2: Geomancer | FA2: Aeromancer | FB2: Pyromancer | FC2: Arcanist | FD2: Solomancer | FE2: Incanter | FF2: Thaumaturge
A3: Code | B3: =COUNTA(C3:FF3)/1.6 -> 100 | C3: 2 | D3: 3 | E3: 4 | F3: 5 | G3: 6 | H3: 7 | I3: 8 | J3: 9 | K3: 10 | L3: 11 | M3: 13 | N3: 14 | O3: 15 | P3: 16 | Q3: 17 | R3: 18 | S3: 19 | T3: 20 | U3: 21 | V3: 22 | W3: 24 | X3: 25 | Y3: 26 | Z3: 27 | AA3: 28 | AB3: 29 | AC3: 30 | AD3: 31 | AE3: 32 | AF3: 33 | AG3: 35 | AH3: 36 | AI3: 37 | AJ3: 38 | AK3: 39 | AL3: 40 | AM3: 41 | AN3: 42 | AO3: 43 | AP3: 44 | AQ3: 46 | AR3: 47 | AS3: 48 | AT3: 49 | AU3: 50 | AV3: 51 | AW3: 52 | AX3: 53 | AY3: 54 | AZ3: 55 | BA3: 57 | BB3: 58 | BC3: 59 | BD3: 60 | BE3: 61 | BF3: 62 | BG3: 63 | BH3: 64 | BI3: 65 | BJ3: 66 | BK3: 68 | BL3: 69 | BM3: 70 | BN3: 71 | BO3: 72 | BP3: 73 | BQ3: 74 | BR3: 75 | BS3: 76 | BT3: 77 | BU3: 79 | BV3: 80 | BW3: 81 | BX3: 82 | BY3: 83 | BZ3: 84 | CA3: 85 | CB3: 86 | CC3: 87 | CD3: 88 | CE3: 90 | CF3: 91 | CG3: 92 | CH3: 93 | CI3: 94 | CJ3: 95 | CK3: 96 | CL3: 97 | CM3: 98 | CN3: 99 | CO3: 101 | CP3: 102 | CQ3: 103 | CR3: 104 | CS3: 105 | CT3: 106 | CU3: 107 | CV3: 108 | CW3: 109 | CX3: 110 | CY3: 112 | CZ3: 113 | DA3: 114 | DB3: 115 | DC3: 116 | DD3: 117 | DE3: 118 | DF3: 119 | DG3: 120 | DH3: 121 | DI3: 123 | DJ3: 124 | DK3: 125 | DL3: 126 | DM3: 127 | DN3: 128 | DO3: 129 | DP3: 130 | DQ3: 131 | DR3: 132 | DS3: 134 | DT3: 135 | DU3: 136 | DV3: 137 | DW3: 138 | DX3: 139 | DY3: 140 | DZ3: 141 | EA3: 142 | EB3: 143 | EC3: 145 | ED3: 146 | EE3: 147 | EF3: 148 | EG3: 149 | EH3: 150 | EI3: 151 | EJ3: 152 | EK3: 153 | EL3: 154 | EM3: 156 | EN3: 157 | EO3: 158 | EP3: 159 | EQ3: 160 | ER3: 161 | ES3: 162 | ET3: 163 | EU3: 164 | EV3: 165 | EW3: 167 | EX3: 168 | EY3: 169 | EZ3: 170 | FA3: 171 | FB3: 172 | FC3: 173 | FD3: 174 | FE3: 175 | FF3: 176
A4: Tier | B4: =COUNTA(C4:FF4)/1.6 -> 100 | C4: 1 | D4: 2 | E4: 6 | F4: 7 | G4: 9 | H4: 13 | I4: 15 | J4: 19 | K4: 21 | L4: 25 | M4: 1 | N4: 2 | O4: 6 | P4: 7 | Q4: 9 | R4: 13 | S4: 15 | T4: 19 | U4: 21 | V4: 25 | W4: 1 | X4: 2 | Y4: 6 | Z4: 7 | AA4: 9 | AB4: 13 | AC4: 15 | AD4: 19 | AE4: 21 | AF4: 25 | AG4: 1 | AH4: 2 | AI4: 6 | AJ4: 7 | AK4: 9 | AL4: 13 | AM4: 15 | AN4: 19 | AO4: 21 | AP4: 25 | AQ4: 1 | AR4: 2 | AS4: 6 | AT4: 7 | AU4: 9 | AV4: 13 | AW4: 15 | AX4: 19 | AY4: 21 | AZ4: 25 | BA4: 1 | BB4: 2 | BC4: 6 | BD4: 7 | BE4: 9 | BF4: 13 | BG4: 15 | BH4: 19 | BI4: 21 | BJ4: 25 | BK4: 1 | BL4: 2 | BM4: 6 | BN4: 7 | BO4: 9 | BP4: 13 | BQ4: 15 | BR4: 19 | BS4: 21 | BT4: 25 | BU4: 1 | BV4: 2 | BW4: 6 | BX4: 7 | BY4: 9 | BZ4: 13 | CA4: 15 | CB4: 19 | CC4: 21 | CD4: 25 | CE4: 1 | CF4: 2 | CG4: 6 | CH4: 7 | CI4: 9 | CJ4: 13 | CK4: 15 | CL4: 19 | CM4: 21 | CN4: 25 | CO4: 1 | CP4: 2 | CQ4: 6 | CR4: 7 | CS4: 9 | CT4: 13 | CU4: 15 | CV4: 19 | CW4: 21 | CX4: 25 | CY4: 1 | CZ4: 2 | DA4: 6 | DB4: 7 | DC4: 9 | DD4: 13 | DE4: 15 | DF4: 19 | DG4: 21 | DH4: 25 | DI4: 1 | DJ4: 2 | DK4: 6 | DL4: 7 | DM4: 9 | DN4: 13 | DO4: 15 | DP4: 19 | DQ4: 21 | DR4: 25 | DS4: 1 | DT4: 2 | DU4: 6 | DV4: 7 | DW4: 9 | DX4: 13 | DY4: 15 | DZ4: 19 | EA4: 21 | EB4: 25 | EC4: 1 | ED4: 2 | EE4: 6 | EF4: 7 | EG4: 9 | EH4: 13 | EI4: 15 | EJ4: 19 | EK4: 21 | EL4: 25 | EM4: 1 | EN4: 2 | EO4: 6 | EP4: 7 | EQ4: 9 | ER4: 13 | ES4: 15 | ET4: 19 | EU4: 21 | EV4: 25 | EW4: 1 | EX4: 2 | EY4: 6 | EZ4: 7 | FA4: 9 | FB4: 13 | FC4: 15 | FD4: 19 | FE4: 21 | FF4: 25
A5: Base Class | B5: =COUNTA(C5:FF5)/1.6 -> 100 | C5: Archer | D5: Archer | E5: Archer | F5: Archer | G5: Archer | H5: Archer | I5: Archer | J5: Archer | K5: Archer | L5: Archer | M5: Monk | N5: Monk | O5: Monk | P5: Monk | Q5: Monk | R5: Monk | S5: Monk | T5: Monk | U5: Monk | V5: Monk | W5: Rogue | X5: Rogue | Y5: Rogue | Z5: Rogue | AA5: Rogue | AB5: Rogue | AC5: Rogue | AD5: Rogue | AE5: Rogue | AF5: Rogue | AG5: Teknixian | AH5: Teknixian | AI5: Teknixian | AJ5: Teknixian | AK5: Teknixian | AL5: Teknixian | AM5: Teknixian | AN5: Teknixian | AO5: Teknixian | AP5: Teknixian | AQ5: Barbarian | AR5: Barbarian | AS5: Barbarian | AT5: Barbarian | AU5: Barbarian | AV5: Barbarian | AW5: Barbarian | AX5: Barbarian | AY5: Barbarian | AZ5: Barbarian | BA5: Fighter | BB5: Fighter | BC5: Fighter | BD5: Fighter | BE5: Fighter | BF5: Fighter | BG5: Fighter | BH5: Fighter | BI5: Fighter | BJ5: Fighter | BK5: Knight | BL5: Knight | BM5: Knight | BN5: Knight | BO5: Knight | BP5: Knight | BQ5: Knight | BR5: Knight | BS5: Knight | BT5: Knight | BU5: Spellsword | BV5: Spellsword | BW5: Spellsword | BX5: Spellsword | BY5: Spellsword | BZ5: Spellsword | CA5: Spellsword | CB5: Spellsword | CC5: Spellsword | CD5: Spellsword | CE5: Bard | CF5: Bard | CG5: Bard | CH5: Bard | CI5: Bard | CJ5: Bard | CK5: Bard | CL5: Bard | CM5: Bard | CN5: Bard | CO5: Binder | CP5: Binder | CQ5: Binder | CR5: Binder | CS5: Binder | CT5: Binder | CU5: Binder | CV5: Binder | CW5: Binder | CX5: Binder | CY5: Cleric | CZ5: Cleric | DA5: Cleric | DB5: Cleric | DC5: Cleric | DD5: Cleric | DE5: Cleric | DF5: Cleric | DG5: Cleric | DH5: Cleric | DI5: Reaper | DJ5: Reaper | DK5: Reaper | DL5: Reaper | DM5: Reaper | DN5: Reaper | DO5: Reaper | DP5: Reaper | DQ5: Reaper | DR5: Reaper | DS5: Psychic | DT5: Psychic | DU5: Psychic | DV5: Psychic | DW5: Psychic | DX5: Psychic | DY5: Psychic | DZ5: Psychic | EA5: Psychic | EB5: Psychic | EC5: Runemage | ED5: Runemage | EE5: Runemage | EF5: Runemage | EG5: Runemage | EH5: Runemage | EI5: Runemage | EJ5: Runemage | EK5: Runemage | EL5: Runemage | EM5: Witch | EN5: Witch | EO5: Witch | EP5: Witch | EQ5: Witch | ER5: Witch | ES5: Witch | ET5: Witch | EU5: Witch | EV5: Witch | EW5: Wizard | EX5: Wizard | EY5: Wizard | EZ5: Wizard | FA5: Wizard | FB5: Wizard | FC5: Wizard | FD5: Wizard | FE5: Wizard | FF5: Wizard
A6: Gender | B6: =COUNTA(C6:FF6)/1.6 -> 100 | C6: Male | D6: Male | E6: Male | F6: Male | G6: Male | H6: Male | I6: Male | J6: Male | K6: Male | L6: Male | M6: Male | N6: Male | O6: Male | P6: Male | Q6: Male | R6: Male | S6: Male | T6: Male | U6: Male | V6: Male | W6: Male | X6: Male | Y6: Male | Z6: Male | AA6: Male | AB6: Male | AC6: Male | AD6: Male | AE6: Male | AF6: Male | AG6: Female | AH6: Female | AI6: Female | AJ6: Female | AK6: Female | AL6: Female | AM6: Female | AN6: Female | AO6: Female | AP6: Female | AQ6: Female | AR6: Female | AS6: Female | AT6: Female | AU6: Female | AV6: Female | AW6: Female | AX6: Female | AY6: Female | AZ6: Female | BA6: Female | BB6: Female | BC6: Female | BD6: Female | BE6: Female | BF6: Female | BG6: Female | BH6: Female | BI6: Female | BJ6: Female | BK6: Male | BL6: Male | BM6: Male | BN6: Male | BO6: Male | BP6: Male | BQ6: Male | BR6: Male | BS6: Male | BT6: Male | BU6: Female | BV6: Female | BW6: Female | BX6: Female | BY6: Female | BZ6: Female | CA6: Female | CB6: Female | CC6: Female | CD6: Female | CE6: Male | CF6: Male | CG6: Male | CH6: Male | CI6: Male | CJ6: Male | CK6: Male | CL6: Male | CM6: Male | CN6: Male | CO6: Female | CP6: Female | CQ6: Female | CR6: Female | CS6: Female | CT6: Female | CU6: Female | CV6: Female | CW6: Female | CX6: Female | CY6: Male | CZ6: Male | DA6: Male | DB6: Male | DC6: Male | DD6: Male | DE6: Male | DF6: Male | DG6: Male | DH6: Male | DI6: Male | DJ6: Male | DK6: Male | DL6: Male | DM6: Male | DN6: Male | DO6: Male | DP6: Male | DQ6: Male | DR6: Male | DS6: Female | DT6: Female | DU6: Female | DV6: Female | DW6: Female | DX6: Female | DY6: Female | DZ6: Female | EA6: Female | EB6: Female | EC6: Male | ED6: Male | EE6: Male | EF6: Male | EG6: Male | EH6: Male | EI6: Male | EJ6: Male | EK6: Male | EL6: Male | EM6: Female | EN6: Female | EO6: Female | EP6: Female | EQ6: Female | ER6: Female | ES6: Female | ET6: Female | EU6: Female | EV6: Female | EW6: Female | EX6: Female | EY6: Female | EZ6: Female | FA6: Female | FB6: Female | FC6: Female | FD6: Female | FE6: Female | FF6: Female
A7: Associated Demon | B7: =COUNTA(C7:FF7)/1.6 -> 36.875 | C7: Ipos | D7: Leraje | E7: Dantalion | F7: Allocer | G7: Pazazu | H7: Baphomet | I7: Demogorgon | J7: Set | K7: Glasya | L7: Andras | M7: Glasya | N7: Gusion | O7: Pazazu | P7: Andras | Q7: Scarmiglione | R7: Sabnock | S7: Orobas | T7: Levistus | U7: Paimon | V7: Gaap | W7: Ipos | X7: Geryon | Y7: Mammon | Z7: Sabnock | AA7: Bifrons | AB7: Glasya | AC7: Gusion | AD7: Orobas | AE7: Andras | AF7: x | AG7: Belial | AH7: Haagenti | AI7: x | AJ7: Mammon | AK7: Orobas | AL7: Tiamat | AM7: Leraje | AN7: Orcus | AO7: Rubicante | AP7: Eligos | AQ7: x | AR7: Dagon | AS7: Gaap | AT7: Demogorgon | AU7: Focalor | AV7: Murmur | AW7: Allocer | AX7: Andras | AY7: Demogorgon | AZ7: Gusion | BA7: Ipos | BB7: Sabnock | BC7: Levistus | BD7: Agares | BE7: Succor-Benoth | BF7: Paimon | BG7: Marchosias | BH7: Dispater | BI7: Focalor
A8: Quote | B8: =COUNTA(C8:FF8)/1.6 -> 9.375 | D8: “A person can turn from predator to prey in just an instant.” | E8: “It’s a simple enough device to use even you should be able to handle it.” | H8: “There’s a bounty for your head. Not sure about the rest of your body.” | M8: “This is what all my training has led to.” | Q8: “Be like the stone, unbreakable, unyielding.” | R8: “Get in. Get the job done. Get out. Don’t get spotted.” | U8: “I strike like lightning, and thunder follows.” | V8: “One more drink and I’ll get to it.” | AQ8: “It’s simple. I am the brute squad.” | AX8: “You look absolutely delicious.” | AY8: “Sometimes to save what we love, we must destroy everything.” | AZ8: “I am the lord of all beasts who walk the earth. They bow before me.” | BA8: “I’ve always wanted to compete in the big show.” | BG8: “Is there no honor in how you fight?” | BH8: “There’s no stopping me now.”
A9: Description | B9: =COUNTA(C9:FF9)/1.6 -> 93.75 | C9: An early-action specialist who seizes the opening of battle with scouted abilities that can only be used as the first action of a wave, then transform into a lesser related ability afterward. He builds aim quickly, attacks enemies at full health for bonus damage, and is difficult to eliminate before he gets to act. | D9: A distance fighter who uses momentum to enhance his arrows and can penetrate armor more effectively the further away his target is. He tracks a specific enemy type, gaining bonuses against others of the same kind as his primary aim target and hitting harder the longer he sustains focus. | E9: A heavy crossbow specialist who attacks more slowly than other archers but deals more damage per shot with greater penetration. He is more defensive than most archer subclasses, reacting to enemy attacks against him rather than purely pressing offense, and can fortify and reload quickly between shots. | F9: An accuracy and penetration specialist who places marks on enemies that grant his allies benefits when they attack the same targets. He is the team's force multiplier at range, making his aim target more dangerous for everyone and sharing his exceptional accuracy with those who follow his lead. | G9: A companion-focused archer whose pet falcon harries targets and enables abilities that either work better in the falcon's presence or require it outright. He uses the falcon to set up aim, distract enemies, and coordinate strikes — making his companion an active offensive asset rather than a passive attendant. | H9: A capture-specialist who places bounty afflictions on enemies as minor actions during combat, with those bounties triggering beneficial effects when the marked enemy dies. He can stun and incapacitate targets to take them alive, gaining increasing payoffs the more bounties he has active when enemies fall. | I9: A shadow-fighter who generates aim from hidden status and converts high accuracy into higher damage, with a defining ability that expends all accumulated aim for a devastating single attack — but then prevents him from targeting that specific enemy for a period scaled to the aim spent. | J9: A kill-opportunist who triggers immediate prepared attacks the moment an enemy becomes endangered, without those poach abilities being interruptible by damage. He gains culling abilities, preferences for specific target types, and benefits from kills — a specialist at finishing weakened prey faster than anyone else can reach them. | K9: A trick-shot specialist whose accuracy-dependent abilities pierce through targets to hit columns behind them and have reduced hit chance but significant effects when they connect. His trick shot success rate scales with current aim relative to maximum aim, rewarding sustained focus on a single target before committing to the high-risk high-reward shots. | L9: A distance-and-duration specialist who builds power over the course of a long battle through eternal buff abilities that grow without limit but become progressively more expensive to enhance. Only one can be active at a time, demanding that the player commit to a single compounding effect and protect the Toxophilite long enough for it to pay off. | M9: A patient striker who builds power by holding his form and releases it explosively on transition. His unleash mechanic rewards stillness — the longer he stays in a single form, the more devastating the eventual change. He has no form preference, making him the most flexible of the monk subclasses and a strong foundation for learning the chakra system. | N9: A relentless single-target brawler who punishes the same enemy turn after turn through his impact mechanic. Any enemy he struck last turn becomes the target of a suite of specialized follow-up attacks covering damage, delay, disruption, and control. Lower chakra focused and strength-enhanced, he hits harder the longer he stays locked onto one target. | O9: A fast, opportunistic fighter who mirrors his enemies' own strengths against them through the matching mechanic. He can temporarily adopt a target's critical stats, damage, accuracy, defense, or dodge — turning powerful enemies into their own worst nightmare. Leopard form focused and haste-driven, he excels at demolishing stunned foes and stacking bleeds through repeated Leopard Claw cycles. | P9: An immovable reactive combatant who weaponizes his chakra configuration to punish every enemy attack. Snake's Response reflects conditions back at attackers based on which chakras are open, with the lower chakras delivering the most devastating punishments — prone, delay, and disarm simultaneously at full configuration. He fights best when pristine, baiting attacks while armed with Reversal, Absorbed Counter, and a full suite of prepared reactions. | Q9: A fortified earth specialist who turns glancing blows from a weakness into a weapon. His attacks deliberately seek glancing hits to trigger stuns, bleeds, delays, and fragility — and his Pressure Crack capstone extends this to critical hits as well. Tiger form focused and endurance-heavy, he is nearly immovable under sustained assault and punishes enemies for every attempt to pierce his defenses. | R9: A burst-damage specialist who cycles through hidden states to deliver devastating arrival attacks. Each time he loses hidden — whether by choice or enemy action — he unleashes a different arrival ability covering area damage, flanking, stunning, or penetrating strikes. Mantis focused and initiative-driven, his Exposed Momentum capstone ensures every exposure accelerates his next turn. | S9: A poison-crafting snake form specialist who generates unique toxins from his own body and bleeds. He creates poisons based on his current form through Venom Chakra, conserves and refreshes them through careful resource management, and delivers them through venomous, insidious, and backbiting strikes. Earth and dark elemental focused, he excels at sustained damage over time and attrition warfare. | T9: A disciplined dragon form purist who draws power from maintaining a state of perfect purity. His most powerful abilities — Fist of Purity, Double Purity, Whirlwind Purity — require being completely unafflicted, while his Condition Fortress capstone makes him progressively harder to afflict as conditions accumulate. He manages corruption, stuns enemies with dragon-powered strikes, and uses focus as both a resource and a defensive tool. | U9: A chain-combat specialist who builds devastating sequences of air, stun, and shatter effects through careful ability ordering. Nearly every move and minor ability has a trigger condition — following a counter, a critical, a shatter, or an air attack — creating dense combo potential that rewards mechanical knowledge. Crane focused and counter-driven, his Thunder Strikes capstone ensures every stunned enemy takes bonus air damage on each hit. | V9: A chaotic form-shifting brawler who embraces randomness and prone states as sources of power rather than liability. He shifts forms rapidly to build Fluid Punch damage, reach Ultimate Punch thresholds, and trigger Chakra Ascension — while deliberately falling prone to counter from the ground and punish enemies with Misplaced Retribution. His unpredictability is his greatest defense, with low accuracy offset by high dodge and a tendency to accidentally hit exactly the wrong person at exactly the right time. | W9: A quick ranged harasser who opens battle at a distance before pivoting to a more dangerous close-quarters fighter when his allies fall. He carries desperation abilities that only activate when he stands alone, rewarding survival over coordinated play. | X9: A dualwield melee brawler who stacks bleed on enemies through relentless two-weapon exchanges and can grant himself intangibility to press the offense without interruption. His advantage generation rewards staying in the fight and bleeding targets dry. | Y9: An ambush specialist who hits hardest against undamaged enemies and strips buffs from those who have fought back. He can artificially recreate full-health windows late in battle by corrupting enemy maximum health, keeping his ambush toolkit relevant throughout. | Z9: A self-sufficient dualwield fighter who steals accuracy, speed, and senses from enemies to empower himself. He can briefly share his incoming healing and mana gain with allies, giving a team-oriented edge to an otherwise personal playstyle. | AA9: A dodge-focused rebuild Rogue who invites attacks, turns misses into advantage, and uses reliable abilities that refund their costs on failure. He thrives in the open and under illumination, unlike most Rogues who prefer the shadows. | AB9: A single-target executioner who signs contracts against chosen enemies, gaining combat bonuses while pursuing them and earning powerful fulfillment rewards when he personally lands the killing blow. Five contract types let the player tailor each hunt to the situation. | AC9: A ranged gambler who wagers advantage and mana on battlefield conditions, collecting larger payoffs when those conditions are met. A good run leaves him flush; a bad one leaves him empty, making risk tolerance the central skill of his playstyle. | AD9: A team-oriented Rogue whose power scales with how many allies are hidden alongside him. He can blanket the party in shadow, share his poisons across the team, and coordinate hidden allies into a unified striking force. | AE9: A defensively self-reliant Rogue who applies aversion to make enemies ignore him, then punishes them for it. He complements aversion with scorn to layer targeting protection, generating advantage steadily from the safety of being overlooked. | AF9: A hidden-mastery specialist who chains haste, advantage, and free bonus attacks by maintaining concealment across multiple actions. He rewards players who have mastered the hidden economy, with insidious attacks and precise sequencing separating competent play from exceptional play. | AG9: A chaotic support-attacker who thrives on unpredictability. Her scavenged abilities reveal their element on preparation rather than use, making her toolkit flexible but harder to plan around. She generates ammo from kills and builds belts from whatever she has on hand — a scrappy, resource-efficient subclass that rewards improvisation. | AH9: A prepared-resource specialist who enters battle with concoctions already brewed and ready to use without cost or preparation. She leans into healing, poison, and resurrection, and her premade system lets her open waves with full-power abilities immediately. Her capstone Premade Reserves deepens this advantage, making her the Teknixian most oriented toward sustained party management. | AI9: A trap-setter and accumulator who builds up power before releasing it. Her accumulation abilities charge on first use and discharge on second, rewarding patience with amplified outputs. She also controls the detonation chain — recovering, redirecting, and shielding through it — and provides elemental shields to allies via Teknos Shielding. | AJ9: A modification-based companion commander who toggles different behavioral modes to reshape her companion and her own attacks. Her four modular abilities — Modular Bomb, Modular Ray, Modular Trap, and Modular Beam — each change behavior based on which modifications are active. Flame Spewer and Lightning Tosser are ammo-sensitive companions that change element and effect based on what's loaded at summoning. | AK9: An ally-empowerment specialist who assigns persistent assistant enchantments to party members. Each assistant type triggers a different proc when the assigned ally attacks — shields, heals, traps, bonus attacks, or quickening — and Activate Assistant can fire all procs simultaneously. She also fields the Shield Guardian, a fixed-behavior healing companion with no ammo interaction, and Minefield Assistant turns any attacker into a trap-seeding machine. | AL9: A high-risk area damage dealer whose bomb abilities hit allies and enemies identically with no discount. She layers countdowns on enemies and manages the self-threat they create using Accept Explosion, Accept Mass Explosion, Gift Bomb, and Transfer Countdown. Explosion Imminent and Kinetic Protection let her mitigate her own friendly fire. The higher the aim output, the harder the landing. | AM9: A pure ranged damage dealer built around called shots and burst ammo expenditure. Called shots are prepared as a minor action, name a target, and add powerful debuff effects — disarm, stun, heartstrike, slow, or delay — to the first attack used against that target on the following turn. Full Clip and Oblivion Shot are her all-in damage options. High Noon and Showdown both guarantee a counter-attack against her, rewarding Take Cover setups. | AN9: A slow-burn debuff-accumulator whose six concoctions apply ongoing effects while building power each clock tick, then discharge a scaled effect when the chain fires or time runs out. More ammo at placement extends the window and increases accumulated power at detonation. A Faraday sub-theme lets her wear lightning rod deliberately and redirect incoming storm damage offensively through Faraday Connection's pain link. | AO9: A companion-amplifier who fields extremely slow, powerful siege engine companions — Ballista, Battering Ram, and Catapult — and spends her own actions making them fire more frequently. Every move and minor ability in her kit serves the companion: Operate Siege Engine quickens it directly, Teamwork Operation converts party delay into companion clock advancement, and Siege Command upgrades whatever the companion would do next. Her own attacks like Amplifying Cannonshot and Earth Cannon give her meaningful damage when she steps away from the engine. | AP9: A relic-stacking power escalator who activates multi-ability relics that grow stronger with each ammo devotion. Each devoted ammo type is locked until the relic ends — which it cannot be cancelled until max devotion — creating deep commitment costs in exchange for battlefield-wide buffs, persistent damage, companion power, or trap generation. Relic Blast and Relic Bolt scale with total ammo devoted across all active relics, making a fully stacked Reliquarian increasingly devastating the longer a wave goes on. | AQ9: The patient tank of the Barbarian family. A slower, higher-endurance variant who defers self-damage costs to the next turn through Consequences, generating Anguish immediately while controlling when the pain lands — or redirecting it to enemies entirely with Share Consequence. | AR9: A shield-and-weapon fighter who builds active defenses only to spend them all at once. Reckless abilities consume all block, dodge, and counter values for amplified attacks, rewarding players who time the exposed window around a supporting tank or use it as a finisher when consequences can't resolve. | AS9: The chaos amplifier of the family, built around Exertion abilities that generate Anguish from repeated misses and spread destruction through Contagious Temper. She leans fully into the Berserk condition, turning random targeting from a liability into an engine, with the Panic pair offering a rare moment of choice between embracing or escaping the disorder. | AT9: A dual-wield closer who grows faster and hits harder the more enemies die. Rampage scales with kills — personal kills more than team kills — making bloodlust and counter abilities the tools that keep her offense rolling between turns and feeding the escalation she depends on. | AU9: A deliberate shield fighter who charges prepared abilities through sustained blocking. Each block adds power to any held ability, and multiple prepared abilities charge independently, rewarding patient setup and precise release timing over the Raider's impulsive spending. | AV9: Pure escalating output. She accumulates damage dealt toward a threshold that briefly unlocks Brink abilities — powerful options that vanish if not taken — and can sustain Endless Wrath longer than any other subclass before the drain finally overtakes her. | AW9: Precise and fast, with a discipline that belies her name. Purity abilities amplify with each use but cancel on specific failure conditions, demanding focused play to maintain multiple stacks simultaneously. She grows faster as she takes damage and reaches peak power when Wrath and Berserk combine. | AX9: A self-sustaining predator who stays hurt to stay fed. Her healing threshold mechanic unlocks powerful abilities as applicable healing accumulates, rewarding healers who time large heals over constant top-offs, while life drain and kill-reaction heals give her independence when the support is occupied elsewhere. | AY9: The armor-stripping heavyweight, built to cross the massive damage threshold and trigger cascading effects that tear down enemy defenses for the whole team. Destruction Wrath amplifies weakness power and defense reduction, but ends in forsaken and strips all enchantments — making dedicated buffers a liability rather than an asset. | AZ9: The apex predator and most complex of the Barbarian subclasses. She cycles between four exclusive beast forms, scales overkill into team-wide debuffs, and generates Anguish from damage dealt to any ally — turning chaotic encounters into fuel. Final Wrath guarantees her death when it ends, making every use of it the last decision she makes. | BA9: A flashy, risk-taking fighter who uses gambit abilities that either succeed spectacularly or backfire against her. Critical Stance generates expertise on critical hits, and her gambits deal high damage or critical effects at a cost — such as becoming prone on a miss or inviting counter attacks — rewarding aggressive play with chain weapons. | BB9: A one-handed sword specialist who excels at counter attacks and is almost impossible to disarm or knock down. Counter Stance generates expertise whenever she counters, and her kit is built around parries and ripostes — parrying an attack, then immediately punishing the attacker with a follow-up strike. | BC9: A heavy shield bearer who fights best alongside ready allies. Shield Stance generates expertise on every block, and her toolkit includes guaranteed blocks, fortification at the cost of tired, and Phalanx Power, which enhances the damage of all ready allies based on how many are still standing. | BD9: A dual-wielding speed specialist whose defining abilities trigger on the second strike of a sequence, becoming more powerful the sooner that second hit follows the first. Speed Stance generates expertise from quicken effects, and she builds momentum and haste through attacks to fuel an escalating flurry of blows. | BE9: An extraordinarily accurate fighter who specializes in pinpoint attacks that can activate additional conditions at high enough values. Pinpoint Stance generates expertise from hit rolls beyond what is needed to connect, and her kit rewards fighting alone — with Alone Damage and Alone Defense passives that keep her effective as the last fighter standing. | BF9: A polearm and spear specialist whose Lancing Blow attacks have a chance to pierce through the primary target and hit the enemy behind them. Retaliation Stance generates expertise through retaliating, and she brings mounted abilities and column-targeting attacks that reward controlling space and threatening multiple rows at once. | BG9: An initiative-focused dual-wielder who seizes the opening of every battle with maximum aggression. Dodge Stance generates expertise on dodges, and Suicide Stance trades increased offense and counter-chance for the willingness to be struck, generating expertise from taking hits and rewarding an all-or-nothing fighting style. | BH9: An immovable defensive combatant who weaponizes his durability offensively. Unmovable Stance generates expertise from movement effects targeting him, and Advanced Unmovable Stance reflects delays back at enemies, turning every attempt to slow him into a punishment for the attacker. | BI9: A sword-fighting parry expert whose feint abilities compel enemies to attack her, then punish them when she parries the incoming strike. Parry Stance generates expertise from each successful parry, and she chains feints into ripostes, bleeds, penetrating attacks, or mass taunts depending on which feint variant she has prepared. | BJ9: A commanding leader who translates her own expertise directly into team-wide benefits. Warlord's Stance generates expertise whenever any ally acts, and her Leadership abilities require a minimum expertise level and become more powerful at higher thresholds — quickening all allies, enhancing their damage, or even making their next attack unerring after she misses. | BK9: The most protective Knight subclass, built around absorbing punishment meant for others. Full Guard shifts all damage to him by chance, and a deep suite of Intercession abilities lets him step in front of specific threats — criticals, deathblows, afflictions, storm attacks — before they reach his guarded ally. | BL9: An overkill specialist who grows stronger the harder he hits. Punishment Guard turns damage against his guarded ally into fuel for his own attacks, and every kill feeds Ire abilities that reward excess — healing, shielding, disrupting, and damaging all enemies based on how far past death the target went. | BM9: A healer-warrior whose offensive power is tied to his guarded ally's suffering. The Righteous mechanic scales his damage and afflictions based on the health gap between his guarded and their target, making him most dangerous when protecting a wounded ally — and most selfless when the cost of that protection is highest. | BN9: A mounted aggressor who rewards speed and positioning. Delay Guard quickens him whenever his guarded is delayed, and his kit emphasizes mount synergy, momentum, and patrol abilities that punish enemies for targeting his guarded ally at all. | BO9: A block-stacking endurance specialist whose Continuous Guard abilities grow stronger with every hit he absorbs. The longer he holds the line, the harder he becomes to bypass — though unchecked stacking risks tipping him into immortality territory that needs playtesting scrutiny. | BP9: A mounted elemental disruptor who turns magic against those who cast it. He reflects elemental afflictions, punishes mana use, and enhances his reflections through magic defense investment — making him the Knight best suited to protecting allies from spellcasters. | BQ9: A dual-wielding conquest machine who chains kill effects into team-wide benefits. Parry Guard extends his parry to his guarded ally, and Conquest abilities convert kills into mana, heals, purges, quickens, and in extremis — resurrection — rewarding aggressive play with cascading advantages. | BR9: A dark mirror of the Knight archetype who weaponizes corruption. He deliberately accumulates it, benefits from it, and shares its dangers with his guarded ally. Vengeance Guard extends retaliation to his guarded, turning incoming damage into a mutual threat. | BS9: A high-ceiling Battalion specialist who demands mastery of turn order to unlock his full potential. He waits, coordinates, and strikes in unison with allies — with rewards that scale based on how long and how many waited together. Most powerful when the player understands the clock. | BT9: A battlefield consecrator who sustains active Temple field effects at the cost of his mana. Each Temple reshapes the conditions of combat for everyone on the field, and Sacred Ground rewards commitment to one Temple over time. At Tier 25, he is the Knight at his most commanding — protecting not just one ally, but the entire sacred space around him. | BU9: Air-element aggressor who punishes stunned enemies. Charges dominion abilities off air damage dealt each turn to gain speed, disrupt her challenge, and deal bonus damage. Lightning Conductor makes every stun a passive damage source, rewarding her heavy stun toolkit with automatic attrition. | BV9: Fire-specialist who wounds foes and punishes them for it. Charges dominions off fire damage to gain retaliation, apply fire countdowns, and weaken fire resistance. Open Wounds amplifies all bleeds against wounded enemies, turning her wound application tools into a force multiplier for the whole team. | BW9: Control-oriented water Knecht who delays and slows her way to dominance. Charges dominions off water damage to regenerate health, delay her challenge, and drain its mana. Accumulating Frost converts incoming delays into damage shields, punishing enemies who try to control her back. | BX9: The tankiest Knecht, built around fortification, damage shields, and defense reduction. Charges dominions off earth damage to build shields, cause earth bleed, and knock her challenge prone. Spike Burst makes every broken damage shield an earth damage counterattack, punishing enemies for hitting through her armor. | BY9: Elemental generalist and dual-wielder who rewards elemental variety. Chains Persistence and Insistence abilities off prior elemental use within the same turn, building toward Rainbow Spectrum's damage bonus. Overriding Challenge lets her re-challenge freely as long as she's already demonstrated two elements that turn — rewarding her natural play pattern. | BZ9: Enhancement-focused Spellsword who builds a personal arsenal of buffs and weaponizes them. Each elemental Transmutation Strike grants a different power enhancement; Enhanced Onslaught converts those stacked enhancements directly into bonus elemental damage against her challenge. Forged Resistance passively builds elemental resistances through offense, and Stolen Form and Match Form let her steal her challenge's own tools against it. | CA9: Arcane penetration specialist who phases in and out of the material plane. Ghostshift makes her intangible, unlocking a suite of unblockable, unparryable, and phasing attacks. Carry to the Ghostrealm lets her drag her challenge into intangibility with her, and Explosive Exit detonates arcane damage against all enemies every time she drops the state. | CB9: The ultimate barrier tank, built entirely around absorbing hits and converting them to offense. Five Abrogation abilities prepare different reactions to barrier triggers — immediate actions, team barriers, arcane damage, delays, or purges. Extended Barrier extends her protection even to phasing attacks, making her the hardest unit in the game to damage outright. | CC9: Evasion-based dark Spellsword who makes herself nearly untargetable by everyone except her challenge. Uses avert, scorn, and hidden to redirect enemy attention while pressuring the challenge with life drain and dark damage. Contemptuous Response punishes the rare enemy that breaks through her defenses with an immediate counter, and Midnight Nemesis resets her aversion after every challenge attack. | CD9: Climactic finisher built around killing her challenge spectacularly. Final Strike abilities each deliver a different team-wide benefit the moment the challenge dies — buffs, enduring, mana, haste, or area damage. Triple and Random Decimation stack the Decimated condition on all enemies, and Death Sentence converts her challenge kill into a decimation wave that crashes across the entire remaining battlefield. | CE9: Crescendo-driven buffer who rewards spending small actions on allies to power up larger payoffs. Builds Crescendo stacks through move and minor buffs, then releases them through scaling heal, shield, damage, bleed, and mana abilities. Leans toward chords and positive effects, with strong regeneration support alongside his offensive Crescendo tools. | CF9: Chaos-specialist who floods enemies with random afflictions, unpredictable conditions, and misdirected attacks. No formal mechanic — the unpredictability is the design. Best used to overwhelm enemy resistances and create openings for allies, with a capstone that turns his own misfortune into tempo. | CG9: The most offensively oriented bard subclass, specializing in life drain, culling, and damage-focused dischords rather than traditional support. He turns the song mechanic toward attrition and erasure — draining life, finishing weakened enemies, and using death itself as an element of his performance. Cacophony abilities reward the whole team's investment in debuffing, making him most dangerous in coordinated groups. | CH9: Earth-focused sustain specialist who stacks litany effects on allies and enemies for escalating pressure. Juggles short-duration stacking conditions that demand constant reapplication — letting them expire collapses the investment. Extended Cuts rewards commitment by progressively raising duration ceilings the more a condition is refreshed. | CI9: Elemental support and disruption specialist who grants deity-named favors to allies, healing them and loading them with elemental damage adds. Simultaneously harasses enemies with water and air magic, knockdowns, and delays. Favor of the Drum doubles every favor with a free untyped add, making his allies' attacks substantially more dangerous. | CJ9: Stealth-integrated bard who supplements song management with disguises and flanking setups. Each disguise grants role-specific bonuses and can be dramatically discharged for a powerful effect at the cost of the disguise itself. Begins every battle already in disguise, giving immediate access to his full toolkit from the first action. | CK9: Dark magic manipulator who fights most effectively when enemies cannot see him. Avert, scorn, and hidden each provide a different path to his veiled abilities, which hit harder than normal. Elusive Rhythm turns successful misdirection into tempo, rewarding a Mountebank who keeps multiple avoidance conditions active simultaneously. | CL9: Conductor-style support who grants allies free attacks through Entourage abilities, drawing enemy aggression onto protected performers. Provokes and taunts redirect incoming damage to allies who are simultaneously shielded, dodging, or enduring. Dedicated Entourage extends every provoke granted, making each protected performer absorb more before attention shifts. | CM9: Resurrection-focused support whose most powerful abilities unlock only after an ally returns to life. Epiphany abilities turn each resurrection into a cascade of heals, buffs, mana, and free attacks. His retaliation theme gives him an offensive identity when not raising allies, and Encore ensures he can survive long enough to finish his performance. | CN9: Aura-and-light specialist who illuminates the battlefield to empower allies and punish enemies. Manages multiple sustained auras simultaneously while spreading illuminate to lock enemies out of hidden and set up targeted light abilities. Constant Light makes him a hard counter to all stealth-based enemy strategies, fundamentally reshaping how battles play out at Tier 25. | CO9: A summoner who fights in concert with her conjured allies, using their mana reserves to amplify her own attacks. She manifests spectral weapons for any ally and directs her companion with precision, growing stronger the more she and her creature act as one. | CP9: A Thanatos-leaning controller who wraps herself and allies in retaliatory spirits, punishing enemies for every strike they land. She pairs water and air magic for freeze and delay with a cross-alignment toolkit that rewards deliberate dips into Eros. | CQ9: A support specialist who prepares a battery of Attendant abilities and waits for her companion to critical — triggering all of them at once in a cascade of healing, damage, and quickening. The longer she waits, the more devastating the payoff. | CR9: A balanced-alignment caster who draws equal power from both dark and light, strongest when she resists pushing to either extreme. Her Harmony abilities detonate from center for massive effect, then push her off balance — and she spends the next turns clawing her way back. | CS9: A spiritual warrior who infuses her companion with procs before it acts and rides a summoned Spirit Beast into mounted combat. She synchronizes her actions with her creature through a shared spiritual bond, raising fallen companions and granting her allies the will to survive past death. | CT9: A desperation specialist whose entire toolkit unlocks at low health, becoming most powerful precisely when she should be most vulnerable. Her transformation locks in that endangered power permanently, turning near-death into a lasting combat state. | CU9: A critical-hit amplifier who builds toward celestial thresholds across multiple turns, generating mana, quickening herself, and purging afflictions with each enemy she crits. She wields the full elemental spectrum through a stellar lens, with her lucky damage toolkit turning probability itself into a weapon. | CV9: A selfish corruptor who damages her own allies to fuel her offensive power, scaling with the total corruption she spreads across the battlefield. She transforms her own self-inflicted corruption into a permanent power state, and turns enemy deaths into mana through Dark Harvest. | CW9: A sanity-sacrificing chaos mage who deliberately accumulates illusory damage on herself to unlock her most powerful abilities. She cannot be killed by her own madness — but when it expires, it becomes very real, making resource management a matter of survival. | CX9: A high-commitment alignment specialist who signs powerful ongoing Pacts, each granting two bonuses at the cost of one persistent drawback. She thrives at the extremes of the alignment scale, and her Lifebond with her companion means their fates are literally intertwined — she cannot fall while it stands. | CY9: Quick and affordable support built around lucky manipulation and regeneration. Generates divinity through hexes, purges, and blessings, then spends it on Benedictions — powerful single-target heals enhanced by current divinity, with overheal effects that range from possession to damage to speed depending on the type used. | CZ9: Pure restoration specialist with the mana economy to sustain heavy healing across a long battle. His cures carry addenda that scale with heal value, turning strong heals into purges, quickens, or damage adds. A Life Domain running on overheal generation lets him convert aggressive healing directly into sustained divinity. | DA9: Affliction-resistant purge specialist who turns enemy pressure into elemental retaliation. Elemental purges double as generators and resistance enhancers scaled to current divinity, and a Protection Domain that rewards affliction resistance creates a feedback loop where enemy affliction pressure fuels his own power. | DB9: Magically aggressive Cleric who layers blessings onto allies while maintaining his own damage shield as an offensive weapon. The Lattice ability line scales with and consumes his shield for light damage and control, Lattice Reflection punishes enemies who target it, and a Sun Domain that generates from light abilities rewards sustained Celestial offense. | DC9: Frontline healer built for endangered allies and active combat. Vitality heals grant temporary bonuses that persist until the target takes damage, and a War Domain that generates from any ally's critical hits rewards pairing him with damage-heavy parties. Perilous Divinity marks low-health targets for stronger healing while generating divinity. | DD9: Light-magic specialist with exclusive access to intangible enemies and strong mana drain. Most abilities gain additional effects against incorporeal targets, and an Exorcism Domain that generates divinity proportional to total enemy mana spent rewards fighting caster-heavy encounters where the domain becomes a powerful self-sustaining engine. | DE9: Sleep-focused controller who worships the sleeping god and grows in power while the world slumbers. Incapacitated allies feed Rest Domain divinity generation even without the Preacher acting, turning sleep from a liability into a resource. Turns ally afflictions into advantages and punishes sleeping enemies with a focused suite of nightmare attacks. | DF9: High-speed melee Cleric who conducts the entire party's tempo through quickening. Ascension abilities require but do not spend full divinity, creating a maintain-and-hold pattern rather than the typical spend-and-rebuild cycle. A mastery class at Tier 19 — maximizing output requires deep awareness of quicken tolerance, Ascension timing, and Fervor Domain generation simultaneously. | DG9: Self-infecting contagion spreader who carries disease deliberately to fuel his domain. Plague Domain generates divinity for each affliction successfully transferred from the Plague Doctor to an enemy, rewarding stacking afflictions on himself and building around affliction resistance to survive the risk. One of the most dangerous and mechanically demanding Cleric subclasses. | DH9: Capstone Cleric whose Furtherance abilities scale with divinity gained during the current turn rather than total on hand. Front-loading a turn with support actions directly amplifies his payoff. A Prophecy Domain that generates divinity when countdowns fire — scaled to their duration — rewards patience and long-term planning over reactive play. | DI9: A water-element Reaper who weaponizes damage afflictions as fuel for conditional kills. He builds bleed, countdown, and hex in a chained cycle, then cashes out their accumulated value in devastating threshold executions — the more damage his curses promise, the deadlier his finishing blow. | DJ9: A cold and efficient finisher who locks onto the weakest enemy and refuses to let them escape. He specializes in culling, conditional kills, and overkill chains, ensuring that no wounded enemy survives long enough to become a threat again. | DK9: An earth-element controller who buries enemies alive, locking them out of combat while setting up punishing follow-up strikes. His buried targets are temporarily untouchable but utterly helpless — patience and precise sequencing determine when they resurface and how much it costs them. | DL9: An air-element strangler who degrades enemy action economy through asphyxiation, building Tired and Exhausted to leave foes gasping and unable to retaliate. He rewards pushing into Spirit Fugue for locked abilities and can sustain himself through near-death with Phoenix Soul. | DM9: A moon-reading diviner who cycles the world's four elemental moons to deliver rotating team-wide enhancements. He adapts his kit to whichever moon is ascendant, shifting between fire, earth, air, and water buffs while wielding chaos, possession, and conditional kill tools between cycles. | DN9: A dark confessor who consumes the afflictions of allies and enemies alike, converting their suffering into fuel for his own attacks. He turns debuffs into weapons — purging curses from his team and launching them back at enemies amplified and weaponized. | DO9: A dream-state manipulator who puts enemies to sleep and punishes them for it, while voluntarily slipping into incapacitation himself to trigger devastating illusory reprisals. He exists in a liminal space between waking and dreaming, exploiting both states with equal precision. | DP9: A paranoia-fueled controller who grows stronger the more enemies surround him, whispering commands into possessed minds and drowning the battlefield in retaliation. He turns enemy numbers from a threat into an advantage, feeding on the chaos of a crowded fight. | DQ9: A relentless finisher who specializes in the endgame of a battle — bleeding, poisoning, and dismantling the last enemy standing. Her kit accelerates toward that final isolated target, delivering the killing blow with empowered fury the moment her prey stands alone. | DR9: A psychological warfare specialist who weaponizes illusion and terror, building illusory damage pools that kill enemies from the inside when they exceed current health. He thrives in Spirit Fugue, his Atmosphere abilities blooming into their full power the deeper into delirium he pushes. | DS9: The entry point for deep influence play. The Telepath specializes in illusory damage and disruption, with heightened abilities that let her translate influence investment into cascading multi-cast effects. She is subtle and methodical, chipping away at enemy defenses before they can act. | DT9: A spread-oriented damage dealer who turns punishment into power. Her kinetic abilities charge between turns based on physical damage she absorbs, making her uniquely dangerous when enemies focus on her. She favors broad pressure and area control over single-target dominance. | DU9: A denial specialist who erodes the enemy's ability to function. She burns through mana, forces enemies into basic attacks, and makes them forget what they were doing. She also carries an unexpected compassionate edge, helping allies forget their wounds. | DV9: A pattern-weaver who controls the entire battlefield through sustained channeled effects. She locks enemies into states of blindness, stun, or vulnerability for as long as she can keep her focus. Patient and methodical, she rewards players who plan their turns carefully. | DW9: An information broker and countdown specialist who fights the future rather than the present. Her divinations expose enemy weaknesses and upcoming actions, letting the whole party respond intelligently, while her countdown abilities punish enemies for the passage of time itself. | DX9: A ghost-touched subclass who exploits enemies at their weakest — specifically when their mana runs dry. She drains, haunts, and possesses with impunity against vulnerable targets, and can become intangible herself to frighten and evade. Death Knell makes her the safest handler of deep influence. | DY9: The party coordinator. Rather than dominating enemies directly, she possesses allies to direct them more efficiently and uses total influence to synchronize team timing. She rewards players who understand their whole roster and rewards smart sequencing over raw power. | DZ9: A high-risk, high-reward glass cannon who bleeds the mind as much as the body. She deals devastating illusory damage that grows stronger the closer she is to death. Her own abilities hurt her, but the connection flows both ways — and she intends to make that cost worth it. | EA9: A spread-influence subclass who bends time itself to delay, rush, and disorient the battlefield. She punishes fast enemies, accelerates allies, and becomes more efficient the more she leans into her hasted or slowed states. Supreme Chronomancy is one of the most powerful single abilities in the psychic tree. | EB9: The pinnacle of possession mastery. She owns enemies outright, bends their will across multiple turns, and profits from every attack they make under her control. Her capstone, Broken Will, ensures that no enemy is ultimately beyond her reach. | EM9: A team-oriented controller who drains stats from maledicted enemies and redistributes them to allies. She weaponizes possession and hexes for direct control while her Malign drain suite debilitates entire maledicted groups — and Share in Consumption ensures no drain benefit passes through her hands without leaving something behind. | EN9: An air-element Witch who turns malediction into a positional weapon. Her whirlwind abilities use a maledicted enemy as an anchor, striking all adjacent foes instead — rewarding grid awareness and central positioning. Bloodlust amplifies her storm attacks while Conductivity makes the entire maledicted field a lightning rod. | EO9: The most aggressive Witch subclass, stacking damage afflictions on targets to fuel piercing effigy attacks that cut through resistance. Flammability turns every fire hit into compounding bleeds, and Personal Effigy rewards taking damage herself — making her a high-risk attacker who burns hotter the more punishment she absorbs. | EP9: A methodical earth-element controller who applies permanent unending afflictions that reserve her mana until enemies die or are purged. She trades mana flexibility for devastating long-term debilitation, and Mana From Dust recycles her investment when corruption finishes the job. | EQ9: A water-element specialist who deals increased damage and effects in inverse proportion to enemy speed — making her strongest against the foes she has already slowed. Chill to Frost converts redundant slows into hard incapacitation, and Inspiring Misfortune makes her one of the strongest mana generators in the entire Witch family. | ER9: A chaotic generalist who trades reliability for volume, deploying cheap bewitch afflictions against maledicted enemies at reduced action cost. Agnostic Afflictions removes elemental opposition penalties on vulnerability and exposure, letting her stack conditions freely regardless of enemy resistances — chaos as a feature, not a flaw. | ES9: A light-element support Witch who harvests fetishes from fallen enemies and deploys them as stat-scaling ally buffs. She transfers afflictions from allies to enemies, drains life, and accumulates mana through Fetish Bag by holding fetishes in reserve — balancing the tension between deploying her toolkit and sustaining herself. | ET9: A dark necromancer who builds zombie companions from killed and afflicted enemies, using Juju Curse to turn her entire malediction toolkit into a zombie pipeline. Corpse Pile makes each death — enemy or companion — strengthen her current zombie, turning attrition into escalating companion power. | EU9: A corruption and bleed specialist who wraps her worst afflictions in criterion shells that resist purging until they deal their full damage. Expiration Surge turns every naturally expiring condition into mana, rewarding patience and long-duration stacking — Plague Cauldron's exponential corruption release is her most catastrophic payoff for waiting. | EV9: The apex Witch, combining covenants, curses, and mass malediction into a comprehensive affliction dominance platform. She channels malediction across entire enemy groups with Malefaction Chant, unifies damage through Sympathy, and elevates her whole party's affliction pressure through Cursed Amplification — the Witch's toolkit at its most absolute. | EW9: All-elements generalist with companion support and momentum-driven efficiency. She cycles through every element in sequence to build stacking cast speed and mana bonuses, summons earth and water elementals, and infuses allies with elemental damage adds — the most versatile and accessible wizard subclass. | EX9: Dark magic specialist who turns death itself into a resource. She raises skeletal companions, scales her storm damage to the body count, and runs a suite of prepared abilities that trigger automatically when enemies fall — rewarding her for battles where allies are doing the killing as much as her own. | EY9: Control-focused water specialist with the deepest incapacitation toolkit in the class. She freezes, slows, and delays entire battlefields, with her most powerful conflux ability scaling both the number of targets incapacitated and how hard they are to wake based on how many elements she has charged. | EZ9: Defensive earth specialist who protects allies while grinding down enemy defenses. She builds damage shields, roots enemies in place, and applies layered weaknesses — her conflux abilities uniquely favor the whole party by granting elemental retaliations and stacking debuffs across every stat. | FA9: High-variance air specialist built around storm damage and stun pressure. She thrives on randomness — chaining lightning across the grid, forking attacks into splits, and stacking storm hits to overwhelm enemies — with the highest individual damage ceiling in the class when lucky damage and maximum damage align. | FB9: Area fire specialist who hits everyone, repeatedly. She applies countdowns, causes wounds, and commits fully to upfront mana costs for abilities that pay off over multiple ticks — Catastrophe and Conflux Meteor reward planning several turns ahead and punish enemies who cannot interrupt her. | FC9: Anti-attunement specialist who grows stronger the more completely she clears her elemental slate. She is the only wizard whose peak performance comes after spending conflux rather than before it, with her most powerful abilities gating behind having no attunements and her conflux damage rewarding precise elemental power investment over breadth. | FD9: Light magic specialist with hex, justice, and a unique mana economy identity. She wants enemies casting expensive spells so her Mana Disparity bonus peaks, making her the only wizard who benefits from enemy casters. Her full-conflux Conflux Enchantment can grant the entire party six simultaneous buffs scaled to her elemental investment. | FE9: Reactive counterspell specialist who punishes enemy spellcasting while sustaining channeled damage. She runs a suite of prepared counterspells that can chain indefinitely, drains mana from enemies, and uses Conflux Channeling to chain successive elemental damage sequences — the only wizard subclass that gets stronger the more the enemy commits to magic. | FF9: Pinnacle attunement-breadth specialist who rewards deliberate, expensive play. She wants all six elements charged simultaneously, spends them through Supreme abilities that scale with attunement count, and uses her previous turn's mana expenditure to amplify the next — the most technically demanding wizard subclass and the one with the highest ceiling.
A10: Mechanic | B10: =COUNTA(C10:FF10)/1.6 -> 31.25 | C10: Scouted Abilities — Scouted abilities are more powerful only on the very first action of battle. After use, they downgrade permanently to a lesser version for the rest of that battle. The New Beginning capstone restores the scouted condition mid-battle if the Scout's momentum is high enough, allowing him to use the upgraded version again. | D10: Banes — Bane abilities target a specific enemy type. When a bane is applied, it typically affects all enemies that share that type simultaneously — either dealing damage to all of them, granting a debuff to all of them, or granting the Hunter advantages when any ally attacks enemies of that type. Bane abilities typically require or consume aim to use. | E10: Rapid Reload — Crossbow attacks apply a reload delay to the Crossbowman after firing. Reload pushes the Crossbowman back on the action clock by an amount equal to the reload value multiplied by his speed — the faster he is, the more punishing the reload penalty. Rapid Reload abilities eliminate the reload from the next attack or the upcoming reload entirely, allowing the Crossbowman to negate this penalty at the cost of a minor or move action. | F10: Marks — Marks are ongoing conditions placed on enemies. Only one mark can be active on any enemy at a time. While a mark is active, allies that attack the marked enemy receive a benefit specific to the mark type. Marks require and consume aim to place, and their duration and effects scale with aim invested. | G10: Falcon — The Falconer's companion is a flying falcon that attacks the Falconer's aim target by default each turn. Many Falconer abilities function without a falcon present but receive bonuses or additional effects when one is active. Some abilities require the falcon companion specifically. | H10: Bounties — Bounty abilities are placed on an enemy as a minor action and must be used as the final action of the Bounty Hunter's turn. They have no immediate effect. When the targeted enemy dies, the bounty triggers and benefits the Bounty Hunter. Each bounty type grants a different reward on death. | J10: Poach Abilities — Poach abilities are prepared using aim. Once prepared, they cannot be disrupted. When any enemy becomes endangered, the prepared poach fires automatically against that enemy and becomes unprepared. Each use targets whichever enemy next hits the endangered threshold. To use a poach against a different enemy than the last, the Poacher must re-prepare it with a fresh aim cost. | K10: Trick Shots — Trick shot abilities have a fixed low accuracy that cannot be improved by any means. Aim does not affect the hit chance. Instead, aim as a percentage of maximum aim determines whether the trick shot's special effect triggers if the attack hits. At higher aim percentages the effect is more likely to trigger; at lower aim it rarely does. Each trick shot has a distinct effect that only fires when the trickshot condition is met. | L10: Eternal Buffs — Eternal buffs are ongoing self-enchantments that stack upward without a limit. Only one eternal buff can be active at a time — activating a new one removes the previous. Each use increases the buff's power and also increases the cost of the next enhancement: they consume increasing amounts of aim or mana with each stack. There is no cap on how high they can go, but the escalating cost creates a practical limit within a wave. | W10: Desperation — Certain Bandit abilities require him to be the last surviving ally. When alone, he gains access to dedicated desperation abilities and advantage generators unavailable while allies are present. Desperation Mana carries no advantage cost, allowing the Bandit to shift into a mana-fueled economy when alone. | AA10: Reliability — Certain Acrobat abilities are tagged as reliable. When a reliable ability fails to connect, its resource cost is refunded in full. The Acrobat still requires the resources to attempt the ability, but failed attempts do not drain his economy. | AB10: Contracts — The Assassin can sign a contract against a single enemy at any point during battle using a Minor action. Only one contract may be active at a time. While a contract is active, the Assassin gains passive benefits for attacking the contracted target. When the Assassin personally kills the contracted target with an active ability, he receives the contract's fulfillment bonus. | AC10: Wagers — Brigand abilities follow a wager-and-pot structure. The Brigand spends advantage or mana as a wager when using certain abilities. If a triggering condition occurs, he collects the pot as a payoff. | AG10: Scavenged Abilities — Scavenged abilities are prepared. On preparation, one of the six primary elements (air, earth, fire, water, light, dark) is randomly selected and locked in. The chosen element is displayed publicly and cannot be changed without consuming or disrupting the ability. This makes scavenged abilities less flexible than standard abilities but potentially more powerful, as the element is committed before targeting decisions are made. | AH10: Premade Concoctions — Premade abilities begin each wave already prepared at no resource or action cost. The first use requires no ammo and the prepared state cannot be disrupted in the conventional sense — only breaking the vial through combat disruption prevents it. After the first use, premade abilities must be re-prepared using the standard preparation system with a mana cost and can be disrupted during preparation. Premades are slightly less powerful than equivalent standard abilities in exchange for their zero-cost first use. | AI10: Accumulation — Accumulation abilities have two uses. The first use activates the ability and begins accumulating power; the ability grows stronger with each clock tick it remains active. The second use expends all accumulated power in a single discharge. The three Accumulator abilities (Beam, Burst, Storm) consume all active ammo on first use — the amount consumed and the active ammo type at that moment determine the base power and damage type when fired. Accumulating Detonation and Accumulating Trap accumulate power over time with no ammo cost. | AJ10: Modifications — Modifications are toggled abilities that alter how the Tinker and her companions function. Each modification costs a move action to toggle on and a move action to toggle off. Any number of modifications can be active simultaneously. Some modifications affect only the Tinker’s abilities, some affect only the companion, and some affect both. Four major abilities — Modular Bomb, Modular Ray, Modular Trap, and Modular Beam — each function differently depending on which modifications are currently active. | AK10: Assistants — Assistant abilities are move-action enchantments placed on chosen allies. Each assistant type grants a different proc that fires whenever the assigned ally attacks. Multiple different assistant types can be active simultaneously on different allies. Each assistant type can only be assigned to one ally at a time — reassigning it to a new ally removes it from the previous one. Assistants that use ammo consume one ammo each time their proc fires. Assistants persist on the ally until reassigned. | AL10: Friendly Fire — The Bomber’s bomb abilities deal high area damage but apply the same damage to allies as to enemies. Base damage values are identical for all targets — there is no ally discount. Scaling abilities scale the same way for all targets. | AM10: Called Shots — Called shot abilities are prepared as a minor action. Each called shot names a specific target at preparation time and applies a powerful secondary effect to the first attack ability used against that target on the following turn. Without the capstone skill Quick Call, the called shot cannot be used and applied on the same turn — the minor action prepares the effect and the attack comes next turn. | AN10: Concoction Detonations — The Savant’s six concoction abilities are detonations with three phases. While placed on a target they apply an ongoing effect. Simultaneously, they accumulate power each clock tick from the moment of placement. When the detonation chain fires, the discharge effect scales with accumulated power. Concoctions also auto-detonate after a period determined by ammo consumed at placement — more ammo extends the active window, allowing greater accumulation and longer ongoing effect duration before the automatic discharge. | AO10: Siege Engine Operation — Siege engine companions (Ballista, Battering Ram, Catapult) can act on their own clock turns, but their base speed is extremely low. Without the Siege Engineer spending actions to advance them, they fire infrequently. The Siege Engineer’s move and minor toolkit exists largely to accelerate siege companions — quickening them, fuelling them with ammo for haste, and upgrading their next action via Siege Command. | AQ10: Consequences — Consequence abilities generate Anguish on use and deal a deferred self-damage cost at the beginning of the Brute's next turn. Only the initial use generates Anguish; the deferred damage does not. | AR10: Reckless Abilities — Reckless abilities are powerful attacks that negate all active defenses and counter chances until the Raider's next turn. These abilities are further enhanced based on the total value of those active defenses at the moment of use. | AS10: Exertion — Exertion abilities have reduced accuracy. On a miss, the attack repeats targeting a random enemy and deals backbiting self-damage to the Berserker. This self-damage generates Anguish. | AT10: Rampage — Rampage accumulates as enemies are killed. Personal kills grant a higher Rampage bonus than team kills. Rampage enhances many of the Marauder's abilities, primarily scaling damage and speed. | AU10: Block Stacking — When the Viking has an ability prepared, each block made adds a charge to that specific ability. Multiple prepared abilities accumulate charges independently. When the ability fires, it consumes all stacks for enhanced damage or effect. Stacks are lost if the ability is disrupted. | AV10: Brink — Brink abilities become available for one turn after the Rager's cumulative damage dealt crosses a fixed threshold. This threshold tracks damage across multiple hits and turns. Once the threshold is crossed, unused Brink abilities expire at the end of the turn. | AW10: Purity Amplification — Purity abilities amplify in power each time they are used without triggering their cancellation condition. Each Purity has its own independent stack and cancellation condition. | AX10: Healing Threshold — The Cannibal can use threshold abilities when she has received enough healing that could actually be applied to her. Overhealing — healing above maximum health — does not count. The threshold accumulates across multiple heals. Some threshold abilities are prepared and activate automatically when the threshold is met; others require manual activation. | AY10: Massive Damage — Massive damage occurs when a single attack deals damage equal to or exceeding a set percentage of the target's maximum health. This threshold scales with target health rather than the Destroyer's stats. | AZ10: Beast Forms are ongoing minor abilities that consume Anguish and provide continuous stat bonuses with additional effects. Only one form can be active at a time — activating a new form replaces the previous one immediately. | BA10: Gambits — Gambit abilities either work to great effect or have a negative consequence on failure. | BB10: Disarm — The Duelist specializes in rare and powerful disarm techniques. She can disarm opponents and take advantage after the target is disarmed. | BC10: Allied Coordination — For each ally that is ready at the same time the Phalanx uses her abilities, the more powerful they are. Some abilities require multiple allies to be ready simultaneously. | BD10: Succession — Succession abilities are dual-wield attacks whose second hit gains enhanced effects based on dual-wield attack speed. The faster her attacks land, the more powerful the succession payoff. | BG10: Bushido — Some Samurai abilities allow enemies to attack her first, though many also delay or reset the enemy's counter afterward. These abilities are stronger relative to the effect of the enemy's action, encouraging the Samurai to fight her most difficult foe. | BH10: Unstoppable Abilities — Dreadnaughts can use their defense to augment physical attacks, enhancing damage or causing other effects. | BI10: Feints — Feint abilities can come in any action type and all compel an enemy and improve the Swashbuckler's parry chance. They grant a reaction on parrying and require a level of expertise. | CE10: Crescendo - The Minstrel tracks the number of buff-type ability actions used by any unit between his turns. Each unique buff action adds one stack of Crescendo, with a maximum cap defined per Crescendo ability. Crescendo resets when a Crescendo ability is used. Because buffs tend to be move and minor actions, building a high Crescendo count means investing smaller actions — creating a genuine trade-off between conventional buffing and setting up a powerful Crescendo payoff. | DI10: Reckoning — Reckoning abilities scale their power based on the current value of a damage affliction on the target, calculating the full potential damage those afflictions represent. | DJ10: Verdict — Verdict abilities can only target the enemy with the lowest health, representing the Executioner's role as the inevitable end for the weakest foe on the battlefield. | DK10: Burial — Burial is a variant of incapacitated that lasts for a fixed duration rather than ending on hit. Buried enemies cannot act, cannot advance their timer, and cannot take direct damage while buried. Burial ends automatically after its duration expires. Follow-up abilities allow the Gravedigger to capitalize on buried enemies through specific interactions. | DL10: Asphyxiation — Asphyxiation abilities build the Tired and Exhausted conditions on enemies, degrading their action economy through strangulation and air damage. Tired reduces an enemy's action options to two per turn. Exhausted, the upgraded condition, reduces actions to just one. | DM10: The Four Moons — The four moons of the world cycle naturally, waxing and waning in intensity. Their benefits are team-wide, peaking when a moon is at its highest and fading as it wanes. Blood Moon enhances fire effects. Harvest Moon enhances earth and healing effects. Strawberry Moon enhances air and enhancement effects. Tidal Moon enhances water and control effects. Spirit Orbs are required to call a specific moon, and Reverse the Skies allows the cycle to be shifted. | DN10: Sin Eating — The Sin Eater purges afflictions from allies and himself, then weaponizes them against enemies. Consuming sin and turning it outward is the core of the Sin Eater's identity. | DO10: Oneiromancy — The Sandman applies incapacitation through dream-state manipulation, exploiting incapacitated enemies with follow-up abilities and existing in a liminal state himself. Voluntarily incapacitating himself turns danger into a powerful offensive tool. | DP10: Paranoia — Paranoia abilities scale their power based on the number of enemies currently present on the battlefield. The Whisperer grows more powerful when facing larger groups, rewarding engagement with full enemy formations. | DQ10: Last Rites — Last Rites abilities interact with the final surviving enemy on the battlefield, representing the Mercy Bringer's role as the deliverer of the final mercy to the last standing foe. | DR10: Delirium — Delirium abilities gain enhanced secondary effects while the Gaslighter is in Spirit Fugue, rewarding the deliberate pursuit of that dangerous state. The Atmosphere suite each provides a baseline effect with a powerful Spirit Fugue bonus. Illusory damage is a stacking pool that kills the target if it ever exceeds their current health, causing a heart attack. Illusory damage can expire or be purged like other conditions.
A11: Lore | B11: =COUNTA(C11:FF11)/1.6 -> 7.5 | AQ11: Brutes often serve as mercenaries and bodyguards, though they have little finesse. They are the hammer compared to a scalpel. | AS11: Berserkers are specialized warriors among Valisian raider parties, those who can lose themselves completely to battle and rage. Though, like all Valisian sailors, they stand to benefit financially from their assaults, they take even more reward in the chaos they cause. | AU11: Vikings are the foot soldiers of Valisian ships, more restrained than many barbarians, but still with a tendency to give into their rage in large groups. | AX11: Cannibals have very little that distinguishes them aside from the fact they eat the flesh of their fellow man. Some live in the wilds, some are members of tribes, some hide in plain sight in noble circles. | AY11: The role of Destroyers in battle is less on defeating the enemy than on demoralizing them, taking away their weapons and armor and leaving them without hope. | BA11: Gladiators are often slaves, or at least indentured to who they fight for. For some, it is a glamorous job, and they delight in the cheers they receive. Many more though, fight for their lives, and know that no one cares about their health except for where it earns a profit. | BC11: Phalanx works together in groups, manning entire squadrons in well-defined ranks. The Dynasians were most likely to use them. | BD11: Dervishes are most commonly from the Zafeer region and run through the plains and deserts to face their foes. | BE11: Fencers are specifically trained in their style, and actively compete in their sword style. | BH11: Dreadnaughts are the heavy infantry of armies. They march together, without stopping, and overrun their foes. | BI11: Swashbucklers are among found out at sea or in coastal towns. They do not have a preference for piracy or privateering, but see being on such ships gives them an opportunity to do what they love: sword fighting. | BJ11: Warlords take control of various armies throughout the world, not all as organized as the different national troops. They are charismatic and capable.
A12: Appearance | B12: =COUNTA(C12:FF12)/1.6 -> 7.5 | AQ12: Her clothes are plain, functional. She is tall, broad of shoulder. She carries a large club, which she taps her opposite hand with. | AW12: Her eyes are wide, and she is ready for battle. Both axes are in her hands, glinting in the sunshine. | AX12: The cannibal is a non-descript member of the public. She wears the same plain clothes of the village she lives in, and the weapons she carries can easily be explained away. She is muscular, but her clothing disguises this. | AY12: At first, it seems the weapons and armor of the Destroyer are held together by spit and hope, but it quickly becomes clear that they are sturdier than they look. | AZ12: It is hard to find the Beastlord beneath her mountain of furs. Her hair is unkempt, with leaves and bones tangled in it, and the smell is potent. She says it is to help her better fit in with the beasts. | BA12: She wears a mismatched set of armor, designed to draw attention to her greater assets. She has some scars, but not so many as to detract from her hard, yet beautiful look. | BC12: She carries spear and shield with a plumed helm. | BD12: Though she wears chain, the armor on the Dervish seems to flow around her, and the chains she fights with dance in her hands. Her long hair is in a ponytail, flickering back and forth. | BF12: She carries a lance, pointed straight to the sky, her king’s favor hanging down from it. She wears heavy armor. | BG12: The Samurai always fights with two swords, one long, one short. Her splint mail is typically enameled in red, and her helm resembles the face of a demon. | BH12: The Dreadnaught wears extremely heavy armor, and it is a wonder she can move in it. Her face is hidden by her helm. She wields a large axe. | BJ12: She carries a sword and shield, her shield emblazoned with her heraldic symbol. Her hair is shoulder length but bound.
A13: Req Dex | B13: =COUNTA(C13:FF13)/1.6 -> 22.5 | C13: 58 | D13: 63 | E13: 62 | F13: 88 | G13: 70 | H13: 142 | I13: 180 | J13: 248 | K13: 193 | L13: 182 | M13: 59 | N13: 58 | O13: 93 | P13: 76 | Q13: 67 | R13: 173 | S13: 88 | T13: 185 | U13: 217 | V13: 263 | AR13: 55 | AS13: 78 | AT13: 76 | AU13: 108 | AW13: 137 | AX13: 95 | AY13: 92 | AZ13: 181 | BA13: 57 | BB13: 65 | BD13: 85 | BE13: 83 | BF13: 78 | BG13: 80 | BI13: 215 | BJ13: 121
A14: Req Int | B14: =COUNTA(C14:FF14)/1.6 -> 6.25 | K14: 90 | L14: 108 | M14: 56 | N14: 54 | R14: 77 | S14: 129 | AR14: 55 | AV14: 74 | BE14: 64 | BF14: 74
A15: Req Str | B15: =COUNTA(C15:FF15)/1.6 -> 20.625 | C15: 54 | E15: 75 | F15: 76 | I15: 86 | L15: 121 | M15: 54 | N15: 64 | O15: 72 | P15: 92 | Q15: 105 | S15: 95 | U15: 140 | V15: 129 | AQ15: 64 | AR15: 68 | AS15: 81 | AT15: 106 | AU15: 91 | AV15: 134 | AW15: 112 | AX15: 98 | AY15: 224 | AZ15: 121 | BA15: 62 | BB15: 56 | BC15: 83 | BD15: 86 | BE15: 84 | BF15: 132 | BG15: 171 | BH15: 252 | BI15: 168 | BJ15: 129
A16: Req Wis | B16: =COUNTA(C16:FF16)/1.6 -> 12.5 | C16: 61 | D16: 63 | E16: 72 | G16: 108 | H16: 95 | I16: 80 | J16: 98 | K16: 95 | T16: 90 | V16: 118 | AQ16: 56 | AW16: 76 | AX16: 132 | AY16: 89 | AZ16: 170 | BB16: 55 | BC16: 70 | BG16: 77 | BH16: 95 | BJ16: 185
A17: Req Cha | B17: =COUNTA(C17:FF17)/1.6 -> 15.625 | C17: 58 | D17: 67 | E17: 84 | F17: 86 | G17: 130 | H17: 95 | I17: 82 | J17: 99 | K17: 238 | L17: 244 | P17: 63 | Q17: 68 | R17: 109 | U17: 131 | V17: 118 | AU17: 68 | AZ17: 118 | BA17: 60 | BB17: 55 | BC17: 71 | BD17: 72 | BE17: 98 | BG17: 79 | BH17: 95 | BJ17: 265
A18: Req End | B18: =COUNTA(C18:FF18)/1.6 -> 16.875 | C18: 53 | E18: 63 | M18: 59 | N18: 67 | O18: 82 | P18: 106 | Q18: 85 | R18: 82 | S18: 213 | T18: 185 | U18: 135 | V18: 128 | AQ18: 60 | AR18: 56 | AS18: 69 | AT18: 105 | AU18: 91 | AV18: 132 | AW18: 82 | AX18: 230 | AY18: 219 | AZ18: 245 | BA18: 53 | BC18: 73 | BF18: 79 | BH18: 152 | BJ18: 128
A19: Req Luc | B19: =COUNTA(C19:FF19)/1.6 -> 15.625 | D19: 59 | E19: 62 | F19: 87 | H19: 95 | I19: 82 | J19: 198 | K19: 96 | L19: 245 | O19: 61 | V19: 122 | AR19: 62 | AS19: 60 | AU19: 70 | AW19: 109 | AY19: 92 | BA19: 56 | BB19: 66 | BC19: 71 | BD19: 94 | BE19: 99 | BF19: 159 | BG19: 139 | BH19: 99 | BI19: 275 | BJ19: 122
A20: Req Wil | B20: =COUNTA(C20:FF20)/1.6 -> 14.375 | C20: 54 | G20: 70 | H20: 95 | I20: 115 | K20: 96 | M20: 60 | N20: 59 | O20: 60 | Q20: 103 | R20: 81 | T20: 183 | U20: 135 | V20: 122 | AQ20: 61 | AR20: 56 | AS20: 80 | AV20: 132 | AW20: 109 | AX20: 138 | AY20: 92 | AZ20: 115 | BB20: 55 | BG20: 79
A21: Dex Growth | B21: =COUNTA(C21:FF21)/1.6 -> 100 | C21: 19 | D21: 25 | E21: 23 | F21: 33 | G21: 27 | H21: 50 | I21: 54 | J21: 62 | K21: 58 | L21: 56 | M21: 23 | N21: 21 | O21: 36 | P21: 28 | Q21: 26 | R21: 50 | S21: 34 | T21: 54 | U21: 66 | V21: 65 | W21: 16 | X21: 20 | Y21: 36 | Z21: 38 | AA21: 42 | AB21: 44 | AC21: 34 | AD21: 47 | AE21: 58 | AF21: 65 | AG21: 23 | AH21: 25 | AI21: 36 | AJ21: 38 | AK21: 26 | AL21: 32 | AM21: 54 | AN21: 47 | AO21: 58 | AP21: 56 | AQ21: 13 | AR21: 18 | AS21: 32 | AT21: 28 | AU21: 37 | AV21: 25 | AW21: 48 | AX21: 39 | AY21: 41 | AZ21: 56 | BA21: 20 | BB21: 24 | BC21: 18 | BD21: 33 | BE21: 32 | BF21: 32 | BG21: 34 | BH21: 31 | BI21: 58 | BJ21: 47 | BK21: 10 | BL21: 11 | BM21: 18 | BN21: 24 | BO21: 11 | BP21: 32 | BQ21: 27 | BR21: 16 | BS21: 16 | BT21: 28 | BU21: 20 | BV21: 14 | BW21: 22 | BX21: 14 | BY21: 27 | BZ21: 18 | CA21: 20 | CB21: 31 | CC21: 50 | CD21: 46 | CE21: 16 | CF21: 25 | CG21: 27 | CH21: 33 | CI21: 32 | CJ21: 44 | CK21: 34 | CL21: 31 | CM21: 33 | CN21: 47 | CO21: 10 | CP21: 18 | CQ21: 13 | CR21: 19 | CS21: 26 | CT21: 38 | CU21: 21 | CV21: 31 | CW21: 50 | CX21: 47 | CY21: 16 | CZ21: 11 | DA21: 9 | DB21: 9 | DC21: 21 | DD21: 25 | DE21: 21 | DF21: 39 | DG21: 25 | DH21: 19 | DI21: 16 | DJ21: 14 | DK21: 9 | DL21: 10 | DM21: 10 | DN21: 19 | DO21: 21 | DP21: 23 | DQ21: 42 | DR21: 37 | DS21: 13 | DT21: 17 | DU21: 14 | DV21: 29 | DW21: 16 | DX21: 32 | DY21: 27 | DZ21: 24 | EA21: 50 | EB21: 46 | EC21: 7 | ED21: 18 | EE21: 9 | EF21: 19 | EG21: 16 | EH21: 25 | EI21: 21 | EJ21: 31 | EK21: 42 | EL21: 19 | EM21: 20 | EN21: 21 | EO21: 18 | EP21: 24 | EQ21: 16 | ER21: 25 | ES21: 34 | ET21: 24 | EU21: 25 | EV21: 37 | EW21: 23 | EX21: 14 | EY21: 23 | EZ21: 24 | FA21: 37 | FB21: 38 | FC21: 27 | FD21: 54 | FE21: 50 | FF21: 47
A22: Int Growth | B22: =COUNTA(C22:FF22)/1.6 -> 100 | C22: 6 | D22: 10 | E22: 13 | F22: 14 | G22: 21 | H22: 12 | I22: 13 | J22: 31 | K22: 41 | L22: 46 | M22: 19 | N22: 17 | O22: 13 | P22: 14 | Q22: 21 | R22: 31 | S22: 40 | T22: 31 | U22: 33 | V22: 27 | W22: 16 | X22: 14 | Y22: 27 | Z22: 28 | AA22: 26 | AB22: 43 | AC22: 33 | AD22: 31 | AE22: 57 | AF22: 64 | AG22: 6 | AH22: 7 | AI22: 13 | AJ22: 19 | AK22: 21 | AL22: 31 | AM22: 20 | AN22: 31 | AO22: 16 | AP22: 46 | AQ22: 10 | AR22: 17 | AS22: 9 | AT22: 14 | AU22: 21 | AV22: 31 | AW22: 13 | AX22: 31 | AY22: 16 | AZ22: 27 | BA22: 6 | BB22: 10 | BC22: 13 | BD22: 9 | BE22: 26 | BF22: 31 | BG22: 13 | BH22: 23 | BI22: 33 | BJ22: 37 | BK22: 13 | BL22: 14 | BM22: 22 | BN22: 28 | BO22: 30 | BP22: 31 | BQ22: 27 | BR22: 54 | BS22: 49 | BT22: 64 | BU22: 19 | BV22: 24 | BW22: 31 | BX22: 23 | BY22: 26 | BZ22: 31 | CA22: 47 | CB22: 31 | CC22: 49 | CD22: 37 | CE22: 9 | CF22: 14 | CG22: 27 | CH22: 14 | CI22: 15 | CJ22: 25 | CK22: 40 | CL22: 38 | CM22: 41 | CN22: 46 | CO22: 19 | CP22: 24 | CQ22: 22 | CR22: 19 | CS22: 21 | CT22: 31 | CU22: 33 | CV22: 54 | CW22: 49 | CX22: 64 | CY22: 9 | CZ22: 17 | DA22: 22 | DB22: 23 | DC22: 21 | DD22: 18 | DE22: 20 | DF22: 31 | DG22: 49 | DH22: 55 | DI22: 13 | DJ22: 10 | DK22: 18 | DL22: 23 | DM22: 26 | DN22: 18 | DO22: 33 | DP22: 46 | DQ22: 24 | DR22: 55 | DS22: 22 | DT22: 17 | DU22: 27 | DV22: 33 | DW22: 36 | DX22: 31 | DY22: 54 | DZ22: 62 | EA22: 49 | EB22: 74 | EC22: 22 | ED22: 24 | EE22: 31 | EF22: 28 | EG22: 26 | EH22: 50 | EI22: 54 | EJ22: 38 | EK22: 49 | EL22: 74 | EM22: 22 | EN22: 24 | EO22: 36 | EP22: 23 | EQ22: 31 | ER22: 31 | ES22: 40 | ET22: 62 | EU22: 57 | EV22: 74 | EW22: 22 | EX22: 24 | EY22: 22 | EZ22: 23 | FA22: 36 | FB22: 37 | FC22: 54 | FD22: 46 | FE22: 66 | FF22: 74
A23: Str Growth | B23: =COUNTA(C23:FF23)/1.6 -> 100 | C23: 17 | D23: 11 | E23: 27 | F23: 29 | G23: 21 | H23: 25 | I23: 34 | J23: 24 | K23: 25 | L23: 47 | M23: 17 | N23: 25 | O23: 27 | P23: 34 | Q23: 37 | R23: 25 | S23: 34 | T23: 32 | U23: 50 | V23: 47 | W23: 20 | X23: 18 | Y23: 18 | Z23: 15 | AA23: 27 | AB23: 25 | AC23: 41 | AD23: 39 | AE23: 25 | AF23: 28 | AG23: 13 | AH23: 14 | AI23: 23 | AJ23: 19 | AK23: 32 | AL23: 32 | AM23: 21 | AN23: 24 | AO23: 50 | AP23: 28 | AQ23: 26 | AR23: 25 | AS23: 32 | AT23: 39 | AU23: 32 | AV23: 44 | AW23: 41 | AX23: 39 | AY23: 67 | AZ23: 47 | BA23: 26 | BB23: 18 | BC23: 32 | BD23: 34 | BE23: 32 | BF23: 44 | BG23: 54 | BH23: 62 | BI23: 50 | BJ23: 47 | BK23: 23 | BL23: 28 | BM23: 23 | BN23: 29 | BO23: 42 | BP23: 44 | BQ23: 54 | BR23: 55 | BS23: 50 | BT23: 47 | BU23: 17 | BV23: 25 | BW23: 28 | BX23: 34 | BY23: 42 | BZ23: 44 | CA23: 41 | CB23: 62 | CC23: 42 | CD23: 74 | CE23: 17 | CF23: 7 | CG23: 9 | CH23: 15 | CI23: 27 | CJ23: 25 | CK23: 27 | CL23: 24 | CM23: 25 | CN23: 19 | CO23: 10 | CP23: 7 | CQ23: 19 | CR23: 19 | CS23: 27 | CT23: 13 | CU23: 34 | CV23: 16 | CW23: 25 | CX23: 28 | CY23: 17 | CZ23: 14 | DA23: 32 | DB23: 34 | DC23: 37 | DD23: 32 | DE23: 41 | DF23: 47 | DG23: 33 | DH23: 47 | DI23: 20 | DJ23: 25 | DK23: 32 | DL23: 34 | DM23: 27 | DN23: 38 | DO23: 27 | DP23: 32 | DQ23: 42 | DR23: 47 | DS23: 13 | DT23: 25 | DU23: 27 | DV23: 24 | DW23: 27 | DX23: 44 | DY23: 27 | DZ23: 47 | EA23: 33 | EB23: 47 | EC23: 20 | ED23: 14 | EE23: 27 | EF23: 29 | EG23: 27 | EH23: 19 | EI23: 21 | EJ23: 31 | EK23: 42 | EL23: 37 | EM23: 10 | EN23: 7 | EO23: 18 | EP23: 24 | EQ23: 21 | ER23: 25 | ES23: 14 | ET23: 24 | EU23: 42 | EV23: 19 | EW23: 10 | EX23: 11 | EY23: 18 | EZ23: 24 | FA23: 11 | FB23: 32 | FC23: 21 | FD23: 32 | FE23: 17 | FF23: 19
A24: Wis Growth | B24: =COUNTA(C24:FF24)/1.6 -> 100 | C24: 23 | D24: 25 | E24: 27 | F24: 19 | G24: 36 | H24: 37 | I24: 33 | J24: 38 | K24: 41 | L24: 37 | M24: 6 | N24: 7 | O24: 13 | P24: 19 | Q24: 21 | R24: 19 | S24: 27 | T24: 38 | U24: 16 | V24: 46 | W24: 13 | X24: 18 | Y24: 9 | Z24: 14 | AA24: 10 | AB24: 12 | AC24: 27 | AD24: 38 | AE24: 24 | AF24: 27 | AG24: 23 | AH24: 24 | AI24: 18 | AJ24: 19 | AK24: 26 | AL24: 31 | AM24: 40 | AN24: 54 | AO24: 41 | AP24: 55 | AQ24: 16 | AR24: 11 | AS24: 18 | AT24: 14 | AU24: 15 | AV24: 25 | AW24: 33 | AX24: 46 | AY24: 41 | AZ24: 55 | BA24: 14 | BB24: 18 | BC24: 27 | BD24: 19 | BE24: 15 | BF24: 19 | BG24: 33 | BH24: 38 | BI24: 24 | BJ24: 55 | BK24: 19 | BL24: 17 | BM24: 27 | BN24: 14 | BO24: 21 | BP24: 18 | BQ24: 27 | BR24: 31 | BS24: 49 | BT24: 46 | BU24: 10 | BV24: 7 | BW24: 9 | BX24: 24 | BY24: 10 | BZ24: 31 | CA24: 27 | CB24: 31 | CC24: 24 | CD24: 27 | CE24: 23 | CF24: 25 | CG24: 27 | CH24: 33 | CI24: 31 | CJ24: 31 | CK24: 33 | CL24: 62 | CM24: 66 | CN24: 74 | CO24: 26 | CP24: 22 | CQ24: 36 | CR24: 38 | CS24: 31 | CT24: 43 | CU24: 47 | CV24: 54 | CW24: 41 | CX24: 46 | CY24: 23 | CZ24: 28 | DA24: 27 | DB24: 29 | DC24: 27 | DD24: 50 | DE24: 54 | DF24: 38 | DG24: 57 | DH24: 64 | DI24: 17 | DJ24: 21 | DK24: 31 | DL24: 28 | DM24: 42 | DN24: 50 | DO24: 54 | DP24: 54 | DQ24: 57 | DR24: 46 | DS24: 17 | DT24: 11 | DU24: 23 | DV24: 9 | DW24: 26 | DX24: 18 | DY24: 27 | DZ24: 23 | EA24: 33 | EB24: 18 | EC24: 16 | ED24: 14 | EE24: 22 | EF24: 20 | EG24: 36 | EH24: 32 | EI24: 40 | EJ24: 54 | EK24: 33 | EL24: 55 | EM24: 13 | EN24: 18 | EO24: 18 | EP24: 23 | EQ24: 36 | ER24: 44 | ES24: 47 | ET24: 46 | EU24: 41 | EV24: 55 | EW24: 9 | EX24: 21 | EY24: 27 | EZ24: 23 | FA24: 21 | FB24: 18 | FC24: 33 | FD24: 23 | FE24: 33 | FF24: 46
A25: Cha Growth | B25: =COUNTA(C25:FF25)/1.6 -> 100 | C25: 20 | D25: 28 | E25: 32 | F25: 34 | G25: 42 | H25: 38 | I25: 34 | J25: 38 | K25: 66 | L25: 65 | M25: 13 | N25: 11 | O25: 14 | P25: 24 | Q25: 27 | R25: 38 | S25: 26 | T25: 23 | U25: 50 | V25: 46 | W25: 23 | X25: 18 | Y25: 27 | Z25: 34 | AA25: 37 | AB25: 32 | AC25: 41 | AD25: 39 | AE25: 33 | AF25: 37 | AG25: 7 | AH25: 18 | AI25: 17 | AJ25: 23 | AK25: 16 | AL25: 12 | AM25: 27 | AN25: 23 | AO25: 25 | AP25: 18 | AQ25: 10 | AR25: 14 | AS25: 9 | AT25: 19 | AU25: 26 | AV25: 19 | AW25: 21 | AX25: 16 | AY25: 17 | AZ25: 47 | BA25: 23 | BB25: 18 | BC25: 26 | BD25: 29 | BE25: 37 | BF25: 25 | BG25: 34 | BH25: 39 | BI25: 33 | BJ25: 64 | BK25: 20 | BL25: 28 | BM25: 36 | BN25: 38 | BO25: 32 | BP25: 44 | BQ25: 33 | BR25: 38 | BS25: 58 | BT25: 65 | BU25: 13 | BV25: 21 | BW25: 14 | BX25: 15 | BY25: 32 | BZ25: 25 | CA25: 33 | CB25: 38 | CC25: 33 | CD25: 28 | CE25: 26 | CF25: 25 | CG25: 22 | CH25: 34 | CI25: 37 | CJ25: 32 | CK25: 41 | CL25: 62 | CM25: 66 | CN25: 55 | CO25: 20 | CP25: 18 | CQ25: 23 | CR25: 15 | CS25: 21 | CT25: 19 | CU25: 27 | CV25: 47 | CW25: 25 | CX25: 47 | CY25: 23 | CZ25: 25 | DA25: 18 | DB25: 34 | DC25: 26 | DD25: 37 | DE25: 33 | DF25: 39 | DG25: 33 | DH25: 55 | DI25: 13 | DJ25: 11 | DK25: 9 | DL25: 10 | DM25: 16 | DN25: 19 | DO25: 27 | DP25: 39 | DQ25: 16 | DR25: 47 | DS25: 23 | DT25: 18 | DU25: 36 | DV25: 34 | DW25: 32 | DX25: 32 | DY25: 53 | DZ25: 54 | EA25: 50 | EB25: 74 | EC25: 10 | ED25: 11 | EE25: 23 | EF25: 24 | EG25: 11 | EH25: 19 | EI25: 27 | EJ25: 16 | EK25: 16 | EL25: 37 | EM25: 20 | EN25: 18 | EO25: 31 | EP25: 19 | EQ25: 32 | ER25: 44 | ES25: 48 | ET25: 38 | EU25: 33 | EV25: 47 | EW25: 20 | EX25: 11 | EY25: 14 | EZ25: 15 | FA25: 27 | FB25: 32 | FC25: 34 | FD25: 46 | FE25: 32 | FF25: 36
A26: End Growth | B26: =COUNTA(C26:FF26)/1.6 -> 100 | C26: 16 | D26: 10 | E26: 23 | F26: 10 | G26: 16 | H26: 13 | I26: 27 | J26: 31 | K26: 16 | L26: 28 | M26: 23 | N26: 28 | O26: 32 | P26: 38 | Q26: 32 | R26: 31 | S26: 54 | T26: 55 | U26: 50 | V26: 47 | W26: 16 | X26: 17 | Y26: 13 | Z26: 14 | AA26: 21 | AB26: 19 | AC26: 41 | AD26: 39 | AE26: 50 | AF26: 37 | AG26: 16 | AH26: 21 | AI26: 18 | AJ26: 19 | AK26: 32 | AL26: 44 | AM26: 34 | AN26: 54 | AO26: 58 | AP26: 47 | AQ26: 23 | AR26: 17 | AS26: 27 | AT26: 38 | AU26: 32 | AV26: 44 | AW26: 34 | AX26: 62 | AY26: 66 | AZ26: 65 | BA26: 16 | BB26: 10 | BC26: 27 | BD26: 19 | BE26: 16 | BF26: 31 | BG26: 21 | BH26: 47 | BI26: 32 | BJ26: 47 | BK26: 23 | BL26: 21 | BM26: 23 | BN26: 19 | BO26: 37 | BP26: 25 | BQ26: 41 | BR26: 39 | BS26: 42 | BT26: 65 | BU26: 6 | BV26: 7 | BW26: 18 | BX26: 24 | BY26: 16 | BZ26: 25 | CA26: 20 | CB26: 39 | CC26: 17 | CD26: 37 | CE26: 10 | CF26: 10 | CG26: 27 | CH26: 19 | CI26: 32 | CJ26: 25 | CK26: 34 | CL26: 24 | CM26: 32 | CN26: 45 | CO26: 23 | CP26: 17 | CQ26: 36 | CR26: 28 | CS26: 42 | CT26: 50 | CU26: 48 | CV26: 39 | CW26: 58 | CX26: 56 | CY26: 10 | CZ26: 14 | DA26: 18 | DB26: 14 | DC26: 26 | DD26: 13 | DE26: 13 | DF26: 31 | DG26: 42 | DH26: 19 | DI26: 23 | DJ26: 21 | DK26: 32 | DL26: 24 | DM26: 32 | DN26: 44 | DO26: 34 | DP26: 31 | DQ26: 42 | DR26: 37 | DS26: 16 | DT26: 24 | DU26: 27 | DV26: 19 | DW26: 21 | DX26: 44 | DY26: 34 | DZ26: 54 | EA26: 50 | EB26: 47 | EC26: 26 | ED26: 28 | EE26: 32 | EF26: 33 | EG26: 32 | EH26: 31 | EI26: 40 | EJ26: 62 | EK26: 58 | EL26: 46 | EM26: 13 | EN26: 10 | EO26: 18 | EP26: 24 | EQ26: 32 | ER26: 31 | ES26: 34 | ET26: 23 | EU26: 50 | EV26: 28 | EW26: 13 | EX26: 14 | EY26: 23 | EZ26: 24 | FA26: 16 | FB26: 13 | FC26: 21 | FD26: 24 | FE26: 16 | FF26: 19
A27: Luc Growth | B27: =COUNTA(C27:FF27)/1.6 -> 100 | C27: 13 | D27: 21 | E27: 22 | F27: 33 | G27: 21 | H27: 38 | I27: 34 | J27: 55 | K27: 42 | L27: 64 | M27: 7 | N27: 10 | O27: 23 | P27: 14 | Q27: 10 | R27: 25 | S27: 28 | T27: 23 | U27: 16 | V27: 46 | W27: 20 | X27: 28 | Y27: 37 | Z27: 33 | AA27: 37 | AB27: 50 | AC27: 33 | AD27: 39 | AE27: 50 | AF27: 65 | AG27: 20 | AH27: 14 | AI27: 18 | AJ27: 24 | AK27: 15 | AL27: 31 | AM27: 41 | AN27: 23 | AO27: 25 | AP27: 46 | AQ27: 10 | AR27: 21 | AS27: 22 | AT27: 19 | AU27: 26 | AV27: 19 | AW27: 40 | AX27: 31 | AY27: 41 | AZ27: 27 | BA27: 19 | BB27: 25 | BC27: 27 | BD27: 38 | BE27: 37 | BF27: 50 | BG27: 48 | BH27: 39 | BI27: 67 | BJ27: 46 | BK27: 6 | BL27: 11 | BM27: 9 | BN27: 19 | BO27: 11 | BP27: 31 | BQ27: 20 | BR27: 31 | BS27: 42 | BT27: 28 | BU27: 23 | BV27: 18 | BW27: 22 | BX27: 23 | BY27: 31 | BZ27: 44 | CA27: 28 | CB27: 31 | CC27: 49 | CD27: 65 | CE27: 20 | CF27: 24 | CG27: 22 | CH27: 33 | CI27: 26 | CJ27: 37 | CK27: 48 | CL27: 38 | CM27: 34 | CN27: 38 | CO27: 6 | CP27: 17 | CQ27: 9 | CR27: 19 | CS27: 21 | CT27: 19 | CU27: 33 | CV27: 23 | CW27: 25 | CX27: 18 | CY27: 10 | CZ27: 10 | DA27: 18 | DB27: 14 | DC27: 26 | DD27: 25 | DE27: 41 | DF27: 47 | DG27: 42 | DH27: 37 | DI27: 19 | DJ27: 28 | DK27: 31 | DL27: 38 | DM27: 26 | DN27: 44 | DO27: 34 | DP27: 47 | DQ27: 66 | DR27: 64 | DS27: 7 | DT27: 14 | DU27: 13 | DV27: 14 | DW27: 26 | DX27: 18 | DY27: 27 | DZ27: 15 | EA27: 41 | EB27: 18 | EC27: 10 | ED27: 17 | EE27: 18 | EF27: 14 | EG27: 26 | EH27: 37 | EI27: 20 | EJ27: 39 | EK27: 49 | EL27: 38 | EM27: 26 | EN27: 25 | EO27: 31 | EP27: 38 | EQ27: 27 | ER27: 32 | ES27: 40 | ET27: 62 | EU27: 49 | EV27: 64 | EW27: 13 | EX27: 17 | EY27: 22 | EZ27: 24 | FA27: 36 | FB27: 43 | FC27: 47 | FD27: 31 | FE27: 49 | FF27: 55
A28: Wil Growth | B28: =COUNTA(C28:FF28)/1.6 -> 100 | C28: 16 | D28: 10 | E28: 13 | F28: 18 | G28: 26 | H28: 37 | I28: 41 | J28: 31 | K28: 41 | L28: 27 | M28: 22 | N28: 21 | O28: 22 | P28: 19 | Q28: 36 | R28: 31 | S28: 27 | T28: 54 | U28: 49 | V28: 46 | W28: 6 | X28: 7 | Y28: 13 | Z28: 14 | AA28: 10 | AB28: 25 | AC28: 20 | AD28: 38 | AE28: 33 | AF28: 47 | AG28: 22 | AH28: 17 | AI28: 37 | AJ28: 29 | AK28: 42 | AL28: 37 | AM28: 33 | AN28: 54 | AO28: 57 | AP28: 74 | AQ28: 22 | AR28: 17 | AS28: 31 | AT28: 19 | AU28: 21 | AV28: 43 | AW28: 40 | AX28: 46 | AY28: 41 | AZ28: 46 | BA28: 6 | BB28: 17 | BC28: 10 | BD28: 9 | BE28: 15 | BF28: 18 | BG28: 33 | BH28: 31 | BI28: 33 | BJ28: 27 | BK28: 16 | BL28: 10 | BM28: 22 | BN28: 19 | BO28: 26 | BP28: 25 | BQ28: 41 | BR28: 46 | BS28: 24 | BT28: 27 | BU28: 22 | BV28: 24 | BW28: 36 | BX28: 33 | BY28: 26 | BZ28: 32 | CA28: 54 | CB28: 47 | CC28: 66 | CD28: 56 | CE28: 9 | CF28: 10 | CG28: 19 | CH28: 9 | CI28: 10 | CJ28: 31 | CK28: 13 | CL28: 31 | CM28: 33 | CN28: 46 | CO28: 16 | CP28: 17 | CQ28: 22 | CR28: 33 | CS28: 21 | CT28: 37 | CU28: 27 | CV28: 46 | CW28: 57 | CX28: 64 | CY28: 22 | CZ28: 21 | DA28: 36 | DB28: 33 | DC28: 26 | DD28: 50 | DE28: 47 | DF28: 38 | DG28: 49 | DH28: 74 | DI28: 9 | DJ28: 10 | DK28: 18 | DL28: 23 | DM28: 31 | DN28: 18 | DO28: 40 | DP28: 38 | DQ28: 41 | DR28: 37 | DS28: 19 | DT28: 14 | DU28: 13 | DV28: 28 | DW28: 26 | DX28: 31 | DY28: 21 | DZ28: 31 | EA28: 24 | EB28: 46 | EC28: 19 | ED28: 14 | EE28: 18 | EF28: 23 | EG28: 36 | EH28: 37 | EI28: 47 | EJ28: 39 | EK28: 41 | EL28: 64 | EM28: 6 | EN28: 17 | EO28: 10 | EP28: 15 | EQ28: 15 | ER28: 18 | ES28: 13 | ET28: 31 | EU28: 33 | EV28: 46 | EW28: 20 | EX28: 28 | EY28: 31 | EZ28: 33 | FA28: 26 | FB28: 37 | FC28: 33 | FD28: 54 | FE28: 67 | FF28: 74
A29: Weapon Name | B29: =COUNTA(C29:FF29)/1.6 -> 100 | C29: Short Bow | D29: Reflex Bow | E29: Heavy Crossbow | F29: True Shot | G29: Recurve Bow | H29: Bolas | I29: Flatbow | J29: Springbow | K29: Composite Bow | L29: Mach Bow | M29: Katar | N29: Brass Knuckes | O29: Tekko | P29: Spiked Knuckles | Q29: Boulder Gauntlet | R29: Neko-te | S29: Bagh Nakh | T29: Bo Staff | U29: Stormgloves | V29: Steins | W29: Blowgun | X29: Shiv | Y29: Crowbar | Z29: Switchblades | AA29: Trapeze Wire | AB29: Stiletto | AC29: Loaded Dice | AD29: Contraband | AE29: Alleyknives | AF29: Paired Jittes | AG29: Ethermist | AH29: Needlegun | AI29: Force Rifle | AJ29: Chaos Cannon | AK29: Stone Blaster | AL29: Scattershot | AM29: Sacred Revolvers | AN29: Water Pistol | AO29: Hand Catapult | AP29: Phantasm Generator | AQ29: Greatclub | AR29: Battle Axe and Spiked Shield | AS29: Lochaber | AT29: Double Axe | AU29: Francisca and Half Shield | AV29: Ravager | AW29: Dual Axes | AX29: Headsplitter | AY29: Battle Scythe | AZ29: Labrys | BA29: Trident and Net | BB29: Rapier | BC29: Pilum and Scutum | BD29: Double Flail | BE29: Estoc and Bracer | BF29: Longspear | BG29: Katana and Wazikashi | BH29: Maul | BI29: Foil and Parry Dagger | BJ29: Halberd and Shield | BK29: Flanged Mace and Hard Shield | BL29: Broadsword and Wideshield | BM29: Gurz | BN29: Lance and Shield | BO29: Bec de Corbin and Bastion Shield | BP29: Great Lance | BQ29: Paired Batons | BR29: Spiked Ball and Chain | BS29: Morgernstern | BT29: Lucerne and Temple Shield | BU29: Stormbreaker | BV29: Flamberge | BW29: Frostbrand and Waveshield | BX29: Bearded Axe and Timber Shield | BY29: Sellswords | BZ29: Catalyst | CA29: Phasehammer | CB29: Mordaxt | CC29: Voidblades | CD29: Zweihander | CE29: Flute | CF29: Trumpet | CG29: Bagpipes | CH29: Lyre | CI29: Wardrums | CJ29: Guitar | CK29: Accordion | CL29: Cello | CM29: Violin | CN29: Harp | CO29: Summoning Seal | CP29: Hand Mirror | CQ29: Tomahawks | CR29: Planchette | CS29: Sagaris | CT29: Precipice Lance | CU29: Telescope | CV29: Lamp | CW29: Tentacles | CX29: Compact | CY29: Psalm | CZ29: Aspergillium | DA29: Thurible | DB29: Crosier | DC29: Absolution | DD29: Morningstar | DE29: Caduceus | DF29: Penitent | DG29: Requiem | DH29: Reliquary | DI29: Harpoon | DJ29: Guillotine Bow | DK29: Coffin Bow | DL29: Noose Strung Crossbow | DM29: Deathknell | DN29: Umbral Bow | DO29: Sandpouch | DP29: Ankou Bow | DQ29: Quietus | DR29: Smoke Lantern | DS29: Mindshard | DT29: Hovering Orbs | DU29: Crystallized Memory | DV29: Pendulum Chain | DW29: Crystal Ball | DX29: Ghostly Accompaniment | DY29: Axiom Rod | DZ29: Trepan | EA29: Hourglass | EB29: Marionette | EC29: Obelisk | ED29: Sign of Girru | EE29: Stone Rod | EF29: Sigil Staff | EG29: Unraveller | EH29: Quill Rod | EI29: Crook | EJ29: Glyph | EK29: Cypher | EL29: Arcanite | EM29: Ritual Dagger | EN29: Wormwood | EO29: Torch | EP29: Sickle | EQ29: Icicle | ER29: Seax | ES29: Wanga | ET29: Stang | EU29: Broom | EV29: Vervain | EW29: Elemental Staff | EX29: Dark Wand | EY29: Water Wand | EZ29: Earth Wand | FA29: Air Wand | FB29: Fire Wand | FC29: Aether Wand | FD29: Light Wand | FE29: Intonation | FF29: Staff of Power
A30: Weapon Mech | B30: =COUNTA(C30:FF30)/1.6 -> 100 | C30: initiative bonus, acts sooner in first round | D30: bonus scales with number of enemies of the hunted type present | E30: very high damage, very long reload | F30: bonus to prepared/vow attacks | G30: accuracy while accompanied | H30: increased prone chance or immobilization | I30: accuracy bonus scaling with target's lost health | J30: quicken when attacking endangered enemies | K30: damage bonus scaling with target's dodge value | L30: increased benefit from pinpoint mechanic | M30: dodge bonus after attacking, duration scales with attack speed | N30: increased damage when attacking same enemy as previous turn | O30: gains percentage of target's base damage on attack | P30: chance to stun on reaction and counter attacks | Q30: increased glancing damage | R30: enhanced critical chance immediately after losing hidden status | S30: poison applies even on glancing hits | T30: chance to parry afflictions | U30: delayed secondary damage add after initial attack | V30: dodge bonus on miss, scales with miss amount | W30: increased affliction power with poisons | X30: increased bleeding | Y30: extra damage against full health enemies | Z30: drains extra health and mana | AA30: increased accuracy to next attack after missing, scales with miss amount | AB30: chance for instant death to overwhelm resistance | AC30: critical damage increases on failed critical | AD30: chance to conserve poisons | AE30: penetration while hidden | AF30: prevents counters on parry | AG30: damage and ammo load based on mana, mana ammo | AH30: natural penetration, penetrate ammo | AI30: delays on hit, delay ammo | AJ30: corrupt damage, corrupt ammo | AK30: clobbering damage, earth ammo | AL30: fires random amount of ammo per shot, flechette ammo | AM30: dual ranged, light damage add, light ammo | AN30: mana gain on attack, water ammo | AO30: chance for area damage, fire ammo | AP30: illusory damage, illusory ammo | AQ30: intrinsic delay on hit | AR30: damage on block or enhanced retaliation | AS30: bonus while berserk | AT30: rampage bonus scaling with enemy deaths | AU30: chance to provoke on block | AV30: chance to maximize damage | AW30: quicken on attack while endangered | AX30: damages self at start of turn for stat bonus | AY30: increased massive damage threshold range | AZ30: increased overkill value | BA30: increased prone chance | BB30: increased disarm chance | BC30: increased damage per ally ready to act | BD30: accuracy builds on consecutive hits | BE30: reduced chance attacks are parried | BF30: bonus damage from momentum | BG30: increased damage for a period after being damaged | BH30: bonus to next damage when quickened | BI30: bonus to reaction ability damage | BJ30: quicken team on parry | BK30: chance to ignore glancing hits at full health | BL30: increased threshold charge from damage | BM30: increased healing and purge based on proximity to death | BN30: chance to avoid block on attack | BO30: highest intrinsic block chance | BP30: increased magic resistance | BQ30: lucky parry, checks twice | BR30: bonus damage based on corruption on self | BS30: damage increases based on time since last action | BT30: overheals spread to allies | BU30: air/lightning damage add | BV30: fire damage add | BW30: earth damage add | BX30: water/ice damage add | BY30: chaos damage add | BZ30: increased personal enhancements | CA30: intrinsic phasing chance | CB30: increased damage while barrier is active | CC30: dark damage add | CD30: light damage add | CE30: enhancement and weakness duration | CF30: increased effect and duration of enhancements and weaknesses on first turn | CG30: increased power of weaken effects | CH30: increased power of conditions already present on unit | CI30: minor quicken to all allies on turn | CJ30: increased enchant power while hidden | CK30: grants scorn against next attack | CL30: increased magic damage but increased mana costs | CM30: improved retaliation and reflection | CN30: increased effects of light-based conditions | CO30: increased summoning speed | CP30: increased retaliation effects on self | CQ30: companion critical chance and damage | CR30: increased spell critical chance | CS30: bonus damage while companion is alive | CT30: endangered damage, bonus when both user and target are endangered | CU30: increased damage for each enemy damaged during turn | CV30: elemental switching with companion element | CW30: reduce affliction resistance on hit | CX30: intrinsic heal siphon and pain link with companion | CY30: increased accuracy/damage/healing while lucky active | CZ30: increased healing to endangered allies | DA30: purge power bonus | DB30: increased damage shield granted | DC30: reduced vitality consumption | DD30: intrinsic ghost touch | DE30: increased incapacitate potency and landing chance | DF30: increased damage and speed when alone | DG30: increased contagion spread | DH30: increased countdown duration, attacks increase countdown power | DI30: increased power from damage afflictions | DJ30: extra damage against lowest health enemy | DK30: intrinsic delay on hit | DL30: increased damage based on tired duration on target | DM30: extra damage to next ally attacking same target | DN30: increased damage after purging or disenchanting | DO30: attacks have chance to be insidious | DP30: increased damage against more enemies present | DQ30: increased damage against solo enemies | DR30: illusory damage add while endangered | DS30: dodge and reflection bonus after attacking | DT30: ranged damage based on magic power | DU30: procs avert on target when attacking | DV30: increased channel duration | DW30: reveals target health after attack | DX30: mana damage | DY30: improves possession effects on allies | DZ30: additional damage based on illusory damage on target | EA30: reduces quicken/delay tolerance | EB30: improved damage when possessing enemies | EC30: increased counterspell value | ED30: next attack deals extra fire damage | EE30: grants clobbering to companion | EF30: improved spell criticals when alone | EG30: chance to proc disenchant on attack | EH30: increased trap damage | EI30: increased resistance piercing on attacks | EJ30: critical multiplier applies to damage adds on critical | EK30: deals portion of countdown damage present on target | EL30: damage scales with total mana used | EM30: drains life on kill | EN30: debuffs also delay | EO30: fire bleed on melee attack | EP30: bonus damage based on corruption on target | EQ30: bonus damage based on target's slow value | ER30: last action each turn has improved magic power | ES30: improved heal and purge per affliction on ally | ET30: damage dealt heals companion by small percentage | EU30: increased affliction power per affliction on self | EV30: improved hexes | EW30: primary elemental power | EX30: dark power | EY30: water power | EZ30: earth power | FA30: air power | FB30: fire power | FC30: arcane power | FD30: light power | FE30: channel power | FF30: magic power based on mana
A31: Weapon Stats | B31: =COUNTA(C31:FF31)/1.6 -> 0
A32: Armor Name | B32: =COUNTA(C32:FF32)/1.6 -> 0
A33: Armor Stats | B33: =COUNTA(C33:FF33)/1.6 -> 0
A34: Ability Count | C34: =COUNTA(C35:C69) -> 25 | D34: =COUNTA(D35:D69) -> 25 | E34: =COUNTA(E35:E69) -> 25 | F34: =COUNTA(F35:F69) -> 25 | G34: =COUNTA(G35:G69) -> 25 | H34: =COUNTA(H35:H69) -> 25 | I34: =COUNTA(I35:I69) -> 0 | J34: =COUNTA(J35:J69) -> 25 | ... FF34: =COUNTA(FF35:FF69) -> 0
A35: Major 1 | B35: =COUNTA(C35:FF35)/1.6 -> 43.75 | C35: Adroit Momentum – Ranged attack with pinpoint and momentum enhancing accuracy | D35: Bane of the Weakest – Ranged attack that targets a single target. Deals damage based on bloodlust to target and all enemies of the same type. (Huntsman) | E35: Close Fire – Ranged attack with pointblank (Crossbowman) | F35: Accuracy Snipe – Ranged attack that causes accuracy weakness on critical (Marksman) | G35: Eagle Eye Shot – Ranged attack with distant, pinpoint, and unerring. Consumes aim (Falconer) | H35: Arrow Spray – Consume aim to make number of random targeting ranged attacks based on aim (Bounty Hunter) | J35: Artery Nick – Ranged attack with pinpoint, that causes bleed based on pinpoint (Poacher) | K35: Arrow Massacre – Ranged attack that causes storm damage three times based on overkill (Sharpshooter) | L35: Ambush Rain – Ranged attack against all enemies at full health, requires preparation. (Toxophilite) | W35: All Down to Me – Powerful ranged attack against single that requires alone and consumes combat advantage (Bandit) | X35: All Out Bleeding – Melee attack that consumes all advantage and causes increased bleeding based on advantage used (Cutthroat) | Y35: Advantageous Ambush – Melee attack against full health that generates advantage (Burglar) | Z35: Accuracy Theft – Lowers target accuracy and raises the Thief's own accuracy. (Thief) | AA35: All Out Advantage, Reliable – Melee attack consuming all advantage that deals increased damage but has reduced accuracy for each advantage spent. Consumes no advantage on a miss (Acrobat) | AB35: All Out Advantage, Final – Extremely powerful attack that consumes all combat advantage, up to 11. Also grants increased critical damage (Multiplier Advantage^2 * 5%, Critical Damage: Advantage *10%) (Assassin) | AC35: Advantageous Cascade – Ranged attack that consumes advantage, cascades and consumes another advantage on each critical (Brigand) | AD35: All Out Advantage, Empowered– Melee attack that consumes all advantage to deal extra damage. Deals between 106% to 586% damage (Smuggler) | AE35: Acid Flanking – Melee attack versus flanked enemy with earth bleed (Skulk) | AF35: Acrid Smoke Strike – Ranged attack that grants Ninja hidden and earth retaliation and consumes advantage (Ninja) | AQ35: Breathtaking Blow – Melee attack that consumes rage to deal clobbering damage and exhaust foe. (Brute) | AR35: Charging Ambush – Melee attack against column. Front target must have full health (Raider) | AS35: Backbiting Exertion – Melee attack with lower accuracy and backbiting. If attack misses, take damage and reattempt once (Berserker) | AT35: Berserk Rampage – Melee attack requiring berserk that deals additional damage based on each enemy killed in battle (Marauder) | AU35: Bloodlust Response – Melee attack with bloodlust following a block (Viking) | AV35: Awesome Cleave – Melee attack versus single that damages all other enemies against combined defense of primary and secondary target (Vandal) | AW35: Amplified Savagery – Melee attack with backbiting and amplification, can be used berserk (Fury) | AX35: Bloodlust Bite – Melee attack with bloodlust requiring rage (Cannibal) | AY35: Approaching Victory – Melee attack that quickens all based on overkill (Destroyer) | AZ35: Animalistic Attack – Melee attack based on current animal form. Consumes rage (Beastlord) | BA35: All-in Strike – Melee attack with high damage, high critical damage, and low accuracy. Gladiator becomes prone on miss (Gladiator) | BB35: Careful Strike – Melee attack with increased accuracy and lower damage (Duelist) | BC35: Inevitable Strike – Melee attack that requires expertise that is unblockable, unerring, and unparryable (Phalanx) | BD35: After Image Blow – Two attacks against one target, requires haste (Dervish) | BE35: Accurate Focus – Melee attack that grants focus if pinpoint value is high enough (Fencer) | BF35: Dash of Expertise – Melee attack versus a column that requires expertise and quickens the user (Lancer) | BG35: Amplification Exploit – Amplified attack, consumes half of expertise, requires minimum expertise (Samurai) | BH35: Counter Breaker – Melee attack that lowers target’s counter damage (Dreadnaught) | BI35: Aorta Slash – Melee attack with penetrate that causes high damage, short term bleed (Swashbuckler) | BJ35: Allied Assistance – Warlord makes a melee attack against the target of each ally’s single target attack, consuming expertise with each attack (Warlord) | CE35: Charming Shot – Ranged attack that charms target (Minstrel) | CF35: Ballad of Cinders – Fire magic damage versus column and grant all allies fire damage add with next attack (Jester) | CO35: Astral Construct – Summons an Eros-enhanced astral construct companion. (Conjurer) | CP35: Bleak Frost Spirit – Single-target water magic attack. Grants the Occultist water retaliation. Consumes Thanatos resource. (Occultist) | CQ35: Attendant Apocalypse – Prepared ability. When the companion scores a critical hit, triggers a high-damage magic attack against all enemies. Reserves mana while held. (Shaman) | CR35: Betrayal in Darkness – Dark magic attack versus all enemies. Possesses enemies on critical hit. (Medium) | CS35: Blunting Charge– Mounted attack that causes the entire column's next attack to be minimized. (Animist) | CT35: Foreboding Spirit – Untyped countdown placed on a target with mana damage. (Spiritualist) | CU35: Constellation – Light countdown placed on all enemies. Requires Eros side of scale. (Astrologer) | CV35: Bound Efreet – Summons a bound efreet companion. Requires Thanatos side of scale. (Vizier) | CW35: Alien Impact – Chaos damage versus all enemies. The Alienist takes illusory damage on use. (Alienist) | CX35: Act of Creation – Raises all allies and grants them regeneration. Requires high Eros scale position. (Pact Master) | DS35: Confusion Spike – Arcane magic attack and confuse. (Telepath) | DU35: Amplified Forgetfulness – Causes all enemies to lose mana with amplification on each use. If any enemy ends up with zero mana, deals damage based on the extra mana lost and resets amplification. (Amnesiac) | DV35: Burning Gaze – Channeled ability that causes fire damage for the duration of the channel and fire bleed on critical. (Hypnotist) | DW35: Death Prediction – Magic attack with culling. Both culling and damage are enhanced by influence. (Diviner) | DX35: Call to Conflict – Possess two random enemies to attack one another. (Haunted) | DY35: Allied Influence – Target ally influences enemies with each attack during their next turn. One influence per attack per target. Benefits allies with multi-hit or area attacks. (Mastermind) | DZ35: Agony Amplification – Target takes additional illusory damage whenever it is damaged. Requires influence. (Mindbleeder) | EA35: Chronal Bleed – Untyped bleed based on target health and timer. Higher damage to fast targets and longer duration on targets sooner to act. (Chronomancer) | EB35: Battle of Wills – Long channeled ability that deals arcane damage and possesses target if not disrupted. Deals arcane damage to the Puppet Master if disrupted. (Puppet Master) | EM35: Accumulating Hex – Afflicts target with untyped hex with damage increasing every iteration (Cultist) | EN35: Blood Gust – Air attack versus all with bloodlust (Warlock) | EO35: Blast Effigy – Area fire damage that has increased damage and piercing based on damage afflictions on target (Effigist) | EP35: Acid Malefaction – Magic affliction that causes earth bleed and malediction (Dustbringer) | EQ35: Chilling Wave – Water magic versus all that delays (Crone) | ER35: Arcane Malediction – Arcane magic attack versus all maledicted enemies (Hedgemage) | ES35: Absolution – Causes all maledicted to grant life drain to attacks against them. Torment. (Mambo) | ET35: Cemetery Dust – Incapacitate target enemy and lower its affliction resistance (Bokor) | EU35: Acid Criterion – Afflicts target with earth bleed and defense weakness. Cannot be removed until it deals a set amount of damage (Hag) | EV35: Affliction Manifestation – Deals damage to target enemy based on damage afflictions present on it (Malefax)
A36: Major 2 | B36: =COUNTA(C36:FF36)/1.6 -> 43.75 | C36: Aimed Momentum – Ranged attack that generates extra aim based on momentum | D36: Bane Splinter – Prepared ranged attack that determines target on preparation. Deals damage to all enemies of same type as target (Huntsman) | E36: Delaying Repetition – Multiple ranged attacks with delay consuming all aim (Crossbowman) | F36: Aimed Assistance – Ranged attack consuming aim. Causes Marksman to attack target whenever an ally attacks the target, consuming aim. Ends when Marksman does not have enough aim to make this attack (Marksman) | G36: Eyestrike Swoop – Ranged attack that attacks alongside falcon, causing blind and delay (Falconer) | H36: Blunted Arrows – Minimized ranged attack with clobbering and disrupt (Bounty Hunter) | J36: Aspect of Death – Deal damage to aim target based on aim at the beginning of each turn. Consume aim at beginning of turn (Poacher) | K36: Arrow Stream – Ranged attack versus column, consuming aim. Deals more damage to targets in back (Sharpshooter) | L36: Disintegrating Arrow – Ranged earth attack that deals corruption with massive damage (Toxophilite) | W36: All Out Advantage, Major – Powerful melee attack that consumes all advantage up to 6 (Multiplier: Advantage^2*9%) (Bandit) | X36: Backstab Rend – Dualwield melee attack that requires flanking. Deals extra damage if both attacks hit (Cutthroat) | Y36: Ambush Decimation – Melee attack with decimate against enemy at full health (Burglar) | Z36: Advantageous Leech – Melee attack with life drain that generates advantage based on life drained (Thief) | AA36: All Out Consequence – Consumes all advantage to attack enemy and afflict it with countdown based on advantage used. Ranged attack (Acrobat) | AB36: Bloodbath Slaughter – Melee attack consuming advantage that causes bleeding on all enemies based on overkill (Assassin) | AC36: All Out Advantage, Enhanced – Uses up to 8 Combat Advantage to deal increased damage with a melee attack (Multiplier: Advantage^2 * 7%) (Brigand) | AD36: Careful Poisoning Strike – Prepared venomous melee attack that conserves poison (Smuggler) | AE36: All Out Advantage, Assured – Melee attack that consumes all advantage to deal extra damage, also gaining increased accuracy (Skulk) | AF36: Black Absolution – High damage melee attack that consumes a high amount of advantage. Consumes no advantage on critical (Ninja) | AQ36: Brutal Consequences – High damage melee attack and generate rage, but take damage at beginning of next turn (Brute) | AR36: Fury Tremor – Melee attack against all requiring raging that consumes all rage to enhance damage and knock enemies prone (Raider) | AS36: Berserk Exertion – Melee attack with lower accuracy that attacks randomly and requires berserk. If attack misses, take damage and reattempt once (Berserker) | AT36: Bloodlust Rampage – Melee attack that has increased bloodlust value for each enemy killed in battle (Marauder) | AU36: Continuous Turmoil – Attack, then attack all on critical (Viking) | AV36: Brink of Death – Melee attack with ruthless damage. Only becomes available for one turn immediately after dealing enough damage (Vandal) | AW36: Blood Purity – Melee attack with increasing bleed, resets if barbarian attacks the target suffering from this bleed. (Fury) | AX36: Devour the Sleeping – Culling melee attack against incapacitated target. Heal on kill (Cannibal) | AY36: Cascading Critical – Melee attack that cascades to random target on critical (Destroyer) | AZ36: Bull’s Rampage – Three random melee attack that cause bleed and requires rage (Beastlord) | BA36: Deflection Gambit – High damage, low accuracy melee attack that randomly attacks another target, enemy or ally, on miss. Requires expertise (Gladiator) | BB36: Critical Disarm – Melee attack that disarms on critical (Duelist) | BC36: Overwhelming Strike – Melee attack with overwhelming. Requires expertise (Phalanx) | BD36: Burst Succession – Dual-wield attack that damages all enemies with second attack based on dual-wield attack speed. (Dervish) | BE36: Beat Attack – Unparryable melee attack (Fencer) | BF36: Expert Charge – Melee attack against column requiring mounted that is enhanced by expertise (Lancer) | BG36: Amplification Rend – Melee attack with both weapons that stacks amplification if both attacks hit. (Samurai) | BH36: Expert Shatter – Melee attack that has a shatter value based off expertise, needs to be prepared. (Dreadnaught) | BI36: Bleeding Feint – Enhances parry chance of swashbuckler and compels target to attack her. If she parries the target before next turn, she attacks the target and causes an untyped bleed. Requires expertise (Swashbuckler) | BJ36: Directing Blow – Melee attack that enhances accuracy of all allies for their next attack based on expertise (Warlord) | CE36: Crescendo of Bleeding – Applies bleed to target enemy. Bleed value scales with current Crescendo count. (Minstrel) | CF36: Chaos Exposure – Afflict target enemy with a random elemental exposure (Jester) | CO36: Companion Flame – Companion casts a fire spell targeting an enemy row. Uses companion's stats and mana from the companion. (Conjurer) | CP36: Corruptive Sleep – Corrupt water damage and incapacitate versus one target. (Occultist) | CQ36: Attendant Resurrection – Prepared ability. When the companion scores a critical hit, raises the Shaman if she is currently dead. Reserves mana while held. (Shaman) | CR36: Blended Shadow – Magic attack enhanced by both light power and dark power simultaneously. (Medium) | CS36: Dark Anima – Dark magic damage versus all enemies. Consumes Thanatos resource. Requires Thanatos. (Animist) | CT36: Hollow Armor – Conjures a hollow armor companion that uses improved defensive and reaction abilities. Power scales with Eros scale position. (Spiritualist) | CU36: Dark Stars – Dark magic attack versus all enemies. Drains life on critical hit. Requires endangered. (Astrologer) | CV36: Corrupt Transformation – Requires the Vizier to be on the Thanatos side of scale and to be suffering corrupt damage equal to at least 20% of her total health. On activation, deals corrupt damage to all enemies. For the rest of battle, grants magic power that scales with corrupt damage currently on the Vizier and grants the companion a corrupt damage add to all attacks. (Vizier) | CW36: Alien Influence Bolt – Chaos damage versus a single enemy. Damage is enhanced by the illusory damage currently on the Alienist. (Alienist) | CX36: Act of Destruction – Deals corrupt heartstrike damage to all enemies. Requires high Thanatos scale position. (Pact Master) | DS36: Disorienting Wave – Stuns and disrupts each enemy based on influence. (Telepath) | DU36: Bleeding Memory – Afflicts target with mana burn and illusory bleed. (Amnesiac) | DV36: Caustic Stare – Channeled ability that causes earth vulnerability and earth bleed for the duration of the channel. (Hypnotist) | DW36: Disastrous Foresight – Deals illusory damage to all enemies based on their current countdown values. (Diviner) | DX36: Fated Superstition – Afflicts target with low mana with fire countdown. Deals extra damage if target is at low mana when it triggers. (Haunted) | DY36: Compelling Ploy – Possesses ally who then compels the target of its attack. (Mastermind) | DZ36: Backbiting Affliction – Affliction on target that deals illusory damage and generates influence on the psychic's turn. Causes physical backbiting to the Mindbleeder each turn. (Mindbleeder) | EA36: Entropism – Magic attack versus all that deals damage based on the duration and value of bleeds on targets. (Chronomancer) | EB36: Call for Obstruction – Possess an ally and delay an enemy based on the ally's attack. (Puppet Master) | EM36: Anathema Hex – Afflicts target with dark hex. Requires three enemies afflicted with malediction (Cultist) | EN36: Blood Pool – Untyped magic bleed enhanced by bloodlust (Warlock) | EO36: Blister – Fire damage to target and extra damage next time hit (Effigist) | EP36: Acidic Suffering – Magic affliction that causes earth bleeding (Dustbringer) | EQ36: Frigid Blast – Deal water damage to all enemies in inverse relationship to speed (Crone) | ER36: Chaos Hex – Afflicts target with a hex that deals random elemental damage on each iteration (Hedgemage) | ES36: Channeled Drain – Channeled dark magic attack with life drain (Mambo) | ET36: Corpse Blast – Damage each enemy enhanced by each creature that has died (Bokor) | EU36: Blood Criterion – Afflicts target with untyped bleed. Cannot be removed until it deals a set amount of damage (Hag) | EV36: Call on Covenant – Powerful magic spells based on current covenant ability (Malefax)
A37: Major 3 | B37: =COUNTA(C37:FF37)/1.6 -> 43.75 | C37: Coordinated Shot – Ranged attack with quick preparation that grants increased accuracy and damage to next attack versus target | D37: Bleeding Bane – Ranged attack that targets a single enemy. That enemy and all that share that type take an untyped bleed (Huntsman) | E37: Hard Shot – Ranged attack with stun and disrupt (Crossbowman) | F37: Distant Aversion – Ranged attack against back row that causes aversion. Prepared (Marksman) | G37: Falcon Bait – Ranged attack against a single target alongside attack from falcon (Falconer) | H37: Elemental Stalker – Ranged attack against target suffering from an elemental vulnerability. Deals elemental damage of each type target is vulnerable to (Bounty Hunter) | J37: Bloodlust Arrow – Ranged attack against single with bloodlust. Consumes mana (Poacher) | K37: Charity Snipe – Ranged attack that causes healing power weakness on critical (Sharpshooter) | L37: Distant Doom – Distant ranged attack with reduced accuracy but increased critical chance and critical damage (Toxophilite) | W37: Desperation Drain – Melee attack against single target with life drain. Advantage cost reduced if alone (Bandit) | X37: Bloodseeker Slash – Melee attack against bleeding target (Cutthroat) | Y37: Disenchanting Ambush – Melee attack against full health that disenchants (Burglar) | Z37: Afterthought Strike – Melee attack that also attacks another random enemy, requires dualwielding (Thief) | AA37: Flip Away – Ranged attack and avert following a dodge. (Acrobat) | AB37: Contract Kill – Melee attack that can only target enemy with a contract on it. Delivers double results of contract (Assassin) | AC37: Ambush Shot – Ranged attack requiring full health that flanks and stuns target (Brigand) | AD37: Damage Theft – Melee attack that lowers enemy damage and raises own damage (Smuggler) | AE37: Dark Rend – Dualwield melee attack that grants hidden and afflicts target with blind if both attacks hit (Skulk) | AF37: Double Advantage – Melee attack that hits twice and grants combat advantage if both hit, costs mana, requires dual wield (Ninja) | AQ37: Dangerous Ruse – Melee attack with reduced accuracy that causes damage to self on a miss (Brute) | AR37: Glancing Blood – Melee attack that causes bleed on glancing hit based on glancing damage dealt (Raider) | AS37: Berserk Ignorance – Melee attack and purge any conditions that occurred since last turn. Requires berserk (Berserker) | AT37: Clobbering Rampage – Melee attack that has increased clobbering value for each enemy killed in battle (Marauder) | AU37: Furious Tumult – Melee attack with bloodlust that consumes rage (Viking) | AV37: Brink of Inferno – Fire melee attack that grants fire damage add. Only becomes available for one turn immediately after dealing enough damage (Vandal) | AW37: Critical Purity – Melee attack with increased critical chance and critical damage, but with reduced accuracy, resets if the barbarian misses. (Fury) | AX37: Devour Whole – Cull target enemy to heal, gain mana, and gain all enchantments on target enemy (Cannibal) | AY37: Critical Balance – Melee attack that cannot critical, but deals additional damage based on critical damage (Destroyer) | AZ37: Call Rampaging Rhino – Summons a rampaging rhino mount with trample abilities (Beastlord) | BA37: Disarming Gambit – Melee attack with disarm, but gladiator becomes disarmed if this fails (Gladiator) | BB37: Disarmed Disaster – Alpha. High damage melee attack versus disarmed enemy (Duelist) | BC37: Phalanx Combo – Melee attack against single enemy with damage enhanced by ready allies (Phalanx) | BD37: Critical Succession – Dual-wield attack with increased critical chance and critical damage for second attack based on dual-wield attack speed. (Dervish) | BE37: Critical Exploit – Damage with increased critical chance and damage based on expertise, enhances critical chance and damage, consumes all expertise (Fencer) | BF37: Extended Penetration – Melee attack with penetration. Next melee attack also has penetration based on expertise (Lancer) | BG37: Bushido Bleed – Melee attack against enemy that causes untyped bleed. Enemy attack Samurai first and bleed is enhanced by enemy’s damage (Samurai) | BH37: Fortifying Slash – Melee attack that grants user fortified, requires expertise (Dreadnaught) | BI37: Desperate Hew – Melee attack with high critical chance and damage requiring endangered (Swashbuckler) | BJ37: Disruption Wave – Prepared melee attack versus all enemies that disrupts (Warlord) | CE37: Crescendo of Pain – Magic attack against target enemy. Damage scales with current Crescendo count. (Minstrel) | CF37: Chaotic Note – Deals random elemental damage and adds target to audience (Jester) | CO37: Companion Lightning – Companion casts an air storm spell. Uses companion's stats and mana from the companion. (Conjurer) | CP37: Drown – Water bleed against target. (Occultist) | CQ37: Consistency of Eternity – Magic attack with increased minimum damage. Minimum scales with Eros scale position. Costs mana. (Shaman) | CR37: Chant of Eros – Channeled light magic attack that generates Eros resource each tick. (Medium) | CS37: Doubling Animation – Buffs the companion so it takes two turns in a row for its next turn. (Animist) | CT37: Lightning Spirits – Air hex against a single target with amplification. (Spiritualist) | CU37: Fanning Flame – Fire countdown placed on target. Increases in value each time any critical hit occurs. (Astrologer) | CV37: Corruption Aura – Deals corrupt bleed to all enemies. Requires Thanatos Full scale position. Costs Thanatos resource each turn to maintain. Grows in power up to four times. Toggled. (Vizier) | CW37: Alien Presence – Magic illusory attack enhanced by the companion. Uses mana from the companion. (Alienist) | CX37: Action Binding – For a period, the Pact Master makes an attack whenever her companion makes an attack. (Pact Master) | DS37: Heightened Disruption Spike – Magic attack that disrupts. If the Telepath has extra mana when used, repeats based on influence and available mana against random targets. (Telepath) | DU37: Burning Mind – Fire magic attack versus target with mana burn. Triggers mana burn effect on all enemies. (Amnesiac) | DV37: Dream and Nightmare – If target is not incapacitated, incapacitate them. If they are incapacitated, remove incapacitation and deal high damage. (Hypnotist) | DW37: Divination Strike – Magic attack with increased critical chance that cannot be countered. (Diviner) | DX37: Final Possession – Arcane attack against single enemy that possesses if it kills. (Haunted) | DY37: Counter Ploy – Magic attack that requires influence on target. Target's next attack is countered. (Mastermind) | DZ37: Brain Hemorrhage – Causes short duration, high damage illusory damage bleed. (Mindbleeder) | EA37: Entropy Unleashed – Decimate storm attack against random enemies. (Chronomancer) | EB37: Domination – Possess target enemy. Requires influence. Can be sustained each turn to choose the target of the enemy's possession. Mana cost to sustain reduced based on influence. (Puppet Master) | EM37: Black Blood Wave – Dark bleed against all enemies (Cultist) | EN37: Blood Whirlwind – Targets maledicted enemy. All enemies adjacent to target gain untyped bleed (Warlock) | EO37: Burning Malefaction – Deals fire damage with piercing, causes malediction on target (Effigist) | EP37: Brittleness – Causes earth vulnerability to each maledicted, maledicted gain stacking lowered defense when attacked with earth. Torment. (Dustbringer) | EQ37: Frigid Bolt – Deal water damage in inverse relationship to speed (Crone) | ER37: Chaos Malediction – Deals chaos damage to all maledicted enemies (Hedgemage) | ES37: Crippling Fetish – Afflict target enemy with corruption, damage weakness, and defense weakness based on highest life of a defeated enemy (Mambo) | ET37: Corpse Explosion – Dark magic attack that culls target and damages all enemies based on target’s max health if it kills (Bokor) | EU37: Corruption of the Swamp – Dark magic attack against all maledicted that deals corruption (Hag) | EV37: Compounding Misery – Places a stacking untyped hex on each maledicted enemy (Malefax)
A38: Major 4 | B38: =COUNTA(C38:FF38)/1.6 -> 43.75 | C38: Delaying Jolt – Ranged attack with delay against stunned target | D38: Blood Trail – Ranged attack that consumes aim to cause bleed and lowers dodge (Huntsman) | E38: Hard Vow – Prepared ranged attack that chooses target on preparation. Delays target on preparation and stuns on use (Crossbowman) | F38: Find the Hole – Ranged attack with penetration (Marksman) | G38: Falcon Call – Summons a falcon pet. The falcon attacks the Falconer’s aim target by default. (Falconer) | H38: Incapacitation Vow – Prepared ranged attack that selects target on preparation. Incapacitates target on use (Bounty Hunter) | J38: Blood Hunger Shot – Ranged attack enhanced by number of endangered enemies (Poacher) | K38: Critical Trickshot - Ranged attack that considered critical with extremely high critical damage triggering if trickshot occurs. (Sharpshooter) | L38: Essential Beginning – Ranged attack against full health requiring aim, deals 20% heartstrike (Toxophilite) | W38: Desperation Onslaught – Multiple random ranged attacks consuming all advantage. The advantage cost per attack is reduced to half if alone (Bandit) | X38: Bloody Evisceration – Melee attack against enemy with stacking bleed that deals additional damage based on bleed (Cutthroat) | Y38: Draining Slash – Melee attack from hidden that drains life. Consumes advantage (Burglar) | Z38: All Out Advantage, Superior – Melee attack that consumes all advantage to deal extra damage. Deals between 108% to 492% damage. (Thief) | AA38: Front Flip Kick – Prepared melee attack with momentum. Automatically prepared after Somersault Dodge (Acrobat) | AB38: Culling Cascade – Ranged attack which cascades to a random target if original target is brought to endangered status, new target must be different (Assassin) | AC38: Chaos Backstab – Ranged attack requiring hidden with chaos damage and wild damage (Brigand) | AD38: Flanking Rend – Dual wield attack against flanked enemy that deals extra damage if both attacks hit (Smuggler) | AE38: Deft Touch – Insidious melee attack (Skulk) | AF38: Double Assurance – Dual-wield melee attack with guaranteed critical for second attack if first attack kills (Ninja) | AQ38: Deliberate Clobber – Melee attack with increased accuracy, critical chance, and clobbering. Requires rage and delays user (Brute) | AR38: Glancing Stun – Melee attack that causes stun on glancing hit based on glancing damage dealt (Raider) | AS38: Berserk Strike – Melee attack that causes berserk to user. Can be used while berserk, but becomes random in that case and extends berserk (Berserker) | AT38: Clobbering Rend – Two melee attacks against a single target. Uses clobbering if both attacks hit (Marauder) | AU38: Razor Shield – Prepared melee attack with high untyped bleed. Enhanced by blocks made since preparation. (Viking) | AV38: Brink of Onslaught – Three randomly targeting melee attacks. Only becomes available for one turn immediately after dealing enough damage (Vandal) | AW38: Endless Exchange – Melee attack that causes tired for self and target. Tired duration increased for target and decreased for herself based on rage (Fury) | AX38: Gnashing Consumption – Melee attack that causes untyped bleed on target. Requires the Cannibal to have received enough healing (Cannibal) | AY38: Destroy Armor – Melee attack with shattering that causes fragile to the target (Destroyer) | AZ38: Feral Health Strike – Melee attack that heals user. Heals extra if attack kills (Beastlord) | BA38: Exciting Exchange – Melee attack that cannot be parried but is always countered (Gladiator) | BB38: Disarming Killer – Melee attack with cull against disarmed target (Duelist) | BC38: Phalanx Decimation – Melee attack with decimate enhanced by ready allies (Phalanx) | BD38: Double Rend – Dualwield melee attack that hits twice with each weapon. If all attacks hit, deal extra damage (Dervish) | BE38: Exact Stroke – Melee attack with high accuracy and pinpoint (Fencer) | BF38: Lancing Bleed – Melee attack that causes untyped bleed, procs the same attack against the target behind, with chance for behind that (Lancer) | BG38: Bushido Blow – Melee attack against enemy. Enemy attacks Samurai first and damage enhanced by enemy’s damage (Samurai) | BH38: Garrison Blow – Melee attack that provokes target and enhances defense (Dreadnaught) | BI38: Expert Blow, Supreme – Melee attack that requires expertise (Swashbuckler) | BJ38: Evading Blow – Melee attack that enhances dodge of all allies until their next attack based on expertise (Warlord) | CE38: Drowning Shot – Ranged attack that causes short duration water bleed on target (Minstrel) | CF38: Chaotic Refrain – Deal chaos magic damage to all enemies in audience (Jester) | CO38: Dedicated Offensive – Magic attack against a single target. The companion targets the same enemy until this ability is used again or the enemy dies. (Conjurer) | CP38: Falling Icicles – Piercing water magic storm. (Occultist) | CQ38: Cultivate Alraune – Summons an alraune companion. (Shaman) | CR38: Chant of Thanatos – Channeled dark magic attack that generates Thanatos resource each tick. (Medium) | CS38: Light Anima – Light magic damage versus all enemies. Consumes Eros resource. Requires Eros. (Animist) | CT38: Mass Hex – Afflicts all enemies with untyped hex. (Spiritualist) | CU38: Frost Storm – Water magic storm. Incapacitates each enemy struck based on the number of critical hits scored against it. (Astrologer) | CV38: Corruptive Touch – Close dark magic attack with a chance to proc all damage as corrupt. (Vizier) | CW38: Alien Tentacles – Four random magic attacks, each dealing a different elemental damage type. (Alienist) | CX38: Corruption Blast – Corrupt damage and delay versus all enemies. (Pact Master) | DS38: Heightened Flame – Fire magic damage. If the Telepath has extra mana when used, repeats against the same enemy with each extra cast. (Telepath) | DU38: Flame Beam – Fire magic attack versus column. (Amnesiac) | DV38: Fires of Command – Piercing fire magic attack that possesses the target if enough resistance is ignored. Possession chance increased by influence on target. (Hypnotist) | DW38: Diviner's Blast – Arcane magic attack versus all. (Diviner) | DX38: Haunting Chant – Channeled ability that lowers the target's mana and deals damage based on how low it is. (Haunted) | DY38: Defensive Possession – Possesses ally and enhances their defense. (Mastermind) | DZ38: Echoing Mindblast – Attack target and damage all influenced. (Mindbleeder) | EA38: Gathering Time Storm – Amplified magic attack that damages allies and enemies, delaying enemies and quickening allies. (Chronomancer) | EB38: Ensorcelled Mind – Whenever any enemy attacks the Puppet Master before her next turn, that enemy attacks them in response. (Puppet Master) | EM38: Crimson Hex – Untyped hex that maledicts target (Cultist) | EN38: Bloodlust Storm – Air magic storm attack with bloodlust (Warlock) | EO38: Burning, Mass – Fire bleed against all enemies (Effigist) | EP38: Disintegrate Mind – Afflict target with permanent magic power and magic resistance weakness and cause mana loss; reserves mana until purged or enemy dies (Dustbringer) | EQ38: Frigid Countdown – Afflicts target with water countdown that deals damage in inverse relationship with its speed (Crone) | ER38: Chaos Malefaction – Chaos damage against single enemy that afflicts them with malediction (Hedgemage) | ES38: Curative Vampirism – Drain life from a single enemy. If this attack kills, also purge witch doctor (Mambo) | ET38: Corruption Anathema – Dark corruption attack versus all maledicted enemies. Requires at least four maledicted enemies. (Bokor) | EU38: Curse Criterion – Afflicts target with dark hex and curse. Cannot be removed until it deals a set amount of damage (Hag) | EV38: Contagion Malediction – Triggers contagion of each malediction or applies contagion (Malefax)
A39: Major 5 | B39: =COUNTA(C39:FF39)/1.6 -> 43.75 | C39: Flanking Shot – Ranged attack that causes flanked | D39: Culling Bane – Ranged attack that targets a single enemy. Requires aim and costs mana. Attacks and culls all enemies that share that type (Huntsman) | E39: High Strung Shot – Ranged attack that deals extra damage based on weapon reload (Crossbowman) | F39: Glancing Aim – Ranged attack that deals additional damage on glancing based on aim (Marksman) | G39: Falcon Claw – Falcon attacks aim target with damage enhanced by aim, causes untyped bleed (Falconer) | H39: Pepper with Arrows – Multiple low damage ranged attacks that delay (Bounty Hunter) | J39: Culling Poach – Prepared ability that cannot be disrupted. Attacks a target with culling when it becomes endangered, then becomes unprepared. Consumes aim when prepared (Poacher) | K39: Critical Vow – Prepared ranged attack that selects target on preparation. Has increased critical chance and critical damage (Sharpshooter) | L39: Eternal Destruction – Ranged attack that grants stacking critical damage enhancement, consuming increasing aim (Toxophilite) | W39: Desperation Ripper – Melee attack against single target with powerful bleed. Advantage cost reduced if alone (Bandit) | X39: Critical Evisceration – Melee attack that causes bleed on critical (Cutthroat) | Y39: Enchanting Advantage – Melee attack against enchanted enemy that disenchants and generates advantage (Burglar) | Z39: Speed Theft – Lowers target speed and raises the Thief's own speed. (Thief) | AA39: Leaping Knives – Ranged attack that attacks target and one random, flanking both (Acrobat) | AB39: Elusive Death Strike – Prepared melee attack with bloodlust that enhances critical damage of next attack based on overkill (Assassin) | AC39: Elemental Snipe – Ranged attack that deals additional elemental damage based on enemy vulnerability (Brigand) | AD39: Flanking Scorn – Ranged attack against flanked enemy that grants smuggler scorn (Smuggler) | AE39: Pit Seeker – Melee attack against averted enemy with high penetration (Skulk) | AF39: Elemental Backstab – Melee attack targeting flanked enemy that determines damage multiplier based on elemental damage (Ninja) | AQ39: Internal Bleeding Blow – Melee attack that causes untyped bleeding with clobber (Brute) | AR39: Gravity Cleave – Melee attack that prevents active defenses until next turn, with decimate based on active defenses lost (Raider) | AS39: Bleeding Exertion – Melee attack with lower accuracy that causes bleeds and quicken self. If attack misses, take damage and reattempt once (Berserker) | AT39: Critical Assault – Melee attack that attacks all on critical. Consumes rage (Marauder) | AU39: Shield Decimation – Prepared melee attack with decimate. Enhanced by blocks made since preparation. (Viking) | AV39: Brink of Violence – Melee attack with backbiting. Only becomes available for one turn immediately after dealing enough damage (Vandal) | AW39: Expeditious Strike – Melee attack that quickens the fury and that requires haste. Can be used while berserk (Fury) | AX39: Grave Hunger – Melee attack with drain requiring Cannibal to be endangered (Cannibal) | AY39: Entropy Hammer – Melee attack with clobbering that deals corrupt damage (Destroyer) | AZ39: Might Exacerbation – Melee attack that requires berserk, enhances damage but Beastlord becomes tired (Beastlord) | BA39: Onslaught Gambit – Melee attack against each enemy with reduced accuracy, but enemies counter gladiator on each miss (Gladiator) | BB39: Disarming Strike – Melee attack with a chance to disarm target (Duelist) | BC39: Phalanx Onslaught – Number of melee attacks based on number of ready allies (Phalanx) | BD39: Dual Momentum – Dual wield attack with both attacks enhanced by momentum (Dervish) | BE39: Expert Blow, Superior – Melee attack that requires 60 expertise (Fencer) | BF39: Lancing Charge – Melee attack with momentum, procs the same attack against the target behind, with chance for behind that (Lancer) | BG39: Bushido Burst – Melee attack against all enemies. Target enemy attacks Samurai first and damage enhanced by enemy’s damage (Samurai) | BH39: Great Defense Strike - Melee attack that enhances defense. Requires wielding a two-handed weapon (Dreadnaught) | BI39: Lucky Feint – Gain lucky on parries until next turn. On parry, gain lucky accuracy and lucky damage and counter (Swashbuckler) | BJ39: Example of Expertise – Melee attack that gains increasing number of modifiers based on expertise, including sudden, unblockable, unparryable, unerring, and phasing. Consumes expertise (Warlord) | CE39: Fiery Refrain – Fire magic attack on all enemies in audience (Minstrel) | CF39: Cruel Joke – Ranged attack with one of: corrupt, cull, heartstrike or decimate (Jester) | CO39: Eros Guardian – Magic attack versus all enemies that minimizes the damage of their next attacks. More powerful with a companion present. Spends mana from companion if available. Requires Eros. (Conjurer) | CP39: Frost Corruption – Water attack that applies corruption against all enemies. Consumes Thanatos resource. Power enhanced by Thanatos scale position. (Occultist) | CQ39: Cultivate Leshy – Summons a leshy companion. (Shaman) | CR39: Chiaroscuro – Deals light or dark damage to all enemies based on the Medium's current scale position. (Medium) | CS39: Mounted Arcana – Arcane magic attack against a single enemy. Requires mounted. Grants mount action. (Animist) | CT39: Partnered Cast – Magic attack versus a single enemy. Magic power is enhanced by the companion's presence. (Spiritualist) | CU39: Star Crystal – Summons a star crystal companion. Enhances light power. Requires Eros side of scale. (Astrologer) | CV39: Forbidden Command – The companion makes an attack against the target with a chance to proc full corrupt damage. (Vizier) | CW39: Alien Transformation – Requires max Thanatos scale position and sufficient illusory damage on the Alienist. On activation, places a low-value, long-duration illusory damage effect on all enemies. For the rest of battle, a pulse of illusory damage hits all enemies on each of the Alienist's turns, and the Alienist gains illusory retaliation — enemies that strike her take illusory damage. (Alienist) | CX39: Corruption Storm – Corrupt dark magic storm. (Pact Master) | DS39: Heightened Illusion – Afflicts target with illusory damage. If the Telepath has extra mana when used, repeats based on influence and available mana against random targets. (Telepath) | DU39: Forget Your Mind – Forces target to use only its basic attack for a period. Duration scales with influence. (Amnesiac) | DV39: Hydrokinesis – Water bleed and delay based on influence on target. (Hypnotist) | DW39: Diviner's Bolt – Arcane unerring magic attack versus single. (Diviner) | DX39: Paranoid Superstition – Possesses all enemies with influence that are at low mana. (Haunted) | DY39: Ghost Ploy – Grant ally intangible and possess it. (Mastermind) | DZ39: Ether Razor – Untyped magic attack that causes stacking bleed with stacks and duration enhanced by influence. (Mindbleeder) | EA39: Gravity Blast – Dark magic attack versus all enemies with damage and delay based on how high timers are. (Chronomancer) | EB39: Possessive Health – Possess enemy to attack with life drain. All health drained goes to the Puppet Master. Afflicts target with Health Siphon after. (Puppet Master) | EM39: Dark Malignancy – Piercing dark magic attack with dark countdown against single (Cultist) | EN39: Conductivity – Air weakness and lightning rod against all maledicted and increases damage taken from random targeting attacks (Warlock) | EO39: Corruption Effigy – Single target corrupt fire damage that has increased damage and piercing based on damage afflictions on target (Effigist) | EP39: Disintegrating Blood – “Your blood will turn to dust in its veins.” – Afflict target with permanent earth bleed; reserves mana until purged or enemy dies (Dustbringer) | EQ39: Frost Anathema – Slow and water vulnerability versus all enemies. Requires 4 enemies with malediction (Crone) | ER39: Confusion Malediction – Confuse all maledicted enemies (Hedgemage) | ES39: Death Fetish – Afflict target with hex based on highest life of a defeated enemy (Mambo) | ET39: Juju Curse – Maledicted targets all have lowered affliction resist and if the bokor does not have a companion when a target dies, the target becomes a zombie companion. Torment. (Bokor) | EU39: Fire Criterion – Afflicts target with fire hex and wound. Cannot be removed until it deals a set amount of damage (Hag) | EV39: Corrupting Afflictions – Deal corrupt damage against target based on number of afflictions on it (Malefax)
A40: Major 6 | B40: =COUNTA(C40:FF40)/1.6 -> 43.75 | C40: Lay of the Land – Ranged attack that enhances dodge of team based on aim | D40: Difficult Prey – Ranged attack with enhanced damage based on target’s dodge (Huntsman) | E40: Pointblank Shot – Ranged attack with pointblank and penetrate (Crossbowman) | F40: Insinuating Shot – Ranged attack that causes next attack to be a guaranteed critical if it deals glancing damage (Marksman) | G40: Harmonious Shot – Prepared unerring ranged attack with unerring attack from companion (Falconer) | H40: Pinpoint Stun – Ranged attack with stun based on pinpoint value. Consumes aim (Bounty Hunter) | J40: Culling Vow – Prepared ability that selects target on preparation. Culls target on use (Poacher) | K40: Explosive Trickshot – Ranged attack that deals fire damage to all if trickshot occurs (Sharpshooter) | L40: Eternal Electrocution – Ranged attack with stacking air add, consuming increasing mana (Toxophilite) | W40: Desperation Shot – Ranged attack with pinpoint that consumes advantage. Consumes less advantage if Bandit is alone (Bandit) | X40: Discrete Dagger – Ranged attack with insidious that causes untyped bleed (Cutthroat) | Y40: Flame Backstab – Fire melee attack requiring hidden that causes fire exposure (Burglar) | Z40: Defense Theft – Melee attack that lowers target defense and raises own (Thief) | AA40: Reliable Cartwheel Strike – Melee attack that quickens the acrobat, costing advantage. Consumes no advantage on a miss. (Acrobat) | AB40: Envenomed Dagger – Ranged attack that deals more damage with applied poisons and generates advantage. Requires preparation and an active poison (Assassin) | AC40: Flanking Knives – Ranged attack against each flanked enemy (Brigand) | AD40: Frost Backstab – Water melee attack requiring hidden that afflicts target with slow (Smuggler) | AE40: Puncturing Blow – Melee attack with penetrate that causes defense weakness based on penetrate value (Skulk) | AF40: Expanded Savagery – Melee attack with increased maximum damage. Requires hidden (Ninja) | AQ40: Mammoth Consequences – Melee attack against all enemies and generate rage, but take damage at beginning of next turn (Brute) | AR40: Lingering Fury – Melee attack and enhance next damage by rage (Raider) | AS40: Bloodlust Quicken – Melee attack that quickens Berserker based on bloodlust (Berserker) | AT40: Double Attack – Two melee attacks that add together before comparison to defense (Marauder) | AU40: Shield Smash — Prepared melee attack. Damage and clobbering value enhanced by blocks made since preparation. (Viking) | AV40: Endless Beating – Prepared melee attack. This attack stays prepared if you are raging (Vandal) | AW40: Furious Drive – Melee attack that enhances speed on critical, stacking. Increased critical chance based on rage and can be used berserk (Fury) | AX40: Health Stealing Bite – Melee attack with drain that also applies heal siphon to target (Cannibal) | AY40: Grudgebearer – Attack with defense weakness against enemy that attacked unit turn before (Destroyer) | AZ40: Raging Charge – Mounted melee attack enhanced by rage (Beastlord) | BA40: Precise Strike, Greater – Melee attack with increased accuracy and critical chance, but delays gladiator (Gladiator) | BB40: Duel Bond – Melee attack that grants enhanced damage against target if it attacks a different ally before next turn (Duelist) | BC40: Phalanx Overrun – Melee attack against row with damage enhanced by ready allies (Phalanx) | BD40: Elusive Succession – Dual-wield attack that grants Dervish enhanced dodge after second attack based on dual-wield attack speed. (Dervish) | BE40: Final Fighter – Melee attack requiring alone that enhances counter chance and parry based on damage (Fencer) | BF40: Lancing Formation – Melee attack against row, procs the same attack against the target behind, with chance for behind that (Lancer) | BG40: Bushido Justice – Melee attack with justice against enemy. Enemy attacks Samurai first and then its counter is set to 0 (Samurai) | BH40: Stamina Blow – Melee attack boosted by endurance (Dreadnaught) | BI40: Onslaught Feint – Enhances parry chance of swashbuckler and compels target to attack her. If she parries the target before next turn, she attacks the target twice. Requires expertise (Swashbuckler) | BJ40: Expert Instruction – Enhances damage of ally’s next attack based on total expertise (Warlord) | CE40: Fire Note – Ranged fire attack that adds target to audience (Minstrel) | CF40: Cutting Jest – Ranged attack with pinpoint that lowers target damage by pinpoint value (Jester) | CO40: Ethereal Delay – Magic attack that delays the target. If companion mana is available, delays all enemies instead. (Conjurer) | CP40: Frozen Eternity – Water magic attack that incapacitates the target. Consumes Eros resource. Duration scales with Eros scale position. (Occultist) | CQ40: Pure Transformation – Requires that the Shaman is unaffected by any afflictions and at max Eros. On activation, purges all afflictions from all allies and companions. Grants the Shaman and her companion enhanced purge power and high affliction resistance for the rest of battle. (Shaman) | CR40: Dark Sunlight – Dark magic attack that lowers the target's light resistance and generates Eros resource. (Medium) | CS40: Phantom Animation – Buffs the companion so its next attack deals damage to all enemies. (Animist) | CT40: Phoenix Destiny – Fire magic attack against all enemies. Grants the Spiritualist a countdown revive. Requires preparation. Costs mana. Consumes Eros resource. (Spiritualist) | CU40: Starfall – Magic light attack against three random enemies. Also applies a light countdown to each target struck. (Astrologer) | CV40: Oblivion Hex – Dark hex placed on target. Hex value is based on Thanatos scale position at time of casting. (Vizier) | CW40: Chaos Wall, Greater – Chaos magic damage versus an enemy row. (Alienist) | CX40: Death's Door – Culls target enemy and revives a random dead ally. The revived ally's health is based on the culled target's current health at time of use. (Pact Master) | DS40: Heightened Possession – Possesses target. If the Telepath has extra mana when used, repeats based on influence and available mana against random targets. (Telepath) | DU40: Forgotten Blessing – Magic attack that disenchants target and causes mana loss. Mana loss and damage are based on enchantment disenchanted. (Amnesiac) | DV40: Hypnotic Pattern – Channeled ability that stuns enemies for the duration of the channel. (Hypnotist) | DW40: Future Betrayal – Possess any influenced enemy over a given timer threshold. (Diviner) | DX40: Piercing Superstition – Arcane magic attack with piercing and phasing against a target with low mana. (Haunted) | DY40: Hyperawareness – Channeled ability that grants all allies guaranteed counters while ongoing. (Mastermind) | DZ40: Exploding Skull – Chance to kill target enemy based on illusory damage. On kill, damage all other enemies. (Mindbleeder) | EA40: Gravity Well – Delay and damage all enemies based on counter above target's counter. (Chronomancer) | EB40: Possessive Pain – Possess enemy and cause the damage it deals to be painlinked to all its allies. (Puppet Master) | EM40: Malign Lamprey – Prepared ability that drains mana from all maledicted and transfers it to targeted ally, cannot target self (Cultist) | EN40: Foehn – Air damage and air bleed against all enemies (Warlock) | EO40: Countdown Effigy – Single target fire countdown that has increased damage and piercing based on damage afflictions on target (Effigist) | EP40: Disintegration – Afflict target with permanent corruption; reserves mana until purged or enemy dies (Dustbringer) | EQ40: Frostbite – Water magic attack versus maledicted lowering speed (Crone) | ER40: Creeping Vines – Channeled earth magic damage to target that also afflicts them with slow (Hedgemage) | ES40: Haunting Malefaction – Magic illusory attack that causes malediction (Mambo) | ET40: Juju Doll – Maledict target and afflict it with pain link (Bokor) | EU40: Flesh Eating Malefaction – Converts lost life on target to corruption and applies malediction (Hag) | EV40: Corruption Malediction – Deals corrupt damage to each maledicted enemy (Malefax)
A41: Major 7 | B41: =COUNTA(C41:FF41)/1.6 -> 43.75 | C41: Quickening Aim – Ranged attack against single target that consumes aim to quicken self | D41: Distant Bane – Ranged attack against enemy in back row that also damages all enemies that share type with target. (Huntsman) | E41: Puncture Shot – Ranged attack with penetrating that lowers target defense (Crossbowman) | F41: Marked Concord – Ranged attack that grants effect of mark for all allies. Requires aim (Marksman) | G41: Immediate Shot – Prepared ranged attack that has to be used the turn after it is prepared (Falconer) | H41: Shackle Shot – Ranged attack against stunned enemy that incapacitates (Bounty Hunter) | J41: Discrete Shot – Insidious ranged attack with bleed that consumes aim (Poacher) | K41: Focal Shot – Ranged attack that generated focus based on pinpoint amount (Sharpshooter) | L41: Eternal Explosion – Ranged attack with stacking area damage, causing Toxophilite increasing delay (Toxophilite) | W41: Desperation Trap – Ranged trap with bleed. Greatly delays bandit unless he is endangered (Bandit) | X41: Distracting Duo – Two melee attacks against a target. First attack causes flanked. Consumes advantage (Cutthroat) | Y41: Hidden Ambush – Melee attack against full health that grants Burglar hidden before attack (typically lost after attack) (Burglar) | Z41: Dissuading Strike – Melee attack that averts and delays target (Thief) | AA41: Reliable Critical – Prepared melee attack with high critical damage that stays prepared if it doesn’t critical (Acrobat) | AB41: Garrote Strangle – Channeled melee attack that causes stun (Assassin) | AC41: Fool's Gambit – Four inaccurate ranged attacks against a single target. For each attack that hits, all allies gain mana. If all four hit, mana generated equals mana spent. (Brigand) | AD41: Hidden Assault – Ranged attack from hidden with increased attacks for each hidden ally (Smuggler) | AE41: Scornful Backstab – Melee attack requiring hidden that grants scorn to the target. (Skulk) | AF41: Finishing Rend – Dualwield melee attack that causes massive damage effect based on total damage dealt (Ninja) | AQ41: Opening Blow – Melee attack against enemy with full health (Brute) | AR41: Looming Threat – Melee attack against compelled target. Switches target of compel (Raider) | AS41: Brutal Exertion – Melee attack with lower accuracy that lowers defense. If attack misses, take damage and reattempt once (Berserker) | AT41: Dual Rampage – Melee attack requiring dual wielding that deals additional damage for each enemy killed in battle (Marauder) | AU41: Shield Throw – Prepared melee attack against all enemies. Enhanced by blocks made since preparation. (Viking) | AV41: Escalating Violence – Melee attack with amplification that is always countered (Vandal) | AW41: Killing Amplification – Melee attack that provides amplification with any other ability on kill (Fury) | AX41: Mana Consumption – Melee attack that drains mana from target. Requires the Cannibal to have received enough healing (Cannibal) | AY41: Massive Burst – Melee attack that damages all enemies if it deals massive damage (Destroyer) | AZ41: Rampant Umbrage – Melee attack that deals damage based on overkill of previous attack (Beastlord) | BA41: Risky Positioning – Melee attack with blessed accuracy and damage, but causes the gladiator to be flanked (Gladiator) | BB41: Dueling Strike – Melee attack that compels target to attack duelist and compels duelist to attack target. Quickens Duelist (Duelist) | BC41: Phalanx Unity – Melee attack that quickens and enhances block chance of all ready allies based on number of ready allies (Phalanx) | BD41: Expert Onslaught – Consumes all expertise to make random melee attacks based on the amount of expertise (Dervish) | BE41: Gap in the Armor – Melee attack with pinpoint accuracy (Fencer) | BF41: Lancing Overrun – Melee attack that causes prone, procs the same attack against the target behind, with chance for behind that (Lancer) | BG41: Bushido Perseverance – Melee attack against enemy. Each enemy in front row attacks Samurai first and damage enhanced by total enemies’ damage (Samurai) | BH41: Unstoppable Advance – Melee attack that causes additional delay based on unit’s defense (Dreadnaught) | BI41: Parried Fury – Series of three melee attacks that follow a parry (Swashbuckler) | BJ41: Galvanizing Blow – Melee attack that enhances damage of all allies for their next attack based on expertise (Warlord) | CE41: Minstrel Ministration – Ranged attack and grants regeneration to ally with lowest health (Minstrel) | CF41: Prank – Magic attack that deals chaos damage and causes one of: blind, distracted, slow, wound (Jester) | CO41: Floating Skull – Summons a Thanatos-enhanced floating skull companion. (Conjurer) | CP41: Pandemonium Wind – Air attack versus all with delay and piercing. Costs mana. Power enhanced by Thanatos scale position. (Occultist) | CQ41: Spirit Assault – Channeled ability that applies untyped hex to multiple enemies over the channel duration. (Shaman) | CR41: Harmony Blast – Magic attack versus all enemies that deals increased damage the closer the Medium is to Balanced. Moves the scale one step away from Balanced on use. Requires Balanced scale position. (Medium) | CS41: Possessing Animation – Buffs the companion so its next attack deals additional illusory damage with a possession effect. (Animist) | CT41: Precarious Companion – The companion makes multiple attacks against enemies. Requires that the companion is endangered. Attacks are more powerful if the Spiritualist is also endangered. (Spiritualist) | CU41: Starlight Blast – Light magic attack versus all enemies with lucky damage. Requires Eros side of scale. Generates Eros resource. (Astrologer) | CV41: Omnipresent Corruption – Dark magic attack versus all enemies, enhanced by all corruption currently on the battlefield. Spends Thanatos resource. (Vizier) | CW41: Eldritch Abomination – Summons an eldritch abomination companion. (Alienist) | CX41: Gleam of Life – Magic light attack against all enemies. Generates Eros resource. (Pact Master) | DS41: Heightened Sleep – Incapacitates target. If the Telepath has extra mana when used, repeats based on influence and available mana against random targets. (Telepath) | DU41: Forsaken Bolt – Arcane magic attack that afflicts target with forsaken, preventing target from gaining enchantments. (Amnesiac) | DV41: Maddening Pattern – Channeled ability that causes illusory damage and lowers affliction resistance for the duration of the channel. (Hypnotist) | DW41: Influence Prediction – Countdown against single enemy that generates high influence when it triggers. (Diviner) | DX41: Poltergeist Ailment – Unlucky accuracy, jinx, and untyped hex. (Haunted) | DY41: Illusory Ploy – Possesses ally for an attack that deals damage as illusory. (Mastermind) | DZ41: Feedback Blast – Arcane attack versus all enemies, but triggers feedback at the same time. (Mindbleeder) | EA41: Mass Slow – Slow all influenced enemies with standard slow value. Duration scales with influence on each target. (Chronomancer) | EB41: Puppet Dance – Chance to possess all enemies based on their influence. (Puppet Master) | EM41: Malign Resurrection – Culls a single enemy. If that enemy is culled, resurrects a random dead ally. (Cultist) | EN41: Malefaction Whirlwind – Targets maledicted enemy. All enemies adjacent to target become maledicted. Prepared (Warlock) | EO41: Fiery Spread – Deals fire damage to all enemies with malediction (Effigist) | EP41: Disintegration Beam – Afflict enemy column with permanent corruption; reserves mana until purged or enemy dies (Dustbringer) | EQ41: Hypothermia – Greater affliction against all maledicted causing water vulnerability and causing stacking speed debuff when hit with water. Torment. (Crone) | ER41: Hemorrhagic Fever – Damage all enemies suffering contagion (Hedgemage) | ES41: Illusory Malediction – Magic attack versus maledicted causing illusory damage (Mambo) | ET41: Loa Strike – Magic attack that damages mana with ghost touch and phasing (Bokor) | EU41: Foul Miasma – Afflicts all enemies with high-potency, high-duration corruption that resists purging and has a lower damage value. (Hag) | EV41: Cursed Malefaction – Dark magic attack that causes malediction and cursed to target (Malefax)
A42: Major 8 | B42: =COUNTA(C42:FF42)/1.6 -> 43.75 | C42: Rapid Vow – Prepared ranged attack that determines target on preparation. Quickens scout on preparation and on use | D42: Distant Shot – Ranged attack that deals more damage to back row and generates aim (Huntsman) | E42: Push Through Bolt – Ranged attack with pointblank that can proc an attack against a column (Crossbowman) | F42: Marked Shot – Ranged attack against enemy with mark. Deals extra damage and generates extra effect from mark (Marksman) | G42: Ongoing Accuracy – Ranged attack requiring aim that enhances Falconer’s accuracy based on pinpoint (Falconer) | H42: Specific Shot – Ranged attack that ignores hidden, avert, and compel (Bounty Hunter) | J42: Ending Quarrel – Ranged attack against single endangered. Consumes aim (Poacher) | K42: Magebane Trickshot – Ranged attack that disrupts and disenchants if trickshot occurs (Sharpshooter) | L42: Eternal Marker – Ranged attack with pinpoint consuming aim, grants stacking accuracy enhancement (Toxophilite) | W42: Final Poison Shot – Ranged attack that uses all poisons. Requires endangered (Bandit) | X42: First Needle – Melee attack that starts stacking bleed, but does not stack itself. Consumes advantage (Cutthroat) | Y42: Lightning Ambush – Melee attack against full health that also deals damage to two random enemies (Burglar) | Z42: Lucky Rend – Dualwield melee attack that grants lucky if both attacks hit (Thief) | AA42: Reliable Heartstrike – Melee attack with heartstrike that costs advantages. Consumes no advantage on a miss. (Acrobat) | AB42: Heartstrike Finisher – Heartstrike damage versus alone enemy (Assassin) | AC42: Hamstring Shot – Ranged attack against flanked enemy that slows target (Brigand) | AD42: Night Raid – All hidden units make random attacks against enemies (Smuggler) | AE42: Shadow Shunt – Melee attack from hidden that averts target (Skulk) | AF42: Hidden Persistence – Melee attack that grants free attack at beginning of next turn if hidden (Ninja) | AQ42: Ruthless Cascade – Melee attack that cascades if it deals ruthless damage. This effect can repeat multiple times, but each enemy can only be targeted once (Brute) | AR42: Precipitous Cleave – Melee attack with sudden; quickens raider if she is raging (Raider) | AS42: Callous Blow – Melee attack that grants barrier to self and can only be used berserk (Berserker) | AT42: Eviscerating Rend – Two melee attacks against a single target. Causes heartstrike if both attacks hit (Marauder) | AU42: Shield Wall – Prepared melee attack against enemy row. Enhanced by blocks made since preparation. (Viking) | AV42: Ferocious Spree – Melee attack with amplification that consumes increasing amounts of rage (Vandal) | AW42: Quickening Purity – Melee attack with increasing quicken effect, but it reduces defense and dodge. This can be disrupted. (Fury) | AX42: Maximum Satiation – Maximized melee attack requiring Cannibal has been healed enough (Cannibal) | AY42: Massive Cascade – Melee attack that cascades if attack deals massive damage. This effect can repeat multiple times, but each cascade must target a different enemy (Destroyer) | AZ42: Rending Force – Melee attack that lowers defense of all enemies by overkill (Beastlord) | BA42: Shattering Sequence – Two shattering melee attacks against a single target consuming expertise (Gladiator) | BB42: End the Duel – Disarm target enemy, then attack it based on expertise. Consumes all expertise (Duelist) | BC42: Puncturing Piercer – Melee attack with penetrate that causes defense weakness on critical (Phalanx) | BD42: Momentum Onslaught – Melee attack that strikes a number of times based on momentum, alpha (Dervish) | BE42: Penetrating Pinpoint – Melee attack with pinpoint, then penetrates based on pinpoint. Prepared (Fencer) | BF42: Long Pierce – Melee attack that can strike any row (Lancer) | BG42: Bushido Provocation – Melee attack against enemy that compels. Enemy attacks Samurai first and damage enhanced by enemy’s damage (Samurai) | BH42: Unstoppable Blow – Melee attack deals extra damage based on unit’s defense (Dreadnaught) | BI42: Parried Surge – Melee attack versus front row following a parry (Swashbuckler) | BJ42: Powerful Exploit – Melee attack that consumes all expertise to increase damage. Requires a minimum level of expertise (Warlord) | CE42: Purifying Stream – Channeled water magic attack that ameliorates afflictions on Minstrel over same period (Minstrel) | CF42: Random Weakness – Ranged attack that afflicts target with a random weakness (Jester) | CO42: Guide Conjuration – Magic attack that heals the companion, grants it mana, and quickens it. (Conjurer) | CP42: Phantom Ritual – Summons a phantom companion. (Occultist) | CQ42: Stone Crusher – Magic piercing earth attack that enhances the companion's critical chance. (Shaman) | CR42: Harmony Bolt – Single-target magic attack that deals increased damage the closer the Medium is to Balanced. Moves the scale one step away from Balanced on use. Requires Balanced scale position. (Medium) | CS42: Purge Spirit – Magic attack that also makes the target intangible. (Animist) | CT42: Precarious Destiny – Light magic attack versus an endangered enemy. If the Spiritualist is also endangered and this attack kills the target, the life of all remaining enemies is averaged with the target's life before the ability fired. (Spiritualist) | CU42: Stellar Burst – Light magic storm with four attacks. After resolving, fires an additional light magic attack versus all enemies based on total critical hits scored. Requires preparation. Costs mana. Generates Eros resource. (Astrologer) | CV42: Treacherous Blast – Fire magic attack against all enemies. Also deals corrupt damage to a random ally. Enhanced by the corrupt damage currently on that ally. (Vizier) | CW42: Illusion of Time – Afflicts all enemies with illusory damage. The balance between damage value and duration is based on alignment — Thanatos-leaning increases damage, Eros-leaning increases duration. (Alienist) | CX42: Inspiring Bolt – Arcane magic attack that quickens the companion. (Pact Master) | DS42: Insightful Strike – Magic attack against single enemy, generates influence and displays target health. (Telepath) | DU42: Mass Mana Burn – Afflict all enemies with mana burn. (Amnesiac) | DV42: Pendulum Swing – Magic attack that generates influence and delays target. (Hypnotist) | DW42: Influenced Countdown – Causes untyped countdown on target enhanced by influence. (Diviner) | DX42: Poltergeist Pain – Magic attack that possesses the target on a critical hit. (Haunted) | DY42: Influence Ploy – Possesses ally to attack a random enemy. Enemy becomes influenced. (Mastermind) | DZ42: Heart Siphon – Drains life from target and converts it to mana gain. (Mindbleeder) | EA42: Steal Youth – Magic attack that drains life. (Chronomancer) | EB42: Repetitive Possession – Possess enemy twice. (Puppet Master) | EM42: Malign Vampirism – Prepared ability that drains life from all maledicted and transfers it to targeted ally (Cultist) | EN42: Razor Whirlwind – Targets maledicted enemy. All enemies adjacent to target take magic air damage. (Warlock) | EO42: Flame Effigy – Single target fire damage that has increased damage and piercing based on damage afflictions on target (Effigist) | EP42: Drought – Prevents enemies from healing or gaining mana until next turn (Dustbringer) | EQ42: Ice Shackles – Afflict enemy with slow and water hex (Crone) | ER42: Hex Wall – Afflict row of enemies with water hex (Hedgemage) | ES42: Malediction Ray – Light magic attack versus column that deals additional damage to maledicted enemies (Mambo) | ET42: Loa’s Kiss – Mana damage versus all maledicted. Enemies reduced to zero mana take damage (Bokor) | EU42: Haemophilia – Causes maledicted targets to have increased chance to take critical hits and to take bleeds when they are criticaled. Torment. (Hag) | EV42: Heartstrike Anathema – Heartstrike damage versus all maledicted enemies. Requires 4 maledicted enemies (Malefax)
A43: Major 9 | B43: =COUNTA(C43:FF43)/1.6 -> 43.75 | C43: Scouted Arrow Burst – Ranged attack against all enemies. Deals less damage and requires aim if not first turn | D43: Ensnaring Arrow – Ranged attack that causes speed weakness. Duration is enhanced with aim and the weakness stacks with itself. (Huntsman) | E43: Reloading Sequence – Two ranged attacks against single, eliminates reload (Crossbowman) | F43: Marking Vow – Prepared ranged attack that selects target on preparation. Lowers dodge of target for a period on preparation (Marksman) | G43: Phantom Hawk – Afflict target with untyped bleed and distract. Requires aim (Falconer) | H43: Speed Snipe – Ranged attack that speed weakness on critical (Bounty Hunter) | J43: Ending Volley – Ranged attack against all endangered. Consumes aim (Poacher) | K43: Penetration Echo Arrow – Ranged attack with countdown, both with penetration (Sharpshooter) | L43: Eternal Truth – Ranged attack requiring aim with increased critical Chance. On critical, it increases critical damage until the end of battle (Toxophilite) | W43: Last Blood – Culling melee attack requiring Bandit is alone (Bandit) | X43: Ghost Strike – Melee attack with heartstrike that requires intangible (Cutthroat) | Y43: Phasing Darkness – Melee attack from hidden with phasing (Burglar) | Z43: Penetration Advantage – Melee attack that consumes all advantage to gain penetration based on advantage used (Thief) | AA43: Reliable Rend – Prepared dualwield melee attack that deals extra damage if both attacks hit and stays prepared if either attack misses (Acrobat) | AB43: Mage Killer – Ranged attack that lowers magic power and magic resistance of target (Assassin) | AC43: Heartstrike Ambush – Prepared ranged attack requiring hidden with increased critical chance and heartstrike on critical (Brigand) | AD43: Poison Slash – Venomous melee attack against flanked enemy (Smuggler) | AE43: Shadow Stab – Melee attack that blinds target and grants skulk hidden (Skulk) | AF43: Hobbling Rend – Dual-wield melee attack that slows if both attacks hit (Ninja) | AQ43: Stunning Consequences – Melee attack with stun and generate rage, but take damage at beginning of next turn (Brute) | AR43: Raid Preparation – Melee attack with low accuracy that enhances damage and dodge on miss (Raider) | AS43: Feckless Blow – Melee attack that causes flanking on berserker (Berserker) | AT43: Off-hand Preparations – Dual wield melee attack that compels target and enhances counter chance (Marauder) | AU43: Steel Suffering – Melee attack that causes untyped bleed and defense weakness (Viking) | AV43: Intimidating Charge – Melee attack with momentum that causes frightened, requires rage (Vandal) | AW43: Ranged Purity – Ranged attack with increasing damage, but this resets if the barbarian attacks a close enemy. (Fury) | AX43: Rabid Bite – Melee attack with untyped bleed and wound (Cannibal) | AY43: Massive Corruption – Melee attack that converts damage to corrupt if it is massive damage (Destroyer) | AZ43: Riven Force – Melee attack that lowers damage of all enemies based on overkill (Beastlord) | BA43: Stunning Gambit – Melee attack that stuns target. Higher chance to be countered and gladiator becomes stunned if countered (Gladiator) | BB43: Expert Blow, Enhanced – Melee attack that requires expertise (Duelist) | BC43: Shield and Strike – Melee attack enhanced by shield following block (Phalanx) | BD43: Quick Succession – Dual-wield attack that quickens the Dervish after second attack based on dual-wield attack speed. (Dervish) | BE43: Penetrating Thrust – Melee attack with penetration on critical (Fencer) | BF43: Long Skewer – Melee attack against column with bleed on critical (Lancer) | BG43: Double Bushido Strike – Two melee attack against enemy. Enemy attacks Samurai first and damage enhanced by enemy’s damage (Samurai) | BH43: Unstoppable Collateral – Melee attack against single enemy that also damage all enemies based on defense (Dreadnaught) | BI43: Strike Off Balance – Melee attack that prevents target from countering until its next turn. Requires expertise (Swashbuckler) | BJ43: Provocation Blow – Melee attack that provokes target and enhances parry chance until target acts (Warlord) | CE43: Recovery Shot – Ranged attack with minimized damage that grants Minstrel regeneration based on what damage roll would have been (Minstrel) | CF43: Remora Note – Ranged attack that drains mana from target and adds them to audience (Jester) | CO43: Thanatos Champion – Melee attack against three random enemies with heartstrike. Gains an extra attack when companion mana is available. Requires Thanatos. (Conjurer) | CP43: Potential of Ephemera – Magic attack with increased maximum damage. Costs mana. Maximum scales with Thanatos scale position. (Occultist) | CQ43: Thanatos Madness – Channeled ability with duration that enhances companion power based on Thanatos scale position, then causes the companion to make attacks against three random enemies. Attacks are considered storm. Spends Thanatos resource. (Shaman) | CR43: Radiant Night – Light magic attack that lowers the target's dark resistance and generates Thanatos resource. (Medium) | CS43: Spirit Beast – Summons a spirit beast mount. (Animist) | CT43: Precarious End – Magic attack versus all endangered enemies. Deals extra damage if the Spiritualist is also endangered. (Spiritualist) | CU43: Stellar Cascade – Light magic attack versus a single enemy. Damages all other enemies on critical hit. Can cascade repeatedly. (Astrologer) | CV43: Treacherous Blood – Afflicts target with a dark bleed. Also deals corrupt damage to a random ally. (Vizier) | CW43: Impossible Horror – Illusory magic attack that uses ruthless with all illusory damage on the target. Requires Thanatos side of scale. (Alienist) | CX43: Maddening Blast – Fire magic attack versus all enemies that enhances companion damage. (Pact Master) | DS43: Invade Dreams – Insidious magic attack versus incapacitated enemies enhanced by influence. (Telepath) | DU43: Mental Crash – Prepared ability that triggers when the next enemy falls below a health threshold. Deals damage and stuns that enemy. (Amnesiac) | DV43: Psychic Blast – Untyped magic attack versus all influenced, with minimum damage based on influence on each individual target and maximum damage based on total influence. (Hypnotist) | DW43: Mass Prediction – Afflict all influenced enemies with untyped countdown. (Diviner) | DX43: Poltergeist Tantrum – Arcane storm that can be sustained for reduced mana cost. (Haunted) | DY43: Inspiring Possession – Possess ally; ally gains mana. (Mastermind) | DZ43: Hemokinesis – Possess target bleeding enemy to attack a random enemy. Secondary target takes bleeds based on bleeds present on initial target. (Mindbleeder) | EA43: Supreme Chronomancy – All allies gain an immediate turn. High mana cost. Exhausts the Chronomancer. (Chronomancer) | EB43: Suspicion – Possess target. It flanks its target and becomes flanked as well. (Puppet Master) | EM43: Narcolepsy – Maledicted targets become incapacitated if not attacked for a period. Torment (Cultist) | EN43: Receptive Depravity – Air magic attack with bloodlust that lowers affliction resistance enhanced by bloodlust (Warlock) | EO43: Flammability – Causes fire vulnerability to all maledicted, targets take stacking fire bleed when hit with fire damage. Torment. (Effigist) | EP43: Dust Choker – Causes an earth bleed to each maledicted target (Dustbringer) | EQ43: Khazri – Damage and defense weakness versus all enemies, then water damage based on weakness values (Crone) | ER43: Sleeping Sickness – Afflicts all with a countdown that causes incapacitate when it goes off. Countdown removed on damage (Hedgemage) | ES43: Radiant Malediction – Light magic damage with justice versus all maledicted enemies (Mambo) | ET43: Malefaction Wave – Magic attack versus all with a low chance to hit that also causes malediction (Bokor) | EU43: Malefaction Criterion – Afflicts target with malediction, dark bleed, and dark resistance weakness. Can only target non-maledicted enemy. Cannot be removed until it deals a set amount of damage. (Hag) | EV43: Incompetence – Afflict target with mana burn, cursed, and forsaken (Malefax)
A44: Major 10 | B44: =COUNTA(C44:FF44)/1.6 -> 43.75 | C44: Scouted Chink – Full penetration ranged attack if first attack of battle. Can proc full penetration with ranged attack after | D44: Magic Hunt – Ranged attack with disruption targeting enemy with most prepared abilities. This eliminates aim if different target (Huntsman) | E44: Repeating Crossbow – Channeled ranged attack (Crossbowman) | F44: Reaping Aim – Ranged attack that deals reaping damage based on aim on target (Marksman) | G44: Preemptive Vow – Prepared ranged attack that selects target on preparation. Companion attacks target on preparation and use (Falconer) | H44: Stunning Shot – Ranged attack that stuns target based on aim (Bounty Hunter) | J44: Pinpoint Push – Ranged attack with pinpoint that delays target (Poacher) | K44: Rubber Trickshot – Attack repeats against random target if trickshot triggers. Occurs multiple times, but consumes aim with each time (Sharpshooter) | L44: Improbable Aim – Ranged attack with pinpoint proc based on current aim (Toxophilite) | W44: Mana Crash – Ranged attack that also deals mana damage. If target ends with zero mana, generates combat advantage (Bandit) | X44: Intangible Advantage – Ranged attack requiring intangible. Generates advantages and disenchants intangible at end of attack (Cutthroat) | Y44: Protective Ambush – Melee attack against full health that grants Burglar enhanced defense. Consumes advantage (Burglar) | Z44: Trip and Stab – Melee attack with chance for prone, second attack if target made prone, requires dual wield (Thief) | AA44: Reliable Shot – Ranged attack with high quicken on miss. (Acrobat) | AB44: Murder Spree – Melee attack from hidden that quickens Assassin based on overkill (Assassin) | AC44: Piercing Pincer Shot – Ranged attack against flanked with increased critical chance (Brigand) | AD44: Poison Splatter Stab – Melee attack requiring poison that deals percentage of poison damage or effect to enemies adjacent to target (Smuggler) | AE44: Startling Arrival – Melee attack against single from hidden that delays all other enemies (Skulk) | AF44: Remove the Needle – Reduce stacking bleed on target to deal immediate damage (Ninja) | AQ44: Tiring Delay – Melee attack that further delays target based on their tired value (Brute) | AR44: Reckless Clobber – Clobbering melee damage. Prevents Raider from using active defenses and counters until next turn (Raider) | AS44: Great Cleave – Melee attack versus single that damages enemies in same row as target against combined defense of primary and secondary target (Berserker) | AT44: Onslaught Rampage – Dual-wield melee attack that makes an additional attack on a random enemy for each enemy killed in battle (Marauder) | AU44: Taunting Axe – Melee attack with damage increased by rage that taunts enemies (Viking) | AV44: Raging Cleave – Large weapon attack that strikes target enhanced by rage and adjacent enemies based on rage (Vandal) | AW44: Sacrifice Purity – Melee attack with increasing damage and backbiting, but this ends if the barbarian is healed. (Fury) | AX44: Sacrificial Consumption – Melee attack with backbiting. Requires having been healed enough (Cannibal) | AY44: Massive Destruction – Melee attack that lowers all enemy defense if it deals massive damage (Destroyer) | AZ44: Trample Underfoot – Mounted melee attack versus column. Each enemy counters the beastlord, but the beastlord generates extra rage for the damage. On a critical, enemies are knocked prone (Beastlord) | BA44: Unremitting Slash – Attack that stays prepared if it misses, lower accuracy (Gladiator) | BB44: Expert Penetration – Melee attack with penetration based off expertise (Duelist) | BC44: Shield Breaker – Melee attack that lowers target’s block chance (Phalanx) | BD44: Shearing Exploit – Damage all and lower defense based on expertise, consumes all expertise (Dervish) | BE44: Pinpoint Parries – Melee attack with pinpoint that enhances parry based on pinpoint. Requires expertise (Fencer) | BF44: Mount Trade Holsteiner – Summons a trade holsteiner mount (Lancer) | BG44: Double Slash – Two melee attacks with reduced accuracy. Requires dual-wielding (Samurai) | BH44: Unstoppable Critical – Melee attack that deals additional damage on critical based on defense. Delays self (Dreadnaught) | BI44: Tripping Blow – Melee attack that has a chance to cause prone while having lower accuracy. Requires expertise (Swashbuckler) | BJ44: Rallying Blow – Melee attack that quickens all allies based on expertise (Warlord) | CE44: Restorative Performance – Channeled ability that heals all allies. Considered regeneration (Minstrel) | CF44: Satiric Shot – Ranged attack that causes elemental resistance weakness (Jester) | CO44: Titanic Growth – All enemies are compelled to attack the companion. The companion's next attack targets all enemies. (Conjurer) | CP44: Seeping Cold – Water attack and bleed with piercing against single target. (Occultist) | CQ44: Threatening Shot – Ranged attack. If the Shaman scores a critical hit, the companion also attacks the same target. (Shaman) | CR44: Shadow Storm – Magic storm attack that makes two light strikes and two dark strikes. (Medium) | CS44: Spirit Charge – Melee attack requiring mounted that also damages all enemies. Bonus damage scales with Thanatos scale position. (Animist) | CT44: Precarious Transformation – Requires the Spiritualist to be endangered and at max Eros. Power level is locked to the Spiritualist's health percentage at activation. On activation, grants Enduring. For the rest of battle: the Spiritualist counts as endangered regardless of actual health; a pulsing light burst targets all enemies each turn with damage that increases per hit taken during that turn; all Precarious abilities function at their enhanced tier automatically. (Spiritualist) | CU44: Stellar Purge – Light magic attack versus all enemies. Purges one affliction per enemy critically hit. Requires preparation. Requires Eros side of scale. (Astrologer) | CV44: Treacherous Oblivion – Corrupt heartstrike magic attack against a single enemy. Also deals corrupt damage to all allies. Both effects are increased by Thanatos scale position. Spends Thanatos resource. (Vizier) | CW44: Insane Resurrection – Raises target ally. Both the target and the Alienist are afflicted with illusory damage. (Alienist) | CX44: Shadow of Death – Magic dark attack against all enemies. Generates Thanatos resource. (Pact Master) | DS44: Pyrokinetic Vulnerability – Afflict all enemies with a minimum level of influence with fire vulnerability. (Telepath) | DU44: Simple Masses – Forces all influenced enemies to use their next basic attack. (Amnesiac) | DV44: Scintillating Pattern – Channeled ability that blinds enemies for the duration of the channel. (Hypnotist) | DW44: Rewrite Fate – Transfer all countdowns from afflicted allies to target enemy. (Diviner) | DX44: Superstitious Hex – Arcane hex against target enemy whose value is determined by how low the target's mana is. (Haunted) | DY44: Mana Reverberation – Damages all enemies based on their current mana. (Mastermind) | DZ44: Illusory Decimation – Deal illusory damage to target based on decimate value. (Mindbleeder) | EA44: Temporal Burn – Arcane magic attack enhanced by target's timer. (Chronomancer) | EB44: Unbreakable Strands – High power possession against target. Reduces target's defense against possession effects. (Puppet Master) | EM44: Possessing Malefaction – Possess enemy and cause malediction (Cultist) | EN44: Shock Spasm – Air magic attack that delays and has a chance to disarm (Warlock) | EO44: Flesh Like Straw – Afflict target enemy with high value fire exposure (Effigist) | EP44: Erosion Fog – Earth bleed against each enemy (Dustbringer) | EQ44: Malefaction Beam – Water magic attack versus column that causes malediction (Crone) | ER44: Susceptibility – Maledicted targets gain elemental vulnerability to the last element to target them. Torment. (Hedgemage) | ES44: Return to Dust – Ongoing decimation damage (Mambo) | ET44: Roach Infestation – Magic attack with enhanced critical chance. Damages all maledicted on critical (Bokor) | EU44: Plague Cauldron – Sustained ability that increases in value each turn used. When the Hag stops using it, deals corrupt damage to all enemies scaled exponentially by the number of turns channeled. Resets after triggering. (Hag) | EV44: Malefaction Chant – Dark magic channel that damages one unmaledicted target for a period before causing malediction and switching targets and repeating the process (Malefax)
