Workbook
Name _Hlk99922360: SubclassAspects!$BE$65

Sheet Sheet1
C1: Name: | D1: Scout
C2: Tier: | D2: 1
C3: Base: | D3: Archer
C4: Code: | D4: 2
C5: Requirements:
C6: =IF(SubclassAspects!C13>0,"Dexterity ", "") -> Dexterity | D6: =IF(SubclassAspects!C13>0,SubclassAspects!C13) -> 58 | E6: =IF(SubclassAspects!C17>0,"Charisma ", "") -> Charisma | F6: =IF(SubclassAspects!C17>0,SubclassAspects!C17, "") -> 58
C7: =IF(SubclassAspects!C14>0,"Dexterity ","") | D7: =IF(SubclassAspects!C14>0,SubclassAspects!C14, "") | E7: =IF(SubclassAspects!C18>0,"Endurance ", "") -> Endurance | F7: =IF(SubclassAspects!C18>0,SubclassAspects!C18, "") -> 53
C8: =IF(SubclassAspects!C15>0,"Strength ","") -> Strength | D8: =IF(SubclassAspects!C15>0,SubclassAspects!C15, "") -> 54 | E8: =IF(SubclassAspects!C19>0,"Luck ", "") | F8: =IF(SubclassAspects!C19>0,SubclassAspects!C19, "")
C9: =IF(SubclassAspects!C16>0,"Wisdom ","") -> Wisdom | D9: =IF(SubclassAspects!C16>0,SubclassAspects!C16, "") -> 61 | E9: =IF(SubclassAspects!C20>0,"Will ", "") -> Will | F9: =IF(SubclassAspects!C20>0,SubclassAspects!C20, "") -> 54
A11: Overview
A13: Quote: | B13: “With proper preparations, the fighting is merely a formality.”
A14: The Scout is an archer-based class that can act early and effectively. He uses preliminary actions to take control of the battlefield, attacks enemies at full health, and quickens himself readily. He is hard to destroy before his turn.
A15: World Notes: Scouts are an essential part of enemy army, as only with knowledge of the enemy can success be found. The scouts prepare the battlefield to best support their army’s success.
A16: Appearance: The scout is lightly armored because he is constantly on the move.
A17: Defining Mechanic: The Scout can implement scouted abilities. These abilities, which come in all three strengths, can only be used as the first action of battle, after which they turn into a related, but lesser, ability.
A19: Equipment
A20: Default Weapon: | C20: Short Bow
A21: Default Armor:
A41: Major Abilities
A42: Adroit Momentum – Ranged attack with pinpoint and momentum enhancing accuracy (Scout)
A43: Aimed Momentum – Ranged attack that generates extra aim based on momentum (Scout)
A44: Coordinated Shot – Ranged attack with quick preparation that grants increased accuracy and damage to next attack versus target (Scout)
A45: Delaying Jolt – Ranged attack with delay against stunned target (Scout)
A46: Flanking Shot – Ranged attack that causes flanked (Scout)
A47: Lay of the Land – Ranged attack that enhances dodge of team based on aim (Scout)
A48: Quickening Aim – Ranged attack against single target that consumes aim to quicken self (Scout)
A49: Rapid Vow – Prepared ranged attack that determines target on preparation. Quickens scout on preparation and on use (Scout)
A50: Scouted Arrow Burst – Ranged attack against all enemies. Deals less damage and requires aim if not first turn (Scout)
A51: Scouted Chink – Full penetration ranged attack if first attack of battle. Can proc full penetration with ranged attack after (Scout)
... A71: Share Momentum – Quicken all allies based on momentum (Scout)

Sheet SubclassAspects
D1: Hunter | P1: Wrestler | AO1: Siege Engineer | AV1: Rager | BR1: Black Knight | CD1: Sword Magus | EQ1: Winter Witch | ES1: Witch Doctor
A2: Name | B2: =COUNTA(C2:FF2)/1.6 -> 100 | C2: Scout | D2: Huntsman | E2: Crossbowman | F2: Marksman | G2: Falconer | H2: Bounty Hunter | I2: Stalker | J2: Poacher | K2: Sharpshooter | L2: Toxophilite | M2: Initiate | N2: Pugilist | O2: Skirmisher | P2: Vajra | Q2: Stonefist | R2: Infiltrator | S2: Viper Fang | T2: Ascetic | U2: Thunderfist | V2: Drunken Master | W2: Bandit | X2: Cutthroat | Y2: Burglar | Z2: Thief | AA2: Acrobat | AB2: Assassin | AC2: Brigand | AD2: Smuggler | AE2: Skulk | AF2: Ninja | AG2: Scavenger | AH2: Alchemist | AI2: Artificer | AJ2: Tinker | AK2: Engineer | AL2: Bomber | AM2: Gunslinger | AN2: Savant | AO2: Machinist | AP2: Reliquarian | AQ2: Brute | AR2: Raider | AS2: Berserker | AT2: Marauder | AU2: Viking | AV2: Vandal | AW2: Fury | AX2: Cannibal | AY2: Destroyer | AZ2: Beastlord | BA2: Gladiator | BB2: Duelist | BC2: Phalanx | BD2: Dervish | BE2: Fencer | BF2: Lancer | BG2: Samurai | BH2: Dreadnaught | BI2: Swashbuckler | BJ2: Warlord | BK2: Bodyguard | BL2: Champion | BM2: Hospitaler | BN2: Cavalier | BO2: Sentinel | BP2: Dragoon | BQ2: Paragon | BR2: Blackguard | BS2: Crusader | BT2: Templar | BU2: Blitzknecht | BV2: Feuerknecht | BW2: Trinknecht | BX2: Drecknecht | BY2: Mercenary | BZ2: Transmuter | CA2: Force Weaver | CB2: Myrmidon | CC2: Nightblade | CD2: Sword Saint | CE2: Minstrel | CF2: Jester | CG2: Dirge Singer | CH2: Balladeer | CI2: Drummer | CJ2: Spy | CK2: Mountebank | CL2: Diva | CM2: Muse | CN2: Lantern Bearer | CO2: Conjurer | CP2: Occultist | CQ2: Shaman | CR2: Medium | CS2: Animist | CT2: Spiritualist | CU2: Astrologer | CV2: Vizier | CW2: Alienist | CX2: Pact Master | CY2: Acolyte | CZ2: Healer | DA2: Disciple | DB2: Priest | DC2: Combat Medic | DD2: Exorcist | DE2: Preacher | DF2: Zealot | DG2: Plague Doctor | DH2: Oracle | DI2: Buccaneer | DJ2: Executioner | DK2: Gravedigger | DL2: Hangman | DM2: Harbinger | DN2: Sin Eater | DO2: Sandman | DP2: Whisperer | DQ2: Mercy Bringer | DR2: Gaslighter | DS2: Telepath | DT2: Kinetic | DU2: Amnesiac | DV2: Hypnotist | DW2: Diviner | DX2: Haunted | DY2: Mastermind | DZ2: Mindbleeder | EA2: Chronomancer | EB2: Puppet Master | EC2: Abjurer | ED2: Symbolist | EE2: Cabalist | EF2: Hermit | EG2: Disenchanter | EH2: Scrivener | EI2: Sage | EJ2: Glyphic | EK2: Cryptic | EL2: Sorcerer | EM2: Cultist | EN2: Warlock | EO2: Effigist | EP2: Dustbringer | EQ2: Crone | ER2: Hedgemage | ES2: Mambo | ET2: Bokor | EU2: Hag | EV2: Malefax | EW2: Elementalist | EX2: Necromancer | EY2: Hydromancer | EZ2: Geomancer | FA2: Aeromancer | FB2: Pyromancer | FC2: Arcanist | FD2: Solomancer | FE2: Incanter | FF2: Thaumaturge
A3: Code | B3: =COUNTA(C3:FF3)/1.6 -> 100 | C3: 2 | D3: 3 | E3: 4 | F3: 5 | G3: 6 | H3: 7 | I3: 8 | J3: 9 | K3: 10 | L3: 11 | M3: 13 | N3: 14 | O3: 15 | P3: 16 | Q3: 17 | R3: 18 | S3: 19 | T3: 20 | U3: 21 | V3: 22 | W3: 24 | X3: 25 | Y3: 26 | Z3: 27 | AA3: 28 | AB3: 29 | AC3: 30 | AD3: 31 | AE3: 32 | AF3: 33 | AG3: 35 | AH3: 36 | AI3: 37 | AJ3: 38 | AK3: 39 | AL3: 40 | AM3: 41 | AN3: 42 | AO3: 43 | AP3: 44 | AQ3: 46 | AR3: 47 | AS3: 48 | AT3: 49 | AU3: 50 | AV3: 51 | AW3: 52 | AX3: 53 | AY3: 54 | AZ3: 55 | BA3: 57 | BB3: 58 | BC3: 59 | BD3: 60 | BE3: 61 | BF3: 62 | BG3: 63 | BH3: 64 | BI3: 65 | BJ3: 66 | BK3: 68 | BL3: 69 | BM3: 70 | BN3: 71 | BO3: 72 | BP3: 73 | BQ3: 74 | BR3: 75 | BS3: 76 | BT3: 77 | BU3: 79 | BV3: 80 | BW3: 81 | BX3: 82 | BY3: 83 | BZ3: 84 | CA3: 85 | CB3: 86 | CC3: 87 | CD3: 88 | CE3: 90 | CF3: 91 | CG3: 92 | CH3: 93 | CI3: 94 | CJ3: 95 | CK3: 96 | CL3: 97 | CM3: 98 | CN3: 99 | CO3: 101 | CP3: 102 | CQ3: 103 | CR3: 104 | CS3: 105 | CT3: 106 | CU3: 107 | CV3: 108 | CW3: 109 | CX3: 110 | CY3: 112 | CZ3: 113 | DA3: 114 | DB3: 115 | DC3: 116 | DD3: 117 | DE3: 118 | DF3: 119 | DG3: 120 | DH3: 121 | DI3: 123 | DJ3: 124 | DK3: 125 | DL3: 126 | DM3: 127 | DN3: 128 | DO3: 129 | DP3: 130 | DQ3: 131 | DR3: 132 | DS3: 134 | DT3: 135 | DU3: 136 | DV3: 137 | DW3: 138 | DX3: 139 | DY3: 140 | DZ3: 141 | EA3: 142 | EB3: 143 | EC3: 145 | ED3: 146 | EE3: 147 | EF3: 148 | EG3: 149 | EH3: 150 | EI3: 151 | EJ3: 152 | EK3: 153 | EL3: 154 | EM3: 156 | EN3: 157 | EO3: 158 | EP3: 159 | EQ3: 160 | ER3: 161 | ES3: 162 | ET3: 163 | EU3: 164 | EV3: 165 | EW3: 167 | EX3: 168 | EY3: 169 | EZ3: 170 | FA3: 171 | FB3: 172 | FC3: 173 | FD3: 174 | FE3: 175 | FF3: 176
A4: Tier | B4: =COUNTA(C4:FF4)/1.6 -> 100 | C4: 1 | D4: 2 | E4: 6 | F4: 7 | G4: 9 | H4: 13 | I4: 15 | J4: 19 | K4: 21 | L4: 25 | M4: 1 | N4: 2 | O4: 6 | P4: 7 | Q4: 9 | R4: 13 | S4: 15 | T4: 19 | U4: 21 | V4: 25 | W4: 1 | X4: 2 | Y4: 6 | Z4: 7 | AA4: 9 | AB4: 13 | AC4: 15 | AD4: 19 | AE4: 21 | AF4: 25 | AG4: 1 | AH4: 2 | AI4: 6 | AJ4: 7 | AK4: 9 | AL4: 13 | AM4: 15 | AN4: 19 | AO4: 21 | AP4: 25 | AQ4: 1 | AR4: 2 | AS4: 6 | AT4: 7 | AU4: 9 | AV4: 13 | AW4: 15 | AX4: 19 | AY4: 21 | AZ4: 25 | BA4: 1 | BB4: 2 | BC4: 6 | BD4: 7 | BE4: 9 | BF4: 13 | BG4: 15 | BH4: 19 | BI4: 21 | BJ4: 25 | BK4: 1 | BL4: 2 | BM4: 6 | BN4: 7 | BO4: 9 | BP4: 13 | BQ4: 15 | BR4: 19 | BS4: 21 | BT4: 25 | BU4: 1 | BV4: 2 | BW4: 6 | BX4: 7 | BY4: 9 | BZ4: 13 | CA4: 15 | CB4: 19 | CC4: 21 | CD4: 25 | CE4: 1 | CF4: 2 | CG4: 6 | CH4: 7 | CI4: 9 | CJ4: 13 | CK4: 15 | CL4: 19 | CM4: 21 | CN4: 25 | CO4: 1 | CP4: 2 | CQ4: 6 | CR4: 7 | CS4: 9 | CT4: 13 | CU4: 15 | CV4: 19 | CW4: 21 | CX4: 25 | CY4: 1 | CZ4: 2 | DA4: 6 | DB4: 7 | DC4: 9 | DD4: 13 | DE4: 15 | DF4: 19 | DG4: 21 | DH4: 25 | DI4: 1 | DJ4: 2 | DK4: 6 | DL4: 7 | DM4: 9 | DN4: 13 | DO4: 15 | DP4: 19 | DQ4: 21 | DR4: 25 | DS4: 1 | DT4: 2 | DU4: 6 | DV4: 7 | DW4: 9 | DX4: 13 | DY4: 15 | DZ4: 19 | EA4: 21 | EB4: 25 | EC4: 1 | ED4: 2 | EE4: 6 | EF4: 7 | EG4: 9 | EH4: 13 | EI4: 15 | EJ4: 19 | EK4: 21 | EL4: 25 | EM4: 1 | EN4: 2 | EO4: 6 | EP4: 7 | EQ4: 9 | ER4: 13 | ES4: 15 | ET4: 19 | EU4: 21 | EV4: 25 | EW4: 1 | EX4: 2 | EY4: 6 | EZ4: 7 | FA4: 9 | FB4: 13 | FC4: 15 | FD4: 19 | FE4: 21 | FF4: 25
A5: Base Class | B5: =COUNTA(C5:FF5)/1.6 -> 100 | C5: Archer | D5: Archer | E5: Archer | F5: Archer | G5: Archer | H5: Archer | I5: Archer | J5: Archer | K5: Archer | L5: Archer | M5: Monk | N5: Monk | O5: Monk | P5: Monk | Q5: Monk | R5: Monk | S5: Monk | T5: Monk | U5: Monk | V5: Monk | W5: Rogue | X5: Rogue | Y5: Rogue | Z5: Rogue | AA5: Rogue | AB5: Rogue | AC5: Rogue | AD5: Rogue | AE5: Rogue | AF5: Rogue | AG5: Teknixian | AH5: Teknixian | AI5: Teknixian | AJ5: Teknixian | AK5: Teknixian | AL5: Teknixian | AM5: Teknixian | AN5: Teknixian | AO5: Teknixian | AP5: Teknixian | AQ5: Barbarian | AR5: Barbarian | AS5: Barbarian | AT5: Barbarian | AU5: Barbarian | AV5: Barbarian | AW5: Barbarian | AX5: Barbarian | AY5: Barbarian | AZ5: Barbarian | BA5: Fighter | BB5: Fighter | BC5: Fighter | BD5: Fighter | BE5: Fighter | BF5: Fighter | BG5: Fighter | BH5: Fighter | BI5: Fighter | BJ5: Fighter | BK5: Knight | BL5: Knight | BM5: Knight | BN5: Knight | BO5: Knight | BP5: Knight | BQ5: Knight | BR5: Knight | BS5: Knight | BT5: Knight | BU5: Spellsword | BV5: Spellsword | BW5: Spellsword | BX5: Spellsword | BY5: Spellsword | BZ5: Spellsword | CA5: Spellsword | CB5: Spellsword | CC5: Spellsword | CD5: Spellsword | CE5: Bard | CF5: Bard | CG5: Bard | CH5: Bard | CI5: Bard | CJ5: Bard | CK5: Bard | CL5: Bard | CM5: Bard | CN5: Bard | CO5: Binder | CP5: Binder | CQ5: Binder | CR5: Binder | CS5: Binder | CT5: Binder | CU5: Binder | CV5: Binder | CW5: Binder | CX5: Binder | CY5: Cleric | CZ5: Cleric | DA5: Cleric | DB5: Cleric | DC5: Cleric | DD5: Cleric | DE5: Cleric | DF5: Cleric | DG5: Cleric | DH5: Cleric | DI5: Reaper | DJ5: Reaper | DK5: Reaper | DL5: Reaper | DM5: Reaper | DN5: Reaper | DO5: Reaper | DP5: Reaper | DQ5: Reaper | DR5: Reaper | DS5: Psychic | DT5: Psychic | DU5: Psychic | DV5: Psychic | DW5: Psychic | DX5: Psychic | DY5: Psychic | DZ5: Psychic | EA5: Psychic | EB5: Psychic | EC5: Runemage | ED5: Runemage | EE5: Runemage | EF5: Runemage | EG5: Runemage | EH5: Runemage | EI5: Runemage | EJ5: Runemage | EK5: Runemage | EL5: Runemage | EM5: Witch | EN5: Witch | EO5: Witch | EP5: Witch | EQ5: Witch | ER5: Witch | ES5: Witch | ET5: Witch | EU5: Witch | EV5: Witch | EW5: Wizard | EX5: Wizard | EY5: Wizard | EZ5: Wizard | FA5: Wizard | FB5: Wizard | FC5: Wizard | FD5: Wizard | FE5: Wizard | FF5: Wizard
A6: Gender | B6: =COUNTA(C6:FF6)/1.6 -> 100 | C6: Male | D6: Male | E6: Male | F6: Male | G6: Male | H6: Male | I6: Male | J6: Male | K6: Male | L6: Male | M6: Male | N6: Male | O6: Male | P6: Male | Q6: Male | R6: Male | S6: Male | T6: Male | U6: Male | V6: Male | W6: Male | X6: Male | Y6: Male | Z6: Male | AA6: Male | AB6: Male | AC6: Male | AD6: Male | AE6: Male | AF6: Male | AG6: Female | AH6: Female | AI6: Female | AJ6: Female | AK6: Female | AL6: Female | AM6: Female | AN6: Female | AO6: Female | AP6: Female | AQ6: Female | AR6: Female | AS6: Female | AT6: Female | AU6: Female | AV6: Female | AW6: Female | AX6: Female | AY6: Female | AZ6: Female | BA6: Female | BB6: Female | BC6: Female | BD6: Female | BE6: Female | BF6: Female | BG6: Female | BH6: Female | BI6: Female | BJ6: Female | BK6: Male | BL6: Male | BM6: Male | BN6: Male | BO6: Male | BP6: Male | BQ6: Male | BR6: Male | BS6: Male | BT6: Male | BU6: Female | BV6: Female | BW6: Female | BX6: Female | BY6: Female | BZ6: Female | CA6: Female | CB6: Female | CC6: Female | CD6: Female | CE6: Male | CF6: Male | CG6: Male | CH6: Male | CI6: Male | CJ6: Male | CK6: Male | CL6: Male | CM6: Male | CN6: Male | CO6: Female | CP6: Female | CQ6: Female | CR6: Female | CS6: Female | CT6: Female | CU6: Female | CV6: Female | CW6: Female | CX6: Female | CY6: Male | CZ6: Male | DA6: Male | DB6: Male | DC6: Male | DD6: Male | DE6: Male | DF6: Male | DG6: Male | DH6: Male | DI6: Male | DJ6: Male | DK6: Male | DL6: Male | DM6: Male | DN6: Male | DO6: Male | DP6: Male | DQ6: Male | DR6: Male | DS6: Female | DT6: Female | DU6: Female | DV6: Female | DW6: Female | DX6: Female | DY6: Female | DZ6: Female | EA6: Female | EB6: Female | EC6: Male | ED6: Male | EE6: Male | EF6: Male | EG6: Male | EH6: Male | EI6: Male | EJ6: Male | EK6: Male | EL6: Male | EM6: Female | EN6: Female | EO6: Female | EP6: Female | EQ6: Female | ER6: Female | ES6: Female | ET6: Female | EU6: Female | EV6: Female | EW6: Female | EX6: Female | EY6: Female | EZ6: Female | FA6: Female | FB6: Female | FC6: Female | FD6: Female | FE6: Female | FF6: Female
A7: Associated Demon | B7: =COUNTA(C7:FF7)/1.6 -> 100 | C7: Ipos | D7: Leraje | E7: Dantalion | F7: Allocer | G7: Pazazu | H7: Baphomet | I7: Demogorgon | J7: Set | K7: Glasya | L7: Andras | M7: Glasya | N7: Gusion | O7: Pazazu | P7: Andras | Q7: Scarmiglione | R7: Sabnock | S7: Orobas | T7: Levistus | U7: Paimon | V7: Gaap | W7: Ipos | X7: Geryon | Y7: Mammon | Z7: Sabnock | AA7: Bifrons | AB7: Glasya | AC7: Gusion | AD7: Orobas | AE7: Andras | AF7: x | AG7: Belial | AH7: Haagenti | AI7: x | AJ7: Mammon | AK7: Orobas | AL7: Tiamat | AM7: Leraje | AN7: Orcus | AO7: Rubicante | AP7: Eligos | AQ7: x | AR7: Dagon | AS7: Gaap | AT7: Demogorgon | AU7: Focalor | AV7: Murmur | AW7: Allocer | AX7: Andras | AY7: Demogorgon | AZ7: Gusion | BA7: Ipos | BB7: Sabnock | BC7: Levistus | BD7: Agares | BE7: Succor-Benoth | BF7: Paimon | BG7: Marchosias | BH7: Dispater | BI7: Focalor | BJ7: Baphomet | BK7: Dispater | BL7: Baalzebul | BM7: Nurgal | BN7: Paimon | BO7: Levistus | BP7: Tiamat | BQ7: Scarmiglione | BR7: Rubicante | BS7: Dantalion | BT7: Moloch | BU7: Gaap | BV7: Rubicante | BW7: Scarmiglione | BX7: Marchosias | BY7: Baphomet | BZ7: Mammon | CA7: Levistus | CB7: Moloch | CC7: Geryon | CD7: Astaroth | CE7: Baalzebul | CF7: Bifrons | CG7: Orcus | CH7: Eligos | CI7: Focalor | CJ7: Marchosias | CK7: Baphoment | CL7: Succor-benoth | CM7: Lilith | CN7: Asmodeus | CO7: Shax | CP7: Set | CQ7: Gusion | CR7: Pazazu | CS7: Allocer | CT7: Murmur | CU7: Lilith | CV7: Mephisto | CW7: Hastur | CX7: Dagon | CY7: Abaddon | CZ7: Lilith | DA7: Dagon | DB7: Asmodeus | DC7: Agares | DD7: Decarabia | DE7: Marchosias | DF7: Astaroth | DG7: Nurgal | DH7: Hecate | DI7: Focalor | DJ7: None | DK7: Baalzebul | DL7: Set | DM7: Abaddon | DN7: Agares | DO7: Murmur | DP7: Succor-benoth | DQ7: Astaroth | DR7: Mephisto | DS7: Pazazu | DT7: Shax | DU7: Murmur | DV7: Bifrons | DW7: Hecate | DX7: Decarabia | DY7: Asmodeus | DZ7: Hastur | EA7: Eligos | EB7: Belial | EC7: Dispater | ED7: Haagenti | EE7: Scarmiglione | EF7: Leraje | EG7: Belial | EH7: Decarabia | EI7: Abaddon | EJ7: Tiamat | EK7: Hastur | EL7: Shax | EM7: Abaddon | EN7: Hecate | EO7: Moloch | EP7: Orcus | EQ7: Ipos | ER7: Haagenti | ES7: Dantalion | ET7: Nurgal | EU7: None | EV7: Geryon | EW7: Eligos | EX7: Orcus | EY7: Dagon | EZ7: Tiamat | FA7: Paimon | FB7: Mephisto | FC7: Baalzebul | FD7: Agares | FE7: Gaap | FF7: Shax
A8: Quote | B8: =COUNTA(C8:FF8)/1.6 -> 39.375 | D8: “A person can turn from predator to prey in just an instant.” | E8: “It’s a simple enough device to use even you should be able to handle it.” | H8: “There’s a bounty for your head. Not sure about the rest of your body.” | M8: “This is what all my training has led to.” | Q8: “Be like the stone, unbreakable, unyielding.” | R8: “Get in. Get the job done. Get out. Don’t get spotted.” | U8: “I strike like lightning, and thunder follows.” | V8: “One more drink and I’ll get to it.” | AQ8: “It’s simple. I am the brute squad.” | AX8: “You look absolutely delicious.” | AY8: “Sometimes to save what we love, we must destroy everything.” | AZ8: “I am the lord of all beasts who walk the earth. They bow before me.” | BA8: “I’ve always wanted to compete in the big show.” | BG8: “Is there no honor in how you fight?” | BH8: “There’s no stopping me now.” | BK8: “You can trust me with your life, as long as the gold is good.” | BL8: “To get to the king, you have to get through me.” | BM8: “By my liege and blade, I will not let you fall.” | BS8: “You shall see the light of Hugh. Accept its glory or burn by it.” | BU8: “Lightning is ideal for keeping your opponents off-balance, though some complain it is unpredictable.” | BX8: “Acid is ideal for destroying an opponent’s defenses, though some complain it works too slow.” | BY8: “You can get anything for the right price.” | CF8: “Let me tell you a joke.” | CG8: “I sing of death and despair. It is an all-too-common song.” | CN8: “The light will shine, and burn corruption away.” | CO8: “Have you met my friends yet?” | CR8: “Everything will be in balance.” | CS8: “These are the souls bound to us, the spirits that guide our path.” | CU8: “I have seen your fate written in the stars.” | CW8: “There are things from beyond our realm that can serve us very well. Or perhaps we shall serve them.” | CY8: “Pray for me now and at the hour of my death.” | DA8: “My faith shall protect me from illness.” | DB8: “And so God filled the flesh of man with his own divinity to protect us from the Calamities that faced the world.” | DC8: “You’re not dying on me. Not here. Not now.” | DD8: “Begone. Back to hell, foul spirit.” | DE8: “Some say we are mere dreams of his. Let us make them happy dreams.” | DG8: “The effects of this disease are most intriguing.” | DJ8: “I do not care whether you are guilty or not, only that you were sent to me.” | DK8: “By Hugh, these bastards won’t just stay buried, will they?” | DL8: “Look at him, swaying in the wind, like a carrion banner.” | DN8: “Your sins are so intricate, so delicious. You are quite the feast.” | DO8: “Sleep now. Let it all fade away.” | DQ8: “Let me give you the mercy of oblivion” | DR8: “It is no longer reality that threatens you the most.” | DS8: “I know what you’re thinking, and I would advise against it.” | DT8: “Don’t bother standing in my way. I have the power to move you.” | DU8: “Let me help you forget it all. Is there any greater gift I could give to you?” | DV8: “Look deep into my eyes…” | DW8: “I knew what you were planning even before you did.” | EA8: “Time is just an illusion.” | EB8: “You have no will of your own.” | EC8: “A simple answer for you: No.” | EF8: “Leave me be, or you will regret it.” | EG8: “You have become overly reliant on these spells of yours.” | EH8: “It is so easy to underestimate the power of the written word.” | EM8: “I didn’t understand what I would be giving up joining them.” | EO8: “Too long has it been witches burned at the stake.” | ET8: “A fingernail, some hair, a bit of blood. The resemblance is uncanny, isn’t it?” | EV8: “I shall be seen as an equal by the demon lords.” | FA8: “I am the fury of the storm incarnate. Behold me and prepare to be blown away.” | FB8: “I shall burn away all resistance and dissent.” | FC8: “Fire, earth, water, air? Inconsequential. All that matters is magic essence.” | FE8: “So, I speak the words, and the words are power, and power becomes reality.”
A9: Description | B9: =COUNTA(C9:FF9)/1.6 -> 100 | C9: An early-action specialist who seizes the opening of battle with scouted abilities that can only be used as the first action of a wave, then transform into a lesser related ability afterward. He builds aim quickly, attacks enemies at full health for bonus damage, and is difficult to eliminate before he gets to act. | D9: A distance fighter who uses momentum to enhance his arrows and can penetrate armor more effectively the further away his target is. He tracks a specific enemy type, gaining bonuses against others of the same kind as his primary aim target and hitting harder the longer he sustains focus. | E9: A heavy crossbow specialist who attacks more slowly than other archers but deals more damage per shot with greater penetration. He is more defensive than most archer subclasses, reacting to enemy attacks against him rather than purely pressing offense, and can fortify and reload quickly between shots. | F9: An accuracy and penetration specialist who places marks on enemies that grant his allies benefits when they attack the same targets. He is the team's force multiplier at range, making his aim target more dangerous for everyone and sharing his exceptional accuracy with those who follow his lead. | G9: A companion-focused archer whose pet falcon harries targets and enables abilities that either work better in the falcon's presence or require it outright. He uses the falcon to set up aim, distract enemies, and coordinate strikes — making his companion an active offensive asset rather than a passive attendant. | H9: A capture-specialist who places bounty afflictions on enemies as minor actions during combat, with those bounties triggering beneficial effects when the marked enemy dies. He can stun and incapacitate targets to take them alive, gaining increasing payoffs the more bounties he has active when enemies fall. | I9: A shadow-fighter who generates aim from hidden status and converts high accuracy into higher damage, with a defining ability that expends all accumulated aim for a devastating single attack — but then prevents him from targeting that specific enemy for a period scaled to the aim spent. | J9: A kill-opportunist who triggers immediate prepared attacks the moment an enemy becomes endangered, without those poach abilities being interruptible by damage. He gains culling abilities, preferences for specific target types, and benefits from kills — a specialist at finishing weakened prey faster than anyone else can reach them. | K9: A trick-shot specialist whose accuracy-dependent abilities pierce through targets to hit columns behind them and have reduced hit chance but significant effects when they connect. His trick shot success rate scales with current aim relative to maximum aim, rewarding sustained focus on a single target before committing to the high-risk high-reward shots. | L9: A distance-and-duration specialist who builds power over the course of a long battle through eternal buff abilities that grow without limit but become progressively more expensive to enhance. Only one can be active at a time, demanding that the player commit to a single compounding effect and protect the Toxophilite long enough for it to pay off. | M9: A patient striker who builds power by holding his form and releases it explosively on transition. His unleash mechanic rewards stillness — the longer he stays in a single form, the more devastating the eventual change. He has no form preference, making him the most flexible of the monk subclasses and a strong foundation for learning the chakra system. | N9: A relentless single-target brawler who punishes the same enemy turn after turn through his impact mechanic. Any enemy he struck last turn becomes the target of a suite of specialized follow-up attacks covering damage, delay, disruption, and control. Lower chakra focused and strength-enhanced, he hits harder the longer he stays locked onto one target. | O9: A fast, opportunistic fighter who mirrors his enemies' own strengths against them through the matching mechanic. He can temporarily adopt a target's critical stats, damage, accuracy, defense, or dodge — turning powerful enemies into their own worst nightmare. Leopard form focused and haste-driven, he excels at demolishing stunned foes and stacking bleeds through repeated Leopard Claw cycles. | P9: An immovable reactive combatant who weaponizes his chakra configuration to punish every enemy attack. Snake's Response reflects conditions back at attackers based on which chakras are open, with the lower chakras delivering the most devastating punishments — prone, delay, and disarm simultaneously at full configuration. He fights best when pristine, baiting attacks while armed with Reversal, Absorbed Counter, and a full suite of prepared reactions. | Q9: A fortified earth specialist who turns glancing blows from a weakness into a weapon. His attacks deliberately seek glancing hits to trigger stuns, bleeds, delays, and fragility — and his Pressure Crack capstone extends this to critical hits as well. Tiger form focused and endurance-heavy, he is nearly immovable under sustained assault and punishes enemies for every attempt to pierce his defenses. | R9: A burst-damage specialist who cycles through hidden states to deliver devastating arrival attacks. Each time he loses hidden — whether by choice or enemy action — he unleashes a different arrival ability covering area damage, flanking, stunning, or penetrating strikes. Mantis focused and initiative-driven, his Exposed Momentum capstone ensures every exposure accelerates his next turn. | S9: A poison-crafting snake form specialist who generates unique toxins from his own body and bleeds. He creates poisons based on his current form through Venom Chakra, conserves and refreshes them through careful resource management, and delivers them through venomous, insidious, and backbiting strikes. Earth and dark elemental focused, he excels at sustained damage over time and attrition warfare. | T9: A disciplined dragon form purist who draws power from maintaining a state of perfect purity. His most powerful abilities — Fist of Purity, Double Purity, Whirlwind Purity — require being completely unafflicted, while his Condition Fortress capstone makes him progressively harder to afflict as conditions accumulate. He manages corruption, stuns enemies with dragon-powered strikes, and uses focus as both a resource and a defensive tool. | U9: A chain-combat specialist who builds devastating sequences of air, stun, and shatter effects through careful ability ordering. Nearly every move and minor ability has a trigger condition — following a counter, a critical, a shatter, or an air attack — creating dense combo potential that rewards mechanical knowledge. Crane focused and counter-driven, his Thunder Strikes capstone ensures every stunned enemy takes bonus air damage on each hit. | V9: A chaotic form-shifting brawler who embraces randomness and prone states as sources of power rather than liability. He shifts forms rapidly to build Fluid Punch damage, reach Ultimate Punch thresholds, and trigger Chakra Ascension — while deliberately falling prone to counter from the ground and punish enemies with Misplaced Retribution. His unpredictability is his greatest defense, with low accuracy offset by high dodge and a tendency to accidentally hit exactly the wrong person at exactly the right time. | W9: A quick ranged harasser who opens battle at a distance before pivoting to a more dangerous close-quarters fighter when his allies fall. He carries desperation abilities that only activate when he stands alone, rewarding survival over coordinated play. | X9: A dualwield melee brawler who stacks bleed on enemies through relentless two-weapon exchanges and can grant himself intangibility to press the offense without interruption. His advantage generation rewards staying in the fight and bleeding targets dry. | Y9: An ambush specialist who hits hardest against undamaged enemies and strips buffs from those who have fought back. He can artificially recreate full-health windows late in battle by corrupting enemy maximum health, keeping his ambush toolkit relevant throughout. | Z9: A self-sufficient dualwield fighter who steals accuracy, speed, and senses from enemies to empower himself. He can briefly share his incoming healing and mana gain with allies, giving a team-oriented edge to an otherwise personal playstyle. | AA9: A dodge-focused rebuild Rogue who invites attacks, turns misses into advantage, and uses reliable abilities that refund their costs on failure. He thrives in the open and under illumination, unlike most Rogues who prefer the shadows. | AB9: A single-target executioner who signs contracts against chosen enemies, gaining combat bonuses while pursuing them and earning powerful fulfillment rewards when he personally lands the killing blow. Five contract types let the player tailor each hunt to the situation. | AC9: A ranged gambler who wagers advantage and mana on battlefield conditions, collecting larger payoffs when those conditions are met. A good run leaves him flush; a bad one leaves him empty, making risk tolerance the central skill of his playstyle. | AD9: A team-oriented Rogue whose power scales with how many allies are hidden alongside him. He can blanket the party in shadow, share his poisons across the team, and coordinate hidden allies into a unified striking force. | AE9: A defensively self-reliant Rogue who applies aversion to make enemies ignore him, then punishes them for it. He complements aversion with scorn to layer targeting protection, generating advantage steadily from the safety of being overlooked. | AF9: A hidden-mastery specialist who chains haste, advantage, and free bonus attacks by maintaining concealment across multiple actions. He rewards players who have mastered the hidden economy, with insidious attacks and precise sequencing separating competent play from exceptional play. | AG9: A chaotic support-attacker who thrives on unpredictability. Her scavenged abilities reveal their element on preparation rather than use, making her toolkit flexible but harder to plan around. She generates ammo from kills and builds belts from whatever she has on hand — a scrappy, resource-efficient subclass that rewards improvisation. | AH9: A prepared-resource specialist who enters battle with concoctions already brewed and ready to use without cost or preparation. She leans into healing, poison, and resurrection, and her premade system lets her open waves with full-power abilities immediately. Her capstone Premade Reserves deepens this advantage, making her the Teknixian most oriented toward sustained party management. | AI9: A trap-setter and accumulator who builds up power before releasing it. Her accumulation abilities charge on first use and discharge on second, rewarding patience with amplified outputs. She also controls the detonation chain — recovering, redirecting, and shielding through it — and provides elemental shields to allies via Teknos Shielding. | AJ9: A modification-based companion commander who toggles different behavioral modes to reshape her companion and her own attacks. Her four modular abilities — Modular Bomb, Modular Ray, Modular Trap, and Modular Beam — each change behavior based on which modifications are active. Flame Spewer and Lightning Tosser are ammo-sensitive companions that change element and effect based on what's loaded at summoning. | AK9: An ally-empowerment specialist who assigns persistent assistant enchantments to party members. Each assistant type triggers a different proc when the assigned ally attacks — shields, heals, traps, bonus attacks, or quickening — and Activate Assistant can fire all procs simultaneously. She also fields the Shield Guardian, a fixed-behavior healing companion with no ammo interaction, and Minefield Assistant turns any attacker into a trap-seeding machine. | AL9: A high-risk area damage dealer whose bomb abilities hit allies and enemies identically with no discount. She layers countdowns on enemies and manages the self-threat they create using Accept Explosion, Accept Mass Explosion, Gift Bomb, and Transfer Countdown. Explosion Imminent and Kinetic Protection let her mitigate her own friendly fire. The higher the aim output, the harder the landing. | AM9: A pure ranged damage dealer built around called shots and burst ammo expenditure. Called shots are prepared as a minor action, name a target, and add powerful debuff effects — disarm, stun, heartstrike, slow, or delay — to the first attack used against that target on the following turn. Full Clip and Oblivion Shot are her all-in damage options. High Noon and Showdown both guarantee a counter-attack against her, rewarding Take Cover setups. | AN9: A slow-burn debuff-accumulator whose six concoctions apply ongoing effects while building power each clock tick, then discharge a scaled effect when the chain fires or time runs out. More ammo at placement extends the window and increases accumulated power at detonation. A Faraday sub-theme lets her wear lightning rod deliberately and redirect incoming storm damage offensively through Faraday Connection's pain link. | AO9: A companion-amplifier who fields extremely slow, powerful siege engine companions — Ballista, Battering Ram, and Catapult — and spends her own actions making them fire more frequently. Every move and minor ability in her kit serves the companion: Operate Siege Engine quickens it directly, Teamwork Operation converts party delay into companion clock advancement, and Siege Command upgrades whatever the companion would do next. Her own attacks like Amplifying Cannonshot and Earth Cannon give her meaningful damage when she steps away from the engine. | AP9: A relic-stacking power escalator who activates multi-ability relics that grow stronger with each ammo devotion. Each devoted ammo type is locked until the relic ends — which it cannot be cancelled until max devotion — creating deep commitment costs in exchange for battlefield-wide buffs, persistent damage, companion power, or trap generation. Relic Blast and Relic Bolt scale with total ammo devoted across all active relics, making a fully stacked Reliquarian increasingly devastating the longer a wave goes on. | AQ9: The patient tank of the Barbarian family. A slower, higher-endurance variant who defers self-damage costs to the next turn through Consequences, generating Anguish immediately while controlling when the pain lands — or redirecting it to enemies entirely with Share Consequence. | AR9: A shield-and-weapon fighter who builds active defenses only to spend them all at once. Reckless abilities consume all block, dodge, and counter values for amplified attacks, rewarding players who time the exposed window around a supporting tank or use it as a finisher when consequences can't resolve. | AS9: The chaos amplifier of the family, built around Exertion abilities that generate Anguish from repeated misses and spread destruction through Contagious Temper. She leans fully into the Berserk condition, turning random targeting from a liability into an engine, with the Panic pair offering a rare moment of choice between embracing or escaping the disorder. | AT9: A dual-wield closer who grows faster and hits harder the more enemies die. Rampage scales with kills — personal kills more than team kills — making bloodlust and counter abilities the tools that keep her offense rolling between turns and feeding the escalation she depends on. | AU9: A deliberate shield fighter who charges prepared abilities through sustained blocking. Each block adds power to any held ability, and multiple prepared abilities charge independently, rewarding patient setup and precise release timing over the Raider's impulsive spending. | AV9: Pure escalating output. She accumulates damage dealt toward a threshold that briefly unlocks Brink abilities — powerful options that vanish if not taken — and can sustain Endless Wrath longer than any other subclass before the drain finally overtakes her. | AW9: Precise and fast, with a discipline that belies her name. Purity abilities amplify with each use but cancel on specific failure conditions, demanding focused play to maintain multiple stacks simultaneously. She grows faster as she takes damage and reaches peak power when Wrath and Berserk combine. | AX9: A self-sustaining predator who stays hurt to stay fed. Her healing threshold mechanic unlocks powerful abilities as applicable healing accumulates, rewarding healers who time large heals over constant top-offs, while life drain and kill-reaction heals give her independence when the support is occupied elsewhere. | AY9: The armor-stripping heavyweight, built to cross the massive damage threshold and trigger cascading effects that tear down enemy defenses for the whole team. Destruction Wrath amplifies weakness power and defense reduction, but ends in forsaken and strips all enchantments — making dedicated buffers a liability rather than an asset. | AZ9: The apex predator and most complex of the Barbarian subclasses. She cycles between four exclusive beast forms, scales overkill into team-wide debuffs, and generates Anguish from damage dealt to any ally — turning chaotic encounters into fuel. Final Wrath guarantees her death when it ends, making every use of it the last decision she makes. | BA9: A flashy, risk-taking fighter who uses gambit abilities that either succeed spectacularly or backfire against her. Critical Stance generates expertise on critical hits, and her gambits deal high damage or critical effects at a cost — such as becoming prone on a miss or inviting counter attacks — rewarding aggressive play with chain weapons. | BB9: A one-handed sword specialist who excels at counter attacks and is almost impossible to disarm or knock down. Counter Stance generates expertise whenever she counters, and her kit is built around parries and ripostes — parrying an attack, then immediately punishing the attacker with a follow-up strike. | BC9: A heavy shield bearer who fights best alongside ready allies. Shield Stance generates expertise on every block, and her toolkit includes guaranteed blocks, fortification at the cost of tired, and Phalanx Power, which enhances the damage of all ready allies based on how many are still standing. | BD9: A dual-wielding speed specialist whose defining abilities trigger on the second strike of a sequence, becoming more powerful the sooner that second hit follows the first. Speed Stance generates expertise from quicken effects, and she builds momentum and haste through attacks to fuel an escalating flurry of blows. | BE9: An extraordinarily accurate fighter who specializes in pinpoint attacks that can activate additional conditions at high enough values. Pinpoint Stance generates expertise from hit rolls beyond what is needed to connect, and her kit rewards fighting alone — with Alone Damage and Alone Defense passives that keep her effective as the last fighter standing. | BF9: A polearm and spear specialist whose Lancing Blow attacks have a chance to pierce through the primary target and hit the enemy behind them. Retaliation Stance generates expertise through retaliating, and she brings mounted abilities and column-targeting attacks that reward controlling space and threatening multiple rows at once. | BG9: An initiative-focused dual-wielder who seizes the opening of every battle with maximum aggression. Dodge Stance generates expertise on dodges, and Suicide Stance trades increased offense and counter-chance for the willingness to be struck, generating expertise from taking hits and rewarding an all-or-nothing fighting style. | BH9: An immovable defensive combatant who weaponizes his durability offensively. Unmovable Stance generates expertise from movement effects targeting him, and Advanced Unmovable Stance reflects delays back at enemies, turning every attempt to slow him into a punishment for the attacker. | BI9: A sword-fighting parry expert whose feint abilities compel enemies to attack her, then punish them when she parries the incoming strike. Parry Stance generates expertise from each successful parry, and she chains feints into ripostes, bleeds, penetrating attacks, or mass taunts depending on which feint variant she has prepared. | BJ9: A commanding leader who translates her own expertise directly into team-wide benefits. Warlord's Stance generates expertise whenever any ally acts, and her Leadership abilities require a minimum expertise level and become more powerful at higher thresholds — quickening all allies, enhancing their damage, or even making their next attack unerring after she misses. | BK9: The most protective Knight subclass, built around absorbing punishment meant for others. Full Guard shifts all damage to him by chance, and a deep suite of Intercession abilities lets him step in front of specific threats — criticals, deathblows, afflictions, storm attacks — before they reach his guarded ally. | BL9: An overkill specialist who grows stronger the harder he hits. Punishment Guard turns damage against his guarded ally into fuel for his own attacks, and every kill feeds Ire abilities that reward excess — healing, shielding, disrupting, and damaging all enemies based on how far past death the target went. | BM9: A healer-warrior whose offensive power is tied to his guarded ally's suffering. The Righteous mechanic scales his damage and afflictions based on the health gap between his guarded and their target, making him most dangerous when protecting a wounded ally — and most selfless when the cost of that protection is highest. | BN9: A mounted aggressor who rewards speed and positioning. Delay Guard quickens him whenever his guarded is delayed, and his kit emphasizes mount synergy, momentum, and patrol abilities that punish enemies for targeting his guarded ally at all. | BO9: A block-stacking endurance specialist whose Continuous Guard abilities grow stronger with every hit he absorbs. The longer he holds the line, the harder he becomes to bypass — though unchecked stacking risks tipping him into immortality territory that needs playtesting scrutiny. | BP9: A mounted elemental disruptor who turns magic against those who cast it. He reflects elemental afflictions, punishes mana use, and enhances his reflections through magic defense investment — making him the Knight best suited to protecting allies from spellcasters. | BQ9: A dual-wielding conquest machine who chains kill effects into team-wide benefits. Parry Guard extends his parry to his guarded ally, and Conquest abilities convert kills into mana, heals, purges, quickens, and in extremis — resurrection — rewarding aggressive play with cascading advantages. | BR9: A dark mirror of the Knight archetype who weaponizes corruption. He deliberately accumulates it, benefits from it, and shares its dangers with his guarded ally. Vengeance Guard extends retaliation to his guarded, turning incoming damage into a mutual threat. | BS9: A high-ceiling Battalion specialist who demands mastery of turn order to unlock his full potential. He waits, coordinates, and strikes in unison with allies — with rewards that scale based on how long and how many waited together. Most powerful when the player understands the clock. | BT9: A battlefield consecrator who sustains active Temple field effects at the cost of his mana. Each Temple reshapes the conditions of combat for everyone on the field, and Sacred Ground rewards commitment to one Temple over time. At Tier 25, he is the Knight at his most commanding — protecting not just one ally, but the entire sacred space around him. | BU9: Air-element aggressor who punishes stunned enemies. Charges dominion abilities off air damage dealt each turn to gain speed, disrupt her challenge, and deal bonus damage. Lightning Conductor makes every stun a passive damage source, rewarding her heavy stun toolkit with automatic attrition. | BV9: Fire-specialist who wounds foes and punishes them for it. Charges dominions off fire damage to gain retaliation, apply fire countdowns, and weaken fire resistance. Open Wounds amplifies all bleeds against wounded enemies, turning her wound application tools into a force multiplier for the whole team. | BW9: Control-oriented water Knecht who delays and slows her way to dominance. Charges dominions off water damage to regenerate health, delay her challenge, and drain its mana. Accumulating Frost converts incoming delays into damage shields, punishing enemies who try to control her back. | BX9: The tankiest Knecht, built around fortification, damage shields, and defense reduction. Charges dominions off earth damage to build shields, cause earth bleed, and knock her challenge prone. Spike Burst makes every broken damage shield an earth damage counterattack, punishing enemies for hitting through her armor. | BY9: Elemental generalist and dual-wielder who rewards elemental variety. Chains Persistence and Insistence abilities off prior elemental use within the same turn, building toward Rainbow Spectrum's damage bonus. Overriding Challenge lets her re-challenge freely as long as she's already demonstrated two elements that turn — rewarding her natural play pattern. | BZ9: Enhancement-focused Spellsword who builds a personal arsenal of buffs and weaponizes them. Each elemental Transmutation Strike grants a different power enhancement; Enhanced Onslaught converts those stacked enhancements directly into bonus elemental damage against her challenge. Forged Resistance passively builds elemental resistances through offense, and Stolen Form and Match Form let her steal her challenge's own tools against it. | CA9: Arcane penetration specialist who phases in and out of the material plane. Ghostshift makes her intangible, unlocking a suite of unblockable, unparryable, and phasing attacks. Carry to the Ghostrealm lets her drag her challenge into intangibility with her, and Explosive Exit detonates arcane damage against all enemies every time she drops the state. | CB9: The ultimate barrier tank, built entirely around absorbing hits and converting them to offense. Five Abrogation abilities prepare different reactions to barrier triggers — immediate actions, team barriers, arcane damage, delays, or purges. Extended Barrier extends her protection even to phasing attacks, making her the hardest unit in the game to damage outright. | CC9: Evasion-based dark Spellsword who makes herself nearly untargetable by everyone except her challenge. Uses avert, scorn, and hidden to redirect enemy attention while pressuring the challenge with life drain and dark damage. Contemptuous Response punishes the rare enemy that breaks through her defenses with an immediate counter, and Midnight Nemesis resets her aversion after every challenge attack. | CD9: Climactic finisher built around killing her challenge spectacularly. Final Strike abilities each deliver a different team-wide benefit the moment the challenge dies — buffs, enduring, mana, haste, or area damage. Triple and Random Decimation stack the Decimated condition on all enemies, and Death Sentence converts her challenge kill into a decimation wave that crashes across the entire remaining battlefield. | CE9: Crescendo-driven buffer who rewards spending small actions on allies to power up larger payoffs. Builds Crescendo stacks through move and minor buffs, then releases them through scaling heal, shield, damage, bleed, and mana abilities. Leans toward chords and positive effects, with strong regeneration support alongside his offensive Crescendo tools. | CF9: Chaos-specialist who floods enemies with random afflictions, unpredictable conditions, and misdirected attacks. No formal mechanic — the unpredictability is the design. Best used to overwhelm enemy resistances and create openings for allies, with a capstone that turns his own misfortune into tempo. | CG9: The most offensively oriented bard subclass, specializing in life drain, culling, and damage-focused dischords rather than traditional support. He turns the song mechanic toward attrition and erasure — draining life, finishing weakened enemies, and using death itself as an element of his performance. Cacophony abilities reward the whole team's investment in debuffing, making him most dangerous in coordinated groups. | CH9: Earth-focused sustain specialist who stacks litany effects on allies and enemies for escalating pressure. Juggles short-duration stacking conditions that demand constant reapplication — letting them expire collapses the investment. Extended Cuts rewards commitment by progressively raising duration ceilings the more a condition is refreshed. | CI9: Elemental support and disruption specialist who grants deity-named favors to allies, healing them and loading them with elemental damage adds. Simultaneously harasses enemies with water and air magic, knockdowns, and delays. Favor of the Drum doubles every favor with a free untyped add, making his allies' attacks substantially more dangerous. | CJ9: Stealth-integrated bard who supplements song management with disguises and flanking setups. Each disguise grants role-specific bonuses and can be dramatically discharged for a powerful effect at the cost of the disguise itself. Begins every battle already in disguise, giving immediate access to his full toolkit from the first action. | CK9: Dark magic manipulator who fights most effectively when enemies cannot see him. Avert, scorn, and hidden each provide a different path to his veiled abilities, which hit harder than normal. Elusive Rhythm turns successful misdirection into tempo, rewarding a Mountebank who keeps multiple avoidance conditions active simultaneously. | CL9: Conductor-style support who grants allies free attacks through Entourage abilities, drawing enemy aggression onto protected performers. Provokes and taunts redirect incoming damage to allies who are simultaneously shielded, dodging, or enduring. Dedicated Entourage extends every provoke granted, making each protected performer absorb more before attention shifts. | CM9: Resurrection-focused support whose most powerful abilities unlock only after an ally returns to life. Epiphany abilities turn each resurrection into a cascade of heals, buffs, mana, and free attacks. His retaliation theme gives him an offensive identity when not raising allies, and Encore ensures he can survive long enough to finish his performance. | CN9: Aura-and-light specialist who illuminates the battlefield to empower allies and punish enemies. Manages multiple sustained auras simultaneously while spreading illuminate to lock enemies out of hidden and set up targeted light abilities. Constant Light makes him a hard counter to all stealth-based enemy strategies, fundamentally reshaping how battles play out at Tier 25. | CO9: A summoner who fights in concert with her conjured allies, using their mana reserves to amplify her own attacks. She manifests spectral weapons for any ally and directs her companion with precision, growing stronger the more she and her creature act as one. | CP9: A Thanatos-leaning controller who wraps herself and allies in retaliatory spirits, punishing enemies for every strike they land. She pairs water and air magic for freeze and delay with a cross-alignment toolkit that rewards deliberate dips into Eros. | CQ9: A support specialist who prepares a battery of Attendant abilities and waits for her companion to critical — triggering all of them at once in a cascade of healing, damage, and quickening. The longer she waits, the more devastating the payoff. | CR9: A balanced-alignment caster who draws equal power from both dark and light, strongest when she resists pushing to either extreme. Her Harmony abilities detonate from center for massive effect, then push her off balance — and she spends the next turns clawing her way back. | CS9: A spiritual warrior who infuses her companion with procs before it acts and rides a summoned Spirit Beast into mounted combat. She synchronizes her actions with her creature through a shared spiritual bond, raising fallen companions and granting her allies the will to survive past death. | CT9: A desperation specialist whose entire toolkit unlocks at low health, becoming most powerful precisely when she should be most vulnerable. Her transformation locks in that endangered power permanently, turning near-death into a lasting combat state. | CU9: A critical-hit amplifier who builds toward celestial thresholds across multiple turns, generating mana, quickening herself, and purging afflictions with each enemy she crits. She wields the full elemental spectrum through a stellar lens, with her lucky damage toolkit turning probability itself into a weapon. | CV9: A selfish corruptor who damages her own allies to fuel her offensive power, scaling with the total corruption she spreads across the battlefield. She transforms her own self-inflicted corruption into a permanent power state, and turns enemy deaths into mana through Dark Harvest. | CW9: A sanity-sacrificing chaos mage who deliberately accumulates illusory damage on herself to unlock her most powerful abilities. She cannot be killed by her own madness — but when it expires, it becomes very real, making resource management a matter of survival. | CX9: A high-commitment alignment specialist who signs powerful ongoing Pacts, each granting two bonuses at the cost of one persistent drawback. She thrives at the extremes of the alignment scale, and her Lifebond with her companion means their fates are literally intertwined — she cannot fall while it stands. | CY9: Quick and affordable support built around lucky manipulation and regeneration. Generates divinity through hexes, purges, and blessings, then spends it on Benedictions — powerful single-target heals enhanced by current divinity, with overheal effects that range from possession to damage to speed depending on the type used. | CZ9: Pure restoration specialist with the mana economy to sustain heavy healing across a long battle. His cures carry addenda that scale with heal value, turning strong heals into purges, quickens, or damage adds. A Life Domain running on overheal generation lets him convert aggressive healing directly into sustained divinity. | DA9: Affliction-resistant purge specialist who turns enemy pressure into elemental retaliation. Elemental purges double as generators and resistance enhancers scaled to current divinity, and a Protection Domain that rewards affliction resistance creates a feedback loop where enemy affliction pressure fuels his own power. | DB9: Magically aggressive Cleric who layers blessings onto allies while maintaining his own damage shield as an offensive weapon. The Lattice ability line scales with and consumes his shield for light damage and control, Lattice Reflection punishes enemies who target it, and a Sun Domain that generates from light abilities rewards sustained Celestial offense. | DC9: Frontline healer built for endangered allies and active combat. Vitality heals grant temporary bonuses that persist until the target takes damage, and a War Domain that generates from any ally's critical hits rewards pairing him with damage-heavy parties. Perilous Divinity marks low-health targets for stronger healing while generating divinity. | DD9: Light-magic specialist with exclusive access to intangible enemies and strong mana drain. Most abilities gain additional effects against incorporeal targets, and an Exorcism Domain that generates divinity proportional to total enemy mana spent rewards fighting caster-heavy encounters where the domain becomes a powerful self-sustaining engine. | DE9: Sleep-focused controller who worships the sleeping god and grows in power while the world slumbers. Incapacitated allies feed Rest Domain divinity generation even without the Preacher acting, turning sleep from a liability into a resource. Turns ally afflictions into advantages and punishes sleeping enemies with a focused suite of nightmare attacks. | DF9: High-speed melee Cleric who conducts the entire party's tempo through quickening. Ascension abilities require but do not spend full divinity, creating a maintain-and-hold pattern rather than the typical spend-and-rebuild cycle. A mastery class at Tier 19 — maximizing output requires deep awareness of quicken tolerance, Ascension timing, and Fervor Domain generation simultaneously. | DG9: Self-infecting contagion spreader who carries disease deliberately to fuel his domain. Plague Domain generates divinity for each affliction successfully transferred from the Plague Doctor to an enemy, rewarding stacking afflictions on himself and building around affliction resistance to survive the risk. One of the most dangerous and mechanically demanding Cleric subclasses. | DH9: Capstone Cleric whose Furtherance abilities scale with divinity gained during the current turn rather than total on hand. Front-loading a turn with support actions directly amplifies his payoff. A Prophecy Domain that generates divinity when countdowns fire — scaled to their duration — rewards patience and long-term planning over reactive play. | DI9: A water-element Reaper who weaponizes damage afflictions as fuel for conditional kills. He builds bleed, countdown, and hex in a chained cycle, then cashes out their accumulated value in devastating threshold executions — the more damage his curses promise, the deadlier his finishing blow. | DJ9: A cold and efficient finisher who locks onto the weakest enemy and refuses to let them escape. He specializes in culling, conditional kills, and overkill chains, ensuring that no wounded enemy survives long enough to become a threat again. | DK9: An earth-element controller who buries enemies alive, locking them out of combat while setting up punishing follow-up strikes. His buried targets are temporarily untouchable but utterly helpless — patience and precise sequencing determine when they resurface and how much it costs them. | DL9: An air-element strangler who degrades enemy action economy through asphyxiation, building Tired and Exhausted to leave foes gasping and unable to retaliate. He rewards pushing into Spirit Fugue for locked abilities and can sustain himself through near-death with Phoenix Soul. | DM9: A moon-reading diviner who cycles the world's four elemental moons to deliver rotating team-wide enhancements. He adapts his kit to whichever moon is ascendant, shifting between fire, earth, air, and water buffs while wielding chaos, possession, and conditional kill tools between cycles. | DN9: A dark confessor who consumes the afflictions of allies and enemies alike, converting their suffering into fuel for his own attacks. He turns debuffs into weapons — purging curses from his team and launching them back at enemies amplified and weaponized. | DO9: A dream-state manipulator who puts enemies to sleep and punishes them for it, while voluntarily slipping into incapacitation himself to trigger devastating illusory reprisals. He exists in a liminal space between waking and dreaming, exploiting both states with equal precision. | DP9: A paranoia-fueled controller who grows stronger the more enemies surround him, whispering commands into possessed minds and drowning the battlefield in retaliation. He turns enemy numbers from a threat into an advantage, feeding on the chaos of a crowded fight. | DQ9: A relentless finisher who specializes in the endgame of a battle — bleeding, poisoning, and dismantling the last enemy standing. Her kit accelerates toward that final isolated target, delivering the killing blow with empowered fury the moment her prey stands alone. | DR9: A psychological warfare specialist who weaponizes illusion and terror, building illusory damage pools that kill enemies from the inside when they exceed current health. He thrives in Spirit Fugue, his Atmosphere abilities blooming into their full power the deeper into delirium he pushes. | DS9: The entry point for deep influence play. The Telepath specializes in illusory damage and disruption, with heightened abilities that let her translate influence investment into cascading multi-cast effects. She is subtle and methodical, chipping away at enemy defenses before they can act. | DT9: A spread-oriented damage dealer who turns punishment into power. Her kinetic abilities charge between turns based on physical damage she absorbs, making her uniquely dangerous when enemies focus on her. She favors broad pressure and area control over single-target dominance. | DU9: A denial specialist who erodes the enemy's ability to function. She burns through mana, forces enemies into basic attacks, and makes them forget what they were doing. She also carries an unexpected compassionate edge, helping allies forget their wounds. | DV9: A pattern-weaver who controls the entire battlefield through sustained channeled effects. She locks enemies into states of blindness, stun, or vulnerability for as long as she can keep her focus. Patient and methodical, she rewards players who plan their turns carefully. | DW9: An information broker and countdown specialist who fights the future rather than the present. Her divinations expose enemy weaknesses and upcoming actions, letting the whole party respond intelligently, while her countdown abilities punish enemies for the passage of time itself. | DX9: A ghost-touched subclass who exploits enemies at their weakest — specifically when their mana runs dry. She drains, haunts, and possesses with impunity against vulnerable targets, and can become intangible herself to frighten and evade. Death Knell makes her the safest handler of deep influence. | DY9: The party coordinator. Rather than dominating enemies directly, she possesses allies to direct them more efficiently and uses total influence to synchronize team timing. She rewards players who understand their whole roster and rewards smart sequencing over raw power. | DZ9: A high-risk, high-reward glass cannon who bleeds the mind as much as the body. She deals devastating illusory damage that grows stronger the closer she is to death. Her own abilities hurt her, but the connection flows both ways — and she intends to make that cost worth it. | EA9: A spread-influence subclass who bends time itself to delay, rush, and disorient the battlefield. She punishes fast enemies, accelerates allies, and becomes more efficient the more she leans into her hasted or slowed states. Supreme Chronomancy is one of the most powerful single abilities in the psychic tree. | EB9: The pinnacle of possession mastery. She owns enemies outright, bends their will across multiple turns, and profits from every attack they make under her control. Her capstone, Broken Will, ensures that no enemy is ultimately beyond her reach. | EC9: The defensive anchor of the Runemage family, specializing in defense runes that proc when attacked and earth magic that punishes aggression. He builds damage shields, stacks fortification, and redirects enemy attention — a runemage who invites attacks rather than avoiding them. | ED9: A fire-and-reaction specialist who layers trigger runes onto enemies and detonates them for chain damage. He excels at punishing enemies who act predictably, converting their own procs and parries against them, and scaling his piercing through exploitation of negative proc triggers. | EE9: An earth-focused runemage who pairs enchantment runes with a golem companion to create a layered defensive presence. He can fortify and redirect damage through his golem, convert a dying companion into personal survivability through Golem Armor, and punish enemies who bypass his defenses with reflected damage. | EF9: A water-and-affliction specialist who escalates conditions over time, with particular mastery of countdowns, hexes, and stacking water effects. Festering makes purging a liability — removed afflictions return stronger — and his alone toolkit rewards surviving after his allies fall. | EG9: A runemage who strips enemy enchantments and turns them into resources, damage, or afflictions. He punishes enchanted enemies, converts his rune board into a single devastating attack through Rune to Oblivion, and can flip the game state by stealing and weaponizing what enemies rely on. | EH9: A trap-focused arcane specialist who builds mana-reactive field hazards and punishes enemy spellcasting and action patterns. He generates and redirects mana through traps and switches, rewarding dense trap setups with the Trap Spotting capstone that converts each activation into action economy. | EI9: An elemental piercing specialist who focuses runemages' natural elemental identity into a concentrated beam of resistances-ignored damage. He builds prisms for deferred area detonations, charges his elemental runes for enhanced power, and covers the team with elemental shielding and empowerments. | EJ9: A proc amplifier who loads allies and enemies with damage runes and triggers them through Stone Glyph attacks and Glyphic Onslaught. He converts stacked procs into multi-hit chain attacks and distributes rune effects across the party, rewarding dense proc setups with escalating damage. | EK9: A timing rune master who builds countdown engines, manipulates their timers, and squeezes maximum value before consuming them. Remnants of Fate converts every countdown — allied or enemy — into mana, making him a resource engine in any fight heavy with time-based effects. | EL9: The pinnacle runemage, commanding multiple power runes, a three-rune runespell, and a self-reinforcing earth countdown trio that multiplies in power when maintained together. He preserves preparation through the Conserve Preparation capstone and sustains himself through personal countdown engines, building toward overwhelming late-game board states. | EM9: A team-oriented controller who drains stats from maledicted enemies and redistributes them to allies. She weaponizes possession and hexes for direct control while her Malign drain suite debilitates entire maledicted groups — and Share in Consumption ensures no drain benefit passes through her hands without leaving something behind. | EN9: An air-element Witch who turns malediction into a positional weapon. Her whirlwind abilities use a maledicted enemy as an anchor, striking all adjacent foes instead — rewarding grid awareness and central positioning. Bloodlust amplifies her storm attacks while Conductivity makes the entire maledicted field a lightning rod. | EO9: The most aggressive Witch subclass, stacking damage afflictions on targets to fuel piercing effigy attacks that cut through resistance. Flammability turns every fire hit into compounding bleeds, and Personal Effigy rewards taking damage herself — making her a high-risk attacker who burns hotter the more punishment she absorbs. | EP9: A methodical earth-element controller who applies permanent unending afflictions that reserve her mana until enemies die or are purged. She trades mana flexibility for devastating long-term debilitation, and Mana From Dust recycles her investment when corruption finishes the job. | EQ9: A water-element specialist who deals increased damage and effects in inverse proportion to enemy speed — making her strongest against the foes she has already slowed. Chill to Frost converts redundant slows into hard incapacitation, and Inspiring Misfortune makes her one of the strongest mana generators in the entire Witch family. | ER9: A chaotic generalist who trades reliability for volume, deploying cheap bewitch afflictions against maledicted enemies at reduced action cost. Agnostic Afflictions removes elemental opposition penalties on vulnerability and exposure, letting her stack conditions freely regardless of enemy resistances — chaos as a feature, not a flaw. | ES9: A light-element support Witch who harvests fetishes from fallen enemies and deploys them as stat-scaling ally buffs. She transfers afflictions from allies to enemies, drains life, and accumulates mana through Fetish Bag by holding fetishes in reserve — balancing the tension between deploying her toolkit and sustaining herself. | ET9: A dark necromancer who builds zombie companions from killed and afflicted enemies, using Juju Curse to turn her entire malediction toolkit into a zombie pipeline. Corpse Pile makes each death — enemy or companion — strengthen her current zombie, turning attrition into escalating companion power. | EU9: A corruption and bleed specialist who wraps her worst afflictions in criterion shells that resist purging until they deal their full damage. Expiration Surge turns every naturally expiring condition into mana, rewarding patience and long-duration stacking — Plague Cauldron's exponential corruption release is her most catastrophic payoff for waiting. | EV9: The apex Witch, combining covenants, curses, and mass malediction into a comprehensive affliction dominance platform. She channels malediction across entire enemy groups with Malefaction Chant, unifies damage through Sympathy, and elevates her whole party's affliction pressure through Cursed Amplification — the Witch's toolkit at its most absolute. | EW9: All-elements generalist with companion support and momentum-driven efficiency. She cycles through every element in sequence to build stacking cast speed and mana bonuses, summons earth and water elementals, and infuses allies with elemental damage adds — the most versatile and accessible wizard subclass. | EX9: Dark magic specialist who turns death itself into a resource. She raises skeletal companions, scales her storm damage to the body count, and runs a suite of prepared abilities that trigger automatically when enemies fall — rewarding her for battles where allies are doing the killing as much as her own. | EY9: Control-focused water specialist with the deepest incapacitation toolkit in the class. She freezes, slows, and delays entire battlefields, with her most powerful conflux ability scaling both the number of targets incapacitated and how hard they are to wake based on how many elements she has charged. | EZ9: Defensive earth specialist who protects allies while grinding down enemy defenses. She builds damage shields, roots enemies in place, and applies layered weaknesses — her conflux abilities uniquely favor the whole party by granting elemental retaliations and stacking debuffs across every stat. | FA9: High-variance air specialist built around storm damage and stun pressure. She thrives on randomness — chaining lightning across the grid, forking attacks into splits, and stacking storm hits to overwhelm enemies — with the highest individual damage ceiling in the class when lucky damage and maximum damage align. | FB9: Area fire specialist who hits everyone, repeatedly. She applies countdowns, causes wounds, and commits fully to upfront mana costs for abilities that pay off over multiple ticks — Catastrophe and Conflux Meteor reward planning several turns ahead and punish enemies who cannot interrupt her. | FC9: Anti-attunement specialist who grows stronger the more completely she clears her elemental slate. She is the only wizard whose peak performance comes after spending conflux rather than before it, with her most powerful abilities gating behind having no attunements and her conflux damage rewarding precise elemental power investment over breadth. | FD9: Light magic specialist with hex, justice, and a unique mana economy identity. She wants enemies casting expensive spells so her Mana Disparity bonus peaks, making her the only wizard who benefits from enemy casters. Her full-conflux Conflux Enchantment can grant the entire party six simultaneous buffs scaled to her elemental investment. | FE9: Reactive counterspell specialist who punishes enemy spellcasting while sustaining channeled damage. She runs a suite of prepared counterspells that can chain indefinitely, drains mana from enemies, and uses Conflux Channeling to chain successive elemental damage sequences — the only wizard subclass that gets stronger the more the enemy commits to magic. | FF9: Pinnacle attunement-breadth specialist who rewards deliberate, expensive play. She wants all six elements charged simultaneously, spends them through Supreme abilities that scale with attunement count, and uses her previous turn's mana expenditure to amplify the next — the most technically demanding wizard subclass and the one with the highest ceiling.
A10: Mechanic | B10: =COUNTA(C10:FF10)/1.6 -> 48.125 | C10: Scouted Abilities — Scouted abilities are more powerful only on the very first action of battle. After use, they downgrade permanently to a lesser version for the rest of that battle. The New Beginning capstone restores the scouted condition mid-battle if the Scout's momentum is high enough, allowing him to use the upgraded version again. | D10: Banes — Bane abilities target a specific enemy type. When a bane is applied, it typically affects all enemies that share that type simultaneously — either dealing damage to all of them, granting a debuff to all of them, or granting the Hunter advantages when any ally attacks enemies of that type. Bane abilities typically require or consume aim to use. | E10: Rapid Reload — Crossbow attacks apply a reload delay to the Crossbowman after firing. Reload pushes the Crossbowman back on the action clock by an amount equal to the reload value multiplied by his speed — the faster he is, the more punishing the reload penalty. Rapid Reload abilities eliminate the reload from the next attack or the upcoming reload entirely, allowing the Crossbowman to negate this penalty at the cost of a minor or move action. | F10: Marks — Marks are ongoing conditions placed on enemies. Only one mark can be active on any enemy at a time. While a mark is active, allies that attack the marked enemy receive a benefit specific to the mark type. Marks require and consume aim to place, and their duration and effects scale with aim invested. | G10: Falcon — The Falconer's companion is a flying falcon that attacks the Falconer's aim target by default each turn. Many Falconer abilities function without a falcon present but receive bonuses or additional effects when one is active. Some abilities require the falcon companion specifically. | H10: Bounties — Bounty abilities are placed on an enemy as a minor action and must be used as the final action of the Bounty Hunter's turn. They have no immediate effect. When the targeted enemy dies, the bounty triggers and benefits the Bounty Hunter. Each bounty type grants a different reward on death. | I10: Finale Abilities — Finale abilities consume all of the Stalker's aim at once for a powerful effect, enhanced by the total aim spent. After using a Finale, the Stalker's aim is locked at zero for a duration that scales with the amount of aim consumed — more aim spent means a more powerful Finale but a longer recovery before aim can build again. | J10: Poach Abilities — Poach abilities are prepared using aim. Once prepared, they cannot be disrupted. When any enemy becomes endangered, the prepared poach fires automatically against that enemy and becomes unprepared. Each use targets whichever enemy next hits the endangered threshold. To use a poach against a different enemy than the last, the Poacher must re-prepare it with a fresh aim cost. | K10: Trick Shots — Trick shot abilities have a fixed low accuracy that cannot be improved by any means. Aim does not affect the hit chance. Instead, aim as a percentage of maximum aim determines whether the trick shot's special effect triggers if the attack hits. At higher aim percentages the effect is more likely to trigger; at lower aim it rarely does. Each trick shot has a distinct effect that only fires when the trickshot condition is met. | L10: Eternal Buffs — Eternal buffs are ongoing self-enchantments that stack upward without a limit. Only one eternal buff can be active at a time — activating a new one removes the previous. Each use increases the buff's power and also increases the cost of the next enhancement: they consume increasing amounts of aim or mana with each stack. There is no cap on how high they can go, but the escalating cost creates a practical limit within a wave. | M10: Unleash — The Initiate has abilities that grow stronger the longer he remains in the same form, but the ability only becomes unleashed when he changes form. Unleash value accumulates while holding a form and is spent on unleashed abilities when a form transition occurs. | N10: Impact — The Pugilist uses impact abilities that require that he struck an enemy in the previous turn. These abilities can only target whoever the Pugilist attacked the previous turn. | O10: Matching — The Skirmisher can utilize matching abilities that allow him to use the statistic of enemies if their statistic is higher. Matching defenses last for a short time, while matching offenses take place with their attack. | Q10: Glancing Mastery — Due to their training, Stone Fists can deal impressive glancing blows to enemies with high defense and that are intangible, and can cause other effects with these glancing blows. | R10: Arrival — While most who hide from their enemies prefer to stay hidden, the Infiltrator uses abilities that expose him to cause effects. These abilities can never conserve hidden, though they may gain other benefits if hidden would otherwise be conserved. | T10: Purity — The Ascetic gains access to powerful abilities if he is not affected by any affliction. Some of these abilities are restricted to specific forms. | U10: Ability Chains — The Thunderfist can use ability chains. Second tier abilities in these chains have a requirement of a precursor action. All of the abilities make the class very synergistic with itself, though precursors can be found in other classes to allow more variety. | V10: Form Shifting — The Drunken Master excels when he is rapidly changing from one form to another. Some abilities are stronger based on the total stages of forms he has shifted in the current turn, while other abilities are only available if he has shifted a minimum number of steps. | W10: Desperation — Certain Bandit abilities require him to be the last surviving ally. When alone, he gains access to dedicated desperation abilities and advantage generators unavailable while allies are present. Desperation Mana carries no advantage cost, allowing the Bandit to shift into a mana-fueled economy when alone. | AA10: Reliability — Certain Acrobat abilities are tagged as reliable. When a reliable ability fails to connect, its resource cost is refunded in full. The Acrobat still requires the resources to attempt the ability, but failed attempts do not drain his economy. | AB10: Contracts — The Assassin can sign a contract against a single enemy at any point during battle using a Minor action. Only one contract may be active at a time. While a contract is active, the Assassin gains passive benefits for attacking the contracted target. When the Assassin personally kills the contracted target with an active ability, he receives the contract's fulfillment bonus. | AC10: Wagers — Brigand abilities follow a wager-and-pot structure. The Brigand spends advantage or mana as a wager when using certain abilities. If a triggering condition occurs, he collects the pot as a payoff. | AG10: Scavenged Abilities — Scavenged abilities are prepared. On preparation, one of the six primary elements (air, earth, fire, water, light, dark) is randomly selected and locked in. The chosen element is displayed publicly and cannot be changed without consuming or disrupting the ability. This makes scavenged abilities less flexible than standard abilities but potentially more powerful, as the element is committed before targeting decisions are made. | AH10: Premade Concoctions — Premade abilities begin each wave already prepared at no resource or action cost. The first use requires no ammo and the prepared state cannot be disrupted in the conventional sense — only breaking the vial through combat disruption prevents it. After the first use, premade abilities must be re-prepared using the standard preparation system with a mana cost and can be disrupted during preparation. Premades are slightly less powerful than equivalent standard abilities in exchange for their zero-cost first use. | AI10: Accumulation — Accumulation abilities have two uses. The first use activates the ability and begins accumulating power; the ability grows stronger with each clock tick it remains active. The second use expends all accumulated power in a single discharge. The three Accumulator abilities (Beam, Burst, Storm) consume all active ammo on first use — the amount consumed and the active ammo type at that moment determine the base power and damage type when fired. Accumulating Detonation and Accumulating Trap accumulate power over time with no ammo cost. | AJ10: Modifications — Modifications are toggled abilities that alter how the Tinker and her companions function. Each modification costs a move action to toggle on and a move action to toggle off. Any number of modifications can be active simultaneously. Some modifications affect only the Tinker’s abilities, some affect only the companion, and some affect both. Four major abilities — Modular Bomb, Modular Ray, Modular Trap, and Modular Beam — each function differently depending on which modifications are currently active. | AK10: Assistants — Assistant abilities are move-action enchantments placed on chosen allies. Each assistant type grants a different proc that fires whenever the assigned ally attacks. Multiple different assistant types can be active simultaneously on different allies. Each assistant type can only be assigned to one ally at a time — reassigning it to a new ally removes it from the previous one. Assistants that use ammo consume one ammo each time their proc fires. Assistants persist on the ally until reassigned. | AL10: Friendly Fire — The Bomber’s bomb abilities deal high area damage but apply the same damage to allies as to enemies. Base damage values are identical for all targets — there is no ally discount. Scaling abilities scale the same way for all targets. | AM10: Called Shots — Called shot abilities are prepared as a minor action. Each called shot names a specific target at preparation time and applies a powerful secondary effect to the first attack ability used against that target on the following turn. Without the capstone skill Quick Call, the called shot cannot be used and applied on the same turn — the minor action prepares the effect and the attack comes next turn. | AN10: Concoction Detonations — The Savant’s six concoction abilities are detonations with three phases. While placed on a target they apply an ongoing effect. Simultaneously, they accumulate power each clock tick from the moment of placement. When the detonation chain fires, the discharge effect scales with accumulated power. Concoctions also auto-detonate after a period determined by ammo consumed at placement — more ammo extends the active window, allowing greater accumulation and longer ongoing effect duration before the automatic discharge. | AO10: Siege Engine Operation — Siege engine companions (Ballista, Battering Ram, Catapult) can act on their own clock turns, but their base speed is extremely low. Without the Siege Engineer spending actions to advance them, they fire infrequently. The Siege Engineer’s move and minor toolkit exists largely to accelerate siege companions — quickening them, fuelling them with ammo for haste, and upgrading their next action via Siege Command. | AQ10: Consequences — Consequence abilities generate Anguish on use and deal a deferred self-damage cost at the beginning of the Brute's next turn. Only the initial use generates Anguish; the deferred damage does not. | AR10: Reckless Abilities — Reckless abilities are powerful attacks that negate all active defenses and counter chances until the Raider's next turn. These abilities are further enhanced based on the total value of those active defenses at the moment of use. | AS10: Exertion — Exertion abilities have reduced accuracy. On a miss, the attack repeats targeting a random enemy and deals backbiting self-damage to the Berserker. This self-damage generates Anguish. | AT10: Rampage — Rampage accumulates as enemies are killed. Personal kills grant a higher Rampage bonus than team kills. Rampage enhances many of the Marauder's abilities, primarily scaling damage and speed. | AU10: Block Stacking — When the Viking has an ability prepared, each block made adds a charge to that specific ability. Multiple prepared abilities accumulate charges independently. When the ability fires, it consumes all stacks for enhanced damage or effect. Stacks are lost if the ability is disrupted. | AV10: Brink — Brink abilities become available for one turn after the Rager's cumulative damage dealt crosses a fixed threshold. This threshold tracks damage across multiple hits and turns. Once the threshold is crossed, unused Brink abilities expire at the end of the turn. | AW10: Purity Amplification — Purity abilities amplify in power each time they are used without triggering their cancellation condition. Each Purity has its own independent stack and cancellation condition. | AX10: Healing Threshold — The Cannibal can use threshold abilities when she has received enough healing that could actually be applied to her. Overhealing — healing above maximum health — does not count. The threshold accumulates across multiple heals. Some threshold abilities are prepared and activate automatically when the threshold is met; others require manual activation. | AY10: Massive Damage — Massive damage occurs when a single attack deals damage equal to or exceeding a set percentage of the target's maximum health. This threshold scales with target health rather than the Destroyer's stats. | AZ10: Beast Forms are ongoing minor abilities that consume Anguish and provide continuous stat bonuses with additional effects. Only one form can be active at a time — activating a new form replaces the previous one immediately. | BA10: Gambits — Gambit abilities either work to great effect or have a negative consequence on failure. | BB10: Disarm — The Duelist specializes in rare and powerful disarm techniques. She can disarm opponents and take advantage after the target is disarmed. | BC10: Allied Coordination — For each ally that is ready at the same time the Phalanx uses her abilities, the more powerful they are. Some abilities require multiple allies to be ready simultaneously. | BD10: Succession — Succession abilities are dual-wield attacks whose second hit gains enhanced effects based on dual-wield attack speed. The faster her attacks land, the more powerful the succession payoff. | BG10: Bushido — Some Samurai abilities allow enemies to attack her first, though many also delay or reset the enemy's counter afterward. These abilities are stronger relative to the effect of the enemy's action, encouraging the Samurai to fight her most difficult foe. | BH10: Unstoppable Abilities — Dreadnaughts can use their defense to augment physical attacks, enhancing damage or causing other effects. | BI10: Feints — Feint abilities can come in any action type and all compel an enemy and improve the Swashbuckler's parry chance. They grant a reaction on parrying and require a level of expertise. | CE10: Crescendo - The Minstrel tracks the number of buff-type ability actions used by any unit between his turns. Each unique buff action adds one stack of Crescendo, with a maximum cap defined per Crescendo ability. Crescendo resets when a Crescendo ability is used. Because buffs tend to be move and minor actions, building a high Crescendo count means investing smaller actions — creating a genuine trade-off between conventional buffing and setting up a powerful Crescendo payoff. | CG10: Cacophony abilities scale in power based on the number of unique non-damaging debuff actions applied to any unit by any ally between the end of the Dirge Singer's previous turn and the end of his current turn. Each distinct debuff action adds one stack, up to a maximum of 10. The count resets at the end of the Dirge Singer's turn. | CH10: Litany abilities apply stacking duration effects. Each cast of the same litany refreshes the duration and increases the value, up to a maximum of 5 stacks. | CI10: Favor abilities call upon named deities to heal a target ally and grant them an elemental damage add corresponding to that deity's domain. | CJ10: The Spy can don disguises in battle. He must be hidden to put on a disguise. Each disguise grants both advantages and disadvantages as he emulates the pretended role. While disguised, each disguise ability can be activated a second time to trigger a unique effect — but doing so removes the disguise. | CK10: As long as enemies cannot target the Mountebank — due to avert, scorn, or hidden — he can use veiled abilities that are stronger than normal | CL10: Entourage abilities grant a free attack to an ally with a provoke rider causing the next enemy to target that ally, plus a varying defensive buff to protect them from that attention. | CM10: The Muse can unlock powerful abilities following a resurrection. Most Epiphany abilities are minor or move actions that can be completed in the same turn the Muse or an ally provides the resurrection. The most powerful Epiphany ability is a major action that requires an ally to have performed a resurrection since the Muse's last turn. | CO10: Companion Mana — The Conjurer works in concert with her companion, using its mana pool to enhance her own abilities. Many of her abilities function on their own but become stronger or gain additional effects when companion mana is available to draw from | CP10: Dark Spirits — The Occultist manipulates dark and light spirits to protect herself and allies with powerful retaliation abilities. These spirits deal a variety of damage types beyond standard elemental damage, and channeling them further shifts her alignment. Her retaliation suite covers multiple damage types and can be granted to any unit. | CQ10: Attendant Abilities — Attendant abilities are prepared abilities that reserve mana while held. They all trigger simultaneously when the Shaman's companion scores a critical hit. Multiple Attendants can be prepared at once — the longer the Shaman waits for the critical, the greater the combined effect when it finally fires. | CR10: Balanced Alignment — Unlike most other Binders, the Medium is strongest near the center of the alignment scale. Her most powerful abilities require Balanced scale position, and she gains bonuses for remaining within the 1/4 range on either side. | CS10: Animation — The Animist infuses her companion with spiritual energy. Animation abilities buff the companion so that its next attack carries an additional effect. These effects do not fire until the companion's next turn, meaning they can be thwarted by defeating the companion before it acts. | CT10: Endangered Enhancements — Precarious abilities have two tiers of power. The first tier activates when either the Spiritualist or the target is endangered. The second, more powerful tier activates when both the Spiritualist and the target are simultaneously endangered. | CU10: Multi-Critical — Many of the Astrologer's abilities gain benefits for each separate enemy they score a critical hit against during a single use. | CV10: Corrupt Power — The Vizier deals corrupt damage to her own allies as a side effect of her most powerful abilities. Many of her abilities scale with total corruption present on the battlefield — on enemies, allies, and herself. | CW10: Sanity Cost — The Alienist deliberately accumulates illusory damage on herself to unlock her most powerful abilities and fuel her damage scaling. Several abilities require that she has taken sufficient illusory damage to use. | CX10: Pacts — Pact abilities are powerful ongoing commitments that each provide two bonuses and one drawback. Only one Pact can be active at a time — activating a new Pact replaces the current one. All Pacts reserve mana while active. | DI10: Reckoning — Reckoning abilities scale their power based on the current value of a damage affliction on the target, calculating the full potential damage those afflictions represent. | DJ10: Verdict — Verdict abilities can only target the enemy with the lowest health, representing the Executioner's role as the inevitable end for the weakest foe on the battlefield. | DK10: Burial — Burial is a variant of incapacitated that lasts for a fixed duration rather than ending on hit. Buried enemies cannot act, cannot advance their timer, and cannot take direct damage while buried. Burial ends automatically after its duration expires. Follow-up abilities allow the Gravedigger to capitalize on buried enemies through specific interactions. | DL10: Asphyxiation — Asphyxiation abilities build the Tired and Exhausted conditions on enemies, degrading their action economy through strangulation and air damage. Tired reduces an enemy's action options to two per turn. Exhausted, the upgraded condition, reduces actions to just one. | DM10: The Four Moons — The four moons of the world cycle naturally, waxing and waning in intensity. Their benefits are team-wide, peaking when a moon is at its highest and fading as it wanes. Blood Moon enhances fire effects. Harvest Moon enhances earth and healing effects. Strawberry Moon enhances air and enhancement effects. Tidal Moon enhances water and control effects. Spirit Orbs are required to call a specific moon, and Reverse the Skies allows the cycle to be shifted. | DN10: Sin Eating — The Sin Eater purges afflictions from allies and himself, then weaponizes them against enemies. Consuming sin and turning it outward is the core of the Sin Eater's identity. | DO10: Oneiromancy — The Sandman applies incapacitation through dream-state manipulation, exploiting incapacitated enemies with follow-up abilities and existing in a liminal state himself. Voluntarily incapacitating himself turns danger into a powerful offensive tool. | DP10: Paranoia — Paranoia abilities scale their power based on the number of enemies currently present on the battlefield. The Whisperer grows more powerful when facing larger groups, rewarding engagement with full enemy formations. | DQ10: Last Rites — Last Rites abilities interact with the final surviving enemy on the battlefield, representing the Mercy Bringer's role as the deliverer of the final mercy to the last standing foe. | DR10: Delirium — Delirium abilities gain enhanced secondary effects while the Gaslighter is in Spirit Fugue, rewarding the deliberate pursuit of that dangerous state. The Atmosphere suite each provides a baseline effect with a powerful Spirit Fugue bonus. Illusory damage is a stacking pool that kills the target if it ever exceeds their current health, causing a heart attack. Illusory damage can expire or be purged like other conditions. | DT10: Kinetic Conversion — Certain Kinetic abilities use telekinetic conversion. These abilities calculate initial damage using (magic power / magic resistance) x magic damage, then route the result through the physical damage path. Converted attacks are subject to dodge, block, counter, and parry, and cannot be countered by counterspells. They trigger cast procs rather than attack procs. All converted attacks deal physical damage.
A11: Lore | B11: =COUNTA(C11:FF11)/1.6 -> 100 | C11: During the war, the Trader States deployed scouts as the eyes of the Concord advance, mapping Abyssal territory and feeding intelligence back to the supply lines that won the war. Five years later, formal Scout units have largely dissolved, and most have traded military contracts for civilian work — surveyors, guides, pathfinders for merchant expeditions into the Abyssal Lands. The skills transfer cleanly. The pay is worse. | D11: The Lion Woods Lodges are old institutions, older than the war, older than most of the nations that now send their wealthy to hunt there. Lodge Huntsmen follow a strict code — clean kills, respected quarry, proper ceremony. To outsiders it looks like theater. To a Huntsman, it is the only thing separating civilization from savagery. | E11: The Trader States never romanticized archery. The crossbow was a tool of war, easier to train, easier to standardize, easier to supply. Crossbowmen served in regimented infantry units, and their discipline shows in everything they do — methodical, patient, institutional. Many now serve as caravan guards or city watch, bringing that same regimental precision to peacetime work. | F11: Dynasia's Marksmen were its answer to the massed enemy formations of the Abyssal war — elite archers trained to break lines, take officers, and hold positions against overwhelming numbers. They carried the same cultural weight as English longbowmen, celebrated in ballads and given honors. Post-war, many struggle with the gap between that reputation and the grinding reality of peacetime, where their skills feel outsized for the problems at hand. | G11: Falconry in Dynasia is older than the GodKing's church and considerably more honest about what it is — a display of wealth, patience, and mastery. Noble families have maintained their lines of trained birds for generations, and the Falconer subclass reflects that aristocratic lineage. Outside Dynasia, Falconers are curiosities, their methods considered elaborate and their birds an unnecessary extravagance. Inside Dynasia, a Falconer without noble blood is almost unheard of. | H11: The Hunter's Guild expanded its mandate after the war, turning its tracking expertise toward war criminals, Abyssal collaborators, and fugitives. It pays well and carries a veneer of legitimacy. The reality is messier — a Trader States bounty hunter pursuing a Dynasian war criminal is a spy to Dynasian eyes, and the Abyssal Lands have no authority to appeal to. Most Bounty Hunters develop a pragmatic relationship with moral complexity early in their careers. | I11: Nobody teaches you to be a Stalker. You learn it from the Abyssal Lands themselves, from years of hunting things that hunt you back. Stalkers have a seedier reputation than most archers — they operate in moral grey areas, take contracts others won't, and rarely ask questions about their quarry. In a land full of desperate people, they are rarely short of work. | J11: The Lodges of the Lion Woods did not consult the locals when they drew their boundaries. Poachers are what happens when people who have hunted these woods for generations are told they need a permit to feed their families. Some are purely opportunistic, selling to wealthy buyers who want exotic meat without the Lodge fees. Others see themselves as something closer to resistors. | K11: Archery contests exploded in popularity in the five years since the Concord's victory — a way to celebrate survival, maintain martial culture, and give veterans somewhere to put their edge. Sharpshooters are the products of that culture, trained not in war but in competition, where consistency and nerve under pressure are everything. They lack the battlefield experience of Marksmen but often surpass them in pure technical precision. | L11: The Toxophilites do not belong to any nation and are not interested in your war. Theirs is a tradition of archery as devotion — the bow as instrument, the shot as meditation, accuracy as a form of self-knowledge. Masters pass the tradition to single students over years of rigorous study. Most archers find them insufferable. Most archers also secretly wish they could shoot like them. | M11: Every practitioner of the martial tradition begins here, regardless of which school or method they will eventually pursue. The Initiate learns the foundational forms passed down since the first knight refused his blade — stances, breathing, the basic flow of chakras that the entire tradition builds upon. What an Initiate becomes depends entirely on where they train and who teaches them, which makes this the most universal and least defined stage of the path. | N11: What began as organized sport in the Trader States — matches, wagers, local champions — gained a harder edge during the war, when gyms that once trained athletes found themselves training soldiers instead. The sporting tradition never disappeared, but it now coexists with a more martial strain born from wartime necessity, and the two influences are visible in how differently individual Pugilists carry themselves depending on which gym shaped them. | O11: Among the old Valisian crews, certain fighters integrated unarmed combat technique directly into raiding culture, finding it suited the chaos of close-quarters shipboard fighting where a dropped weapon could mean death. A handful of crews specialize in the method and train it formally. More often, Skirmishers are independent specialists who drift between crews, valued for a skill set that doesn't require carrying anything that can be lost overboard. | P11: Named for the founder himself, the Vajra school claims direct descent from the original knight who swore off weapons after being tricked into killing his emperor's son. True to that origin, Vajra practice centers on reaction rather than initiation — countering, redirecting, answering violence rather than seeking it. It is considered the most orthodox lineage, the closest living link to a man whose entire philosophy was built from being wronged rather than from choosing to strike first. | Q11: One branch of the original unarmed tradition, grown over generations into a school defined by endurance and immovability. Stonefist practitioners train toward the unbreakable stance — absorbing punishment, refusing to yield ground, outlasting opponents rather than overwhelming them. The geography that separated them from their Thunderfist cousins centuries ago has long since calcified into a real philosophical identity, even though neither school can point to a founding disagreement that caused the original split. | R11: Dynasia recognized early that a tradition built on unarmed discipline, careful movement, and patient observation produces excellent spies almost by accident. Talented Monks are recruited from various schools and redirected toward espionage, serving noble houses and church interests that need discreet operatives more than they need visible warriors. Infiltrators tend to maintain whatever surface tradition trained them while quietly serving a very different purpose underneath. | S11: No school within the tradition sits in starker contradiction to its founder than Viper Fang. Where Vajra traces back to a man destroyed by poison, Viper Fang has built an entire practice around it — and their justification is not philosophical reclamation but practical advantage. Poisoners and assassins find Viper Fang training useful precisely because it provides camouflage: a respected martial tradition's legitimacy, worn as cover for work that has nothing to do with serenity or honor. Other schools know this, and most keep careful distance. | T11: The highest religious order among Dynasian Monks, Ascetics have taken the church's incorporation of martial training to its furthest devotional extreme — years of discipline aimed not just at combat mastery but at perfecting the body as an act of faith, drawing the practitioner closer to the divine image of the GodKing himself. Where the Crusader spreads the faith and the Templar embodies it, the Ascetic refines themselves in its image, one form and one breath at a time. | U11: The other branch of that same root tradition, shaped instead toward explosive, overwhelming offense — speed and force concentrated into single decisive moments rather than Stonefist's patient endurance. Like Stonefist, Thunderfist's distinct identity emerged gradually from simple distance rather than philosophical intention, but generations of practitioners have since built a genuine and proud tradition around what started as an accident of geography. | V11: Outside every formal school, lineage, and institution, certain practitioners reach a level of mastery that no longer resembles discipline at all. The Drunken Master's technique looks unsteady, almost comedic, until the moment it isn't — a flow between forms so complete that intention and improvisation become indistinguishable. They emerge from any tradition and belong to none, having gone far enough beyond their original training that the question of where they started stops being relevant. | W11: The Bandit works close to civilization rather than far from it, preying on the visitors and travelers who move through a town's outskirts while maintaining hideouts among the peasantry who either sympathize, fear them, or both. It is a profession that requires social intelligence as much as physical capability — the Bandit who cannot read a community, who cannot tell which farmers will shelter them and which will report them, does not last long in the trade. | X11: Cities produce the Cutthroat the way they produce everything else — through density, desperation, and the particular anonymity of urban life where a body in an alley might not be found until morning. The Cutthroat is not uniquely murderous among Rogues so much as uniquely unsentimental about it, treating violence as a practical tool in the pursuit of robbery rather than a last resort. They work in cities because cities are where the money is, and because cities are where violence disappears fastest into the noise. | Y11: The ideal Burglar job ends with the victim discovering days later that something is missing. No confrontation, no witnesses, no moment where the Burglar has to make a decision about what happens if someone wakes up. They are specialists in absence — of themselves, of evidence, of any sign that the space they entered was ever touched. The craft requires patience and preparation that most other Rogues find excessive. Burglars consider it basic professionalism. | Z11: Where the Burglar avoids all contact, the Thief simply prefers not to be caught. Picking a pocket in a crowded market, lifting a purse at a festival, walking out of a shop with something that wasn't paid for — these require confidence and presence rather than technical breaking-and-entering skill. The Thief's relationship with risk is more casual than the Burglar's careful planning allows for, which produces faster work and occasionally faster consequences. | AA11: The Wagon Folk produce Acrobats as naturally as they produce Mountebanks and Psychics — performance is part of their cultural identity, and physical mastery of one's own body is respected regardless of what it's used for. The criminal reputation that follows Acrobats is largely borrowed from the general suspicion that follows Wagon Folk everywhere, rather than earned by the Acrobats themselves. This does not make it less persistent or less unfair. | AB11: Two distinct traditions operate under the same name. The professional Assassin is a contractor — trained, discreet, available to any nation, guild, or private party with sufficient coin and legitimate enough grievance to make the risk worthwhile. The Cult of Glasya represents something more structured and more theologically invested, the most renowned killers in the known world who happen to serve a demon lord and happen to be available for hire. Engaging the Cult is not joining their faith. It is simply the most reliable way to ensure a specific person stops being alive. | AC11: Roads are where money moves, and the Brigand knows this better than anyone. Operating in organized groups along trade routes and caravan paths, Brigands function more like an informal tax on commerce than simple robbery — predictable enough in their habits that experienced merchants factor them into shipping costs. In the Abyssal Lands, where Concord authority thins to nothing along the major routes, Brigand groups have become powerful enough to function as de facto territorial powers in their own right. | AD11: The Trader States built their guild system to regulate commerce, and where regulation exists, someone will find profit in circumventing it. Smugglers began as tax-evaders and traffickers of contraband, and that version still thrives in the cities and ports. The more complicated version emerged in the Abyssal Lands, where the same skills applied to moving goods the system refuses to provide to people who genuinely need them. Bryan Lowe understands both versions intimately. Which one he considers his real work probably depends on the day. | AE11: Information is currency in a cold war, and the Skulk has no institutional loyalty that would complicate turning it into coin. They specialize in stealth as a means of gathering what others don't want known — secrets, correspondences, the private conversations of powerful people — and in turning that knowledge into personal advantage through blackmail and coercion as readily as through sale. Where the Spy performs a function, the Skulk accumulates leverage. | AF11: Strip away the cultural trappings the term carries in the wider world and what remains is a practitioner who has achieved mastery of a specific and demanding craft: moving unseen, killing cleanly, extracting information without leaving evidence, using poison as a tool rather than a weapon of last resort. The Ninja tradition is less a cultural identity than a professional standard — a ceiling that the best in the broader Rogue tradition aspire toward, achieved through discipline that most of their peers mistake for something more exotic than it actually is. | AG11: The Arachnians are gone and their devices don't manufacture themselves, which means someone has to find them. Scavengers operate mostly within Valisian waters, diving shipwrecks and picking through coastal ruins for artifacts that predate every current civilization. They work outside the crew structure that defines most Valisian life, tolerated rather than integrated, valued for what they bring up from the deep rather than for any loyalty to a particular flag. What they find they sell, keep, or quietly deliver to whichever Order has made them the better offer. | AH11: The Alchemist's work happens before the battle rather than during it — potions, compounds, and potables prepared carefully in advance and deployed when the moment requires. The tradition exists entirely independent of Teknos devices, practiced by chemists and herbalists across all three Concord nations, but a Teknixian Alchemist brings the device's capabilities to bear on both preparation and application, producing effects that purely mundane alchemy cannot replicate. Calpurnia Moss has a particular appreciation for preparation, having learned through long experience that improvisation is what happens when preparation fails. | AI11: Where most Teknixian work produces immediate effects, the Artificer's creations improve over time — devices that learn, adapt, and become more capable the longer they are in use. There is something of the Arachnian philosophy in this approach, a sympathy for technology that develops rather than simply functions. Artificers tend toward patience as a personality trait, which is either cause or effect of working in a tradition where the best results require years rather than minutes. | AJ11: Every device breaks, degrades, or proves poorly suited to the specific situation it encounters. The Tinker exists to fix that — modifying, repairing, and adapting Teknos devices and mundane technology alike to better serve whatever purpose is currently required. The tradition values improvisation over precision, a willingness to work with what's available rather than what's ideal. Tinkers are often found in the Abyssal Lands, where ideal is rarely on offer and functional is the best anyone can hope for. | AK11: The Engineer's relationship with Teknos technology is the most practically minded of any subclass — construction, fortification, siege equipment, the unglamorous infrastructure of warfare and peacetime alike. Machinists build weapons of war, but Engineers build everything else, including the machines that move those weapons into position. During the Abyssal war they were invaluable on both sides, their skills too useful for either faction to refuse, which has left them with the most politically complicated postwar reputation of the purely practical Teknixian traditions. | AL11: Explosive applications of Teknos technology serve military and civilian purposes with equal enthusiasm, which is either reassuring or concerning depending on one's perspective. Bombers found consistent employment during the Abyssal war, and the same skills translate cleanly to mining, demolition, and the occasional very emphatic resolution of a dispute. The Corrupted Order has produced Bombers whose applications lean exclusively toward the destructive end of the spectrum, using crude facsimile devices that the Ancient and New Orders regard with the specific horror of people watching their tradition desecrated. | AM11: The Teknos device's capacity to function as a ranged weapon has been developed most deliberately by the Gunslinger tradition, which approaches accuracy and technique with something approaching the Archer's professional rigor. Called shots, precise targeting, the discipline of knowing exactly where something will hit before it hits — these are Gunslinger concerns, and the tradition has more in common with Samson Graves' Hunter's Guild background than either would necessarily want to admit. | AN11: The most innovative of the Teknixian traditions, the Savant pursues self-fueling device designs that operate beyond the standard limitations of Teknos technology — creations that generate their own resources rather than consuming finite ones. Whether this represents a genuine understanding of how the Arachnians intended their devices to eventually develop, or an inspired accident of experimentation, is a question the Savant tradition debates with considerable enthusiasm and no consensus. | AO11: Catapults, arbalests, siege engines, the heavy machinery of organized warfare — the Machinist builds what armies need to take and hold ground. The tradition exists entirely independently of Teknos devices in its mundane form, practiced by military engineers across all three Concord nations, but a Teknixian Machinist produces equipment that operates at a different level of capability entirely. During the Abyssal war, Machinists on both sides were responsible for some of the conflict's most devastating engagements, a legacy that sits heavily in a world still rebuilding. | AP11: The pinnacle of Teknixian practice is not defined by what a practitioner can build or destroy but by what they understand. The Reliquarian has developed a genuine comprehension of Arachnian technology at a foundational level — not just how to use the devices but why they work, what the Arachnians intended, and what the symbiotic relationship between device and practitioner was truly meant to become. In a world where the creators are gone, betrayed by the race they mentored and erased from history, the Reliquarian carries something irreplaceable: the closest thing remaining to the Arachnians' actual knowledge, preserved in the relationship between a living person and a device that is, in its own way, still alive. | AQ11: Every tribe has them — the biggest, the strongest, the ones who lead from the front because nothing has ever stopped them yet. Brutes are not a tradition so much as a fact of tribal life, found in Horse Tribes and Wolf Tribes and every desperate settlement scratching out existence in the Abyssal Lands. Civilized soldiers call them unsophisticated. They are usually saying this while retreating. | AR11: The Valis Confederacy produced a particular type of fighter during the war — one who could shift on a heartbeat from disciplined defense to reckless overwhelming assault. Raiders trained that instinct into a fighting style, the sudden lurch from shield to sword that breaks formations and unnerves veterans. Post-war, many Raiders have drifted into mercenary work in the Abyssal Lands, where that volatile quality is either prized or feared depending on who's hiring. | AS11: The Berserker does not choose to lose control. That is the point. The tradition, found across tribal cultures in various forms, is built around a fighter whose rage responds to damage, to threat, to the heat of battle — reactive and escalating. Tribes that produce Berserkers regard them with a mixture of pride and wariness. They are invaluable in the right circumstances. The right circumstances require careful management. | AT11: Land-bound and relentless, Marauders measure themselves in kills and territory held. They exist across the Abyssal Lands in various tribal and non-tribal forms, defined less by culture than by philosophy — that dominance is proven through accumulation, that every battle is an opportunity to add to a tally that matters. Some tribes regard Marauder traditions with respect. Others consider them a corruption of what honorable warfare means. | AU11: The old Valisian crews have sailed and raided and fought since before the Confederacy existed, and they intend to keep doing so long after political arrangements come and go. Vikings carry the weight of that cultural identity proudly — the longships, the reputation, the songs. Paradoxically they are among the most loyal to the Grand Commodore, because the Confederacy is their institution, built on their tradition, and they have no intention of letting newer members dilute it. | AV11: When the war ended, not everyone received liberation equally. Some peoples found themselves displaced twice — first by the Abyssals, then by the Concord's redrawing of the world. Vandal bands formed in the margins of the Abyssal Lands from these dispossessed groups, united less by tribe or blood than by shared grievance. Their destructive reputation is not entirely unearned, but neither is it the whole story. | AW11: Somewhere in the deep tribal territories, certain warriors began teaching that rage was not a weapon to be unleashed but a fire to be tended. Fury lodges exist quietly within and between tribes, passing their discipline from master to student with something approaching monastic rigor. Where the Berserker loses himself in battle, the Fury never does. Outsiders who expect a screaming savage are often the last ones surprised. | AX11: The practice exists across many tribes and outside the tribal structure entirely, and it is rarely what outsiders imagine. In its traditional form it is ritual — consuming the strength of a worthy enemy, honoring them through incorporation. Cults have taken that ritual and hollowed it into something genuinely vile, which has poisoned the reputation of practitioners who still follow the old ways. The distinction matters enormously to those who observe it. It matters very little to those who fear them. | AY11: The Trader States and Dynasia both discovered the same uncomfortable truth during the war — sometimes you need someone who simply does not care what they break. Destroyers were recruited from tribal warriors and shaped into military specialists, siege-breakers and fortification-wreckers deployed where finesse was beside the point. They occupy an uneasy place, too institutionalized for the tribes, too savage for polite military society. | AZ11: Every animal tribe tells stories of warriors who went so deep into their totem identity that they stopped being entirely human. Most are legends. Some are not. Beastlords emerge rarely, across all tribes, and when they do they tend to outgrow the tribe that produced them — not through rejection but through transcendence. They carry their tribal origins with them but belong to something older and wilder, a connection to the animal world that no lodge or tradition fully owns or understands. | BA11: The arenas of the Abyssal Lands predate the Abyssal occupation and survived it, which says something about human nature that most people prefer not to examine. They exist in grand purpose-built structures in the major cities and in basement rooms that smell of blood and coin in equal measure, and the fighters who populate them range from willing professionals chasing fame and purses to the enslaved and indentured who have no choice in the matter. Daracha Rowe was the former — a willing participant who became famous enough to have a manager, and human enough to eventually want something different. The arena did not take her retirement gracefully. | BB11: Dueling schools exist across all three Concord nations, built on the explicit premise that the sword is an equalizer — that a farmer's son with enough talent and discipline can stand across from a merchant prince's heir and have the better of it. The premise is not entirely false. The schools do produce genuine meritocracy within their walls, and the traditions they teach favor skill over strength. Outside their walls, the question of who can afford tuition quietly reasserts itself. The ideal survives contact with the world imperfectly, as ideals tend to. | BC11: The Trader States have always understood that individual heroism is a liability in a supply line and a formation is only as strong as its least disciplined member. The Phalanx tradition reflects that institutional philosophy — shield walls, coordinated advances, tactics designed around the unit rather than the individual. Dynasia employs similar formations, arriving at the same conclusions through a feudal military tradition rather than a mercantile one. Phalanx fighters are uncomfortable fighting alone. They are also uncomfortable watching anyone else fight without proper formation discipline, which makes them difficult companions. | BD11: The Zafeer brought this tradition into Dynasia along with the Vizier, and like the Vizier it found institutional accommodation in its new home. Originally a spiritual practice — the whirling combat style a form of moving meditation, the fighter seeking union with something divine through the perfect expression of movement — it has shed most of that theological context since the Zafeer's conversion to the faith of Alister High. What remains is the technique, preserved with impressive fidelity by practitioners who have largely forgotten what it was originally for. Something in the movement still feels like prayer, even to those who would not use that word. | BE11: The blade as hobby and the blade as livelihood produce very different fighters, and both call themselves Fencers. Wealthy practitioners treat it as an accomplishment to be displayed at social occasions, their technique elegant and their actual combat experience minimal. Poorer Fencers fight in demonstration matches, private disputes, and arrangements that exist in the grey area between sport and violence, their technique equally elegant and considerably more tested. The two groups share a vocabulary and very little else, and each tends to regard the other with a contempt they consider well-earned. | BF11: Dynasia's feudal aristocracy produces Lancers as naturally as it produces everything else that requires expensive horses and years of dedicated training. They are mounted soldiers first, devastating with the spear from horseback, but the Dynasian tradition insists on competence on foot as well — particularly training against other cavalry, a specialization that proved its worth repeatedly during the war. Lancers carry the specific pride of people who have mastered something genuinely difficult and expensive, which is to say they can be insufferable at dinner but are extremely useful in a fight. | BG11: The Valis Confederacy produces a specific type of fighter that could not have emerged anywhere else — lightly armored, aggressively mobile, as comfortable fighting on a rolling deck as on solid ground, and possessed of a charisma that functions as both social currency and tactical asset. The Swashbuckler's style is performative in the best sense, every fight an opportunity to be remembered, every victory ideally achieved with enough flair that the story improves in the retelling. This aesthetic serves practical purposes in a Confederacy where reputation is a form of power and the crews that follow you do so partly because of who you are. | BH11: Nobody founded the Dreadnaught tradition. It emerged independently, repeatedly, across the hard places of the Abyssal Lands — the discovery that enough armor, enough will, and enough refusal to acknowledge damage can make a person functionally unstoppable in the short term. Dreadnaughts are typically the most heavily armored fighters anyone has ever encountered, and they share a psychological profile that is either admirable or alarming depending on one's perspective — an absolute unwillingness to go down that has been refined through survival into something approaching a fighting philosophy. | BI11: The Valis Confederacy produces a specific type of fighter that could not have emerged anywhere else — lightly armored, aggressively mobile, as comfortable fighting on a rolling deck as on solid ground, and possessed of a charisma that functions as both social currency and tactical asset. The Swashbuckler's style is performative in the best sense, every fight an opportunity to be remembered, every victory ideally achieved with enough flair that the story improves in the retelling. This aesthetic serves practical purposes in a Confederacy where reputation is a form of power and the crews that follow you do so partly because of who you are. | BJ11: Most Warlords are recent. The war produced them — people whose talent for command revealed itself under conditions that made talent impossible to hide, who found themselves directing dozens and then hundreds and then more because the alternative was losing. Five years later they occupy an awkward position in a world that no longer needs them in the same way. Some have transitioned into political roles in the Abyssal Lands, their military authority translating imperfectly into civilian governance. Others have found that the skills transfer well to the power vacuums the cold war keeps creating. The best of them are trying to build something. The rest are trying to stay relevant. | BK11: The most literal expression of the Knight's defining purpose, the Bodyguard exists to stand between a single charge and harm, full stop. Some serve nobility, some serve merchants wealthy enough to fear for their lives, and a smaller number serve people who have nothing to offer but need protecting anyway. The role is unglamorous compared to other Knight traditions — no banners, no temples, no tournaments — but Bodyguards take a particular pride in the purity of the function. There is nothing complicated about what they do. They simply do not let their charge die. | BL11: Not everyone can fight their own battles, and the Champion exists to fight them instead. The role spans an unusually wide social range — Champions represent downtrodden petitioners who have no standing to demand justice themselves, and they represent nobles in formal duels and tournament tilts where personal combat would be beneath their dignity or simply unwise. The common thread is representation rather than personal stake. A good Champion fights as hard for a farmer's land dispute as for a baron's honor, which is either admirable consistency or a troubling lack of judgment, depending on who is asking. | BM11: Unlike the Templar, fully bound to the GodKing's faith, the Hospitaler maintains only a loose connection to Dynasia's church. They operate as knights without fixed borders, taking commissions and causes wherever they find them, sometimes with church sponsorship and sometimes entirely independent of it. This flexibility makes them useful in the Abyssal Lands, where Dynasian institutional authority is thin and a knight who doesn't need official sanction to act can move faster than one who does. | BN11: Dynasia's aristocracy produces the Cavalier as its most stylish mounted tradition, combining the expense and prestige of cavalry training with a personal code of conduct that Cavaliers discuss at every opportunity and violate only with great personal anguish. They are proud, sometimes insufferably so, but the pride is generally backed by genuine competence and genuine commitment to the code they have adopted. A Cavalier without honor is, in their own estimation, simply a man on a horse. | BO11: Watchfulness over a place rather than a person defines the Sentinel tradition. They guard gates, bridges, storehouses, shrines, and city walls with equal diligence, and the role carries no particular mystical weight — a Sentinel posted at a temple and one posted at a granary approach their duty identically. What matters is the place, and the people who depend on it remaining secure. Sentinels develop an intimate, almost territorial relationship with what they protect, and dislike few things more than being reassigned somewhere new. | BP11: Mounted combat meets magical practice in the Dragoon tradition, a step beyond the purely martial Lancer. Dragoons maintain the deep bond with their mount that defines Knight culture broadly, but layer onto it abilities oriented around reflection and elemental resistance — a defensive magical sensibility that suits a tradition built around protecting others. They are less common than Lancers, requiring both the expensive cavalry training and a magical aptitude that not every aspiring mounted knight possesses. | BQ11: Dual blades and exceptional parrying define the Paragon's combat style, and the skill required to master it produces a tradition with a healthy and largely earned sense of its own excellence. Paragons carry themselves with confidence bordering on ego, but it tends to be the kind of confidence that survives contact with a real fight, which buys considerable tolerance from people who might otherwise resent it. They are selectively recruited for tasks that genuinely merit their particular talents, and they have little patience for being asked to do anything less. | BR11: Every virtue the Knight represents, the Blackguard inverts without abandoning the underlying structure. They still guard. They still serve a charge and take vengeance for harm done to that charge. The difference is who they choose to protect — tyrants, witches, anyone whose power justifies the investment of a Blackguard's considerable skill. They consider themselves proudly fallen rather than corrupted, having concluded that protection should flow toward power rather than need. Every Blackguard secretly aspires to invert the relationship entirely and become the one served rather than the one serving, which makes them dangerously unreliable allies even to those they currently protect. | BS11: The Crusader tradition reaches deep into Dynasian history, and not all of that history is comfortable to discuss. For centuries, Crusaders spread the GodKing's faith at the point of a sword, converting through conquest as much as conviction. The current GodKing's notable kindness and tolerance has redirected the tradition toward gentler purposes, and most active Crusaders today understand their role as defense of the faithful rather than expansion of the faith by force. The older mandate has not entirely disappeared, and the gap between what Crusaders once did and what they do now is a source of quiet generational tension within the order. | BT11: The pinnacle of the Knight's devotional purpose, the Templar does not merely serve the GodKing's faith — their presence creates something like sacred ground wherever they stand, a living extension of Alister High's temple carried into the world. Where the Crusader's history is complicated and the Hospitaler's commitment is loose, the Templar's investment in the faith is total and uncomplicated by ambiguity. They represent what the Knight class aspires toward at its most complete: protection in service of something larger than the person being protected. | BU11: Named for the first master of lightning, the Blitzknecht school occupies one corner of the Abyssal Lands with the particular pride of an institution that considers itself the fastest and most aggressive of the four academies. Their collaboration with the Abyssals was enthusiastic rather than reluctant, and their graduates filled officer roles in the Abyssal armies with a comfort that has made postwar reconciliation difficult. The school still operates, because the alternative was a siege nobody wanted, and the instructors teach the same curriculum they always have. | BV11: The fire school produces practitioners whose combat philosophy matches their element — overwhelming, consuming, difficult to redirect once committed. Feuerknecht graduates were among the most visible Abyssal collaborators during the war, their destructive capabilities deployed against Concord forces in engagements that veterans remember specifically and bitterly. The school's current leadership maintains that the collaboration was a matter of survival rather than ideology. Most people who fought against Feuerknecht graduates find this distinction less meaningful than the school does. | BW11: The water school carries the same collaboration history as its three counterparts, though its elemental focus lends itself to adaptability and flow rather than the more immediately destructive applications of fire and lightning. Trinknecht graduates tend to be the most politically flexible of the four schools' alumni, a quality that served them during the war and continues to serve them in the complicated postwar landscape, where the ability to move with circumstances rather than against them has genuine survival value. | BX11: Earth magic lends itself to endurance and fortification, and the Drecknecht school produced some of the most effective defensive practitioners the Abyssal forces deployed. Where Blitzknecht and Feuerknecht graduates led assaults, Drecknecht alumni held positions — the unglamorous, grinding work of keeping ground taken. Five years later they are perhaps the least visible of the four schools' graduates, their defensive specialty translating more quietly into postwar life than their more aggressive counterparts. | BY11: Some Spellsword graduates were never particularly loyal to their schools' elemental traditions, and even less loyal to the Abyssal cause their academies endorsed. Mercenaries took their training and sold it to whoever would pay, serving Concord forces as readily as Abyssal ones during the war and paying no particular price for it afterward. They carry the most comfortable postwar reputation of any Spellsword tradition, which the academy loyalists resent considerably. | BZ11: The insight that drove the Transmuter tradition was simple and radical — that the enchantment work Spellswords applied to their weapons could also be applied to themselves. Transmuters augment their own physical capabilities alongside their blade and magic work, producing a fighting style that is harder to categorize and harder to predict than standard Spellsword practice. The tradition developed independently of the four schools, and its practitioners tend to have a flexible relationship with the collaboration history that most Spellswords carry. | CA11: Where most Spellswords treat arcane magic as a complement to their blade work, the Force Weaver inverted that relationship, building their combat style on magical force as the foundation with the sword playing a supporting role. The tradition developed outside the four schools' framework, drawing on general Spellsword training redirected toward a more overtly magical application. Force Weavers exist at the edge of what distinguishes a Spellsword from a combat wizard, and practitioners on both sides of that line have opinions about which side of it the Force Weaver actually occupies. | CB11: The academies reserved their best graduates for Myrmidon training, producing elite protectors for Abyssal dignitaries and high-ranking commanders. They were, by any measure, excellent at their work. Five years after the war's end, that excellence is precisely the problem — the Concord nations are aware that somewhere in the Abyssal Lands there are highly trained, deeply loyal practitioners whose charges are either dead, imprisoned, or in hiding, and who have not necessarily transferred that loyalty anywhere safer. | CC11: A quiet rejection of the Spellsword orthodoxy, the Nightblade tradition challenges the fundamental assumption that one foe deserves absolute focus. Where the standard Spellsword philosophy builds entirely around the Challenge — the singular obsession with a chosen enemy — the Nightblade sees wisdom in adaptability, moving between opponents, accepting damage as part of a rhythm rather than a failure of commitment. Their elemental focus on dark as void rather than darkness proper reflects the same philosophy: not the presence of something malevolent, but the deliberate absence of limitation. | CD11: The pinnacle of Spellsword mastery carries a theological dimension that the elemental schools, with their founder-worship and collaborative history, never quite achieved. Sword Saints have moved through multiple elemental traditions toward light as synthesis — not a fifth element so much as the convergence of all four, a clarity achieved through comprehensive mastery rather than singular focus. Their strikes carry the certainty of practitioners who have stopped fighting to prove something and started fighting to finish something. Elia Scarlotto, trained outside the system by a master the academies killed, pursuing her revenge through every elemental tradition he taught her, is perhaps following a path toward this without having chosen it. | CE11: Nobody hired them to be there. The Minstrel shows up at the inn, passes the hat, and moves on before anyone can ask where they came from. In the Abyssal Lands, where joy is scarce and memories of the occupation are still raw, Minstrels have become something quietly essential — traveling folk musicians carrying songs between isolated settlements, keeping oral traditions alive that no institution bothered to preserve. They are not celebrated. They are needed, which is better. | CF11: Every court needs someone willing to say the unsayable, and Dynasia's feudal structure produced the Jester as a formalized answer to that need. The fool's motley is a license — to mock the powerful, to speak truths that would cost anyone else their head, to make the GodKing's nobility laugh at themselves. The license has limits, and every Jester knows exactly where those limits are. The good ones push right up against them. The great ones occasionally step over, and either survive or don't. | CG11: The church of Alister High has elaborate ceremonies for the dead, and the Dirge Singer emerged from those ceremonies as a specialized role — voices trained to carry grief in a register that feels almost liturgical. Five years after the war's end, with so many dead to mourn across every nation, Dirge Singers have rarely been busier. Some have wandered far from Dynasia, finding that grief is universal even when the specific prayers are not. | CH11: The Trader States reward excellence in many forms, and the Balladeer occupies a strange position in that system — artists kept by guild masters and merchant princes to compose odes to their greatness. The work requires genuine talent and produces genuine art, which makes the compromise all the more uncomfortable. In recent years, Balladeers have been asked to do more than flatter their patrons — to smooth over supply line failures, to reframe massacres as necessities, to make the history of the war sound cleaner than it was. Most comply. The ones who don't find new patrons quickly. | CI11: The galleys of Valis run on rhythm. The Drummer sits at the heart of the ship, setting the pace of the oars, and in the tradition of the old Valisian faith they are doing something more than keeping time — they are invoking Marduk, Enlil, and Tammuz, the Trinity whose blessing keeps the sea from swallowing the crew whole. The Pnang, arriving from the Far West centuries ago with a strangely similar faith, integrated into this tradition more smoothly than anyone expected. Whether that convergence means something, nobody has satisfactorily explained. | CJ11: Every nation with interests in the Abyssal Lands needs eyes it can trust, and the Spy discovered long ago that a lute is better cover than almost anything else. People talk around performers. They forget they are being listened to. Some Spies maintain genuine loyalty to the nation that trained them, though determining which nation that is can be genuinely difficult when the same operative has accepted commissions from three different employers. Others have dispensed with loyalty entirely and sell information to whoever pays. The cold war developing between the Concord nations has made both varieties extremely busy. | CK11: The Wagon Folk have traveled every road in the known world since before any of the current nations drew their borders, bound by ancient pacts to keep moving and to harm no community they pass through. The Mountebank is their contribution to the performing arts — part musician, part trickster, part merchant of small miracles. They deal in sleight of hand and misdirection, in the gap between what an audience believes and what is actually happening. This makes them either charming or deeply unsettling depending on the mark. | CL11: In every major city, there are performers whose talent has elevated them into something approaching social currency. The Diva aspires to that status — the celebrated voice that powerful people compete to host, whose presence at a gathering signals the host's importance as much as any political alliance. The reality is more complicated. A Diva without a patron is simply a very talented person without income, and the patrons who collect them do not always remember that the instrument they prize is also a person. | CM11: Nobody decides to become a Muse. The reputation accumulates around certain rare individuals whose presence seems to unlock something in the people around them — artists who create better work, soldiers who fight with more conviction, grieving people who find unexpected reserves of hope. Whether this is a form of magic or simply the effect of an exceptionally rare kind of personality is a question that tends to bore the people it most applies to. They are usually too busy helping someone else to discuss it. | CN11: In a world still finding its way out of the dark, the Lantern Bearer is less a title than a calling — a Bard who has stopped performing for recognition and started performing because the world needs light and they happen to know how to make it. They carry music, and warmth, and something harder to name into places that have been without those things for too long. They are the apex of what a Bard can become, not through technical mastery alone but through a quality of presence that has nothing to do with technique. Lance Hadley, young and optimistic and native to the darkest territory in the known world, is perhaps a natural candidate — though he would be the last to say so. | CO11: The academies of the Trader States teach the Conjurer tradition with an emphasis on containment. Before any student is permitted to reach through the veil, they spend years learning the safeguards — the circles, the bindings, the precise language of compulsion that keeps summoned entities from turning on their summoner. The Conjurer considers this rigor a mark of professionalism that distinguishes them from every other Binder tradition. Other Binder traditions consider the Conjurer dangerously overconfident in their circles. | CP11: Nobody taught the Occultist. That is both their distinction and their danger. Driven by obsession rather than institutional training, the Occultist pursues veil knowledge through whatever texts, ruins, and ill-advised experiments they can access, accumulating understanding the hard way. With the veil weakened since Abaddon's summoning, self-taught practitioners are finding it easier than ever to make contact — and considerably harder to maintain control of what answers. The Occultist tradition produces remarkable breakthroughs and remarkable disasters in roughly equal measure. | CQ11: The tribes of the Abyssal Lands have always lived close to things that civilized peoples prefer to pretend do not exist, and the Shaman tradition emerged from that proximity over generations. Shamans serve their tribes as intermediaries between the living and whatever lies beyond — negotiating, appeasing, occasionally compelling. They regard the academic Binder traditions with open skepticism, having watched formally trained practitioners blunder into situations that any Shaman child would have known to avoid. | CR11: The Medium's relationship with the veil is the most permeable of any Binder tradition — less a practitioner who reaches through than one who allows things to reach back. Lorewise this means a willingness to let spirits temporarily inhabit and work through them, a practice that other Binder traditions find either impressive or horrifying depending on their temperament. The Medium walks a careful line between openness and dissolution, and not all of them maintain it indefinitely. | CS11: Among the exile communities and displaced peoples of the Abyssal Lands, the Animist tradition holds that every living thing carries a fragment of something beyond the veil — that the spirit world is not elsewhere but threaded through everything present. This is a less dramatic form of Binder practice than most, concerned less with summoning and more with listening. Animists tend to be patient people. The tradition selects for it. | CT11: Where the Medium balances between forces, the Spiritualist leans entirely toward the creative side of the veil — the generative, the living, the light that exists beyond mortal perception. This sounds gentler than it is. The Spiritualist's pursuit of that creative force often pushes her to physical extremes, treating her own body as a secondary concern compared to what she is reaching toward. The results can be extraordinary. The cost is rarely small. | CU11: The navigators of the Valis Confederacy read the stars to find their position on the sea, and the Astrologer tradition emerged from the discovery that the same stars that chart physical position also mark currents in the spirit realm. Valisian academies formalized this into a discipline — celestial observation as a form of veil-reading, omens extracted from the same sky that guides the fleet home. The Astrologer is among the most educated of Binder traditions and among the most comfortable with ambiguity, having learned that the stars rarely give simple answers. | CV11: The Zafeer people of Dynasia carry a tradition older than their current peace with the feudal throne — advisors trained to see what rulers cannot, drawing on veil knowledge to counsel, warn, and occasionally manipulate the powerful toward better decisions. The Vizier does not rule. The Vizier makes rulers worth following, or failing that, finds better ones. Dynasia absorbed the Zafeer tradition because it was too useful to suppress, and the Vizier has navigated that complicated institutional position with characteristic patience ever since. | CW11: Most Binders reach through the veil toward spirits, demons, entities that exist in relationship to humanity even if that relationship is predatory. The Alienist reaches further, toward presences that predate that relationship entirely — elder things, cosmic entities, beings for whom humanity is not an adversary or a resource but simply a fact of no particular significance. Hastur straddles the border between demon lord and elder presence, and Alienists who have contacted him rarely describe the experience in reassuring terms. The distinction between the Alienist and the Cultist is control — the Alienist refuses to serve. Whether the elder things notice this distinction is another question. | CX11: Every other Binder tradition involves some degree of asymmetry — the practitioner reaching toward something more powerful and managing that imbalance through skill, safeguards, or faith. The Pact Master has closed that gap. Through decades of accumulated power and understanding, the Pact Master negotiates with summoned entities as a genuine equal, offering terms rather than issuing commands or making supplications. Sandra Martin, who passed through the space between Heaven and Hell without training and survived, understands something about what lies beyond the veil that most Pact Masters spend lifetimes approaching. She arrived at that knowledge in an afternoon. It was not a pleasant afternoon. | CY11: The first step in the Dynasian church's long path of devotion, the Acolyte has accepted the faith of Alister High and begun the slow process of earning divine favor through service and study. The healing gifts that manifest in early training are modest and inconsistent — the church teaches that this is as it should be, that power proportional to devotion is the correct order of things. Most Acolytes spend years in this state before advancing. Some never do, and serve the church in other capacities. Father Martin began here, as everyone does. | CZ11: Outside the great cities and cathedral towns, the Healer is often the only representative of organized faith a farming community ever sees. They live among the people they serve — tending the sick, blessing the harvest, presiding over births and deaths — and their divine gifts are calibrated to exactly that scale of need. The church regards them as essential and somewhat unglamorous. The communities they serve regard them as indispensable. In the Abyssal Lands, where institutional presence is thin and suffering is not, traveling Healers are among the most quietly important people in the region. | DA11: Further along the Dynasian devotional path than the Acolyte, the Disciple has proven their commitment through years of service and begun to access more reliable and more powerful divine gifts. They are recognizable figures in Dynasian society — respected, trusted, occasionally envied. The political side of the church regards Disciples as a resource to be cultivated and directed. The religious side regards them as souls doing exactly what souls should do. The tension between those two perspectives is something every Disciple eventually has to navigate personally. | DB11: The institutional backbone of the Dynasian church, the Priest occupies a formal role within the hierarchy — conducting ceremonies, administering sacraments, serving as the official face of Alister High's faith in a specific community or region. The distinction between the political and religious sides of the church manifests most visibly at the Priest level, where assignments are made and careers are managed by people whose motivations are not always purely spiritual. A Priest who serves their congregation well and a Priest who serves the church's political interests well are not always the same person. | DC11: War produced the Combat Medic as a necessity and the peace has not eliminated them. Where the Healer serves a community, the Combat Medic serves a nation — embedded with military units, trained to work under conditions that would paralyze a sanctuary healer, devoted as much to the flag as to the faith. They come from all three Concord nations and their theological backgrounds vary considerably, united less by doctrine than by the particular psychology required to heal people while people are actively trying to kill them. | DD11: The church of Alister High has always maintained Exorcists, but for most of its history they were a minor specialty dealing with rare cases of possession and haunting. The weakening of the veil changed that overnight. The Abyssal Lands now host more spiritual corruption than the church has ever encountered, and Exorcists have flooded into the region in numbers that alarm the Binder traditions and deeply unsettle the Reapers. To the Exorcist, what the Reaper venerates and the Binder attempts to control is simply a problem to be solved. This perspective is not universally appreciated. | DE11: The faith of Shaetavar the Sleeping God does not demand that its followers evangelize in the aggressive sense. The Preacher's role is gentler — to guide people toward right action, to interpret the subtle influence of the god's dreams on daily life, to maintain the faith as a living and breathing thing in communities across the Trader States. Some Preachers are genuinely devoted to this purpose. Others have noticed that a trusted religious figure occupies a position of considerable social influence, and have adjusted their priorities accordingly. Shaetavar, dreaming, may or may not be aware of the difference. | DF11: The Trinity of Marduk, Enlil, and Tammuz does not produce gentle faithful. The Valisian faith is a religion of the sea — of storms survived and enemies outrun and battles won through ferocity when seamanship was not enough — and the Zealot is its most extreme expression. In battle they function as something approaching clerical berserkers, their devotion translating directly into a frightening capacity for violence done in the name of their gods. The Grand Commodore values them as shock troops. The quieter members of the Valisian faith regard them with the complicated pride of people whose most famous representatives are also their most embarrassing ones. | DG11: Nobody is quite sure where Plague Doctors come from or who trained them, which is part of the problem. They appear in communities suffering from disease outbreaks, treat the sick with methods that blend religious ritual and genuine medicine, and move on before anyone can ask too many questions. The unaffiliated nature that makes them flexible and broadly deployable also makes them deeply suspect in a world already paranoid about cult activity. The accusation that they bring the diseases they claim to cure follows them everywhere. For the most part it is not true. The most part is doing a lot of work in that sentence. | DH11: No faith owns the Oracle and no faith entirely trusts them. They exist at the intersection of all religious traditions as figures who have moved beyond institutional devotion into something that resembles a direct line to divinity itself — readers of Shaetavar's dreams who have stopped needing the interpretation the Preacher provides, visionaries whose pronouncements the Dynasian church cannot officially sanction and cannot afford to ignore. They are mythologized across all three Concord nations and regarded with the specific unease that genuinely holy things tend to produce in institutions built around managing holiness. They are rare, they are usually inconvenient, and they are almost always right. | DI11: The line between Valisian pirate crews and the island folk they raid is blurrier than either side likes to admit, and the Buccaneer tradition exists in that blur. Spirit worship runs deep in both communities, mixed freely with the faith of the Trinity in a way Dynasia would find scandalous and Valis finds unremarkable. Buccaneer Reapers serve aboard ships and in island settlements alike, calling on spirits of drowned sailors and lost crews, the dead who never quite made it home being among the most pervasive and powerful presences the sea produces. | DJ11: Nobles understand that fear is a useful tool, and the Executioner's public function has always been as much about the watching crowd as the condemned. Trained and retained by noble houses to perform sanctioned killings with theatrical weight, Executioners carry an uncomfortable relationship with the spirits their work generates — the newly dead rarely depart peacefully when their death was staged for someone else's political benefit. | DK11: The most literal relationship with death in the Reaper tradition, the Gravedigger spends their working life in cemeteries and burial grounds, and over years in that company they develop an unusually practical familiarity with spirits. Graveyards accumulate the confused and newly formed — presences that have not yet settled into understanding what they are or what happened to them. The Gravedigger's role is often simply to be present for that confusion, a familiar face in an unfamiliar transition. | DL11: Where the Executioner serves noble intimidation, the Hangman serves something closer to civic order, a tradition with deep roots in Dynasian frontier history. Bringing structured justice to lawless edges of settled territory, the Hangman's grim profession represents the line between chaos and a functioning community — someone has to do this so that everyone else doesn't have to resort to it themselves. The work is unloved. The function is, in its own bleak way, foundational. | DM11: The four moons of the world move in patterns that Harbingers have studied for generations, reading omens in their phases and alignments the way an Astrologer reads the stars. Death, disaster, and significant turning points all seem to leave traces in that lunar pattern if a Harbinger knows how to look, and their reputation as bringers of bad news follows them everywhere. Nobody is happy to see a Harbinger arrive. Everyone wants to know what they've seen. | DN11: Drawing on old folk tradition, the Sin Eater takes on the burdens of both the dead and the living, a function that manifests as much in purification as in consumption. Disenchanting what should not have been earned, purging what should not be carried, the Sin Eater's work toward spirits serves a similar purpose — sometimes guiding a tormented presence toward peace, sometimes recognizing that peace isn't possible and ending the spirit instead. Neither outcome is treated as a failure. Both are considered mercy, depending on what the spirit actually needs. | DO11: Dreams carry real power in this world, and the Sandman works in the space where powerful dreams cross over into spirit formation — distinct from the nightmares that spawn goblins, a darker and more chaotic phenomenon entirely. The Sandman's tradition shares an uneasy proximity with the faith of Shaetavar the Sleeping God, both concerned with what dreams can create and mean, though Sandmen generally avoid claiming any direct theological connection to a god who might, after all, still be dreaming them into being. | DP11: Communication runs in two directions for the Whisperer — listening to spirits, and using spirits to relay messages and information to others. It is an effective and unsettling skill, and the constant presence of voices that aren't quite there tends to leave a mark. Whisperers develop a particular paranoid edge over time, an inability to fully trust silence, having spent too long aware of how much can be listening that nobody else can perceive. | DQ11: Death and mercy are not opposites in this tradition, and the Mercy Bringer moves fluidly between them. Sometimes mercy means ensuring a kill is quick and clean rather than prolonged. Sometimes mercy means the kill itself, ending suffering that has no other resolution. The Mercy Bringer carries the weight of being trusted with that judgment, and the best of them never stop finding it heavy. | DR11: The most quietly dangerous Reaper tradition, the Gaslighter manipulates — the living, through careful deception, and the spirits themselves, bent toward serving the Gaslighter's interests rather than their own nature or peace. It is a deliberate exploitation of the exact vulnerability that shaped Stephen Blackwell's introduction to the tradition: a spirit that looks and feels like comfort, that a grieving person desperately wants to believe, twisted by someone willing to use that desperation rather than gently correct it. | DS11: The clearest expression of what the Formless Ones once sought, the Telepath reaches mind to mind, reading and communicating in ways no spoken language can match. It is the most recognizable face of Psychic ability to ordinary people, and also the most uncomfortable one — nobody enjoys knowing their thoughts aren't entirely private. Telepaths who can control the depth of their reach are rare. Most simply learn to live with knowing more than anyone wants them to. | DT11: Where the Telepath reaches into other minds, the Kinetic reaches into the physical world directly, moving objects and bodies through will alone. It is the most visibly inhuman of the Psychic disciplines — there is no mistaking a Kinetic's ability for ordinary cleverness or charisma, and that visibility tends to draw exactly the kind of fearful attention most Psychics try to avoid. Among the Wagon Folk, Kinetics are valued and unremarkable. Almost everywhere else, they are watched. | DU11: Making others forget is a quietly devastating ability, and the Amnesiac pays for it in kind — gaps in their own memory growing wider the more they use their gift on others. Some Amnesiacs barely remember their own childhoods. Few discuss what that cost feels like, partly because the words for it tend to slip away along with everything else. | DV11: Subtler than the Kinetic and quieter than the Telepath, the Hypnotist works through sustained channeling and careful, patient influence rather than dramatic displays of power. Where other Psychics force their way into a situation, the Hypnotist prefers the slow approach — suggestion building on suggestion until the target's own choices start working in the Hypnotist's favor. It is the most insidious discipline precisely because it rarely looks like anything is happening at all. | DW11: Knowing things before they happen is the Diviner's gift, an extension of the Formless inheritance toward prediction rather than perception or force. Diviners read the immediate future of conflict with unsettling accuracy — what an enemy will do, how badly they're hurt, where the danger is about to come from. It is a quieter ability than Kinetic's, but no less unsettling to those on the receiving end of a stranger who seems to know exactly what's about to happen to them. | DX11: The Haunted reach toward spirits, and spirits reach back. This is among the more dangerous expressions of Psychic ability, since contact runs in both directions — a Haunted practitioner who spends years calling on the dead for insight finds the dead increasingly willing to call on them in return. The affliction is not separate from the gift. It is the gift, working exactly as it always has, simply turned around. | DY11: Not every Psychic's instability comes from the gift corroding them. The Mastermind's affliction runs the other way — an egotism so total that it predates and shapes how they use their ability, every act of influence bent toward proving their own brilliance. Masterminds are controlled, calculating, and genuinely effective. They are also, almost without exception, exhausting to work with. | DZ11: Illusion and false perception are the Mindbleeder's tools, bending what others see and experience until reality and fabrication blur. The cost runs the same direction as the gift — Mindbleeders increasingly struggle to trust their own perceptions, uncertain where the illusions they craft for others end and their own grip on what's real begins. | EA11: True time travel does not exist in this world, but the Chronomancer comes closer to touching time than any other discipline — manipulating its perception, and sometimes its actual passage, though only ever in a single forward direction. They can quicken a moment or stretch it thin, but never reverse it, never branch it, never escape the line everyone else is also walking. It is a profound gift with a humbling limitation built directly into its nature. | EB11: Where the Mastermind's flaw is ego, the Puppet Master's is something colder — a manipulative streak that borders on sociopathy, expressed through literal control over others rather than mere influence. The ability and the personality reinforce each other so thoroughly that it becomes difficult to say which came first. Puppet Masters impose control because something in them needs to, and the gift simply gave them the means. | EC11: The most defensively oriented of the Runemage traditions, the Abjurer specializes in protective circles and warding inscriptions, most commonly etched into armor rather than cast through the air. The tradition traces back to the earliest practical applications of Titan runic knowledge — the first thing any civilization wants from magic, once they have access to it, is to stop being hurt. Abjurers are not glamorous practitioners, but they are consistently employed. | ED11: Where most Runemages inscribe their work on objects or places, the Symbolist inscribes directly on people — runes triggered by specific actions, lying dormant until the conditions of their activation are met. The work requires both technical precision and a careful read of how a person moves and fights, since a rune that triggers at the wrong moment is either useless or dangerous. Symbolists tend to develop an unusually intimate understanding of whoever they're working with, which not everyone finds comfortable. | EE11: Among the oldest Runemage traditions, the Cabalist draws on pre-church texts that predate Harold Hugh and the founding of Dynasia's faith, pursuing the creation of golem companions through runic inscription as a form of devotional practice. The current church accommodates this tradition uneasily — those foundational texts are still used, but the old religion never imagined its god becoming flesh, and the Cabalist's work of creating artificial life sits in a theological space nobody has cleanly resolved. The golems, for their part, do not appear to have opinions on the matter. | EF11: Every major Runemage academy produces a handful of students who take their foundational training and then disappear — into remote locations, private obsessions, decades of solitary refinement. The Hermit is not self-taught, but they have long since outgrown whatever institution shaped them, pursuing runic mastery in directions no curriculum anticipated. They accumulate knowledge the way their chosen locations accumulate dust, and share it with roughly the same enthusiasm. | EG11: Born from the practical need to counter hostile magic, the Disenchanter tradition developed a philosophy as much as a technique — that another practitioner's enchantments are not just obstacles to be removed but resources to be claimed. Disenchanters fuel their own work with what they strip from others, a parasitic elegance that more orthodox Runemages find philosophically distasteful and practically undeniable. | EH11: The Scrivener's work is architectural rather than personal — runes etched into doorframes, floors, walls, and roads, waiting for the right trigger to activate. It is a patient tradition that rewards preparation over improvisation, and Scriveners tend to be most effective in environments they have had time to prepare thoroughly. A Scrivener who has spent a week in a building before a conflict begins is a significantly more dangerous practitioner than one who arrives at the same time as the enemy. | EI11: The closest any Runemage tradition comes to Wizard territory, the Sage specializes in elemental runes with an academic enthusiasm that occasionally outpaces their judgment about what the knowledge should be used for. They are among the most broadly educated of Runemage practitioners, drawn to understanding for its own sake, which produces both impressive versatility and a certain moral flexibility that more focused traditions tend to find concerning. | EJ11: Weapon inscription is as old as the Titan tradition itself — the original fusion of forging and magic that gave non-magical races their first foothold against progenitor power. The Glyphic has made that ancient practice into a specialization, mastering the enhancement of weapon-etched runes beyond what most practitioners consider achievable. They carry forward the most direct lineage to the Titans' original purpose, even if most Glyphics think of themselves in considerably more practical terms. | EK11: Timing runes that last only briefly but can be consumed for dramatically amplified effect represent a particular school of runic philosophy — that power concentrated and released in a single moment outweighs power distributed across time. Cryptics are specialists in that concentrated burst, managing runes that are simultaneously fragile and explosive, requiring both precise timing and a tolerance for the risk of something going wrong at exactly the worst moment. | EL11: The pinnacle of Runemage practice, the Sorcerer has mastered power runes and, more importantly, mastered sequence — understanding not just what individual runes do but how their combination and ordering shapes reality at a fundamental level. Where other Runemages write words, the Sorcerer writes sentences, and understands the difference between a list of powerful things and a story that changes how things are. Adair Taggart, curmudgeonly and underestimated and in possession of knowledge about Hellstones that his academic peers consider beneath their attention, understands something about runic sequence that most Sorcerers spend their careers approaching. | EM11: Every cult has new members, and not all of them arrive knowing exactly what they have joined. The Cultist represents the earliest stage of demon lord service — drawn in by promises of power, belonging, or escape from circumstances that felt impossible to endure otherwise. Some discover the truth of their patron and embrace it. Some, like Kayla Edgars, discover it and find themselves unable to continue. The demon lords are patient with new recruits. They have learned that clarity about the arrangement tends to come later, when leaving is considerably more difficult. | EN11: Pazazu's servants carry the wind with them, a cold and howling presence that makes their allegiance difficult to mistake for anything benign. Warlocks are fully aware of what they have chosen and have chosen it deliberately, finding in Pazazu's domain a power that suits their particular temperament. The masculine associations the title carries in common usage are a misunderstanding the tradition itself does not share — Warlocks are defined by their compact with Pazazu, not by anything as incidental as gender. | EO11: Mephisto and Moloch both claim fire, and the Effigist serves whichever of the two has claimed them, channeling infernal flame through effigy work that targets the representation of a person as much as the person themselves. The tradition has obvious dramatic power — burning an effigy carries cultural weight across most societies — and Effigists exploit that weight deliberately, understanding that fear of the symbolic act often precedes and amplifies the actual damage. | EP11: Earth magic in service of a demon lord does not produce growth. The Dustbringer's tradition is associated with disintegration and a specific, creeping corruption that resists every attempt at purging — afflictions that settle into their targets and simply remain, indifferent to remedy. The earth theme here is entropy rather than foundation, the slow reduction of everything solid into something that blows away. Dustbringers tend to be patient practitioners. Their work rewards patience. | EQ11: Ipos leaves his mark in frost, and the Crone tradition carries that cold deep into its Russian-inflected folk practice — winter magic, ice and preservation, the specific cruelty of a cold that does not kill cleanly but preserves its victims in suffering. Crones exist at the intersection of old folk tradition and infernal service, their practice dressed in the clothing of grandmother wisdom while drawing on something considerably less benign. The aesthetic of the kindly old woman in the woods has always been ambivalent in the places where Crone tradition is strongest. It is more ambivalent now. | ER11: Nobody becomes a Hedgemage through ambition. They arrive at it through alienation — living on the outskirts of villages that want their folk cures but not their company, offering what help they can in exchange for an acceptance that never quite materializes. The power they access through their demon lord connection is real, even if they don't fully understand its source, and it serves genuine community purposes right up until the community disrespects them one time too many. The transformation from tolerated healer to vengeful practitioner rarely happens all at once. It accumulates. | ES11: The Mambo tradition sits close enough to Reaper spirit practice that outsiders frequently confuse the two, but the distinction matters to practitioners on both sides. Where Reapers approach spirits with something approaching respect, the Mambo's fetish bag work operates in service of demon lord power rather than the spirit hierarchy, using similar vocabulary for fundamentally different ends. Mambos exist most commonly in Valis and the Abyssal Lands, where the cultural proximity to genuine spirit worship provides both cover and occasional uncomfortable confrontation with Reapers who notice the difference. | ET11: The Bokor's zombies are not spirit-inhabited bodies and they are not the honored dead. They are enslaved — sometimes corpses, sometimes people who are technically still alive, rendered mindless and compliant through demon lord granted power that the Bokor deploys with complete indifference to the distinction. The Bokor does not care what their servants were before. They care only that they serve now. In the Abyssal Lands, where the war left bodies and broken people in abundance, the Bokor tradition has found more raw material than it has ever had before. | EU11: Where the Crone operates alone in her winter isolation, Hags gather. Three is traditional, though the number is flexible, and what they share is less a specific demon lord patron than a collective practice of malevolence — the weaving of fate, the cursing of the presumptuous, the specific satisfaction of power exercised without apology. They are among the most self-aware practitioners in the Witch tradition, under no illusions about what they serve or why, and find the self-deception of newer Cultists either amusing or contemptible depending on their mood. | EV11: Every demon lord needs representatives in the mortal realm, and the Malefax has decided that representative should be them. Through forged covenants and accumulated power, the Malefax negotiates directly with demon lords for primacy among their cults — the right to speak with their patron's authority, to rule the networks of servants below them, to be the face of infernal power in the world. It is an arrangement that feels like elevation and functions like a leash. The demon lords have made these covenants before. They know exactly how much rope to extend and exactly when to pull it taut. | EW11: The generalist path through Wizard tradition, the Elementalist spreads their study across multiple elements without committing to the deep specialization their more focused peers pursue. This is sometimes a deliberate philosophical choice and sometimes simply an inability to choose, and the tradition does not particularly distinguish between these motivations. What it produces is breadth — practitioners who can adapt to whatever a situation requires, at the cost of the concentrated power that specialization provides. In a world as unpredictable as the post-war Abyssal Lands, breadth has genuine value. | EX11: Dark magic applied to life and death does not require demonic service, and the Necromancer tradition has always maintained that animating the dead is a neutral act rather than an evil one. Society has largely accepted this position, partly because Necromancers demonstrably don't serve demon lords and partly because after a war that produced as many dead as the last one, pragmatism about corpses has become more widespread. The only reliable source of offense is personal — the people who knew the skeleton companions in life, for whom the neutrality of the act is considerably harder to maintain. | EY11: Water magic attracts practitioners with a particular temperament — patient, adaptive, interested in flow and pressure rather than direct confrontation. Hydromancer traditions exist across all three Concord nations but flourish especially in Valis, where the element is immediately and constantly present and its properties are understood practically before they are understood magically. Valisian Hydromancers tend to have a sailor's relationship with water — respectful, unsentimental, aware of exactly how dangerous it can be. | EZ11: Earth magic is the slowest and most enduring of the elemental disciplines, and Geomancers reflect that in their practice — methodical, heavily defensive, concerned with permanence in a way that more volatile elemental traditions find excessive. They are disproportionately common in the Trader States, where the guild system's appreciation for reliable infrastructure finds a natural resonance with magic that builds and holds rather than burns and moves. | FA11: Air magic is the most difficult elemental discipline to visualize and the most difficult to defend against, operating in the space between things rather than through direct force. Aeromancers tend toward an intellectual detachment that other elemental practitioners sometimes find frustrating — they are interested in the movement of things, in the spaces and pressures that govern how everything else behaves, which produces a distinctive combat style and a distinctive conversational style equally. | FB11: Fire finds practitioners in every nation and social context, partly because it requires less patience than earth or water and partly because its effects are immediately visible and dramatic in ways that attract a certain temperament. Pyromancer schools exist everywhere, producing the largest volume of Wizard graduates of any elemental specialty and consequently the widest range of quality. The Abyssal war found uses for Pyromancers on both sides, and their postwar reputation is complicated by how enthusiastically many of them participated. | FC11: The Arcanist's central conviction is that shaping raw magical energy into an element loses something essential in the process — that the purest and most powerful form of magic is arcana before it becomes anything specific. Where every other Wizard tradition treats elemental attunement as the goal, the Arcanist treats it as a compromise. This position is not popular in schools built around elemental curricula, and most Arcanists are either self-taught or trained by masters who found institutional magic too limiting. Mary Stanfield's wealthy, free-ranging education gave her exposure to this tradition among others, and its philosophical independence probably resonates with someone who has always had the resources to chart her own course. | FD11: Light magic is not moral magic, despite what its name implies and what practitioners in Dynasia's religiously inflected schools sometimes suggest. The Solomancer illuminates — literally and metaphorically, piercing defenses, exposing what is hidden, bringing things into clarity that preferred to remain obscure. In a world thick with cult activity and political deception, these are useful abilities that make Solomancers simultaneously valuable and unwelcome depending on whose secrets are being illuminated. | FE11: While most Wizards are concerned with what magic they can create, the Incanter is equally concerned with what magic they can stop. Channeling and counterspell work define the tradition — a deep familiarity with how other practitioners' magic operates, developed specifically to interrupt it. Incanters can recognize magical effects as they form and unmake them before they land, a defensive capability that makes them uniquely frustrating opponents for every other magic-using tradition. They are not popular at schools where the curriculum assumes magic is primarily something you do to others. | FF11: The pinnacle of Wizard practice belongs to those who have passed through elemental specialization and out the other side into genuine mastery of the full spectrum. Where the Elementalist spreads study without depth, the Thaumaturge has achieved depth in every element and learned to combine them in ways that individual specialists cannot approach. The most difficult magic of every element becomes available at this level — not through raw power but through comprehensive understanding, the accumulated wisdom of a practitioner who has refused to stop learning. Mary Stanfield, with her private tutors and elite schooling and the financial freedom to pursue knowledge wherever it leads, is perhaps better positioned than most to eventually walk this path.
A12: Appearance | B12: =COUNTA(C12:FF12)/1.6 -> 7.5 | AQ12: Her clothes are plain, functional. She is tall, broad of shoulder. She carries a large club, which she taps her opposite hand with. | AW12: Her eyes are wide, and she is ready for battle. Both axes are in her hands, glinting in the sunshine. | AX12: The cannibal is a non-descript member of the public. She wears the same plain clothes of the village she lives in, and the weapons she carries can easily be explained away. She is muscular, but her clothing disguises this. | AY12: At first, it seems the weapons and armor of the Destroyer are held together by spit and hope, but it quickly becomes clear that they are sturdier than they look. | AZ12: It is hard to find the Beastlord beneath her mountain of furs. Her hair is unkempt, with leaves and bones tangled in it, and the smell is potent. She says it is to help her better fit in with the beasts. | BA12: She wears a mismatched set of armor, designed to draw attention to her greater assets. She has some scars, but not so many as to detract from her hard, yet beautiful look. | BC12: She carries spear and shield with a plumed helm. | BD12: Though she wears chain, the armor on the Dervish seems to flow around her, and the chains she fights with dance in her hands. Her long hair is in a ponytail, flickering back and forth. | BF12: She carries a lance, pointed straight to the sky, her king’s favor hanging down from it. She wears heavy armor. | BG12: The Samurai always fights with two swords, one long, one short. Her splint mail is typically enameled in red, and her helm resembles the face of a demon. | BH12: The Dreadnaught wears extremely heavy armor, and it is a wonder she can move in it. Her face is hidden by her helm. She wields a large axe. | BJ12: She carries a sword and shield, her shield emblazoned with her heraldic symbol. Her hair is shoulder length but bound.
A13: Req Dex | B13: =COUNTA(C13:FF13)/1.6 -> 61.875 | C13: 58 | D13: 63 | E13: 62 | F13: 88 | G13: 70 | H13: 142 | I13: 180 | J13: 248 | K13: 193 | L13: 182 | M13: 59 | N13: 58 | O13: 93 | P13: 76 | Q13: 67 | R13: 173 | S13: 88 | T13: 185 | U13: 217 | V13: 263 | W13: 54 | X13: 61 | Y13: 90 | Z13: 97 | AA13: 110 | AB13: 126 | AC13: 87 | AD13: 162 | AE13: 207 | AF13: 253 | AG13: 60 | AH13: 66 | AI13: 103 | AJ13: 119 | AK13: 68 | AL13: 78 | AM13: 181 | AN13: 134 | AO13: 175 | AP13: 172 | AR13: 55 | AS13: 78 | AT13: 76 | AU13: 108 | AW13: 137 | AX13: 95 | AY13: 92 | AZ13: 181 | BA13: 57 | BB13: 65 | BD13: 85 | BE13: 83 | BF13: 78 | BG13: 80 | BI13: 215 | BJ13: 121 | BN13: 66 | BP13: 81 | BU13: 57 | BW13: 61 | BY13: 67 | CC13: 146 | CD13: 112 | CE13: 54 | CF13: 64 | CG13: 75 | CH13: 85 | CI13: 83 | CJ13: 152 | CK13: 83 | CN13: 120 | CP13: 56 | CS13: 71 | CT13: 96 | CW13: 145 | CX13: 113 | CY13: 54 | DF13: 106 | DI13: 55 | DQ13: 97 | DT13: 56 | DV13: 76 | DX13: 78 | EA13: 166 | EB13: 105 | ED13: 56 | EK13: 98 | EM13: 57 | EN13: 60 | EP13: 66 | ES13: 79 | EW13: 61 | EY13: 64 | EZ13: 66 | FA13: 100 | FB13: 100 | FD13: 187 | FE13: 142 | FF13: 111 | FG13: =SUM(C13:FF13) -> 10401
A14: Req Int | B14: =COUNTA(C14:FF14)/1.6 -> 61.25 | K14: 90 | L14: 108 | M14: 56 | N14: 54 | R14: 77 | S14: 129 | W14: 53 | Y14: 68 | Z14: 71 | AA14: 63 | AB14: 121 | AC14: 82 | AE14: 197 | AF14: 237 | AL14: 74 | AP14: 102 | AR14: 55 | AV14: 74 | BE14: 64 | BF14: 74 | BM14: 60 | BN14: 79 | BO14: 77 | BP14: 77 | BR14: 177 | BS14: 137 | BT14: 220 | BU14: 57 | BV14: 62 | BW14: 80 | BX14: 62 | BY14: 64 | BZ14: 77 | CA14: 143 | CC14: 135 | CG14: 72 | CK14: 111 | CL14: 89 | CM14: 101 | CN14: 107 | CO14: 56 | CP14: 65 | CQ14: 59 | CT14: 69 | CU14: 82 | CV14: 166 | CW14: 137 | CX14: 220 | CZ14: 55 | DA14: 60 | DB14: 59 | DG14: 157 | DH14: 151 | DL14: 60 | DM14: 65 | DO14: 82 | DP14: 143 | DR14: 205 | DS14: 61 | DT14: 56 | DU14: 70 | DV14: 86 | DW14: 107 | DX14: 74 | DY14: 191 | DZ14: 128 | EA14: 157 | EB14: 257 | EC14: 59 | ED14: 67 | EE14: 84 | EF14: 79 | EG14: 64 | EH14: 156 | EI14: 164 | EJ14: 89 | EK14: 146 | EL14: 303 | EM14: 60 | EN14: 64 | EO14: 96 | EP14: 64 | EQ14: 83 | ER14: 77 | ES14: 100 | ET14: 206 | EU14: 217 | EV14: 279 | EW14: 61 | EX14: 65 | EY14: 62 | EZ14: 64 | FA14: 96 | FB14: 96 | FC14: 176 | FD14: 132 | FE14: 213 | FF14: 259 | FG14: =SUM(C14:FF14) -> 10595
A15: Req Str | B15: =COUNTA(C15:FF15)/1.6 -> 61.25 | C15: 54 | E15: 75 | F15: 76 | I15: 86 | L15: 121 | M15: 54 | N15: 64 | O15: 72 | P15: 92 | Q15: 105 | S15: 95 | U15: 140 | V15: 129 | W15: 58 | X15: 56 | AA15: 67 | AC15: 127 | AD15: 110 | AI15: 64 | AK15: 87 | AL15: 80 | AO15: 140 | AQ15: 64 | AR15: 68 | AS15: 81 | AT15: 106 | AU15: 91 | AV15: 134 | AW15: 112 | AX15: 98 | AY15: 224 | AZ15: 121 | BA15: 62 | BB15: 56 | BC15: 83 | BD15: 86 | BE15: 84 | BF15: 132 | BG15: 171 | BH15: 252 | BI15: 168 | BJ15: 129 | BK15: 61 | BL15: 69 | BM15: 63 | BN15: 82 | BO15: 110 | BP15: 144 | BQ15: 198 | BR15: 188 | BS15: 149 | BT15: 116 | BU15: 54 | BV15: 64 | BW15: 73 | BX15: 93 | BY15: 117 | BZ15: 144 | CA15: 118 | CB15: 273 | CC15: 101 | CD15: 316 | CE15: 54 | CI15: 66 | CS15: 74 | CU15: 91 | CY15: 54 | DA15: 87 | DB15: 86 | DC15: 119 | DD15: 77 | DE15: 107 | DF15: 164 | DH15: 110 | DI15: 59 | DJ15: 65 | DK15: 81 | DL15: 86 | DM15: 68 | DN15: 98 | DQ15: 101 | DR15: 137 | DT15: 68 | DU15: 73 | DV15: 64 | DW15: 71 | DX15: 135 | DZ15: 193 | EB15: 110 | EC15: 57 | EE15: 75 | EF15: 82 | EG15: 68 | EK15: 107 | EP15: 67 | EU15: 111 | EZ15: 67 | FB15: 77 | FG15: =SUM(C15:FF15) -> 10016
A16: Req Wis | B16: =COUNTA(C16:FF16)/1.6 -> 62.5 | C16: 61 | D16: 63 | E16: 72 | G16: 108 | H16: 95 | I16: 80 | J16: 98 | K16: 95 | T16: 90 | V16: 118 | X16: 53 | AD16: 101 | AG16: 59 | AH16: 65 | AK16: 66 | AL16: 77 | AM16: 113 | AN16: 168 | AO16: 87 | AP16: 172 | AQ16: 56 | AW16: 76 | AX16: 132 | AY16: 89 | AZ16: 170 | BB16: 55 | BC16: 70 | BG16: 77 | BH16: 95 | BJ16: 185 | BK16: 56 | BL16: 55 | BM16: 73 | BS16: 140 | BT16: 105 | BX16: 63 | BZ16: 82 | CE16: 59 | CF16: 62 | CG16: 73 | CH16: 84 | CI16: 82 | CJ16: 83 | CK16: 82 | CL16: 230 | CM16: 277 | CN16: 310 | CO16: 62 | CP16: 60 | CQ16: 93 | CR16: 110 | CS16: 94 | CT16: 118 | CU16: 158 | CV16: 167 | CW16: 98 | CX16: 110 | CY16: 60 | CZ16: 71 | DA16: 74 | DB16: 74 | DC16: 71 | DD16: 146 | DE16: 154 | DF16: 104 | DG16: 223 | DH16: 208 | DI16: 54 | DJ16: 59 | DK16: 78 | DL16: 72 | DM16: 115 | DN16: 137 | DO16: 196 | DP16: 197 | DQ16: 183 | DR16: 132 | DS16: 53 | DU16: 60 | DW16: 69 | EC16: 53 | EE16: 60 | EG16: 99 | EH16: 79 | EI16: 112 | EJ16: 186 | EL16: 182 | EN16: 54 | EP16: 64 | EQ16: 103 | ER16: 140 | ES16: 131 | ET16: 130 | EU16: 104 | EV16: 167 | EX16: 61 | EY16: 76 | EZ16: 64 | FC16: 85 | FF16: 109 | FG16: =SUM(C16:FF16) -> 10481
A17: Req Cha | B17: =COUNTA(C17:FF17)/1.6 -> 61.875 | C17: 58 | D17: 67 | E17: 84 | F17: 86 | G17: 130 | H17: 95 | I17: 82 | J17: 99 | K17: 238 | L17: 244 | P17: 63 | Q17: 68 | R17: 109 | U17: 131 | V17: 118 | W17: 61 | X17: 55 | Y17: 71 | Z17: 85 | AA17: 94 | AB17: 76 | AC17: 121 | AD17: 102 | AH17: 55 | AJ17: 68 | AU17: 68 | AZ17: 118 | BA17: 60 | BB17: 55 | BC17: 71 | BD17: 72 | BE17: 98 | BG17: 79 | BH17: 95 | BJ17: 265 | BK17: 57 | BL17: 69 | BM17: 98 | BN17: 110 | BO17: 80 | BP17: 140 | BQ17: 83 | BR17: 93 | BS17: 191 | BT17: 226 | BV17: 59 | BY17: 82 | CA17: 83 | CB17: 100 | CE17: 64 | CF17: 63 | CG17: 61 | CH17: 83 | CI17: 99 | CJ17: 84 | CK17: 116 | CL17: 230 | CM17: 280 | CN17: 181 | CO17: 57 | CP17: 55 | CQ17: 62 | CV17: 136 | CX17: 112 | CY17: 60 | CZ17: 66 | DB17: 84 | DC17: 71 | DD17: 100 | DE17: 79 | DF17: 104 | DH17: 164 | DP17: 106 | DR17: 132 | DS17: 62 | DT17: 55 | DU17: 92 | DV17: 86 | DW17: 91 | DX17: 76 | DY17: 195 | DZ17: 161 | EA17: 166 | EB17: 265 | EE17: 62 | EF17: 64 | EM17: 57 | EN17: 54 | EO17: 86 | EQ17: 87 | ER17: 143 | ES17: 134 | ET17: 96 | EV17: 118 | EW17: 58 | FA17: 92 | FB17: 77 | FC17: 85 | FD17: 141 | FG17: =SUM(C17:FF17) -> 10164
A18: Req End | B18: =COUNTA(C18:FF18)/1.6 -> 61.875 | C18: 53 | E18: 63 | M18: 59 | N18: 67 | O18: 82 | P18: 106 | Q18: 85 | R18: 82 | S18: 213 | T18: 185 | U18: 135 | V18: 128 | W18: 54 | X18: 56 | AC18: 122 | AD18: 109 | AE18: 152 | AG18: 53 | AH18: 61 | AK18: 87 | AL18: 132 | AM18: 83 | AN18: 171 | AO18: 178 | AP18: 109 | AQ18: 60 | AR18: 56 | AS18: 69 | AT18: 105 | AU18: 91 | AV18: 132 | AW18: 82 | AX18: 230 | AY18: 219 | AZ18: 245 | BA18: 53 | BC18: 73 | BF18: 79 | BH18: 152 | BJ18: 128 | BK18: 60 | BL18: 69 | BM18: 62 | BO18: 96 | BQ18: 122 | BR18: 97 | BS18: 96 | BT18: 233 | BX18: 64 | CB18: 109 | CG18: 75 | CI18: 82 | CK18: 83 | CN18: 116 | CO18: 60 | CP18: 56 | CQ18: 93 | CR18: 81 | CS18: 139 | CT18: 144 | CU18: 158 | CV18: 93 | CW18: 189 | CX18: 168 | DC18: 72 | DG18: 109 | DI18: 62 | DJ18: 59 | DK18: 79 | DL18: 61 | DM18: 82 | DN18: 119 | DO18: 89 | DQ18: 96 | DS18: 54 | DT18: 67 | DU18: 73 | DX18: 132 | DY18: 89 | DZ18: 161 | EA18: 163 | EB18: 109 | EC18: 63 | ED18: 73 | EE18: 87 | EF18: 97 | EG18: 82 | EH18: 79 | EI18: 110 | EJ18: 230 | EK18: 203 | EL18: 115 | EP18: 65 | EQ18: 87 | ER18: 82 | ES18: 77 | EU18: 163 | EY18: 64 | EZ18: 65 | FG18: =SUM(C18:FF18) -> 10362
A19: Req Luc | B19: =COUNTA(C19:FF19)/1.6 -> 61.875 | D19: 59 | E19: 62 | F19: 87 | H19: 95 | I19: 82 | J19: 198 | K19: 96 | L19: 245 | O19: 61 | V19: 122 | W19: 58 | X19: 71 | Y19: 89 | Z19: 84 | AA19: 94 | AB19: 149 | AC19: 121 | AD19: 104 | AE19: 152 | AF19: 245 | AG19: 56 | AJ19: 67 | AL19: 77 | AM19: 115 | AP19: 109 | AR19: 62 | AS19: 60 | AU19: 70 | AW19: 109 | AY19: 92 | BA19: 56 | BB19: 66 | BC19: 71 | BD19: 94 | BE19: 99 | BF19: 159 | BG19: 139 | BH19: 99 | BI19: 275 | BJ19: 122 | BP19: 80 | BS19: 95 | BU19: 60 | BV19: 54 | BW19: 61 | BX19: 64 | BY19: 82 | BZ19: 139 | CC19: 142 | CD19: 242 | CE19: 57 | CF19: 63 | CG19: 62 | CH19: 85 | CI19: 66 | CJ19: 118 | CK19: 150 | CL19: 94 | CP19: 55 | CU19: 86 | DC19: 72 | DE19: 104 | DF19: 160 | DG19: 106 | DI19: 58 | DJ19: 69 | DK19: 80 | DL19: 96 | DM19: 66 | DN19: 118 | DO19: 86 | DP19: 148 | DQ19: 235 | DR19: 294 | DW19: 70 | EA19: 106 | ED19: 56 | EG19: 66 | EH19: 104 | EJ19: 94 | EK19: 152 | EM19: 64 | EN19: 65 | EO19: 86 | EP19: 111 | EQ19: 68 | ER19: 80 | ES19: 104 | ET19: 211 | EU19: 163 | EV19: 227 | EX19: 55 | EY19: 63 | EZ19: 65 | FA19: 110 | FB19: 123 | FC19: 147 | FE19: 135 | FF19: 158 | FG19: =SUM(C19:FF19) -> 10501
A20: Req Wil | B20: =COUNTA(C20:FF20)/1.6 -> 62.5 | C20: 54 | G20: 70 | H20: 95 | I20: 115 | K20: 96 | M20: 60 | N20: 59 | O20: 60 | Q20: 103 | R20: 81 | T20: 183 | U20: 135 | V20: 122 | AD20: 105 | AF20: 115 | AG20: 60 | AH20: 55 | AI20: 101 | AJ20: 83 | AK20: 120 | AL20: 104 | AM20: 83 | AN20: 170 | AO20: 178 | AP20: 286 | AQ20: 61 | AR20: 56 | AS20: 80 | AV20: 132 | AW20: 109 | AX20: 138 | AY20: 92 | AZ20: 115 | BB20: 55 | BG20: 79 | BK20: 54 | BM20: 62 | BO20: 65 | BQ20: 122 | BR20: 138 | BU20: 60 | BV20: 63 | BW20: 93 | BX20: 91 | BY20: 66 | BZ20: 80 | CA20: 181 | CB20: 161 | CC20: 234 | CD20: 180 | CJ20: 85 | CN20: 116 | CO20: 53 | CP20: 55 | CQ20: 61 | CR20: 96 | CT20: 95 | CV20: 131 | CW20: 189 | CX20: 227 | CY20: 60 | CZ20: 60 | DA20: 97 | DB20: 84 | DC20: 73 | DD20: 149 | DE20: 131 | DF20: 105 | DG20: 163 | DH20: 267 | DL20: 62 | DM20: 82 | DO20: 122 | DP20: 99 | DQ20: 96 | DS20: 58 | DV20: 75 | DW20: 70 | DX20: 77 | EB20: 104 | EC20: 56 | EF20: 65 | EG20: 99 | EH20: 104 | EI20: 139 | EJ20: 94 | EK20: 102 | EL20: 250 | EN20: 54 | EV20: 109 | EW20: 58 | EX20: 71 | EY20: 89 | EZ20: 96 | FA20: 109 | FB20: 99 | FC20: 82 | FD20: 183 | FE20: 218 | FF20: 263 | FG20: =SUM(C20:FF20) -> 10742
A21: Dex Growth | B21: =COUNTA(C21:FF21)/1.6 -> 100 | C21: 19 | D21: 25 | E21: 23 | F21: 33 | G21: 27 | H21: 50 | I21: 54 | J21: 62 | K21: 58 | L21: 56 | M21: 23 | N21: 21 | O21: 36 | P21: 28 | Q21: 26 | R21: 50 | S21: 34 | T21: 54 | U21: 66 | V21: 65 | W21: 16 | X21: 20 | Y21: 36 | Z21: 38 | AA21: 42 | AB21: 44 | AC21: 34 | AD21: 47 | AE21: 58 | AF21: 65 | AG21: 23 | AH21: 25 | AI21: 36 | AJ21: 38 | AK21: 26 | AL21: 32 | AM21: 54 | AN21: 47 | AO21: 58 | AP21: 56 | AQ21: 13 | AR21: 18 | AS21: 32 | AT21: 28 | AU21: 37 | AV21: 25 | AW21: 48 | AX21: 39 | AY21: 41 | AZ21: 56 | BA21: 20 | BB21: 24 | BC21: 18 | BD21: 33 | BE21: 32 | BF21: 32 | BG21: 34 | BH21: 31 | BI21: 58 | BJ21: 47 | BK21: 10 | BL21: 11 | BM21: 18 | BN21: 24 | BO21: 11 | BP21: 32 | BQ21: 27 | BR21: 16 | BS21: 16 | BT21: 28 | BU21: 20 | BV21: 14 | BW21: 22 | BX21: 14 | BY21: 27 | BZ21: 18 | CA21: 20 | CB21: 31 | CC21: 50 | CD21: 46 | CE21: 16 | CF21: 25 | CG21: 27 | CH21: 33 | CI21: 32 | CJ21: 44 | CK21: 34 | CL21: 31 | CM21: 33 | CN21: 47 | CO21: 10 | CP21: 18 | CQ21: 13 | CR21: 19 | CS21: 26 | CT21: 38 | CU21: 21 | CV21: 31 | CW21: 50 | CX21: 47 | CY21: 16 | CZ21: 11 | DA21: 9 | DB21: 9 | DC21: 21 | DD21: 25 | DE21: 21 | DF21: 39 | DG21: 25 | DH21: 19 | DI21: 16 | DJ21: 14 | DK21: 9 | DL21: 10 | DM21: 10 | DN21: 19 | DO21: 21 | DP21: 23 | DQ21: 42 | DR21: 37 | DS21: 13 | DT21: 17 | DU21: 14 | DV21: 29 | DW21: 16 | DX21: 32 | DY21: 27 | DZ21: 24 | EA21: 50 | EB21: 46 | EC21: 7 | ED21: 18 | EE21: 9 | EF21: 19 | EG21: 16 | EH21: 25 | EI21: 21 | EJ21: 31 | EK21: 42 | EL21: 19 | EM21: 20 | EN21: 21 | EO21: 18 | EP21: 24 | EQ21: 16 | ER21: 25 | ES21: 34 | ET21: 24 | EU21: 25 | EV21: 37 | EW21: 23 | EX21: 14 | EY21: 23 | EZ21: 24 | FA21: 37 | FB21: 38 | FC21: 27 | FD21: 54 | FE21: 50 | FF21: 47
A22: Int Growth | B22: =COUNTA(C22:FF22)/1.6 -> 100 | C22: 6 | D22: 10 | E22: 13 | F22: 14 | G22: 21 | H22: 12 | I22: 13 | J22: 31 | K22: 41 | L22: 46 | M22: 19 | N22: 17 | O22: 13 | P22: 14 | Q22: 21 | R22: 31 | S22: 40 | T22: 31 | U22: 33 | V22: 27 | W22: 16 | X22: 14 | Y22: 27 | Z22: 28 | AA22: 26 | AB22: 43 | AC22: 33 | AD22: 31 | AE22: 57 | AF22: 64 | AG22: 6 | AH22: 7 | AI22: 13 | AJ22: 19 | AK22: 21 | AL22: 31 | AM22: 20 | AN22: 31 | AO22: 16 | AP22: 46 | AQ22: 10 | AR22: 17 | AS22: 9 | AT22: 14 | AU22: 21 | AV22: 31 | AW22: 13 | AX22: 31 | AY22: 16 | AZ22: 27 | BA22: 6 | BB22: 10 | BC22: 13 | BD22: 9 | BE22: 26 | BF22: 31 | BG22: 13 | BH22: 23 | BI22: 33 | BJ22: 37 | BK22: 13 | BL22: 14 | BM22: 22 | BN22: 28 | BO22: 30 | BP22: 31 | BQ22: 27 | BR22: 54 | BS22: 49 | BT22: 64 | BU22: 19 | BV22: 24 | BW22: 31 | BX22: 23 | BY22: 26 | BZ22: 31 | CA22: 47 | CB22: 31 | CC22: 49 | CD22: 37 | CE22: 9 | CF22: 14 | CG22: 27 | CH22: 14 | CI22: 15 | CJ22: 25 | CK22: 40 | CL22: 38 | CM22: 41 | CN22: 46 | CO22: 19 | CP22: 24 | CQ22: 22 | CR22: 19 | CS22: 21 | CT22: 31 | CU22: 33 | CV22: 54 | CW22: 49 | CX22: 64 | CY22: 9 | CZ22: 17 | DA22: 22 | DB22: 23 | DC22: 21 | DD22: 18 | DE22: 20 | DF22: 31 | DG22: 49 | DH22: 55 | DI22: 13 | DJ22: 10 | DK22: 18 | DL22: 23 | DM22: 26 | DN22: 18 | DO22: 33 | DP22: 46 | DQ22: 24 | DR22: 55 | DS22: 22 | DT22: 17 | DU22: 27 | DV22: 33 | DW22: 36 | DX22: 31 | DY22: 54 | DZ22: 62 | EA22: 49 | EB22: 74 | EC22: 22 | ED22: 24 | EE22: 31 | EF22: 28 | EG22: 26 | EH22: 50 | EI22: 54 | EJ22: 38 | EK22: 49 | EL22: 74 | EM22: 22 | EN22: 24 | EO22: 36 | EP22: 23 | EQ22: 31 | ER22: 31 | ES22: 40 | ET22: 62 | EU22: 57 | EV22: 74 | EW22: 22 | EX22: 24 | EY22: 22 | EZ22: 23 | FA22: 36 | FB22: 37 | FC22: 54 | FD22: 46 | FE22: 66 | FF22: 74
A23: Str Growth | B23: =COUNTA(C23:FF23)/1.6 -> 100 | C23: 17 | D23: 11 | E23: 27 | F23: 29 | G23: 21 | H23: 25 | I23: 34 | J23: 24 | K23: 25 | L23: 47 | M23: 17 | N23: 25 | O23: 27 | P23: 34 | Q23: 37 | R23: 25 | S23: 34 | T23: 32 | U23: 50 | V23: 47 | W23: 20 | X23: 18 | Y23: 18 | Z23: 15 | AA23: 27 | AB23: 25 | AC23: 41 | AD23: 39 | AE23: 25 | AF23: 28 | AG23: 13 | AH23: 14 | AI23: 23 | AJ23: 19 | AK23: 32 | AL23: 32 | AM23: 21 | AN23: 24 | AO23: 50 | AP23: 28 | AQ23: 26 | AR23: 25 | AS23: 32 | AT23: 39 | AU23: 32 | AV23: 44 | AW23: 41 | AX23: 39 | AY23: 67 | AZ23: 47 | BA23: 26 | BB23: 18 | BC23: 32 | BD23: 34 | BE23: 32 | BF23: 44 | BG23: 54 | BH23: 62 | BI23: 50 | BJ23: 47 | BK23: 23 | BL23: 28 | BM23: 23 | BN23: 29 | BO23: 42 | BP23: 44 | BQ23: 54 | BR23: 55 | BS23: 50 | BT23: 47 | BU23: 17 | BV23: 25 | BW23: 28 | BX23: 34 | BY23: 42 | BZ23: 44 | CA23: 41 | CB23: 62 | CC23: 42 | CD23: 74 | CE23: 17 | CF23: 7 | CG23: 9 | CH23: 15 | CI23: 27 | CJ23: 25 | CK23: 27 | CL23: 24 | CM23: 25 | CN23: 19 | CO23: 10 | CP23: 7 | CQ23: 19 | CR23: 19 | CS23: 27 | CT23: 13 | CU23: 34 | CV23: 16 | CW23: 25 | CX23: 28 | CY23: 17 | CZ23: 14 | DA23: 32 | DB23: 34 | DC23: 37 | DD23: 32 | DE23: 41 | DF23: 47 | DG23: 33 | DH23: 47 | DI23: 20 | DJ23: 25 | DK23: 32 | DL23: 34 | DM23: 27 | DN23: 38 | DO23: 27 | DP23: 32 | DQ23: 42 | DR23: 47 | DS23: 13 | DT23: 25 | DU23: 27 | DV23: 24 | DW23: 27 | DX23: 44 | DY23: 27 | DZ23: 47 | EA23: 33 | EB23: 47 | EC23: 20 | ED23: 14 | EE23: 27 | EF23: 29 | EG23: 27 | EH23: 19 | EI23: 21 | EJ23: 31 | EK23: 42 | EL23: 37 | EM23: 10 | EN23: 7 | EO23: 18 | EP23: 24 | EQ23: 21 | ER23: 25 | ES23: 14 | ET23: 24 | EU23: 42 | EV23: 19 | EW23: 10 | EX23: 11 | EY23: 18 | EZ23: 24 | FA23: 11 | FB23: 32 | FC23: 21 | FD23: 32 | FE23: 17 | FF23: 19
A24: Wis Growth | B24: =COUNTA(C24:FF24)/1.6 -> 100 | C24: 23 | D24: 25 | E24: 27 | F24: 19 | G24: 36 | H24: 37 | I24: 33 | J24: 38 | K24: 41 | L24: 37 | M24: 6 | N24: 7 | O24: 13 | P24: 19 | Q24: 21 | R24: 19 | S24: 27 | T24: 38 | U24: 16 | V24: 46 | W24: 13 | X24: 18 | Y24: 9 | Z24: 14 | AA24: 10 | AB24: 12 | AC24: 27 | AD24: 38 | AE24: 24 | AF24: 27 | AG24: 23 | AH24: 24 | AI24: 18 | AJ24: 19 | AK24: 26 | AL24: 31 | AM24: 40 | AN24: 54 | AO24: 41 | AP24: 55 | AQ24: 16 | AR24: 11 | AS24: 18 | AT24: 14 | AU24: 15 | AV24: 25 | AW24: 33 | AX24: 46 | AY24: 41 | AZ24: 55 | BA24: 14 | BB24: 18 | BC24: 27 | BD24: 19 | BE24: 15 | BF24: 19 | BG24: 33 | BH24: 38 | BI24: 24 | BJ24: 55 | BK24: 19 | BL24: 17 | BM24: 27 | BN24: 14 | BO24: 21 | BP24: 18 | BQ24: 27 | BR24: 31 | BS24: 49 | BT24: 46 | BU24: 10 | BV24: 7 | BW24: 9 | BX24: 24 | BY24: 10 | BZ24: 31 | CA24: 27 | CB24: 31 | CC24: 24 | CD24: 27 | CE24: 23 | CF24: 25 | CG24: 27 | CH24: 33 | CI24: 31 | CJ24: 31 | CK24: 33 | CL24: 62 | CM24: 66 | CN24: 74 | CO24: 26 | CP24: 22 | CQ24: 36 | CR24: 38 | CS24: 31 | CT24: 43 | CU24: 47 | CV24: 54 | CW24: 41 | CX24: 46 | CY24: 23 | CZ24: 28 | DA24: 27 | DB24: 29 | DC24: 27 | DD24: 50 | DE24: 54 | DF24: 38 | DG24: 57 | DH24: 64 | DI24: 17 | DJ24: 21 | DK24: 31 | DL24: 28 | DM24: 42 | DN24: 50 | DO24: 54 | DP24: 54 | DQ24: 57 | DR24: 46 | DS24: 17 | DT24: 11 | DU24: 23 | DV24: 9 | DW24: 26 | DX24: 18 | DY24: 27 | DZ24: 23 | EA24: 33 | EB24: 18 | EC24: 16 | ED24: 14 | EE24: 22 | EF24: 20 | EG24: 36 | EH24: 32 | EI24: 40 | EJ24: 54 | EK24: 33 | EL24: 55 | EM24: 13 | EN24: 18 | EO24: 18 | EP24: 23 | EQ24: 36 | ER24: 44 | ES24: 47 | ET24: 46 | EU24: 41 | EV24: 55 | EW24: 9 | EX24: 21 | EY24: 27 | EZ24: 23 | FA24: 21 | FB24: 18 | FC24: 33 | FD24: 23 | FE24: 33 | FF24: 46
