Workbook
Name _Hlk99922360: SubclassAspects!$BE$57

Sheet Sheet1
C1: Name: | D1: Scout
C2: Tier: | D2: 1
C3: Base: | D3: Archer
C4: Code: | D4: 2
C5: Requirements:
C6: =IF(SubclassAspects!C13>0,"Dexterity ", "") -> Dexterity | D6: =IF(SubclassAspects!C13>0,SubclassAspects!C13) -> 58 | E6: =IF(SubclassAspects!C17>0,"Charisma ", "") -> Charisma | F6: =IF(SubclassAspects!C17>0,SubclassAspects!C17, "") -> 58
C7: =IF(SubclassAspects!C14>0,"Dexterity ","") | D7: =IF(SubclassAspects!C14>0,SubclassAspects!C14, "") | E7: =IF(SubclassAspects!C18>0,"Endurance ", "") -> Endurance | F7: =IF(SubclassAspects!C18>0,SubclassAspects!C18, "") -> 53
C8: =IF(SubclassAspects!C15>0,"Strength ","") -> Strength | D8: =IF(SubclassAspects!C15>0,SubclassAspects!C15, "") -> 54 | E8: =IF(SubclassAspects!C19>0,"Luck ", "") | F8: =IF(SubclassAspects!C19>0,SubclassAspects!C19, "")
C9: =IF(SubclassAspects!C16>0,"Wisdom ","") -> Wisdom | D9: =IF(SubclassAspects!C16>0,SubclassAspects!C16, "") -> 61 | E9: =IF(SubclassAspects!C20>0,"Will ", "") -> Will | F9: =IF(SubclassAspects!C20>0,SubclassAspects!C20, "") -> 54
A11: Overview
A13: Quote: | B13: “With proper preparations, the fighting is merely a formality.”
A14: The Scout is an archer-based class that can act early and effectively. He uses preliminary actions to take control of the battlefield, attacks enemies at full health, and quickens himself readily. He is hard to destroy before his turn.
A15: World Notes: Scouts are an essential part of enemy army, as only with knowledge of the enemy can success be found. The scouts prepare the battlefield to best support their army’s success.
A16: Appearance: The scout is lightly armored because he is constantly on the move.
A17: Defining Mechanic: The Scout can implement scouted abilities. These abilities, which come in all three strengths, can only be used as the first action of battle, after which they turn into a related, but lesser, ability.
A19: Equipment
A20: Default Weapon: | C20: Short Bow
A21: Default Armor:
A41: Major Abilities
A42: Adroit Momentum – Ranged attack with pinpoint and momentum enhancing accuracy (Scout)
A43: Aimed Momentum – Ranged attack that generates extra aim based on momentum (Scout)
A44: Coordinated Shot – Ranged attack with quick preparation that grants increased accuracy and damage to next attack versus target (Scout)
A45: Delaying Jolt – Ranged attack with delay against stunned target (Scout)
A46: Flanking Shot – Ranged attack that causes flanked (Scout)
A47: Lay of the Land – Ranged attack that enhances dodge of team based on aim (Scout)
A48: Quickening Aim – Ranged attack against single target that consumes aim to quicken self (Scout)
A49: Rapid Vow – Prepared ranged attack that determines target on preparation. Quickens scout on preparation and on use (Scout)
A50: Scouted Arrow Burst – Ranged attack against all enemies. Deals less damage and requires aim if not first turn (Scout)
A51: Scouted Chink – Full penetration ranged attack if first attack of battle. Can proc full penetration with ranged attack after (Scout)
... A71: Share Momentum – Quicken all allies based on momentum (Scout)

Sheet SubclassAspects
D1: Hunter | P1: Wrestler | AO1: Siege Engineer | AV1: Rager | CD1: Sword Magus | EQ1: Winter Witch | ES1: Witch Doctor
A2: Name | B2: =COUNTA(C2:FF2)/1.6 -> 100 | C2: Scout | D2: Huntsman | E2: Crossbowman | F2: Marksman | G2: Falconer | H2: Bounty Hunter | I2: Stalker | J2: Poacher | K2: Sharpshooter | L2: Toxophilite | M2: Initiate | N2: Pugilist | O2: Skirmisher | P2: Vajra | Q2: Stonefist | R2: Infiltrator | S2: Viper Fang | T2: Ascetic | U2: Thunderfist | V2: Drunken Master | W2: Bandit | X2: Cutthroat | Y2: Burglar | Z2: Thief | AA2: Acrobat | AB2: Assassin | AC2: Brigand | AD2: Smuggler | AE2: Skulk | AF2: Ninja | AG2: Scavenger | AH2: Alchemist | AI2: Artificer | AJ2: Tinker | AK2: Engineer | AL2: Bomber | AM2: Gunslinger | AN2: Savant | AO2: Machinist | AP2: Reliquarian | AQ2: Brute | AR2: Raider | AS2: Berserker | AT2: Marauder | AU2: Viking | AV2: Vandal | AW2: Fury | AX2: Cannibal | AY2: Destroyer | AZ2: Beastlord | BA2: Gladiator | BB2: Duelist | BC2: Phalanx | BD2: Dervish | BE2: Fencer | BF2: Lancer | BG2: Samurai | BH2: Dreadnaught | BI2: Swashbuckler | BJ2: Warlord | BK2: Bodyguard | BL2: Champion | BM2: Hospitaler | BN2: Cavalier | BO2: Sentinel | BP2: Dragoon | BQ2: Paragon | BR2: Black Knight | BS2: Crusader | BT2: Templar | BU2: Blitzknecht | BV2: Feuerknecht | BW2: Drecknecht | BX2: Trinknecht | BY2: Mercenary | BZ2: Transmuter | CA2: Force Weaver | CB2: Myrmidon | CC2: Nightblade | CD2: Sword Saint | CE2: Minstrel | CF2: Jester | CG2: Dirge Singer | CH2: Balladeer | CI2: Drummer | CJ2: Spy | CK2: Mountebank | CL2: Diva | CM2: Muse | CN2: Lantern Bearer | CO2: Conjurer | CP2: Occultist | CQ2: Shaman | CR2: Medium | CS2: Animist | CT2: Spiritualist | CU2: Astrologer | CV2: Vizier | CW2: Alienist | CX2: Pact Master | CY2: Acolyte | CZ2: Healer | DA2: Disciple | DB2: Priest | DC2: Combat Medic | DD2: Exorcist | DE2: Preacher | DF2: Zealot | DG2: Plague Doctor | DH2: Oracle | DI2: Buccaneer | DJ2: Executioner | DK2: Gravedigger | DL2: Hangman | DM2: Harbinger | DN2: Sin Eater | DO2: Sandman | DP2: Whisperer | DQ2: Mercy Bringer | DR2: Gaslighter | DS2: Telepath | DT2: Kinetic | DU2: Amnesiac | DV2: Hypnotist | DW2: Diviner | DX2: Haunted | DY2: Mastermind | DZ2: Mindbleeder | EA2: Chronomancer | EB2: Puppet Master | EC2: Abjurer | ED2: Symbolist | EE2: Cabalist | EF2: Hermit | EG2: Disenchanter | EH2: Scrivener | EI2: Sage | EJ2: Glyphic | EK2: Cryptic | EL2: Sorcerer | EM2: Cultist | EN2: Warlock | EO2: Effigist | EP2: Dustbringer | EQ2: Crone | ER2: Hedgemage | ES2: Mambo | ET2: Bokor | EU2: Hag | EV2: Malefax | EW2: Elementalist | EX2: Necromancer | EY2: Hydromancer | EZ2: Geomancer | FA2: Aeromancer | FB2: Pyromancer | FC2: Arcanist | FD2: Solomancer | FE2: Incanter | FF2: Thaumaturge
A3: Code | B3: =COUNTA(C3:FF3)/1.6 -> 100 | C3: 2 | D3: 3 | E3: 4 | F3: 5 | G3: 6 | H3: 7 | I3: 8 | J3: 9 | K3: 10 | L3: 11 | M3: 13 | N3: 14 | O3: 15 | P3: 16 | Q3: 17 | R3: 18 | S3: 19 | T3: 20 | U3: 21 | V3: 22 | W3: 24 | X3: 25 | Y3: 26 | Z3: 27 | AA3: 28 | AB3: 29 | AC3: 30 | AD3: 31 | AE3: 32 | AF3: 33 | AG3: 35 | AH3: 36 | AI3: 37 | AJ3: 38 | AK3: 39 | AL3: 40 | AM3: 41 | AN3: 42 | AO3: 43 | AP3: 44 | AQ3: 46 | AR3: 47 | AS3: 48 | AT3: 49 | AU3: 50 | AV3: 51 | AW3: 52 | AX3: 53 | AY3: 54 | AZ3: 55 | BA3: 57 | BB3: 58 | BC3: 59 | BD3: 60 | BE3: 61 | BF3: 62 | BG3: 63 | BH3: 64 | BI3: 65 | BJ3: 66 | BK3: 68 | BL3: 69 | BM3: 70 | BN3: 71 | BO3: 72 | BP3: 73 | BQ3: 74 | BR3: 75 | BS3: 76 | BT3: 77 | BU3: 79 | BV3: 80 | BW3: 81 | BX3: 82 | BY3: 83 | BZ3: 84 | CA3: 85 | CB3: 86 | CC3: 87 | CD3: 88 | CE3: 90 | CF3: 91 | CG3: 92 | CH3: 93 | CI3: 94 | CJ3: 95 | CK3: 96 | CL3: 97 | CM3: 98 | CN3: 99 | CO3: 101 | CP3: 102 | CQ3: 103 | CR3: 104 | CS3: 105 | CT3: 106 | CU3: 107 | CV3: 108 | CW3: 109 | CX3: 110 | CY3: 112 | CZ3: 113 | DA3: 114 | DB3: 115 | DC3: 116 | DD3: 117 | DE3: 118 | DF3: 119 | DG3: 120 | DH3: 121 | DI3: 123 | DJ3: 124 | DK3: 125 | DL3: 126 | DM3: 127 | DN3: 128 | DO3: 129 | DP3: 130 | DQ3: 131 | DR3: 132 | DS3: 134 | DT3: 135 | DU3: 136 | DV3: 137 | DW3: 138 | DX3: 139 | DY3: 140 | DZ3: 141 | EA3: 142 | EB3: 143 | EC3: 145 | ED3: 146 | EE3: 147 | EF3: 148 | EG3: 149 | EH3: 150 | EI3: 151 | EJ3: 152 | EK3: 153 | EL3: 154 | EM3: 156 | EN3: 157 | EO3: 158 | EP3: 159 | EQ3: 160 | ER3: 161 | ES3: 162 | ET3: 163 | EU3: 164 | EV3: 165 | EW3: 167 | EX3: 168 | EY3: 169 | EZ3: 170 | FA3: 171 | FB3: 172 | FC3: 173 | FD3: 174 | FE3: 175 | FF3: 176
A4: Tier | B4: =COUNTA(C4:FF4)/1.6 -> 100 | C4: 1 | D4: 2 | E4: 6 | F4: 7 | G4: 9 | H4: 13 | I4: 15 | J4: 19 | K4: 21 | L4: 25 | M4: 1 | N4: 2 | O4: 6 | P4: 7 | Q4: 9 | R4: 13 | S4: 15 | T4: 19 | U4: 21 | V4: 25 | W4: 1 | X4: 2 | Y4: 6 | Z4: 7 | AA4: 9 | AB4: 13 | AC4: 15 | AD4: 19 | AE4: 21 | AF4: 25 | AG4: 1 | AH4: 2 | AI4: 6 | AJ4: 7 | AK4: 9 | AL4: 13 | AM4: 15 | AN4: 19 | AO4: 21 | AP4: 25 | AQ4: 1 | AR4: 2 | AS4: 6 | AT4: 7 | AU4: 9 | AV4: 13 | AW4: 15 | AX4: 19 | AY4: 21 | AZ4: 25 | BA4: 1 | BB4: 2 | BC4: 6 | BD4: 7 | BE4: 9 | BF4: 13 | BG4: 15 | BH4: 19 | BI4: 21 | BJ4: 25 | BK4: 1 | BL4: 2 | BM4: 6 | BN4: 7 | BO4: 9 | BP4: 13 | BQ4: 15 | BR4: 19 | BS4: 21 | BT4: 25 | BU4: 1 | BV4: 2 | BW4: 6 | BX4: 7 | BY4: 9 | BZ4: 13 | CA4: 15 | CB4: 19 | CC4: 21 | CD4: 25 | CE4: 1 | CF4: 2 | CG4: 6 | CH4: 7 | CI4: 9 | CJ4: 13 | CK4: 15 | CL4: 19 | CM4: 21 | CN4: 25 | CO4: 1 | CP4: 2 | CQ4: 6 | CR4: 7 | CS4: 9 | CT4: 13 | CU4: 15 | CV4: 19 | CW4: 21 | CX4: 25 | CY4: 1 | CZ4: 2 | DA4: 6 | DB4: 7 | DC4: 9 | DD4: 13 | DE4: 15 | DF4: 19 | DG4: 21 | DH4: 25 | DI4: 1 | DJ4: 2 | DK4: 6 | DL4: 7 | DM4: 9 | DN4: 13 | DO4: 15 | DP4: 19 | DQ4: 21 | DR4: 25 | DS4: 1 | DT4: 2 | DU4: 6 | DV4: 7 | DW4: 9 | DX4: 13 | DY4: 15 | DZ4: 19 | EA4: 21 | EB4: 25 | EC4: 1 | ED4: 2 | EE4: 6 | EF4: 7 | EG4: 9 | EH4: 13 | EI4: 15 | EJ4: 19 | EK4: 21 | EL4: 25 | EM4: 1 | EN4: 2 | EO4: 6 | EP4: 7 | EQ4: 9 | ER4: 13 | ES4: 15 | ET4: 19 | EU4: 21 | EV4: 25 | EW4: 1 | EX4: 2 | EY4: 6 | EZ4: 7 | FA4: 9 | FB4: 13 | FC4: 15 | FD4: 19 | FE4: 21 | FF4: 25
A5: Base Class | B5: =COUNTA(C5:FF5)/1.6 -> 100 | C5: Archer | D5: Archer | E5: Archer | F5: Archer | G5: Archer | H5: Archer | I5: Archer | J5: Archer | K5: Archer | L5: Archer | M5: Monk | N5: Monk | O5: Monk | P5: Monk | Q5: Monk | R5: Monk | S5: Monk | T5: Monk | U5: Monk | V5: Monk | W5: Rogue | X5: Rogue | Y5: Rogue | Z5: Rogue | AA5: Rogue | AB5: Rogue | AC5: Rogue | AD5: Rogue | AE5: Rogue | AF5: Rogue | AG5: Teknixian | AH5: Teknixian | AI5: Teknixian | AJ5: Teknixian | AK5: Teknixian | AL5: Teknixian | AM5: Teknixian | AN5: Teknixian | AO5: Teknixian | AP5: Teknixian | AQ5: Barbarian | AR5: Barbarian | AS5: Barbarian | AT5: Barbarian | AU5: Barbarian | AV5: Barbarian | AW5: Barbarian | AX5: Barbarian | AY5: Barbarian | AZ5: Barbarian | BA5: Fighter | BB5: Fighter | BC5: Fighter | BD5: Fighter | BE5: Fighter | BF5: Fighter | BG5: Fighter | BH5: Fighter | BI5: Fighter | BJ5: Fighter | BK5: Knight | BL5: Knight | BM5: Knight | BN5: Knight | BO5: Knight | BP5: Knight | BQ5: Knight | BR5: Knight | BS5: Knight | BT5: Knight | BU5: Spellsword | BV5: Spellsword | BW5: Spellsword | BX5: Spellsword | BY5: Spellsword | BZ5: Spellsword | CA5: Spellsword | CB5: Spellsword | CC5: Spellsword | CD5: Spellsword | CE5: Bard | CF5: Bard | CG5: Bard | CH5: Bard | CI5: Bard | CJ5: Bard | CK5: Bard | CL5: Bard | CM5: Bard | CN5: Bard | CO5: Binder | CP5: Binder | CQ5: Binder | CR5: Binder | CS5: Binder | CT5: Binder | CU5: Binder | CV5: Binder | CW5: Binder | CX5: Binder | CY5: Cleric | CZ5: Cleric | DA5: Cleric | DB5: Cleric | DC5: Cleric | DD5: Cleric | DE5: Cleric | DF5: Cleric | DG5: Cleric | DH5: Cleric | DI5: Reaper | DJ5: Reaper | DK5: Reaper | DL5: Reaper | DM5: Reaper | DN5: Reaper | DO5: Reaper | DP5: Reaper | DQ5: Reaper | DR5: Reaper | DS5: Psychic | DT5: Psychic | DU5: Psychic | DV5: Psychic | DW5: Psychic | DX5: Psychic | DY5: Psychic | DZ5: Psychic | EA5: Psychic | EB5: Psychic | EC5: Runemage | ED5: Runemage | EE5: Runemage | EF5: Runemage | EG5: Runemage | EH5: Runemage | EI5: Runemage | EJ5: Runemage | EK5: Runemage | EL5: Runemage | EM5: Witch | EN5: Witch | EO5: Witch | EP5: Witch | EQ5: Witch | ER5: Witch | ES5: Witch | ET5: Witch | EU5: Witch | EV5: Witch | EW5: Wizard | EX5: Wizard | EY5: Wizard | EZ5: Wizard | FA5: Wizard | FB5: Wizard | FC5: Wizard | FD5: Wizard | FE5: Wizard | FF5: Wizard
A6: Gender | B6: =COUNTA(C6:FF6)/1.6 -> 100 | C6: Male | D6: Male | E6: Male | F6: Male | G6: Male | H6: Male | I6: Male | J6: Male | K6: Male | L6: Male | M6: Male | N6: Male | O6: Male | P6: Male | Q6: Male | R6: Male | S6: Male | T6: Male | U6: Male | V6: Male | W6: Male | X6: Male | Y6: Male | Z6: Male | AA6: Male | AB6: Male | AC6: Male | AD6: Male | AE6: Male | AF6: Male | AG6: Female | AH6: Female | AI6: Female | AJ6: Female | AK6: Female | AL6: Female | AM6: Female | AN6: Female | AO6: Female | AP6: Female | AQ6: Female | AR6: Female | AS6: Female | AT6: Female | AU6: Female | AV6: Female | AW6: Female | AX6: Female | AY6: Female | AZ6: Female | BA6: Female | BB6: Female | BC6: Female | BD6: Female | BE6: Female | BF6: Female | BG6: Female | BH6: Female | BI6: Female | BJ6: Female | BK6: Male | BL6: Male | BM6: Male | BN6: Male | BO6: Male | BP6: Male | BQ6: Male | BR6: Male | BS6: Male | BT6: Male | BU6: Female | BV6: Female | BW6: Female | BX6: Female | BY6: Female | BZ6: Female | CA6: Female | CB6: Female | CC6: Female | CD6: Female | CE6: Male | CF6: Male | CG6: Male | CH6: Male | CI6: Male | CJ6: Male | CK6: Male | CL6: Male | CM6: Male | CN6: Male | CO6: Female | CP6: Female | CQ6: Female | CR6: Female | CS6: Female | CT6: Female | CU6: Female | CV6: Female | CW6: Female | CX6: Female | CY6: Male | CZ6: Male | DA6: Male | DB6: Male | DC6: Male | DD6: Male | DE6: Male | DF6: Male | DG6: Male | DH6: Male | DI6: Male | DJ6: Male | DK6: Male | DL6: Male | DM6: Male | DN6: Male | DO6: Male | DP6: Male | DQ6: Male | DR6: Male | DS6: Female | DT6: Female | DU6: Female | DV6: Female | DW6: Female | DX6: Female | DY6: Female | DZ6: Female | EA6: Female | EB6: Female | EC6: Male | ED6: Male | EE6: Male | EF6: Male | EG6: Male | EH6: Male | EI6: Male | EJ6: Male | EK6: Male | EL6: Male | EM6: Female | EN6: Female | EO6: Female | EP6: Female | EQ6: Female | ER6: Female | ES6: Female | ET6: Female | EU6: Female | EV6: Female | EW6: Female | EX6: Female | EY6: Female | EZ6: Female | FA6: Female | FB6: Female | FC6: Female | FD6: Female | FE6: Female | FF6: Female
A7: Associated Demon | B7: =COUNTA(C7:FF7)/1.6 -> 25 | C7: Ipos | D7: Leraje | E7: Dantalion | F7: Allocer | G7: Pazazu | H7: Baphomet | I7: Demogorgon | J7: Set | K7: Glasya | L7: Andras | M7: Glasya | N7: Gusion | O7: Pazazu | P7: Andras | Q7: Scarmiglione | R7: Sabnock | S7: Orobas | T7: Levistus | U7: Paimon | V7: Gaap | W7: Ipos | X7: Geryon | Y7: Mammon | Z7: Sabnock | AA7: Bifrons | AB7: Glasya | AC7: Gusion | AD7: Orobas | AE7: Andras | AF7: x | AG7: Belial | AH7: Haagenti | AI7: x | AJ7: Mammon | AK7: Orobas | AL7: Tiamat | AM7: Leraje | AN7: Orcus | AO7: Rubicante | AP7: Eligos
A8: Quote | B8: =COUNTA(C8:FF8)/1.6 -> 0
A9: Description | B9: =COUNTA(C9:FF9)/1.6 -> 75 | C9: An early-action specialist who seizes the opening of battle with scouted abilities that can only be used as the first action of a wave, then transform into a lesser related ability afterward. He builds aim quickly, attacks enemies at full health for bonus damage, and is difficult to eliminate before he gets to act. | D9: A distance fighter who uses momentum to enhance his arrows and can penetrate armor more effectively the further away his target is. He tracks a specific enemy type, gaining bonuses against others of the same kind as his primary aim target and hitting harder the longer he sustains focus. | E9: A heavy crossbow specialist who attacks more slowly than other archers but deals more damage per shot with greater penetration. He is more defensive than most archer subclasses, reacting to enemy attacks against him rather than purely pressing offense, and can fortify and reload quickly between shots. | F9: An accuracy and penetration specialist who places marks on enemies that grant his allies benefits when they attack the same targets. He is the team's force multiplier at range, making his aim target more dangerous for everyone and sharing his exceptional accuracy with those who follow his lead. | G9: A companion-focused archer whose pet falcon harries targets and enables abilities that either work better in the falcon's presence or require it outright. He uses the falcon to set up aim, distract enemies, and coordinate strikes — making his companion an active offensive asset rather than a passive attendant. | H9: A capture-specialist who places bounty afflictions on enemies as minor actions during combat, with those bounties triggering beneficial effects when the marked enemy dies. He can stun and incapacitate targets to take them alive, gaining increasing payoffs the more bounties he has active when enemies fall. | I9: A shadow-fighter who generates aim from hidden status and converts high accuracy into higher damage, with a defining ability that expends all accumulated aim for a devastating single attack — but then prevents him from targeting that specific enemy for a period scaled to the aim spent. | J9: A kill-opportunist who triggers immediate prepared attacks the moment an enemy becomes endangered, without those poach abilities being interruptible by damage. He gains culling abilities, preferences for specific target types, and benefits from kills — a specialist at finishing weakened prey faster than anyone else can reach them. | K9: A trick-shot specialist whose accuracy-dependent abilities pierce through targets to hit columns behind them and have reduced hit chance but significant effects when they connect. His trick shot success rate scales with current aim relative to maximum aim, rewarding sustained focus on a single target before committing to the high-risk high-reward shots. | L9: A distance-and-duration specialist who builds power over the course of a long battle through eternal buff abilities that grow without limit but become progressively more expensive to enhance. Only one can be active at a time, demanding that the player commit to a single compounding effect and protect the Toxophilite long enough for it to pay off. | M9: A patient striker who builds power by holding his form and releases it explosively on transition. His unleash mechanic rewards stillness — the longer he stays in a single form, the more devastating the eventual change. He has no form preference, making him the most flexible of the monk subclasses and a strong foundation for learning the chakra system. | N9: A relentless single-target brawler who punishes the same enemy turn after turn through his impact mechanic. Any enemy he struck last turn becomes the target of a suite of specialized follow-up attacks covering damage, delay, disruption, and control. Lower chakra focused and strength-enhanced, he hits harder the longer he stays locked onto one target. | O9: A fast, opportunistic fighter who mirrors his enemies' own strengths against them through the matching mechanic. He can temporarily adopt a target's critical stats, damage, accuracy, defense, or dodge — turning powerful enemies into their own worst nightmare. Leopard form focused and haste-driven, he excels at demolishing stunned foes and stacking bleeds through repeated Leopard Claw cycles. | P9: An immovable reactive combatant who weaponizes his chakra configuration to punish every enemy attack. Snake's Response reflects conditions back at attackers based on which chakras are open, with the lower chakras delivering the most devastating punishments — prone, delay, and disarm simultaneously at full configuration. He fights best when pristine, baiting attacks while armed with Reversal, Absorbed Counter, and a full suite of prepared reactions. | Q9: A fortified earth specialist who turns glancing blows from a weakness into a weapon. His attacks deliberately seek glancing hits to trigger stuns, bleeds, delays, and fragility — and his Pressure Crack capstone extends this to critical hits as well. Tiger form focused and endurance-heavy, he is nearly immovable under sustained assault and punishes enemies for every attempt to pierce his defenses. | R9: A burst-damage specialist who cycles through hidden states to deliver devastating arrival attacks. Each time he loses hidden — whether by choice or enemy action — he unleashes a different arrival ability covering area damage, flanking, stunning, or penetrating strikes. Mantis focused and initiative-driven, his Exposed Momentum capstone ensures every exposure accelerates his next turn. | S9: A poison-crafting snake form specialist who generates unique toxins from his own body and bleeds. He creates poisons based on his current form through Venom Chakra, conserves and refreshes them through careful resource management, and delivers them through venomous, insidious, and backbiting strikes. Earth and dark elemental focused, he excels at sustained damage over time and attrition warfare. | T9: A disciplined dragon form purist who draws power from maintaining a state of perfect purity. His most powerful abilities — Fist of Purity, Double Purity, Whirlwind Purity — require being completely unafflicted, while his Condition Fortress capstone makes him progressively harder to afflict as conditions accumulate. He manages corruption, stuns enemies with dragon-powered strikes, and uses focus as both a resource and a defensive tool. | U9: A chain-combat specialist who builds devastating sequences of air, stun, and shatter effects through careful ability ordering. Nearly every move and minor ability has a trigger condition — following a counter, a critical, a shatter, or an air attack — creating dense combo potential that rewards mechanical knowledge. Crane focused and counter-driven, his Thunder Strikes capstone ensures every stunned enemy takes bonus air damage on each hit. | V9: A chaotic form-shifting brawler who embraces randomness and prone states as sources of power rather than liability. He shifts forms rapidly to build Fluid Punch damage, reach Ultimate Punch thresholds, and trigger Chakra Ascension — while deliberately falling prone to counter from the ground and punish enemies with Misplaced Retribution. His unpredictability is his greatest defense, with low accuracy offset by high dodge and a tendency to accidentally hit exactly the wrong person at exactly the right time. | W9: A quick ranged harasser who opens battle at a distance before pivoting to a more dangerous close-quarters fighter when his allies fall. He carries desperation abilities that only activate when he stands alone, rewarding survival over coordinated play. | X9: A dualwield melee brawler who stacks bleed on enemies through relentless two-weapon exchanges and can grant himself intangibility to press the offense without interruption. His advantage generation rewards staying in the fight and bleeding targets dry. | Y9: An ambush specialist who hits hardest against undamaged enemies and strips buffs from those who have fought back. He can artificially recreate full-health windows late in battle by corrupting enemy maximum health, keeping his ambush toolkit relevant throughout. | Z9: A self-sufficient dualwield fighter who steals accuracy, speed, and senses from enemies to empower himself. He can briefly share his incoming healing and mana gain with allies, giving a team-oriented edge to an otherwise personal playstyle. | AA9: A dodge-focused rebuild Rogue who invites attacks, turns misses into advantage, and uses reliable abilities that refund their costs on failure. He thrives in the open and under illumination, unlike most Rogues who prefer the shadows. | AB9: A single-target executioner who signs contracts against chosen enemies, gaining combat bonuses while pursuing them and earning powerful fulfillment rewards when he personally lands the killing blow. Five contract types let the player tailor each hunt to the situation. | AC9: A ranged gambler who wagers advantage and mana on battlefield conditions, collecting larger payoffs when those conditions are met. A good run leaves him flush; a bad one leaves him empty, making risk tolerance the central skill of his playstyle. | AD9: A team-oriented Rogue whose power scales with how many allies are hidden alongside him. He can blanket the party in shadow, share his poisons across the team, and coordinate hidden allies into a unified striking force. | AE9: A defensively self-reliant Rogue who applies aversion to make enemies ignore him, then punishes them for it. He complements aversion with scorn to layer targeting protection, generating advantage steadily from the safety of being overlooked. | AF9: A hidden-mastery specialist who chains haste, advantage, and free bonus attacks by maintaining concealment across multiple actions. He rewards players who have mastered the hidden economy, with insidious attacks and precise sequencing separating competent play from exceptional play. | AG9: A chaotic support-attacker who thrives on unpredictability. Her scavenged abilities reveal their element on preparation rather than use, making her toolkit flexible but harder to plan around. She generates ammo from kills and builds belts from whatever she has on hand — a scrappy, resource-efficient subclass that rewards improvisation. | AH9: A prepared-resource specialist who enters battle with concoctions already brewed and ready to use without cost or preparation. She leans into healing, poison, and resurrection, and her premade system lets her open waves with full-power abilities immediately. Her capstone Premade Reserves deepens this advantage, making her the Teknixian most oriented toward sustained party management. | AI9: A trap-setter and accumulator who builds up power before releasing it. Her accumulation abilities charge on first use and discharge on second, rewarding patience with amplified outputs. She also controls the detonation chain — recovering, redirecting, and shielding through it — and provides elemental shields to allies via Teknos Shielding. | AJ9: A modification-based companion commander who toggles different behavioral modes to reshape her companion and her own attacks. Her four modular abilities — Modular Bomb, Modular Ray, Modular Trap, and Modular Beam — each change behavior based on which modifications are active. Flame Spewer and Lightning Tosser are ammo-sensitive companions that change element and effect based on what's loaded at summoning. | AK9: An ally-empowerment specialist who assigns persistent assistant enchantments to party members. Each assistant type triggers a different proc when the assigned ally attacks — shields, heals, traps, bonus attacks, or quickening — and Activate Assistant can fire all procs simultaneously. She also fields the Shield Guardian, a fixed-behavior healing companion with no ammo interaction, and Minefield Assistant turns any attacker into a trap-seeding machine. | AL9: A high-risk area damage dealer whose bomb abilities hit allies and enemies identically with no discount. She layers countdowns on enemies and manages the self-threat they create using Accept Explosion, Accept Mass Explosion, Gift Bomb, and Transfer Countdown. Explosion Imminent and Kinetic Protection let her mitigate her own friendly fire. The higher the aim output, the harder the landing. | AM9: A pure ranged damage dealer built around called shots and burst ammo expenditure. Called shots are prepared as a minor action, name a target, and add powerful debuff effects — disarm, stun, heartstrike, slow, or delay — to the first attack used against that target on the following turn. Full Clip and Oblivion Shot are her all-in damage options. High Noon and Showdown both guarantee a counter-attack against her, rewarding Take Cover setups. | AN9: A slow-burn debuff-accumulator whose six concoctions apply ongoing effects while building power each clock tick, then discharge a scaled effect when the chain fires or time runs out. More ammo at placement extends the window and increases accumulated power at detonation. A Faraday sub-theme lets her wear lightning rod deliberately and redirect incoming storm damage offensively through Faraday Connection's pain link. | AO9: A companion-amplifier who fields extremely slow, powerful siege engine companions — Ballista, Battering Ram, and Catapult — and spends her own actions making them fire more frequently. Every move and minor ability in her kit serves the companion: Operate Siege Engine quickens it directly, Teamwork Operation converts party delay into companion clock advancement, and Siege Command upgrades whatever the companion would do next. Her own attacks like Amplifying Cannonshot and Earth Cannon give her meaningful damage when she steps away from the engine. | AP9: A relic-stacking power escalator who activates multi-ability relics that grow stronger with each ammo devotion. Each devoted ammo type is locked until the relic ends — which it cannot be cancelled until max devotion — creating deep commitment costs in exchange for battlefield-wide buffs, persistent damage, companion power, or trap generation. Relic Blast and Relic Bolt scale with total ammo devoted across all active relics, making a fully stacked Reliquarian increasingly devastating the longer a wave goes on. | AQ9: The patient tank of the Barbarian family. A slower, higher-endurance variant who defers self-damage costs to the next turn through Consequences, generating Anguish immediately while controlling when the pain lands — or redirecting it to enemies entirely with Share Consequence. | AR9: A shield-and-weapon fighter who builds active defenses only to spend them all at once. Reckless abilities consume all block, dodge, and counter values for amplified attacks, rewarding players who time the exposed window around a supporting tank or use it as a finisher when consequences can't resolve. | AS9: The chaos amplifier of the family, built around Exertion abilities that generate Anguish from repeated misses and spread destruction through Contagious Temper. She leans fully into the Berserk condition, turning random targeting from a liability into an engine, with the Panic pair offering a rare moment of choice between embracing or escaping the disorder. | AT9: A dual-wield closer who grows faster and hits harder the more enemies die. Rampage scales with kills — personal kills more than team kills — making bloodlust and counter abilities the tools that keep her offense rolling between turns and feeding the escalation she depends on. | AU9: A deliberate shield fighter who charges prepared abilities through sustained blocking. Each block adds power to any held ability, and multiple prepared abilities charge independently, rewarding patient setup and precise release timing over the Raider's impulsive spending. | AV9: Pure escalating output. She accumulates damage dealt toward a threshold that briefly unlocks Brink abilities — powerful options that vanish if not taken — and can sustain Endless Wrath longer than any other subclass before the drain finally overtakes her. | AW9: Precise and fast, with a discipline that belies her name. Purity abilities amplify with each use but cancel on specific failure conditions, demanding focused play to maintain multiple stacks simultaneously. She grows faster as she takes damage and reaches peak power when Wrath and Berserk combine. | AX9: A self-sustaining predator who stays hurt to stay fed. Her healing threshold mechanic unlocks powerful abilities as applicable healing accumulates, rewarding healers who time large heals over constant top-offs, while life drain and kill-reaction heals give her independence when the support is occupied elsewhere. | AY9: The armor-stripping heavyweight, built to cross the massive damage threshold and trigger cascading effects that tear down enemy defenses for the whole team. Destruction Wrath amplifies weakness power and defense reduction, but ends in forsaken and strips all enchantments — making dedicated buffers a liability rather than an asset. | AZ9: The apex predator and most complex of the Barbarian subclasses. She cycles between four exclusive beast forms, scales overkill into team-wide debuffs, and generates Anguish from damage dealt to any ally — turning chaotic encounters into fuel. Final Wrath guarantees her death when it ends, making every use of it the last decision she makes. | BA9: A flashy, risk-taking fighter who uses gambit abilities that either succeed spectacularly or backfire against her. Critical Stance generates expertise on critical hits, and her gambits deal high damage or critical effects at a cost — such as becoming prone on a miss or inviting counter attacks — rewarding aggressive play with chain weapons. | BB9: A one-handed sword specialist who excels at counter attacks and is almost impossible to disarm or knock down. Counter Stance generates expertise whenever she counters, and her kit is built around parries and ripostes — parrying an attack, then immediately punishing the attacker with a follow-up strike. | BC9: A heavy shield bearer who fights best alongside ready allies. Shield Stance generates expertise on every block, and her toolkit includes guaranteed blocks, fortification at the cost of tired, and Phalanx Power, which enhances the damage of all ready allies based on how many are still standing. | BD9: A dual-wielding speed specialist whose defining abilities trigger on the second strike of a sequence, becoming more powerful the sooner that second hit follows the first. Speed Stance generates expertise from quicken effects, and she builds momentum and haste through attacks to fuel an escalating flurry of blows. | BE9: An extraordinarily accurate fighter who specializes in pinpoint attacks that can activate additional conditions at high enough values. Pinpoint Stance generates expertise from hit rolls beyond what is needed to connect, and her kit rewards fighting alone — with Alone Damage and Alone Defense passives that keep her effective as the last fighter standing. | BF9: A polearm and spear specialist whose Lancing Blow attacks have a chance to pierce through the primary target and hit the enemy behind them. Retaliation Stance generates expertise through retaliating, and she brings mounted abilities and column-targeting attacks that reward controlling space and threatening multiple rows at once. | BG9: An initiative-focused dual-wielder who seizes the opening of every battle with maximum aggression. Dodge Stance generates expertise on dodges, and Suicide Stance trades increased offense and counter-chance for the willingness to be struck, generating expertise from taking hits and rewarding an all-or-nothing fighting style. | BH9: An immovable defensive combatant who weaponizes his durability offensively. Unmovable Stance generates expertise from movement effects targeting him, and Advanced Unmovable Stance reflects delays back at enemies, turning every attempt to slow him into a punishment for the attacker. | BI9: A sword-fighting parry expert whose feint abilities compel enemies to attack her, then punish them when she parries the incoming strike. Parry Stance generates expertise from each successful parry, and she chains feints into ripostes, bleeds, penetrating attacks, or mass taunts depending on which feint variant she has prepared. | BJ9: A commanding leader who translates her own expertise directly into team-wide benefits. Warlord's Stance generates expertise whenever any ally acts, and her Leadership abilities require a minimum expertise level and become more powerful at higher thresholds — quickening all allies, enhancing their damage, or even making their next attack unerring after she misses. | CE9: Crescendo-driven buffer who rewards spending small actions on allies to power up larger payoffs. Builds Crescendo stacks through move and minor buffs, then releases them through scaling heal, shield, damage, bleed, and mana abilities. Leans toward chords and positive effects, with strong regeneration support alongside his offensive Crescendo tools. | CF9: Chaos-specialist who floods enemies with random afflictions, unpredictable conditions, and misdirected attacks. No formal mechanic — the unpredictability is the design. Best used to overwhelm enemy resistances and create openings for allies, with a capstone that turns his own misfortune into tempo. | CG9: The most offensively oriented bard subclass, specializing in life drain, culling, and damage-focused dischords rather than traditional support. He turns the song mechanic toward attrition and erasure — draining life, finishing weakened enemies, and using death itself as an element of his performance. Cacophony abilities reward the whole team's investment in debuffing, making him most dangerous in coordinated groups. | CH9: Earth-focused sustain specialist who stacks litany effects on allies and enemies for escalating pressure. Juggles short-duration stacking conditions that demand constant reapplication — letting them expire collapses the investment. Extended Cuts rewards commitment by progressively raising duration ceilings the more a condition is refreshed. | CI9: Elemental support and disruption specialist who grants deity-named favors to allies, healing them and loading them with elemental damage adds. Simultaneously harasses enemies with water and air magic, knockdowns, and delays. Favor of the Drum doubles every favor with a free untyped add, making his allies' attacks substantially more dangerous. | CJ9: Stealth-integrated bard who supplements song management with disguises and flanking setups. Each disguise grants role-specific bonuses and can be dramatically discharged for a powerful effect at the cost of the disguise itself. Begins every battle already in disguise, giving immediate access to his full toolkit from the first action. | CK9: Dark magic manipulator who fights most effectively when enemies cannot see him. Avert, scorn, and hidden each provide a different path to his veiled abilities, which hit harder than normal. Elusive Rhythm turns successful misdirection into tempo, rewarding a Mountebank who keeps multiple avoidance conditions active simultaneously. | CL9: Conductor-style support who grants allies free attacks through Entourage abilities, drawing enemy aggression onto protected performers. Provokes and taunts redirect incoming damage to allies who are simultaneously shielded, dodging, or enduring. Dedicated Entourage extends every provoke granted, making each protected performer absorb more before attention shifts. | CM9: Resurrection-focused support whose most powerful abilities unlock only after an ally returns to life. Epiphany abilities turn each resurrection into a cascade of heals, buffs, mana, and free attacks. His retaliation theme gives him an offensive identity when not raising allies, and Encore ensures he can survive long enough to finish his performance. | CN9: Aura-and-light specialist who illuminates the battlefield to empower allies and punish enemies. Manages multiple sustained auras simultaneously while spreading illuminate to lock enemies out of hidden and set up targeted light abilities. Constant Light makes him a hard counter to all stealth-based enemy strategies, fundamentally reshaping how battles play out at Tier 25. | CO9: A summoner who fights in concert with her conjured allies, using their mana reserves to amplify her own attacks. She manifests spectral weapons for any ally and directs her companion with precision, growing stronger the more she and her creature act as one. | CP9: A Thanatos-leaning controller who wraps herself and allies in retaliatory spirits, punishing enemies for every strike they land. She pairs water and air magic for freeze and delay with a cross-alignment toolkit that rewards deliberate dips into Eros. | CQ9: A support specialist who prepares a battery of Attendant abilities and waits for her companion to critical — triggering all of them at once in a cascade of healing, damage, and quickening. The longer she waits, the more devastating the payoff. | CR9: A balanced-alignment caster who draws equal power from both dark and light, strongest when she resists pushing to either extreme. Her Harmony abilities detonate from center for massive effect, then push her off balance — and she spends the next turns clawing her way back. | CS9: A spiritual warrior who infuses her companion with procs before it acts and rides a summoned Spirit Beast into mounted combat. She synchronizes her actions with her creature through a shared spiritual bond, raising fallen companions and granting her allies the will to survive past death. | CT9: A desperation specialist whose entire toolkit unlocks at low health, becoming most powerful precisely when she should be most vulnerable. Her transformation locks in that endangered power permanently, turning near-death into a lasting combat state. | CU9: A critical-hit amplifier who builds toward celestial thresholds across multiple turns, generating mana, quickening herself, and purging afflictions with each enemy she crits. She wields the full elemental spectrum through a stellar lens, with her lucky damage toolkit turning probability itself into a weapon. | CV9: A selfish corruptor who damages her own allies to fuel her offensive power, scaling with the total corruption she spreads across the battlefield. She transforms her own self-inflicted corruption into a permanent power state, and turns enemy deaths into mana through Dark Harvest. | CW9: A sanity-sacrificing chaos mage who deliberately accumulates illusory damage on herself to unlock her most powerful abilities. She cannot be killed by her own madness — but when it expires, it becomes very real, making resource management a matter of survival. | CX9: A high-commitment alignment specialist who signs powerful ongoing Pacts, each granting two bonuses at the cost of one persistent drawback. She thrives at the extremes of the alignment scale, and her Lifebond with her companion means their fates are literally intertwined — she cannot fall while it stands. | CY9: Quick and affordable support built around lucky manipulation and regeneration. Generates divinity through hexes, purges, and blessings, then spends it on Benedictions — powerful single-target heals enhanced by current divinity, with overheal effects that range from possession to damage to speed depending on the type used. | CZ9: Pure restoration specialist with the mana economy to sustain heavy healing across a long battle. His cures carry addenda that scale with heal value, turning strong heals into purges, quickens, or damage adds. A Life Domain running on overheal generation lets him convert aggressive healing directly into sustained divinity. | DA9: Affliction-resistant purge specialist who turns enemy pressure into elemental retaliation. Elemental purges double as generators and resistance enhancers scaled to current divinity, and a Protection Domain that rewards affliction resistance creates a feedback loop where enemy affliction pressure fuels his own power. | DB9: Magically aggressive Cleric who layers blessings onto allies while maintaining his own damage shield as an offensive weapon. The Lattice ability line scales with and consumes his shield for light damage and control, Lattice Reflection punishes enemies who target it, and a Sun Domain that generates from light abilities rewards sustained Celestial offense. | DC9: Frontline healer built for endangered allies and active combat. Vitality heals grant temporary bonuses that persist until the target takes damage, and a War Domain that generates from any ally's critical hits rewards pairing him with damage-heavy parties. Perilous Divinity marks low-health targets for stronger healing while generating divinity. | DD9: Light-magic specialist with exclusive access to intangible enemies and strong mana drain. Most abilities gain additional effects against incorporeal targets, and an Exorcism Domain that generates divinity proportional to total enemy mana spent rewards fighting caster-heavy encounters where the domain becomes a powerful self-sustaining engine. | DE9: Sleep-focused controller who worships the sleeping god and grows in power while the world slumbers. Incapacitated allies feed Rest Domain divinity generation even without the Preacher acting, turning sleep from a liability into a resource. Turns ally afflictions into advantages and punishes sleeping enemies with a focused suite of nightmare attacks. | DF9: High-speed melee Cleric who conducts the entire party's tempo through quickening. Ascension abilities require but do not spend full divinity, creating a maintain-and-hold pattern rather than the typical spend-and-rebuild cycle. A mastery class at Tier 19 — maximizing output requires deep awareness of quicken tolerance, Ascension timing, and Fervor Domain generation simultaneously. | DG9: Self-infecting contagion spreader who carries disease deliberately to fuel his domain. Plague Domain generates divinity for each affliction successfully transferred from the Plague Doctor to an enemy, rewarding stacking afflictions on himself and building around affliction resistance to survive the risk. One of the most dangerous and mechanically demanding Cleric subclasses. | DH9: Capstone Cleric whose Furtherance abilities scale with divinity gained during the current turn rather than total on hand. Front-loading a turn with support actions directly amplifies his payoff. A Prophecy Domain that generates divinity when countdowns fire — scaled to their duration — rewards patience and long-term planning over reactive play. | DS9: The entry point for deep influence play. The Telepath specializes in illusory damage and disruption, with heightened abilities that let her translate influence investment into cascading multi-cast effects. She is subtle and methodical, chipping away at enemy defenses before they can act. | DT9: A spread-oriented damage dealer who turns punishment into power. Her kinetic abilities charge between turns based on physical damage she absorbs, making her uniquely dangerous when enemies focus on her. She favors broad pressure and area control over single-target dominance. | DU9: A denial specialist who erodes the enemy's ability to function. She burns through mana, forces enemies into basic attacks, and makes them forget what they were doing. She also carries an unexpected compassionate edge, helping allies forget their wounds. | DV9: A pattern-weaver who controls the entire battlefield through sustained channeled effects. She locks enemies into states of blindness, stun, or vulnerability for as long as she can keep her focus. Patient and methodical, she rewards players who plan their turns carefully. | DW9: An information broker and countdown specialist who fights the future rather than the present. Her divinations expose enemy weaknesses and upcoming actions, letting the whole party respond intelligently, while her countdown abilities punish enemies for the passage of time itself. | DX9: A ghost-touched subclass who exploits enemies at their weakest — specifically when their mana runs dry. She drains, haunts, and possesses with impunity against vulnerable targets, and can become intangible herself to frighten and evade. Death Knell makes her the safest handler of deep influence. | DY9: The party coordinator. Rather than dominating enemies directly, she possesses allies to direct them more efficiently and uses total influence to synchronize team timing. She rewards players who understand their whole roster and rewards smart sequencing over raw power. | DZ9: A high-risk, high-reward glass cannon who bleeds the mind as much as the body. She deals devastating illusory damage that grows stronger the closer she is to death. Her own abilities hurt her, but the connection flows both ways — and she intends to make that cost worth it. | EA9: A spread-influence subclass who bends time itself to delay, rush, and disorient the battlefield. She punishes fast enemies, accelerates allies, and becomes more efficient the more she leans into her hasted or slowed states. Supreme Chronomancy is one of the most powerful single abilities in the psychic tree. | EB9: The pinnacle of possession mastery. She owns enemies outright, bends their will across multiple turns, and profits from every attack they make under her control. Her capstone, Broken Will, ensures that no enemy is ultimately beyond her reach. | EM9: A team-oriented controller who drains stats from maledicted enemies and redistributes them to allies. She weaponizes possession and hexes for direct control while her Malign drain suite debilitates entire maledicted groups — and Share in Consumption ensures no drain benefit passes through her hands without leaving something behind. | EN9: An air-element Witch who turns malediction into a positional weapon. Her whirlwind abilities use a maledicted enemy as an anchor, striking all adjacent foes instead — rewarding grid awareness and central positioning. Bloodlust amplifies her storm attacks while Conductivity makes the entire maledicted field a lightning rod. | EO9: The most aggressive Witch subclass, stacking damage afflictions on targets to fuel piercing effigy attacks that cut through resistance. Flammability turns every fire hit into compounding bleeds, and Personal Effigy rewards taking damage herself — making her a high-risk attacker who burns hotter the more punishment she absorbs. | EP9: A methodical earth-element controller who applies permanent unending afflictions that reserve her mana until enemies die or are purged. She trades mana flexibility for devastating long-term debilitation, and Mana From Dust recycles her investment when corruption finishes the job. | EQ9: A water-element specialist who deals increased damage and effects in inverse proportion to enemy speed — making her strongest against the foes she has already slowed. Chill to Frost converts redundant slows into hard incapacitation, and Inspiring Misfortune makes her one of the strongest mana generators in the entire Witch family. | ER9: A chaotic generalist who trades reliability for volume, deploying cheap bewitch afflictions against maledicted enemies at reduced action cost. Agnostic Afflictions removes elemental opposition penalties on vulnerability and exposure, letting her stack conditions freely regardless of enemy resistances — chaos as a feature, not a flaw. | ES9: A light-element support Witch who harvests fetishes from fallen enemies and deploys them as stat-scaling ally buffs. She transfers afflictions from allies to enemies, drains life, and accumulates mana through Fetish Bag by holding fetishes in reserve — balancing the tension between deploying her toolkit and sustaining herself. | ET9: A dark necromancer who builds zombie companions from killed and afflicted enemies, using Juju Curse to turn her entire malediction toolkit into a zombie pipeline. Corpse Pile makes each death — enemy or companion — strengthen her current zombie, turning attrition into escalating companion power. | EU9: A corruption and bleed specialist who wraps her worst afflictions in criterion shells that resist purging until they deal their full damage. Expiration Surge turns every naturally expiring condition into mana, rewarding patience and long-duration stacking — Plague Cauldron's exponential corruption release is her most catastrophic payoff for waiting. | EV9: The apex Witch, combining covenants, curses, and mass malediction into a comprehensive affliction dominance platform. She channels malediction across entire enemy groups with Malefaction Chant, unifies damage through Sympathy, and elevates her whole party's affliction pressure through Cursed Amplification — the Witch's toolkit at its most absolute. | EW9: All-elements generalist with companion support and momentum-driven efficiency. She cycles through every element in sequence to build stacking cast speed and mana bonuses, summons earth and water elementals, and infuses allies with elemental damage adds — the most versatile and accessible wizard subclass. | EX9: Dark magic specialist who turns death itself into a resource. She raises skeletal companions, scales her storm damage to the body count, and runs a suite of prepared abilities that trigger automatically when enemies fall — rewarding her for battles where allies are doing the killing as much as her own. | EY9: Control-focused water specialist with the deepest incapacitation toolkit in the class. She freezes, slows, and delays entire battlefields, with her most powerful conflux ability scaling both the number of targets incapacitated and how hard they are to wake based on how many elements she has charged. | EZ9: Defensive earth specialist who protects allies while grinding down enemy defenses. She builds damage shields, roots enemies in place, and applies layered weaknesses — her conflux abilities uniquely favor the whole party by granting elemental retaliations and stacking debuffs across every stat. | FA9: High-variance air specialist built around storm damage and stun pressure. She thrives on randomness — chaining lightning across the grid, forking attacks into splits, and stacking storm hits to overwhelm enemies — with the highest individual damage ceiling in the class when lucky damage and maximum damage align. | FB9: Area fire specialist who hits everyone, repeatedly. She applies countdowns, causes wounds, and commits fully to upfront mana costs for abilities that pay off over multiple ticks — Catastrophe and Conflux Meteor reward planning several turns ahead and punish enemies who cannot interrupt her. | FC9: Anti-attunement specialist who grows stronger the more completely she clears her elemental slate. She is the only wizard whose peak performance comes after spending conflux rather than before it, with her most powerful abilities gating behind having no attunements and her conflux damage rewarding precise elemental power investment over breadth. | FD9: Light magic specialist with hex, justice, and a unique mana economy identity. She wants enemies casting expensive spells so her Mana Disparity bonus peaks, making her the only wizard who benefits from enemy casters. Her full-conflux Conflux Enchantment can grant the entire party six simultaneous buffs scaled to her elemental investment. | FE9: Reactive counterspell specialist who punishes enemy spellcasting while sustaining channeled damage. She runs a suite of prepared counterspells that can chain indefinitely, drains mana from enemies, and uses Conflux Channeling to chain successive elemental damage sequences — the only wizard subclass that gets stronger the more the enemy commits to magic. | FF9: Pinnacle attunement-breadth specialist who rewards deliberate, expensive play. She wants all six elements charged simultaneously, spends them through Supreme abilities that scale with attunement count, and uses her previous turn's mana expenditure to amplify the next — the most technically demanding wizard subclass and the one with the highest ceiling.
A10: Mechanic | B10: =COUNTA(C10:FF10)/1.6 -> 0
A11: Lore | B11: =COUNTA(C11:FF11)/1.6 -> 0
A12: Appearance | B12: =COUNTA(C12:FF12)/1.6 -> 0
A13: Req Dex | B13: =COUNTA(C13:FF13)/1.6 -> 12.5 | C13: 58 | D13: 63 | E13: 62 | F13: 88 | G13: 70 | H13: 142 | I13: 180 | J13: 248 | K13: 193 | L13: 182 | M13: 59 | N13: 58 | O13: 93 | P13: 76 | Q13: 67 | R13: 173 | S13: 88 | T13: 185 | U13: 217 | V13: 263
A14: Req Int | B14: =COUNTA(C14:FF14)/1.6 -> 3.75 | K14: 90 | L14: 108 | M14: 56 | N14: 54 | R14: 77 | S14: 129
A15: Req Str | B15: =COUNTA(C15:FF15)/1.6 -> 8.125 | C15: 54 | E15: 75 | F15: 76 | I15: 86 | L15: 121 | M15: 54 | N15: 64 | O15: 72 | P15: 92 | Q15: 105 | S15: 95 | U15: 140 | V15: 129
A16: Req Wis | B16: =COUNTA(C16:FF16)/1.6 -> 6.25 | C16: 61 | D16: 63 | E16: 72 | G16: 108 | H16: 95 | I16: 80 | J16: 98 | K16: 95 | T16: 90 | V16: 118
A17: Req Cha | B17: =COUNTA(C17:FF17)/1.6 -> 9.375 | C17: 58 | D17: 67 | E17: 84 | F17: 86 | G17: 130 | H17: 95 | I17: 82 | J17: 99 | K17: 238 | L17: 244 | P17: 63 | Q17: 68 | R17: 109 | U17: 131 | V17: 118
A18: Req End | B18: =COUNTA(C18:FF18)/1.6 -> 7.5 | C18: 53 | E18: 63 | M18: 59 | N18: 67 | O18: 82 | P18: 106 | Q18: 85 | R18: 82 | S18: 213 | T18: 185 | U18: 135 | V18: 128
A19: Req Luc | B19: =COUNTA(C19:FF19)/1.6 -> 6.25 | D19: 59 | E19: 62 | F19: 87 | H19: 95 | I19: 82 | J19: 198 | K19: 96 | L19: 245 | O19: 61 | V19: 122
A20: Req Wil | B20: =COUNTA(C20:FF20)/1.6 -> 8.125 | C20: 54 | G20: 70 | H20: 95 | I20: 115 | K20: 96 | M20: 60 | N20: 59 | O20: 60 | Q20: 103 | R20: 81 | T20: 183 | U20: 135 | V20: 122
A21: Weapon Name | B21: =COUNTA(C21:FF21)/1.6 -> 100 | C21: Short Bow | D21: Reflex Bow | E21: Heavy Crossbow | F21: True Shot | G21: Recurve Bow | H21: Bolas | I21: Flatbow | J21: Springbow | K21: Composite Bow | L21: Mach Bow | M21: Katar | N21: Brass Knuckes | O21: Tekko | P21: Spiked Knuckles | Q21: Boulder Gauntlet | R21: Neko-te | S21: Bagh Nakh | T21: Bo Staff | U21: Stormgloves | V21: Steins | W21: Blowgun | X21: Shiv | Y21: Crowbar | Z21: Switchblades | AA21: Trapeze Wire | AB21: Stiletto | AC21: Loaded Dice | AD21: Contraband | AE21: Alleyknives | AF21: Paired Jittes | AG21: Ethermist | AH21: Needlegun | AI21: Force Rifle | AJ21: Chaos Cannon | AK21: Stone Blaster | AL21: Scattershot | AM21: Sacred Revolvers | AN21: Water Pistol | AO21: Hand Catapult | AP21: Phantasm Generator | AQ21: Greatclub | AR21: Battle Axe and Spiked Shield | AS21: Lochaber | AT21: Double Axe | AU21: Francisca and Half Shield | AV21: Ravager | AW21: Dual Axes | AX21: Headsplitter | AY21: Battle Scythe | AZ21: Labrys | BA21: Trident and Net | BB21: Rapier | BC21: Pilum and Scutum | BD21: Double Flail | BE21: Estoc and Bracer | BF21: Longspear | BG21: Katana and Wazikashi | BH21: Maul | BI21: Foil and Parry Dagger | BJ21: Halberd and Shield | BK21: Flanged Mace and Hard Shield | BL21: Broadsword and Wideshield | BM21: Gurz | BN21: Lance and Shield | BO21: Bec de Corbin and Bastion Shield | BP21: Great Lance | BQ21: Paired Batons | BR21: Spiked Ball and Chain | BS21: Morgernstern | BT21: Lucerne and Temple Shield | BU21: Stormbreaker | BV21: Flamberge | BW21: Frostbrand and Waveshield | BX21: Bearded Axe and Timber Shield | BY21: Sellswords | BZ21: Catalyst | CA21: Phasehammer | CB21: Mordaxt | CC21: Voidblades | CD21: Zweihander | CE21: Flute | CF21: Trumpet | CG21: Bagpipes | CH21: Lyre | CI21: Wardrums | CJ21: Guitar | CK21: Accordion | CL21: Cello | CM21: Violin | CN21: Harp | CO21: Summoning Seal | CP21: Hand Mirror | CQ21: Tomahawks | CR21: Planchette | CS21: Sagaris | CT21: Precipice Lance | CU21: Telescope | CV21: Lamp | CW21: Tentacles | CX21: Compact | CY21: Psalm | CZ21: Aspergillium | DA21: Thurible | DB21: Crosier | DC21: Absolution | DD21: Morningstar | DE21: Caduceus | DF21: Penitent | DG21: Requiem | DH21: Reliquary | DI21: Harpoon | DJ21: Guillotine Bow | DK21: Coffin Bow | DL21: Noose Strung Crossbow | DM21: Deathknell | DN21: Umbral Bow | DO21: Sandpouch | DP21: Ankou Bow | DQ21: Quietus | DR21: Smoke Lantern | DS21: Mindshard | DT21: Hovering Orbs | DU21: Crystallized Memory | DV21: Pendulum Chain | DW21: Crystal Ball | DX21: Ghostly Accompaniment | DY21: Axiom Rod | DZ21: Trepan | EA21: Hourglass | EB21: Marionette | EC21: Obelisk | ED21: Sign of Girru | EE21: Stone Rod | EF21: Sigil Staff | EG21: Unraveller | EH21: Quill Rod | EI21: Crook | EJ21: Glyph | EK21: Cypher | EL21: Arcanite | EM21: Ritual Dagger | EN21: Wormwood | EO21: Torch | EP21: Sickle | EQ21: Icicle | ER21: Seax | ES21: Wanga | ET21: Stang | EU21: Broom | EV21: Vervain | EW21: Elemental Staff | EX21: Dark Wand | EY21: Water Wand | EZ21: Earth Wand | FA21: Air Wand | FB21: Fire Wand | FC21: Aether Wand | FD21: Light Wand | FE21: Intonation | FF21: Staff of Power
A22: Weapon Mech | B22: =COUNTA(C22:FF22)/1.6 -> 100 | C22: initiative bonus, acts sooner in first round | D22: bonus scales with number of enemies of the hunted type present | E22: very high damage, very long reload | F22: bonus to prepared/vow attacks | G22: accuracy while accompanied | H22: increased prone chance or immobilization | I22: accuracy bonus scaling with target's lost health | J22: quicken when attacking endangered enemies | K22: damage bonus scaling with target's dodge value | L22: increased benefit from pinpoint mechanic | M22: dodge bonus after attacking, duration scales with attack speed | N22: increased damage when attacking same enemy as previous turn | O22: gains percentage of target's base damage on attack | P22: chance to stun on reaction and counter attacks | Q22: increased glancing damage | R22: enhanced critical chance immediately after losing hidden status | S22: poison applies even on glancing hits | T22: chance to parry afflictions | U22: delayed secondary damage add after initial attack | V22: dodge bonus on miss, scales with miss amount | W22: increased affliction power with poisons | X22: increased bleeding | Y22: extra damage against full health enemies | Z22: drains extra health and mana | AA22: increased accuracy to next attack after missing, scales with miss amount | AB22: chance for instant death to overwhelm resistance | AC22: critical damage increases on failed critical | AD22: chance to conserve poisons | AE22: penetration while hidden | AF22: prevents counters on parry | AG22: damage and ammo load based on mana, mana ammo | AH22: natural penetration, penetrate ammo | AI22: delays on hit, delay ammo | AJ22: corrupt damage, corrupt ammo | AK22: clobbering damage, earth ammo | AL22: fires random amount of ammo per shot, flechette ammo | AM22: dual ranged, light damage add, light ammo | AN22: mana gain on attack, water ammo | AO22: chance for area damage, fire ammo | AP22: illusory damage, illusory ammo | AQ22: intrinsic delay on hit | AR22: damage on block or enhanced retaliation | AS22: bonus while berserk | AT22: rampage bonus scaling with enemy deaths | AU22: chance to provoke on block | AV22: chance to maximize damage | AW22: quicken on attack while endangered | AX22: damages self at start of turn for stat bonus | AY22: increased massive damage threshold range | AZ22: increased overkill value | BA22: increased prone chance | BB22: increased disarm chance | BC22: increased damage per ally ready to act | BD22: accuracy builds on consecutive hits | BE22: reduced chance attacks are parried | BF22: bonus damage from momentum | BG22: increased damage for a period after being damaged | BH22: bonus to next damage when quickened | BI22: bonus to reaction ability damage | BJ22: quicken team on parry | BK22: chance to ignore glancing hits at full health | BL22: increased threshold charge from damage | BM22: increased healing and purge based on proximity to death | BN22: chance to avoid block on attack | BO22: highest intrinsic block chance | BP22: increased magic resistance | BQ22: lucky parry, checks twice | BR22: bonus damage based on corruption on self | BS22: damage increases based on time since last action | BT22: overheals spread to allies | BU22: air/lightning damage add | BV22: fire damage add | BW22: earth damage add | BX22: water/ice damage add | BY22: chaos damage add | BZ22: increased personal enhancements | CA22: intrinsic phasing chance | CB22: increased damage while barrier is active | CC22: dark damage add | CD22: light damage add | CE22: enhancement and weakness duration | CF22: increased effect and duration of enhancements and weaknesses on first turn | CG22: increased power of weaken effects | CH22: increased power of conditions already present on unit | CI22: minor quicken to all allies on turn | CJ22: increased enchant power while hidden | CK22: grants scorn against next attack | CL22: increased magic damage but increased mana costs | CM22: improved retaliation and reflection | CN22: increased effects of light-based conditions | CO22: increased summoning speed | CP22: increased retaliation effects on self | CQ22: companion critical chance and damage | CR22: increased spell critical chance | CS22: bonus damage while companion is alive | CT22: endangered damage, bonus when both user and target are endangered | CU22: increased damage for each enemy damaged during turn | CV22: elemental switching with companion element | CW22: reduce affliction resistance on hit | CX22: intrinsic heal siphon and pain link with companion | CY22: increased accuracy/damage/healing while lucky active | CZ22: increased healing to endangered allies | DA22: purge power bonus | DB22: increased damage shield granted | DC22: reduced vitality consumption | DD22: intrinsic ghost touch | DE22: increased incapacitate potency and landing chance | DF22: increased damage and speed when alone | DG22: increased contagion spread | DH22: increased countdown duration, attacks increase countdown power | DI22: increased power from damage afflictions | DJ22: extra damage against lowest health enemy | DK22: intrinsic delay on hit | DL22: increased damage based on tired duration on target | DM22: extra damage to next ally attacking same target | DN22: increased damage after purging or disenchanting | DO22: attacks have chance to be insidious | DP22: increased damage against more enemies present | DQ22: increased damage against solo enemies | DR22: illusory damage add while endangered | DS22: dodge and reflection bonus after attacking | DT22: ranged damage based on magic power | DU22: procs avert on target when attacking | DV22: increased channel duration | DW22: reveals target health after attack | DX22: mana damage | DY22: improves possession effects on allies | DZ22: additional damage based on illusory damage on target | EA22: reduces quicken/delay tolerance | EB22: improved damage when possessing enemies | EC22: increased counterspell value | ED22: next attack deals extra fire damage | EE22: grants clobbering to companion | EF22: improved spell criticals when alone | EG22: chance to proc disenchant on attack | EH22: increased trap damage | EI22: increased resistance piercing on attacks | EJ22: critical multiplier applies to damage adds on critical | EK22: deals portion of countdown damage present on target | EL22: damage scales with total mana used | EM22: drains life on kill | EN22: debuffs also delay | EO22: fire bleed on melee attack | EP22: bonus damage based on corruption on target | EQ22: bonus damage based on target's slow value | ER22: last action each turn has improved magic power | ES22: improved heal and purge per affliction on ally | ET22: damage dealt heals companion by small percentage | EU22: increased affliction power per affliction on self | EV22: improved hexes | EW22: primary elemental power | EX22: dark power | EY22: water power | EZ22: earth power | FA22: air power | FB22: fire power | FC22: arcane power | FD22: light power | FE22: channel power | FF22: magic power based on mana
A23: Weapon Stats | B23: =COUNTA(C23:FF23)/1.6 -> 0
A24: Armor Name | B24: =COUNTA(C24:FF24)/1.6 -> 0
A25: Armor Stats | B25: =COUNTA(C25:FF25)/1.6 -> 0
A26: Ability Count | C26: =COUNTA(C27:C61) -> 25 | D26: =COUNTA(D27:D61) -> 0 | E26: =COUNTA(E27:E61) -> 0 | F26: =COUNTA(F27:F61) -> 0 | G26: =COUNTA(G27:G61) -> 0 | H26: =COUNTA(H27:H61) -> 0 | I26: =COUNTA(I27:I61) -> 0 | J26: =COUNTA(J27:J61) -> 0 | ... FF26: =COUNTA(FF27:FF61) -> 0
A27: Major 1 | B27: =COUNTA(C27:FF27)/1.6 -> 14.375 | C27: Adroit Momentum – Ranged attack with pinpoint and momentum enhancing accuracy | W27: All Down to Me – Powerful ranged attack against single that requires alone and consumes combat advantage (Bandit) | X27: All Out Bleeding – Melee attack that consumes all advantage and causes increased bleeding based on advantage used (Cutthroat) | AQ27: Breathtaking Blow – Melee attack that consumes rage to deal clobbering damage and exhaust foe. (Brute) | AR27: Charging Ambush – Melee attack against column. Front target must have full health (Raider) | AS27: Backbiting Exertion – Melee attack with lower accuracy and backbiting. If attack misses, take damage and reattempt once (Berserker) | AT27: Berserk Rampage – Melee attack requiring berserk that deals additional damage based on each enemy killed in battle (Marauder) | AU27: Bloodlust Response – Melee attack with bloodlust following a block (Viking) | AV27: Awesome Cleave – Melee attack versus single that damages all other enemies against combined defense of primary and secondary target (Vandal) | AW27: Amplified Savagery – Melee attack with backbiting and amplification, can be used berserk (Fury) | AX27: Bloodlust Bite – Melee attack with bloodlust requiring rage (Cannibal) | AY27: Approaching Victory – Melee attack that quickens all based on overkill (Destroyer) | AZ27: Animalistic Attack – Melee attack based on current animal form. Consumes rage (Beastlord) | BA27: All-in Strike – Melee attack with high damage, high critical damage, and low accuracy. Gladiator becomes prone on miss (Gladiator) | BB27: Careful Strike – Melee attack with increased accuracy and lower damage (Duelist) | BC27: Inevitable Strike – Melee attack that requires expertise that is unblockable, unerring, and unparryable (Phalanx) | BD27: After Image Blow – Two attacks against one target, requires haste (Dervish) | BE27: Accurate Focus – Melee attack that grants focus if pinpoint value is high enough (Fencer) | BF27: Dash of Expertise – Melee attack versus a column that requires expertise and quickens the user (Lancer) | BG27: Amplification Exploit – Amplified attack, consumes half of expertise, requires minimum expertise (Samurai) | BH27: Counter Breaker – Melee attack that lowers target’s counter damage (Dreadnaught) | BI27: Aorta Slash – Melee attack with penetrate that causes high damage, short term bleed (Swashbuckler) | BJ27: Allied Assistance – Warlord makes a melee attack against the target of each ally’s single target attack, consuming expertise with each attack (Warlord)
A28: Major 2 | B28: =COUNTA(C28:FF28)/1.6 -> 14.375 | C28: Aimed Momentum – Ranged attack that generates extra aim based on momentum | W28: All Out Advantage, Major – Powerful melee attack that consumes all advantage up to 6 (Multiplier: Advantage^2*9%) (Bandit) | X28: Backstab Rend – Dualwield melee attack that requires flanking. Deals extra damage if both attacks hit (Cutthroat) | AQ28: Brutal Consequences – High damage melee attack and generate rage, but take damage at beginning of next turn (Brute) | AR28: Fury Tremor – Melee attack against all requiring raging that consumes all rage to enhance damage and knock enemies prone (Raider) | AS28: Berserk Exertion – Melee attack with lower accuracy that attacks randomly and requires berserk. If attack misses, take damage and reattempt once (Berserker) | AT28: Bloodlust Rampage – Melee attack that has increased bloodlust value for each enemy killed in battle (Marauder) | AU28: Continuous Turmoil – Attack, then attack all on critical (Viking) | AV28: Brink of Death – Melee attack with ruthless damage. Only becomes available for one turn immediately after dealing enough damage (Vandal) | AW28: Blood Purity – Melee attack with increasing bleed, resets if barbarian attacks the target suffering from this bleed. (Fury) | AX28: Devour the Sleeping – Culling melee attack against incapacitated target. Heal on kill (Cannibal) | AY28: Cascading Critical – Melee attack that cascades to random target on critical (Destroyer) | AZ28: Bull’s Rampage – Three random melee attack that cause bleed and requires rage (Beastlord) | BA28: Deflection Gambit – High damage, low accuracy melee attack that randomly attacks another target, enemy or ally, on miss. Requires expertise (Gladiator) | BB28: Critical Disarm – Melee attack that disarms on critical (Duelist) | BC28: Overwhelming Strike – Melee attack with overwhelming. Requires expertise (Phalanx) | BD28: Burst Succession – Dual-wield attack that damages all enemies with second attack based on dual-wield attack speed. (Dervish) | BE28: Beat Attack – Unparryable melee attack (Fencer) | BF28: Expert Charge – Melee attack against column requiring mounted that is enhanced by expertise (Lancer) | BG28: Amplification Rend – Melee attack with both weapons that stacks amplification if both attacks hit. (Samurai) | BH28: Expert Shatter – Melee attack that has a shatter value based off expertise, needs to be prepared. (Dreadnaught) | BI28: Bleeding Feint – Enhances parry chance of swashbuckler and compels target to attack her. If she parries the target before next turn, she attacks the target and causes an untyped bleed. Requires expertise (Swashbuckler) | BJ28: Directing Blow – Melee attack that enhances accuracy of all allies for their next attack based on expertise (Warlord)
A29: Major 3 | B29: =COUNTA(C29:FF29)/1.6 -> 14.375 | C29: Coordinated Shot – Ranged attack with quick preparation that grants increased accuracy and damage to next attack versus target | W29: Desperation Drain – Melee attack against single target with life drain. Advantage cost reduced if alone (Bandit) | X29: Bloodseeker Slash – Melee attack against bleeding target (Cutthroat) | AQ29: Dangerous Ruse – Melee attack with reduced accuracy that causes damage to self on a miss (Brute) | AR29: Glancing Blood – Melee attack that causes bleed on glancing hit based on glancing damage dealt (Raider) | AS29: Berserk Ignorance – Melee attack and purge any conditions that occurred since last turn. Requires berserk (Berserker) | AT29: Clobbering Rampage – Melee attack that has increased clobbering value for each enemy killed in battle (Marauder) | AU29: Furious Tumult – Melee attack with bloodlust that consumes rage (Viking) | AV29: Brink of Inferno – Fire melee attack that grants fire damage add. Only becomes available for one turn immediately after dealing enough damage (Vandal) | AW29: Critical Purity – Melee attack with increased critical chance and critical damage, but with reduced accuracy, resets if the barbarian misses. (Fury) | AX29: Devour Whole – Cull target enemy to heal, gain mana, and gain all enchantments on target enemy (Cannibal) | AY29: Critical Balance – Melee attack that cannot critical, but deals additional damage based on critical damage (Destroyer) | AZ29: Call Rampaging Rhino – Summons a rampaging rhino mount with trample abilities (Beastlord) | BA29: Disarming Gambit – Melee attack with disarm, but gladiator becomes disarmed if this fails (Gladiator) | BB29: Disarmed Disaster – Alpha. High damage melee attack versus disarmed enemy (Duelist) | BC29: Phalanx Combo – Melee attack against single enemy with damage enhanced by ready allies (Phalanx) | BD29: Critical Succession – Dual-wield attack with increased critical chance and critical damage for second attack based on dual-wield attack speed. (Dervish) | BE29: Critical Exploit – Damage with increased critical chance and damage based on expertise, enhances critical chance and damage, consumes all expertise (Fencer) | BF29: Extended Penetration – Melee attack with penetration. Next melee attack also has penetration based on expertise (Lancer) | BG29: Bushido Bleed – Melee attack against enemy that causes untyped bleed. Enemy attack Samurai first and bleed is enhanced by enemy’s damage (Samurai) | BH29: Fortifying Slash – Melee attack that grants user fortified, requires expertise (Dreadnaught) | BI29: Desperate Hew – Melee attack with high critical chance and damage requiring endangered (Swashbuckler) | BJ29: Disruption Wave – Prepared melee attack versus all enemies that disrupts (Warlord)
A30: Major 4 | B30: =COUNTA(C30:FF30)/1.6 -> 14.375 | C30: Delaying Jolt – Ranged attack with delay against stunned target | W30: Desperation Onslaught – Multiple random ranged attacks consuming all advantage. The advantage cost per attack is reduced to half if alone (Bandit) | X30: Bloody Evisceration – Melee attack against enemy with stacking bleed that deals additional damage based on bleed (Cutthroat) | AQ30: Deliberate Clobber – Melee attack with increased accuracy, critical chance, and clobbering. Requires rage and delays user (Brute) | AR30: Glancing Stun – Melee attack that causes stun on glancing hit based on glancing damage dealt (Raider) | AS30: Berserk Strike – Melee attack that causes berserk to user. Can be used while berserk, but becomes random in that case and extends berserk (Berserker) | AT30: Clobbering Rend – Two melee attacks against a single target. Uses clobbering if both attacks hit (Marauder) | AU30: Razor Shield – Prepared melee attack with high untyped bleed. Enhanced by blocks made since preparation. (Viking) | AV30: Brink of Onslaught – Three randomly targeting melee attacks. Only becomes available for one turn immediately after dealing enough damage (Vandal) | AW30: Endless Exchange – Melee attack that causes tired for self and target. Tired duration increased for target and decreased for herself based on rage (Fury) | AX30: Gnashing Consumption – Melee attack that causes untyped bleed on target. Requires the Cannibal to have received enough healing (Cannibal) | AY30: Destroy Armor – Melee attack with shattering that causes fragile to the target (Destroyer) | AZ30: Feral Health Strike – Melee attack that heals user. Heals extra if attack kills (Beastlord) | BA30: Exciting Exchange – Melee attack that cannot be parried but is always countered (Gladiator) | BB30: Disarming Killer – Melee attack with cull against disarmed target (Duelist) | BC30: Phalanx Decimation – Melee attack with decimate enhanced by ready allies (Phalanx) | BD30: Double Rend – Dualwield melee attack that hits twice with each weapon. If all attacks hit, deal extra damage (Dervish) | BE30: Exact Stroke – Melee attack with high accuracy and pinpoint (Fencer) | BF30: Lancing Bleed – Melee attack that causes untyped bleed, procs the same attack against the target behind, with chance for behind that (Lancer) | BG30: Bushido Blow – Melee attack against enemy. Enemy attacks Samurai first and damage enhanced by enemy’s damage (Samurai) | BH30: Garrison Blow – Melee attack that provokes target and enhances defense (Dreadnaught) | BI30: Expert Blow, Supreme – Melee attack that requires expertise (Swashbuckler) | BJ30: Evading Blow – Melee attack that enhances dodge of all allies until their next attack based on expertise (Warlord)
A31: Major 5 | B31: =COUNTA(C31:FF31)/1.6 -> 14.375 | C31: Flanking Shot – Ranged attack that causes flanked | W31: Desperation Ripper – Melee attack against single target with powerful bleed. Advantage cost reduced if alone (Bandit) | X31: Critical Evisceration – Melee attack that causes bleed on critical (Cutthroat) | AQ31: Internal Bleeding Blow – Melee attack that causes untyped bleeding with clobber (Brute) | AR31: Gravity Cleave – Melee attack that prevents active defenses until next turn, with decimate based on active defenses lost (Raider) | AS31: Bleeding Exertion – Melee attack with lower accuracy that causes bleeds and quicken self. If attack misses, take damage and reattempt once (Berserker) | AT31: Critical Assault – Melee attack that attacks all on critical. Consumes rage (Marauder) | AU31: Shield Decimation – Prepared melee attack with decimate. Enhanced by blocks made since preparation. (Viking) | AV31: Brink of Violence – Melee attack with backbiting. Only becomes available for one turn immediately after dealing enough damage (Vandal) | AW31: Expeditious Strike – Melee attack that quickens the fury and that requires haste. Can be used while berserk (Fury) | AX31: Grave Hunger – Melee attack with drain requiring Cannibal to be endangered (Cannibal) | AY31: Entropy Hammer – Melee attack with clobbering that deals corrupt damage (Destroyer) | AZ31: Might Exacerbation – Melee attack that requires berserk, enhances damage but Beastlord becomes tired (Beastlord) | BA31: Onslaught Gambit – Melee attack against each enemy with reduced accuracy, but enemies counter gladiator on each miss (Gladiator) | BB31: Disarming Strike – Melee attack with a chance to disarm target (Duelist) | BC31: Phalanx Onslaught – Number of melee attacks based on number of ready allies (Phalanx) | BD31: Dual Momentum – Dual wield attack with both attacks enhanced by momentum (Dervish) | BE31: Expert Blow, Superior – Melee attack that requires 60 expertise (Fencer) | BF31: Lancing Charge – Melee attack with momentum, procs the same attack against the target behind, with chance for behind that (Lancer) | BG31: Bushido Burst – Melee attack against all enemies. Target enemy attacks Samurai first and damage enhanced by enemy’s damage (Samurai) | BH31: Great Defense Strike - Melee attack that enhances defense. Requires wielding a two-handed weapon (Dreadnaught) | BI31: Lucky Feint – Gain lucky on parries until next turn. On parry, gain lucky accuracy and lucky damage and counter (Swashbuckler) | BJ31: Example of Expertise – Melee attack that gains increasing number of modifiers based on expertise, including sudden, unblockable, unparryable, unerring, and phasing. Consumes expertise (Warlord)
A32: Major 6 | B32: =COUNTA(C32:FF32)/1.6 -> 14.375 | C32: Lay of the Land – Ranged attack that enhances dodge of team based on aim | W32: Desperation Shot – Ranged attack with pinpoint that consumes advantage. Consumes less advantage if Bandit is alone (Bandit) | X32: Discrete Dagger – Ranged attack with insidious that causes untyped bleed (Cutthroat) | AQ32: Mammoth Consequences – Melee attack against all enemies and generate rage, but take damage at beginning of next turn (Brute) | AR32: Lingering Fury – Melee attack and enhance next damage by rage (Raider) | AS32: Bloodlust Quicken – Melee attack that quickens Berserker based on bloodlust (Berserker) | AT32: Double Attack – Two melee attacks that add together before comparison to defense (Marauder) | AU32: Shield Smash — Prepared melee attack. Damage and clobbering value enhanced by blocks made since preparation. (Viking) | AV32: Endless Beating – Prepared melee attack. This attack stays prepared if you are raging (Vandal) | AW32: Furious Drive – Melee attack that enhances speed on critical, stacking. Increased critical chance based on rage and can be used berserk (Fury) | AX32: Health Stealing Bite – Melee attack with drain that also applies heal siphon to target (Cannibal) | AY32: Grudgebearer – Attack with defense weakness against enemy that attacked unit turn before (Destroyer) | AZ32: Raging Charge – Mounted melee attack enhanced by rage (Beastlord) | BA32: Precise Strike, Greater – Melee attack with increased accuracy and critical chance, but delays gladiator (Gladiator) | BB32: Duel Bond – Melee attack that grants enhanced damage against target if it attacks a different ally before next turn (Duelist) | BC32: Phalanx Overrun – Melee attack against row with damage enhanced by ready allies (Phalanx) | BD32: Elusive Succession – Dual-wield attack that grants Dervish enhanced dodge after second attack based on dual-wield attack speed. (Dervish) | BE32: Final Fighter – Melee attack requiring alone that enhances counter chance and parry based on damage (Fencer) | BF32: Lancing Formation – Melee attack against row, procs the same attack against the target behind, with chance for behind that (Lancer) | BG32: Bushido Justice – Melee attack with justice against enemy. Enemy attacks Samurai first and then its counter is set to 0 (Samurai) | BH32: Stamina Blow – Melee attack boosted by endurance (Dreadnaught) | BI32: Onslaught Feint – Enhances parry chance of swashbuckler and compels target to attack her. If she parries the target before next turn, she attacks the target twice. Requires expertise (Swashbuckler) | BJ32: Expert Instruction – Enhances damage of ally’s next attack based on total expertise (Warlord)
A33: Major 7 | B33: =COUNTA(C33:FF33)/1.6 -> 14.375 | C33: Quickening Aim – Ranged attack against single target that consumes aim to quicken self | W33: Desperation Trap – Ranged trap with bleed. Greatly delays bandit unless he is endangered (Bandit) | X33: Distracting Duo – Two melee attacks against a target. First attack causes flanked. Consumes advantage (Cutthroat) | AQ33: Opening Blow – Melee attack against enemy with full health (Brute) | AR33: Looming Threat – Melee attack against compelled target. Switches target of compel (Raider) | AS33: Brutal Exertion – Melee attack with lower accuracy that lowers defense. If attack misses, take damage and reattempt once (Berserker) | AT33: Dual Rampage – Melee attack requiring dual wielding that deals additional damage for each enemy killed in battle (Marauder) | AU33: Shield Throw – Prepared melee attack against all enemies. Enhanced by blocks made since preparation. (Viking) | AV33: Escalating Violence – Melee attack with amplification that is always countered (Vandal) | AW33: Killing Amplification – Melee attack that provides amplification with any other ability on kill (Fury) | AX33: Mana Consumption – Melee attack that drains mana from target. Requires the Cannibal to have received enough healing (Cannibal) | AY33: Massive Burst – Melee attack that damages all enemies if it deals massive damage (Destroyer) | AZ33: Rampant Umbrage – Melee attack that deals damage based on overkill of previous attack (Beastlord) | BA33: Risky Positioning – Melee attack with blessed accuracy and damage, but causes the gladiator to be flanked (Gladiator) | BB33: Dueling Strike – Melee attack that compels target to attack duelist and compels duelist to attack target. Quickens Duelist (Duelist) | BC33: Phalanx Unity – Melee attack that quickens and enhances block chance of all ready allies based on number of ready allies (Phalanx) | BD33: Expert Onslaught – Consumes all expertise to make random melee attacks based on the amount of expertise (Dervish) | BE33: Gap in the Armor – Melee attack with pinpoint accuracy (Fencer) | BF33: Lancing Overrun – Melee attack that causes prone, procs the same attack against the target behind, with chance for behind that (Lancer) | BG33: Bushido Perseverance – Melee attack against enemy. Each enemy in front row attacks Samurai first and damage enhanced by total enemies’ damage (Samurai) | BH33: Unstoppable Advance – Melee attack that causes additional delay based on unit’s defense (Dreadnaught) | BI33: Parried Fury – Series of three melee attacks that follow a parry (Swashbuckler) | BJ33: Galvanizing Blow – Melee attack that enhances damage of all allies for their next attack based on expertise (Warlord)
A34: Major 8 | B34: =COUNTA(C34:FF34)/1.6 -> 14.375 | C34: Rapid Vow – Prepared ranged attack that determines target on preparation. Quickens scout on preparation and on use | W34: Final Poison Shot – Ranged attack that uses all poisons. Requires endangered (Bandit) | X34: First Needle – Melee attack that starts stacking bleed, but does not stack itself. Consumes advantage (Cutthroat) | AQ34: Ruthless Cascade – Melee attack that cascades if it deals ruthless damage. This effect can repeat multiple times, but each enemy can only be targeted once (Brute) | AR34: Precipitous Cleave – Melee attack with sudden; quickens raider if she is raging (Raider) | AS34: Callous Blow – Melee attack that grants barrier to self and can only be used berserk (Berserker) | AT34: Eviscerating Rend – Two melee attacks against a single target. Causes heartstrike if both attacks hit (Marauder) | AU34: Shield Wall – Prepared melee attack against enemy row. Enhanced by blocks made since preparation. (Viking) | AV34: Ferocious Spree – Melee attack with amplification that consumes increasing amounts of rage (Vandal) | AW34: Quickening Purity – Melee attack with increasing quicken effect, but it reduces defense and dodge. This can be disrupted. (Fury) | AX34: Maximum Satiation – Maximized melee attack requiring Cannibal has been healed enough (Cannibal) | AY34: Massive Cascade – Melee attack that cascades if attack deals massive damage. This effect can repeat multiple times, but each cascade must target a different enemy (Destroyer) | AZ34: Rending Force – Melee attack that lowers defense of all enemies by overkill (Beastlord) | BA34: Shattering Sequence – Two shattering melee attacks against a single target consuming expertise (Gladiator) | BB34: End the Duel – Disarm target enemy, then attack it based on expertise. Consumes all expertise (Duelist) | BC34: Puncturing Piercer – Melee attack with penetrate that causes defense weakness on critical (Phalanx) | BD34: Momentum Onslaught – Melee attack that strikes a number of times based on momentum, alpha (Dervish) | BE34: Penetrating Pinpoint – Melee attack with pinpoint, then penetrates based on pinpoint. Prepared (Fencer) | BF34: Long Pierce – Melee attack that can strike any row (Lancer) | BG34: Bushido Provocation – Melee attack against enemy that compels. Enemy attacks Samurai first and damage enhanced by enemy’s damage (Samurai) | BH34: Unstoppable Blow – Melee attack deals extra damage based on unit’s defense (Dreadnaught) | BI34: Parried Surge – Melee attack versus front row following a parry (Swashbuckler) | BJ34: Powerful Exploit – Melee attack that consumes all expertise to increase damage. Requires a minimum level of expertise (Warlord)
A35: Major 9 | B35: =COUNTA(C35:FF35)/1.6 -> 14.375 | C35: Scouted Arrow Burst – Ranged attack against all enemies. Deals less damage and requires aim if not first turn | W35: Last Blood – Culling melee attack requiring Bandit is alone (Bandit) | X35: Ghost Strike – Melee attack with heartstrike that requires intangible (Cutthroat) | AQ35: Stunning Consequences – Melee attack with stun and generate rage, but take damage at beginning of next turn (Brute) | AR35: Raid Preparation – Melee attack with low accuracy that enhances damage and dodge on miss (Raider) | AS35: Feckless Blow – Melee attack that causes flanking on berserker (Berserker) | AT35: Off-hand Preparations – Dual wield melee attack that compels target and enhances counter chance (Marauder) | AU35: Steel Suffering – Melee attack that causes untyped bleed and defense weakness (Viking) | AV35: Intimidating Charge – Melee attack with momentum that causes frightened, requires rage (Vandal) | AW35: Ranged Purity – Ranged attack with increasing damage, but this resets if the barbarian attacks a close enemy. (Fury) | AX35: Rabid Bite – Melee attack with untyped bleed and wound (Cannibal) | AY35: Massive Corruption – Melee attack that converts damage to corrupt if it is massive damage (Destroyer) | AZ35: Riven Force – Melee attack that lowers damage of all enemies based on overkill (Beastlord) | BA35: Stunning Gambit – Melee attack that stuns target. Higher chance to be countered and gladiator becomes stunned if countered (Gladiator) | BB35: Expert Blow, Enhanced – Melee attack that requires expertise (Duelist) | BC35: Shield and Strike – Melee attack enhanced by shield following block (Phalanx) | BD35: Quick Succession – Dual-wield attack that quickens the Dervish after second attack based on dual-wield attack speed. (Dervish) | BE35: Penetrating Thrust – Melee attack with penetration on critical (Fencer) | BF35: Long Skewer – Melee attack against column with bleed on critical (Lancer) | BG35: Double Bushido Strike – Two melee attack against enemy. Enemy attacks Samurai first and damage enhanced by enemy’s damage (Samurai) | BH35: Unstoppable Collateral – Melee attack against single enemy that also damage all enemies based on defense (Dreadnaught) | BI35: Strike Off Balance – Melee attack that prevents target from countering until its next turn. Requires expertise (Swashbuckler) | BJ35: Provocation Blow – Melee attack that provokes target and enhances parry chance until target acts (Warlord)
A36: Major 10 | B36: =COUNTA(C36:FF36)/1.6 -> 14.375 | C36: Scouted Chink – Full penetration ranged attack if first attack of battle. Can proc full penetration with ranged attack after | W36: Mana Crash – Ranged attack that also deals mana damage. If target ends with zero mana, generates combat advantage (Bandit) | X36: Intangible Advantage – Ranged attack requiring intangible. Generates advantages and disenchants intangible at end of attack (Cutthroat) | AQ36: Tiring Delay – Melee attack that further delays target based on their tired value (Brute) | AR36: Reckless Clobber – Clobbering melee damage. Prevents Raider from using active defenses and counters until next turn (Raider) | AS36: Great Cleave – Melee attack versus single that damages enemies in same row as target against combined defense of primary and secondary target (Berserker) | AT36: Onslaught Rampage – Dual-wield melee attack that makes an additional attack on a random enemy for each enemy killed in battle (Marauder) | AU36: Taunting Axe – Melee attack with damage increased by rage that taunts enemies (Viking) | AV36: Raging Cleave – Large weapon attack that strikes target enhanced by rage and adjacent enemies based on rage (Vandal) | AW36: Sacrifice Purity – Melee attack with increasing damage and backbiting, but this ends if the barbarian is healed. (Fury) | AX36: Sacrificial Consumption – Melee attack with backbiting. Requires having been healed enough (Cannibal) | AY36: Massive Destruction – Melee attack that lowers all enemy defense if it deals massive damage (Destroyer) | AZ36: Trample Underfoot – Mounted melee attack versus column. Each enemy counters the beastlord, but the beastlord generates extra rage for the damage. On a critical, enemies are knocked prone (Beastlord) | BA36: Unremitting Slash – Attack that stays prepared if it misses, lower accuracy (Gladiator) | BB36: Expert Penetration – Melee attack with penetration based off expertise (Duelist) | BC36: Shield Breaker – Melee attack that lowers target’s block chance (Phalanx) | BD36: Shearing Exploit – Damage all and lower defense based on expertise, consumes all expertise (Dervish) | BE36: Pinpoint Parries – Melee attack with pinpoint that enhances parry based on pinpoint. Requires expertise (Fencer) | BF36: Mount Trade Holsteiner – Summons a trade holsteiner mount (Lancer) | BG36: Double Slash – Two melee attacks with reduced accuracy. Requires dual-wielding (Samurai) | BH36: Unstoppable Critical – Melee attack that deals additional damage on critical based on defense. Delays self (Dreadnaught) | BI36: Tripping Blow – Melee attack that has a chance to cause prone while having lower accuracy. Requires expertise (Swashbuckler) | BJ36: Rallying Blow – Melee attack that quickens all allies based on expertise (Warlord)
A37: Major 11 | B37: =COUNTA(C37:FF37)/1.6 -> 14.375 | C37: Scouted Shot – Ranged attack with momentum. Generates aim if first turn | W37: Ranged Backstab – Ranged attack against flanked enemy with pinpoint (Bandit) | X37: Precise Cut – Melee attack with enhanced accuracy that causes untyped bleed on critical. Requires preparation (Cutthroat) | AQ37: Unbalancing Attack – Melee attack that lowers Brute’s dodge until next turn (Brute) | AR37: Reckless Flames – Fire damage versus all enemies. Prevents Raider from using active defenses and counters until next turn (Raider) | AS37: Raging Exertion – Melee attack based enhanced by rage. If this attack misses, take damage and repeat. (Berserker) | AT37: Vicious Tumult – Melee attack with bloodlust with increased accuracy and critical chance based on bloodlust, consumes rage (Marauder) | AU37: Taunting Shield – Melee attack that enhances block chance and taunts enemies (Viking) | AV37: Ruthless Strike – Ruthless melee attack requiring rage (Vandal) | AW37: Staggering Fury – Melee storm with delay on each hit (Fury) | AX37: Unsated Hunger – Prepared melee attack with life drain that becomes unprepared if Cannibal is healed (Cannibal) | AY37: Massive Stupidity – Melee attack that disrupts and deals mana damage to all enemies if it deals massive damage (Destroyer) | AZ37: Ultimate Rage Strike – Consume all remaining rage and end rage form immediately to make massive attack (Beastlord) | BA37: Wild Hope – Melee attack with low accuracy that heals self on hit and damages self on miss (Gladiator) | BB37: Inevitable Blade – Melee attack. On miss, gain enhanced accuracy and damage with next melee attack. Requires expertise (Duelist) | BC37: Shield Press – Melee attack with stun and disrupt following block (Phalanx) | BD37: Stunning Succession – Dual-wield attack that stuns target on second hit based on dual-wield attack speed. (Dervish) | BE37: Pinpoint Surge – Melee attack that delays all other enemies based on pinpoint value. Requires expertise (Fencer) | BF37: Run Through – Melee attack versus a column that requires mana (Lancer) | BG37: Expert Decimation – Melee attack with decimation based on expertise, prepared (Samurai) | BH37: Unstoppable Destruction – Melee attack that lowers defense of target based on Dreadnaught’s defense. Requires preparation (Dreadnaught) | BI37: Unerring Stroke – Unerring melee attack that consumes expertise (Swashbuckler) | BJ37: Rallying Riposte – Prepared ability that counters following parry and quickens all allies (Warlord)
A38: Major 12 | B38: =COUNTA(C38:FF38)/1.6 -> 10.625 | C38: Speed Shot – Ranged attack that requires momentum and grants aim and deals extra damage based on momentum | W38: Sniper Shot 3 – Ranged attack that consumes all advantage for extra damage, up to 6 combat advantage. Gains critical chance based on combat advantage (Bandit) | X38: Thousand Needles – Storm ranged attack that afflicts targets with individual stacks of stacking bleed. Consumes advantage (Cutthroat) | AQ38: Unguarded Advance – Melee attack that lowers unit’s defense until next turn (Brute) | AR38: Reckless Rampage – Three melee attacks against random enemies. Prevents Raider from using active defenses and counters until next turn (Raider) | AT38: Wave of Bloodlust – Melee attack against all with bloodlust (Marauder) | AU38: Undertow Blow – Prepared unblockable water melee attack that delays and causes water bleed (Viking) | AV38: Ultimate Violence – Melee attack consuming rage that deals maximum damage (Vandal) | AW38: Storm Purity – Melee attack. Each use makes an additional random attack, each with backbite, but this ends if the same enemy is hit twice in a turn. (Fury) | AX38: Vampiric Bite – Melee attack with drain requiring rage (Cannibal) | AY38: Massive Suffering – Massive damage melee attack with backbiting (Destroyer) | BA38: Wound Striker – Melee attack against target wounded enemy (Gladiator) | BB38: Off-Balance Disarm – Melee attack with a chance to disarm target enemy. Requires flanked (Duelist) | BC38: Shield Rush – Melee attack with chance to cause prone based on block chance (Phalanx) | BD38: Whirling Blades – Dual-wielding attack that quickens the dervish and damages enemies adjacent to the target (Dervish) | BE38: Solo Strike – Melee attack with pinpoint requiring alone (Fencer) | BF38: Shatterlance – Melee attack with shattering and momentum, deals damage to all based on momentum (Lancer)
A39: Major 13 | B39: =COUNTA(C39:FF39)/1.6 -> 5 | C39: Sudden Shot – Ranged attack with sudden | X39: Toxic Blood Slash – Melee attack with venomous that further enhances bleeding poisons (Cutthroat) | AR39: Reckless Reaper – Melee attack with ruthless against single enemy. Prevents Raider from using active defenses and counters until next turn (Raider) | AU39: Violent Push – Melee attack that causes prone to enemies behind target (Viking) | AY39: Weapon Fracture – Melee attack with shattering that can disarm the target (Destroyer) | BB39: Pinpoint Stab – Melee attack with bleed based off pinpoint. Requires expertise to use (Duelist) | BC39: Spear and Shield – Melee attack with reduced accuracy and ranged 1 that enhances block chance (Phalanx) | BD39: Zephyr Strike – Melee attack that quickens all on critical, critical modifier affects quicken (Dervish)
A40: Major 14 | B40: =COUNTA(C40:FF40)/1.6 -> 0.625 | C40: Supplemented Shot – Ranged attack. Causes the target to take damage on the next x times it misses. Consumes aim
A41: Major 15 | B41: =COUNTA(C41:FF41)/1.6 -> 0
A42: Move 1 | B42: =COUNTA(C42:FF42)/1.6 -> 11.25 | C42: Aimed Pursuit – Follows hit, quickens ally and enhances accuracy based on aim on target | W42: Delaying Poison – Provides Rogue with a poison that delays target (Bandit) | X42: Blood in the Eyes – Blind enemy suffering from bleed (Cutthroat) | AQ42: Benefit from Consequences – Enhance defense based on damage taken at beginning of turn (Brute) | AR42: Glancing Guarantee – Melee attack that deals only glancing damage (Raider) | AS42: Berserk Jab – Melee attack that requires berserk (Berserker) | AT42: Counter Rampage – Guarantee counter against next attack. Requires enough enemies killed in battle, and enhanced for total enemies killed in battle (Marauder) | AU42: Last Stand – Gain enduring. Backbiting (Viking) | BA42: Claim Glory – Prepared reaction to any enemy using a compel or provoke ability. Melee attack against enemy (Gladiator) | BB42: Disarming Counter – Duelist has a chance to disarm on counters until next turn (Duelist) | BC42: Defensive Exploit – Gains damage shield and increased counter chance based on expertise, consumes all expertise (Phalanx) | BD42: Aura of Blades – Grants Dervish retaliation which increases when quickened. Requires expertise (Dervish) | BE42: Blade Flow – Enhance accuracy following parry (Fencer) | BF42: Dodge Stratagem – Spend expertise when next attacked to guarantee dodge (Lancer) | BG42: Accelerating Taunt – Taunts enemy and quickens self when damaged (Samurai) | BH42: Armor Stratagem – Spend expertise when next attacked to turn attack into glancing blow (Dreadnaught) | BI42: Control Exploit – Delay target and lower dodge and defense based on expertise, consumes all expertise (Swashbuckler) | BJ42: Animated Exploit – Consumes all expertise to quicken all allies. Requires a minimum level of expertise (Warlord)
A43: Move 2 | B43: =COUNTA(C43:FF43)/1.6 -> 11.25 | C43: Danger Warning – Grants all allies enhanced dodge until next turn | W43: Desperation Mana – Drains mana from all enemies and grants it to bandit. Advantage cost reduced if alone (Bandit) | X43: Blood Thinner – Grants Cutthroat poison that applies stacking bleed to target (Cutthroat) | AQ43: Great Stomp – Delay all enemies. If any enemy would go below 0 timer, knock it prone (Brute) | AR43: Rage Shield – Consume rage to guarantee block against next attack. Also stuns attacker (Raider) | AS43: Berserk Patience – Counter next attack. Requires berserk (Berserker) | AT43: Deadly Persistence – Follows a kill with a melee attack (Marauder) | AU43: Savage Shield – Melee attack with shield following block. Consumes rage (Viking) | BA43: Counter Gambit – Guaranteed counter against next attack, but next attack is a critical hit versus the Gladiator (Gladiator) | BB43: Disarming Dominance – Melee attack following disarm against the disarmed (Duelist) | BC43: Expert Blocking – Enhances block chance of the target. This enhancement is increased by expertise if user is a fighter (Phalanx) | BD43: Critical Momentum – Enhances critical chance based on momentum until end of turn (Dervish) | BE43: Blade Stratagem – Spend expertise when next attacked to guarantee parry (Fencer) | BF43: Expert Riding – Quicken and enhance damage of mount based on expertise. Consumes expertise (Lancer) | BG43: Amplified Dodge – Enhance dodge and counter chance. Amplified. Consumes expertise (Samurai) | BH43: Defensive Provocation – Provoke enemy and reflect damage based on amount defended (Dreadnaught) | BI43: Expert Dodge – Enhances dodge of an ally. Enhanced by expertise (Swashbuckler) | BJ43: Expediting Taunt – Provoke enemy and quicken allies (Warlord)
A44: Move 3 | B44: =COUNTA(C44:FF44)/1.6 -> 11.25 | C44: Momentum Arrow – Ranged attack requiring momentum | W44: Endangering Advantage – Spot an endangered enemy to gain advantage (Bandit) | X44: Bloodlet – Melee attack following a bleed (Cutthroat) | AQ44: Guardian Consequences – Taunt all enemies, gain damage shield, and generate rage, but take damage and lose damage shield at beginning of next turn (Brute) | AR44: Reckless Haste – Gain haste based on block chance and amount. Prevents active defenses and counters for same duration (Raider) | AS44: Berserker Strength – Enhance damage for a period. Requires berserk (Berserker) | AT44: Doubled Counter – Next counter attacks with both weapons. Requires dual-wielding (Marauder) | AU44: Shield Sacrifice – Enhance block chance until next turn. Costs life. (Viking) | BA44: Face the Coward – Purges all allies and field of aversion and scorn effects. (Gladiator) | BB44: Expert Retaliation – Grants untyped retaliation based off expertise (Duelist) | BC44: Phalanx Guard – Grant damage shield to all ready allies enhanced by number of ready allies (Phalanx) | BD44: Expert Speed – Enhances speed of an ally, increased by expertise (Dervish) | BE44: Expert Accuracy – Enhances accuracy of the target, increased by expertise (Fencer) | BF44: Intercept Charge – Counter next attack with damage enhanced by target’s momentum (Lancer) | BG44: Armor Rend – Follows dual-wield attack. Lowers enemy defense (Samurai) | BH44: Expert Prevention – Prevent portion of next damage based on expertise. Consumes percentage of expertise (Dreadnaught) | BI44: Parried Understanding – Unparryable melee attack, follows a parry, requires expertise (Swashbuckler) | BJ44: Expert Education – Refreshes and updates all expert training abilities on team (Warlord)
A45: Move 4 | B45: =COUNTA(C45:FF45)/1.6 -> 11.25 | C45: Scouted Positions – Flanks and delays all enemies as first action. Otherwise flanks and delays single enemy | W45: Nothing Left at All – Prepared ability that grants intangible. Requires alone (Bandit) | X45: Critical Hematoma – Follow a critical hit with afflicting target with untyped bleed (Cutthroat) | AQ45: Purging Consequences – Purge affliction from Brute and generate rage, but take damage at beginning of next turn (Brute) | AR45: Reckless Impact – Delay all enemies. Prevents Raider from using active defenses and counters until next turn (Raider) | AS45: Contagious Temper – Berserks all allies and enhances damage for their next attack. Requires berserk, can be used berserk (Berserker) | AT45: Rage Counter – Counter next attack with damage enhanced by rage. Requires and consumes rage (Marauder) | AU45: Shield Smash – Melee attack. Prevents blocking until next turn, based on usual block chance and block amount (Viking) | BA45: Fist Stratagem – Spend expertise when next attacked to guarantee counter (Gladiator) | BB45: Instant Counter – On next counter, instead gain an immediate turn (Duelist) | BC45: Respond for Me – Next time phalanx takes a critical hit, she quickens and enhances damage of all allies (Phalanx) | BD45: Final Sprint – Sudden melee attack that consumes haste (Dervish) | BE45: Flanking Response – Prepared reaction to become flanked. Melee attack against flanker and ignore flanked (Fencer) | BF45: Lancing Follow-Up – Melee attack from mount against all enemies affected by lancing ability (Lancer) | BG45: Bushido Counter – Counter next attack against Samurai, with counter benefiting from damage enemy deals. Delays Samurai (Samurai) | BH45: Fortified Stomp – Delay all enemies. Requires fortify (Dreadnaught) | BI45: Penetrating Feint – Enhances parry chance of swashbuckler and compels target to attack her. If she parries the target before next turn, she attacks the target with penetrating. Requires expertise and delays Swashbuckler (Swashbuckler) | BJ45: Invigorating Exploit – Consumes all expertise to enhance damage of all allies. Requires a minimum level of expertise (Warlord)
A46: Move 5 | B46: =COUNTA(C46:FF46)/1.6 -> 11.25 | C46: Scouted Preparations – Provides initial bonuses as a period enhancement to all allies on first turn. Otherwise only provides them until next turn | W46: Spirotoxin – Grants the target an air damage poison to their attacks (Bandit) | X46: Etherealness — costs mana, grants any hero intangible (Cutthroat) | AQ46: Stomp – Melee attack against prone enemy (Brute) | AR46: Shield Clobber – Melee attack using shield with clobber (Raider) | AS46: Extra Exertion – Take damage and repeat exertion ability that missed twice. (Berserker) | AT46: Rampage Haste – Grants Marauder haste based on the number of enemies killed in battle (Marauder) | AU46: Shield of Superstition – Enhance magic resistance and lower block chance until next turn (Viking) | BA46: Parry Stun – Follows parrying since last turn. Stuns target that was parried (Gladiator) | BB46: Penetrating Counter – Counter next attack with penetration (Duelist) | BC46: Shield Stratagem – Spend expertise when next attacked to guarantee block (Phalanx) | BD46: Self-Propulsion – Gain haste following critical (Dervish) | BE46: Focused Deflection – Consume focus when next attacked to guarantee parry (Fencer) | BF46: Long Spear – Lancer can counter at range, but has reduced chance to counter. Toggled (Lancer) | BG46: Disarming Response – Prepared ability. Disarms enemy in response to enemy failing to disarm Samurai (Samurai) | BH46: Receive the Charge – Enemy deals less damage based on its own momentum (Dreadnaught) | BI46: Pinpoint Feint – Enhances parry chance of swashbuckler and compels target to attack her. If she parries the target before next turn, she attacks the target with pinpoint. Requires expertise and delays Swashbuckler (Swashbuckler) | BJ46: Parry Shards – Damage all enemies on next parry. If this parries a critical attack, also inflict bleed (Warlord)
A47: Move 6 | B47: =COUNTA(C47:FF47)/1.6 -> 11.25 | C47: Speed Screen – Grants haste until next turn and generates aim, must be used as last action | W47: Sunlens Toxin – Provides Bandit with poison that causes light exposure (Bandit) | X47: Pneumotoxin – Poison that adds water bleeds to attacks (Cutthroat) | AQ47: Unbroken Flesh – Brute gains fortification; requires full health (Brute) | AR47: Shield Recklessness – Melee attack following block. Prevents all active defenses until next turn (Raider) | AS47: Vicious Rampage – Enhance damage and speed for a period. Become fatigued when buff is lost (Berserker) | AT47: Rampage Hostility – Enhances damage based on number of enemies killed. Consumes rage (Marauder) | AU47: Shield to Shield – Prepared ability that triggers on block. Prevent target enemy from blocking for a period (Viking) | BA47: Rip Armor – Lower defense of target stunned enemy (Gladiator) | BB47: Shield Disarm – Prevent disarmed enemy from blocking while it is disarmed (Duelist) | BC47: Turtle Command – All allies gain enhanced blocking until their next turn (Phalanx) | BD47: Tangling Momentum – Delays target based on momentum (Dervish) | BE47: Pinpoint Retaliation – Gain untyped retaliation based on pinpoint value of last attack (Fencer) | BF47: Mount’s Momentum – Grants the Lancer momentum at the beginning of her next turn based on her mount (Lancer) | BG47: Evasive Taunt – Taunts enemy and enhances dodge based on expertise (Samurai) | BH47: Unstoppable Purge – Enhances Dreadnaught defense, then purges based on defense (Dreadnaught) | BI47: Provoking Feint – Provokes all enemies to attack the swashbuckler. Enhances her parry chance and quickens her with each parry (Swashbuckler) | BJ47: Target Order – Compel target ally and increase their time by half the time to act (Warlord)
A48: Move 7 | B48: =COUNTA(C48:FF48)/1.6 -> 5 | AT48: Rampage Speed – Quickens Marauder based on number of enemies killed in battle (Marauder) | AU48: Splash Shield – Prepared ability that deals water damage to front row on next block (Viking) | BA48: Sand in the Eyes – Blinds the target (Gladiator) | BE48: Riposte – Melee attack that follows a parry (Fencer) | BF48: Spiked Barding – Mount gains retaliation based on expertise (Lancer) | BG48: Expert Resistance – Enhances elemental resistance of the target. This enhancement is increased by expertise if user is a fighter (Samurai) | BH48: Unstoppable Shield – Enhance defense, then gain damage shield based on defense (Dreadnaught) | BJ48: War Party – Quickens all allies and enhances damage, requires expertise and preparation (Warlord)
A49: Move 8 | B49: =COUNTA(C49:FF49)/1.6 -> 1.25 | BF49: Steady Taunt – Taunts enemy and prevents Lancer from taking delays until next turn (Lancer) | BG49: Fuel the Strike – Target enemy attacks unit. Unit gains enhanced damage to next attack based on damage taken (Samurai)
A50: Move 9 | B50: =COUNTA(C50:FF50)/1.6 -> 0
A51: Move 10 | B51: =COUNTA(C51:FF51)/1.6 -> 0
A52: Minor 1 | B52: =COUNTA(C52:FF52)/1.6 -> 14.375 | C52: Momentous Initiative – Gain initial bonuses until beginning of next turn. Requires momentum | W52: Accuracy Advantage – Consumes some advantage to gain accuracy to next attack based on advantage (Bandit) | X52: Anatomic Knowledge – Increase damage of next bleed effect (Cutthroat) | AQ52: Greater Consequences – Increase effect of consequence ability and take more damage from it at beginning of next turn (Brute) | AR52: Blue Warpaint – “I’m already dead. I will not yield.” – Grants immunity to slow and enhanced water resistance (Raider) | AS52: Angry Vengeance – Enhance damage each time berserker is attacked before next turn (Berserker) | AT52: Berserk Response – Enhance counter chance until next turn. Requires berserk (Marauder) | AU52: Berserk Block – Guaranteed block versus next attack. Requires berserk (Viking) | AV52: Brink of Eternity – Grants Vandal enduring. Only becomes available for one turn immediately after dealing enough damage (Vandal) | AW52: Adrenaline – Quicken self and enhance damage, only usable endangered (Fury) | AX52: Hungry Rage – The Barbarian drains life with melee attacks while in this rage. When this rage ends, the Barbarian becomes wounded. (Cannibal) | AY52: Destruction Rage – The Barbarian lowers enemy defense on attacks and has increased weakness power while in this rage. When this rage ends, the Barbarian loses all enchantments and becomes forsaken. (Destroyer) | AZ52: Final Defender – Gain rage and enhance defense. Requires being alone (Beastlord) | BA52: Critical Expertise – Generate expertise following a critical (Gladiator) | BB52: Advance on Disarmed – Gain expertise if an enemy is disarmed (Duelist) | BC52: Exhaustive Defense – Gain fortified in return for becoming tired (Phalanx) | BD52: Bounding Advance – Next melee attack can be used at range (Dervish) | BE52: Accurate Line Up – Enhance accuracy of next attack (Fencer) | BF52: Bleeding Momentum – Damage all enemies based on momentum (Lancer) | BG52: Dodge Stance – Gains expertise whenever the fighter dodges an attack. Increases dodge (Samurai) | BH52: Dig In – Prevents movement effects until next turn and enhances damage of next attack based on movement effects (Dreadnaught) | BI52: Basic Feint – Enhances parry chance of swashbuckler and compels target to attack her. If she parries the target before next turn, she attacks the target. Requires expertise and delays the Swashbuckler (Swashbuckler) | BJ52: Aggressive Propulsion – Quicken based on damage of next attack (Warlord)
A53: Minor 2 | B53: =COUNTA(C53:FF53)/1.6 -> 14.375 | C53: Perilous Ground – Follows ranged attack, flanks target | W53: Advantageous Loneliness – Generates one advantage, requires alone (Bandit) | X53: Bloody Missteps – Flank all bleeding enemies. Omega (Cutthroat) | AQ53: Green Warpaint – Grants immunity to wound and enhanced earth resistance (Brute) | AR53: Reckless Recovery - Prepared ability. If the Raider takes a critical hit while Reckless, remove the Reckless status. (Raider) | AS53: Berserk Rage – The Barbarian gains untyped retaliation while in this rage. When this rage ends, the Barbarian becomes flanked. (Berserker) | AT53: Marauder’s Rage – The Barbarian gains increased critical chance and critical damage while in this rage. When this rage ends, the Barbarian becomes fragile. (Marauder) | AU53: Block and Respond – Quickens unit on block until next turn (Viking) | AV53: Brink of Speed – Quicken Vandal. Only becomes available for one turn immediately after dealing enough damage (Vandal) | AW53: Black Warpaint – Grants immunity to illuminate and enhanced dodge (Fury) | AX53: Rage Consumption – Generate rage. Requires having been healed enough (Cannibal) | AY53: Greater Mass – Increase massive damage values until end of turn (Destroyer) | AZ53: Final Rage – The Barbarian gains massive damage bonuses and enduring while in this rage. When this rage ends, the Barbarian dies. (Beastlord) | BA53: Critical Stance – Enhances critical chance, gladiator generates expertise when she criticals (Gladiator) | BB53: Counter Stance – Enhances counter chance, duelist generates expertise when she counters (Duelist) | BC53: Healthy Block – Guaranteed block against next attack. Requires full health and delays Phalanx (Phalanx) | BD53: Double Accuracy – Enhance accuracy of next dual-wield attack (Dervish) | BE53: Battle Flow – Quicken following a parry (Fencer) | BF53: Prepare Momentum – Lose any current clock above max and regain at beginning of next turn (Lancer) | BG53: Dual Wield Expertise – Generate expertise following dual-wield attack (Samurai) | BH53: Expert Vitality – Gain regeneration based on expertise, consuming all expertise (Dreadnaught) | BI53: Delaying Feint – Enhances parry chance of swashbuckler and compels target to attack her. If she parries the target before next turn, she delays the target. Requires expertise (Swashbuckler) | BJ53: Enduring Parry – Warlord gains enduring after parrying until next turn. Prepared (Warlord)
A54: Minor 3 | B54: =COUNTA(C54:FF54)/1.6 -> 14.375 | C54: Scouted Aim – Alpha, generates aim. Also enhances accuracy and quickens self as first action | W54: Desperation Hide – Gain hidden, requires being alone (Bandit) | X54: Extended Bleed – Refreshes bleeds on the target (Cutthroat) | AQ54: Share Consequences – The first target the Brute attacks takes the same damage she did from consequences (Brute) | AR54: Reckless Speed – Quickens Raider. Prevents Raider from using active defenses and counters until next turn (Raider) | AS54: Combat Surge – Melee attack. Requires berserk. Follows missing with an attack (Berserker) | AT54: Off-hand Counter – Guaranteed counter with off-hand weapon against next melee attack (Marauder) | AU54: Brown Warpaint – Grants immunity to compel and avert and resistance versus delays (Viking) | AV54: Endless Rage – The Barbarian gains more rage from abilities and effects, while abilities that consume rage have greater effect while in the rage. When this rage ends, the Barbarian becomes unable to gain rage. (Vandal) | AW54: Dedicated Speed – Quicken next turn but are compelled against same target (Fury) | AX54: Sated Purge – Prepared ability that activates when Cannibal has been healed enough. Purges afflictions (Cannibal) | AY54: Grey Warpaint – “I paint my skin like stone and steel.” – Grants immunity to fragile and enhanced defense (Destroyer) | AZ54: Form of the Bull – The Beastlord gain ongoing enhanced defense. The Beastlord also gains fortify on critical hits. Consumes rage. (Beastlord) | BA54: Intimidation Gambit – Either stuns all enemies or ends turn of gladiator, alpha (Gladiator) | BB54: Disarming Preparation – Increases chance to disarm, requires expertise (Duelist) | BC54: Phalanx Power – Enhance damage of all ready allies until end of their turn based on the number of ready allies (Phalanx) | BD54: Expert Sprint – Quicken self. Consumes expertise (Dervish) | BE54: Beat Blade – Reduce target parry chance (Fencer) | BF54: Response Expertise – Taunt enemy and gain expertise on counter (Lancer) | BG54: Lure to Disaster – Quicken all enemies and enhance counter chance until next turn based on enemies quickened (Samurai) | BH54: Greataxe Block – Dreadnaught can block with two-handed weapon until next turn. Enhances passive. Requires and enhanced by expertise (Dreadnaught) | BI54: Parried Opening – Enhance critical chance following parry (Swashbuckler) | BJ54: Expertise Observation – Alpha & Omega; gain expertise whenever an ally attacks until next turn (Warlord)
A55: Minor 4 | B55: =COUNTA(C55:FF55)/1.6 -> 14.375 | C55: Scouted Maneuvers - Quicken all and remove flanked as first action. Otherwise only quickens and removes flanked from a single target | W55: Desperate Foolishness — Minor, alone required, disrupts and damages mana (Bandit) | X55: Poisonous Advantage – Consume advantage to enhance potency of poison (Cutthroat) | AQ55: Solid Sarcophagy – Brutes damages himself and enhances defense (Brute) | AR55: Shield Counters – Instead of blocking, makes counters based on shield. Toggled ability (Raider) | AS55: Enraging Counter – Counter next attack. Requires endangered. Gain berserk after counter (Berserker) | AT55: Rampage Raid – Gain rage based on number of enemies killed in battle (Marauder) | AU55: Heavy Shield – Add clobber to next melee attack but lower block chance until next turn (Viking) | AV55: Exacerbate Rage – Vandal gains more rage from damage until next turn (Vandal) | AW55: Speed Rage – The Barbarian gains haste and increased speed while in this rage. When this rage ends, the Barbarian is slowed. (Fury) | AX55: Sickness Sarcophagy – Cannibal takes damage and enhances affliction resistance (Cannibal) | AY55: Massive Rage – Generate rage, follows massive damage (Destroyer) | AZ55: Form of the Eagle – The Beastlord gain ongoing enhanced dodge. The Beastlord can also make attacks and counters at range. Consumes rage. (Beastlord) | BA55: Prepared Correction – Gladiator reattempts the next attack that misses. Prepared and consumes expertise (Gladiator) | BB55: Learn from my Mistake – Generate expertise if previous attack was countered (Duelist) | BC55: Prepare Phalanx – Set the timer of all ready allies to 1000 minus their speed. Alpha, Omega. (Phalanx) | BD55: Rapid Dualwield – Increases dual-wield speed until end of turn. (Dervish) | BE55: Pinpoint Inspiration – Quicken self based on pinpoint value of last attack (Fencer) | BF55: Retaliation Stance – Grants the fighter untyped retaliation or enhances present retaliation, generates expertise through retaliation (Lancer) | BG55: Shame – Target enemy that missed since it's last turn gains damage weakness (Samurai) | BH55: Parry Defense – Enhance defense on each parry before next turn (Dreadnaught) | BI55: Parry Preference – Reduce dodge chance and increase parry until next turn (Swashbuckler) | BJ55: Strike Like Me – Enhance ally’s critical chance and damage with next attack. Follows critical (Warlord)
A56: Minor 5 | B56: =COUNTA(C56:FF56)/1.6 -> 14.375 | C56: Share Momentum – Quicken all allies based on momentum | W56: Desperate Evasion — alone required, increases dodge vs next attack (Bandit) | X56: Revel in Bloodshed – Spot at least one bleeding enemy for a chance to gain advantage. The more bleeding enemies, the more advantage that can be gained. (Cutthroat) | AQ56: Speed Consequences – Quicken self and generate rage, but take damage at beginning of next turn (Brute) | AR56: Take the Hit – Prevent all active defenses until next turn to raise defense based on active defenses (Raider) | AS56: Growing Fury – Gain rage. Requires berserk (Berserker) | AT56: Red Warpaint – “You can’t see my blood. I will not bleed.” – Grants to immunity to bleeds and enhanced fire resistance (Marauder) | AU56: Shield Fighting – Enhances damage and weakens block chance while active (Viking) | AV56: Fiery Rage – Vandal gains fire damage add to next attack this turn. Requires berserk (Vandal) | AW56: Speed through Pain – Deals damage to self to quicken (Fury) | AX56: Spread Satiation – Heal all allies and take damage based on healing. Requires Cannibal to have received enough healing. (Cannibal) | AY56: Massive Strength – Enhance damage, follows massive damage and based off massive damage (Destroyer) | AZ56: Form of the Panther – The Beastlord gain ongoing enhanced speed. The Beastlord also gains hidden at the beginning of her turns. Consumes rage. (Beastlord) | BA56: Reaping Gambit – Next attack deals reaping damage. On miss, it also deals reaping damage to Gladiator (Gladiator) | BB56: Parry Clang – Next parry distracts parried enemy (Duelist) | BC56: Shield Expertise – Follow a block with generating expertise (Phalanx) | BD56: Rended Speed – Quicken self following dual wield attack (Dervish) | BE56: Pinpoint Stance – Gains expertise based on hit roll beyond that necessary to hit. Increases accuracy and the value of pinpoint effects. Advanced Pinpoint Stance grants all attacks a natural pinpoint effect. (Fencer) | BF56: Shattered Lance – Disarm self to deal untyped bleed damage to all enemies. Follows attack (Lancer) | BG56: Suicide Stance – Increases offense and chance to be countered. Generates expertise when attacked. This does not require the samurai to be hit. (Samurai) | BH56: Singular Defense – Gain damage shield against next attack, then lower defense until next turn (Dreadnaught) | BI56: Parry Stance – Gains expertise whenever the fighter parries an attack. Increases parry chance (Swashbuckler) | BJ56: Urged to Act – Quicken compelled ally (Warlord)
A57: Minor 6 | B57: =COUNTA(C57:FF57)/1.6 -> 13.125 | W57: Seize on Critical – Enhance dodge following critical (Bandit) | X57: Shift into Position – Flank target following a miss (Cutthroat) | AQ57: Stoic Rage – Consume rage to ignore criticals until next turn (Brute) | AR57: Vengeance Rage – The Barbarian gains increased counter chance and damage while in this rage. When this rage ends, the Barbarian becomes unable to make counters and has reduced dodge. (Raider) | AS57: Orange Warpaint – Grants immunity to stun and enhanced air resistance (Berserker) | AT57: Roar of Triumph – Follows killing an enemy. Reduces defenses of all enemies for a period (Marauder) | AU57: Shield Rage – The Barbarian gains increased block chance and amount while in this rage. When this rage ends, the Barbarian loses all active defenses. (Viking) | AV57: Mystic Sarcophagy – Vandal deals damage to himself and enhances elemental resistance (Vandal) | AW57: Suffer for Savagery – Take damage to increase critical chance until end of turn (Fury) | AX57: Urge to Feed – Quicken after draining life based on life drained (Cannibal) | AY57: Massive Taunt – Provoke all enemies and gain damage shield following massive attack (Destroyer) | AZ57: Form of the Wolf – The Beastlord gain ongoing enhanced damage. The Beastlord also has a chance to cause prone when attacking flanked targets. Consumes rage. (Beastlord) | BA57: Turn to Enemy – Purges Gladiator of aversion (Gladiator) | BB57: Solid Grip – Cannot be disarmed until next turn (Duelist) | BC57: Shield Stance – Increases block chance, gain expertise on blocking (Phalanx) | BD57: Speed Stance – Gains expertise whenever the fighter is affected by a quicken effect. Increases the speed of the fighter (Dervish) | BE57: Push Response – Delay and flank next parried enemy. Requires expertise (Fencer) | BG57: Violence Meets Violence – Melee attack following being criticaled during turn. Requires dual wielding (Samurai) | BH57: Steady Footing – Cannot become knocked prone until next turn (Dreadnaught) | BI57: Sharp Edge Parry – Damages enemies when the swashbuckler parries before next turn (Swashbuckler) | BJ57: Warlord’s Stance – Gains expertise whenever allies act. Increases enhance effects and quickens on all allies. (Warlord)
A58: Minor 7 | B58: =COUNTA(C58:FF58)/1.6 -> 5.625 | W58: Seize on Dodge – Enhance critical chance following dodge. (Bandit) | AQ58: Stubborn Rage – The Barbarian deals extra damage with glancing blows and takes reduced damage from glancing blows while in this rage. When this rage ends, the Barbarian becomes blind. (Brute) | AS58: Panic Clarity – Purge berserk and enhance defense until next turn. Requires berserk and endangered (Berserker) | AV58: Yellow Warpaint – Grants immunity to blind and enhanced light resistance (Vandal) | AX58: Violet Warpaint – Grants immunity to vulnerability and enhanced dark resistance (Cannibal) | AZ58: Golden Warpaint – Grants immunity to weakness and enhanced healing received (Beastlord) | BH58: Unmovable Stance – Gains expertise whenever targeted by movement effects. Reduces effects of movement effects. (Dreadnaught) | BI58: Swashbuckler Taunt – Compel target enemy and weaken accuracy after next parry. Prepared (Swashbuckler) | BJ58: You Try – Ally’s next attack is unerring. Follows miss (Warlord)
A59: Minor 8 | B59: =COUNTA(C59:FF59)/1.6 -> 1.875 | AS59: Panic Might – Gain berserk and enhance damage of next attack. Requires endangered and not berserk. Consumes rage. (Berserker) | AZ59: Rage Observation – Beastlord generates rage from damage dealt to any ally. (Beastlord) | BI59: Taunting Parry – Compels any enemy the Swashbuckler parries before next turn (Swashbuckler)
A60: Minor 9 | B60: =COUNTA(C60:FF60)/1.6 -> 0
A61: Minor 10 | B61: =COUNTA(C61:FF61)/1.6 -> 0
A62: Capstone Skill | B62: =COUNTA(C62:FF62)/1.6 -> 75.625 | C62: New Beginning (Momentum Modifier) – If momentum is high enough, gain initial bonuses on turn, including ability to use scouted abilities. | D62: Bane Targeting – The modified skill has a chance to target all enemies of the same type. | E62: Instant Reload – The Crossbowman has a chance to reload after any ranged attack. | F62: Unerring Marks – After the Marksman attacks a target, all attacks against the target are unerring for a number of times. | G62: Flying Falcon – Falcon can only be targeted by ranged attacks and has increased dodge. | H62: Shared Bounty – Bounty abilities affect the entire team when they trigger. | M62: Tempered Resolve — Whenever the Initiate resists a percentage damage or death effect, his next attack gains increased damage. | N62: Impact Power – The Pugilist deals increased damage if he struck the same target the turn before. | O62: Stunning Roars — Any enemy that is stunned at the beginning of the Skirmisher's turn has their stun duration extended based on level. | P62: Diamond Body — If the Vajra does not target an enemy during his turn, he has a chance to ignore all damage until his next turn. | Q62: Pressure Crack — When the Stone Fist scores a critical hit, it also triggers any glancing hit effects on that attack. | R62: Exposed Momentum — Whenever the Infiltrator loses hidden, he is quickened. | S62: Poisonous Refreshment – Whenever the associated proc triggers, the Viper Fang gains a poison use. | T62: Condition Fortress — The Ascetic gains increased affliction resistance for each condition currently affecting him, whether affliction or enchantment. | U62: Thunder Strikes — Whenever the Thunderfist attacks a stunned enemy, that enemy also takes air damage. | V62: Counter from the Ground – The Drunken Master can counter even if prone or disarmed. Higher levels increase chance to counter. | W62: Extended Ambush – Ambush abilities can be used while target has over a percentage of life. | X62: Stacking Bleed Proc – The modified skill has a chance to afflict the target with a stacking bleed. | Y62: Trap Disarmament – Whenever the Burglar would otherwise trigger a trap on the field, they have a chance to remove that trap completely. | Z62: Grand Larceny — Steal abilities have a chance to trigger a free attack (uses tag system) | AA62: Glancing Dodge – Whenever the Acrobat suffers a glancing hit, it has a chance to be considered a dodge based on this skill. | AB62: Transfer Contract — Next attack after a contract ends applies that contract to the new target | AC62: Double Down — Enemies have a chance not to lose flanked at the start of their turn | AD62: Smuggled Poisons - The first poison gained by the smuggler is also shared with all allies. The amount of uses is based on this skill. | AE62: Aversion Backstab – Whenever an enemy averted by the skulk attacks, the skulk attacks it in response. | AF62: Second Poison — The Ninja can apply a second poison simultaneously | AH62: Premade Reserves – Premade abilities have a chance to have multiple uses at the beginning of battle. | AJ62: True Chaos – Chaos abilities both use a random elemental power and target a random elemental resistance. | AM62: Quick Call – Called shots can be activated the same turn they are used. | AQ62: Ignore Consequences – Whenever the brute would suffer consequences at the beginning of her turn due to a consequences ability, she has a chance to ignore those consequences. | AR62: Reckless Attack – Attacks from the Raider have a chance to deal increased damage at the cost of preventing any active defenses until next turn. | AS62: Double Exertion – Exertion effects trigger twice. | AT62: Initial Rampage – The Marauder begins battle with a value of rampage based on this skill. | AV62: Close to the Edge – Attacks the Rager make generate more threshold towards her Brink abilities | AW62: Bloody Berserk – Attack the Rager makes while berserk also have backbiting based on the level of this skill. | AX62: Vampiric Devotion – Life drain effects are not affected by vitality, but healing has a greater drain on vitality. | AY62: Massive Power – The threshold for triggering massive damage is lowered for the Destroyer. | AZ62: Reactive Beast Form – The Beastlord has a chance to gain a beast form whenever damaged. | BA62: High Stakes – Whenever the Gladiator attacks, he has a chance to deal 150% damage or 75% damage, as determined by skill level. | BB62: Disarming Follow Up – The Duelist makes an immediate attack against any enemy that gains the disarmed condition. | BC62: Hurry Phalanx – Whenever the Phalanx becomes ready, she quickens any ally within a short timer of action threshold to also become ready. | BD62: Constant Momentum – If the Dervish begins her turn under a momentum threshold, she generates momentum but is delayed by a greater amount. | BE62: Reactive Quickness — whenever the unit uses an ability with the reaction tag, they gain a minor quicken. | BF62: Brace for Charge — the unit gains a defense bonus against each incoming attack scaled to the attacker's current momentum. | BG62: Battle Hardened — whenever the unit takes damage during its own turn from combat exchanges such as Bushido, counters, or retaliation, it gains enhanced dodge until its next turn. | BH62: Growing Defenses - Each attack against Dreadnaught enhances defense until end of her turn. | BI62: Responsive Parries – Whenever the Swashbuckler parries an attack, she also makes a counter attack. She has a reduced chance to make counter attacks without parrying though. | BJ62: Field Commander — Aid abilities used by the unit have enhanced effects and last two turns instead of one. | BK62: Protected Intercessions – Whenever the Bodyguard would take damage for an ally, the amount of damage received is reduced by this skill level. | BL62: Constant Ire – Attacks from the Champion that deal overkill damage have a multiplier to the overkill value based on this passive. | BM62: Justice for the Infirm – The Hospitaler determines his justice modifier based on the character with the lowest health. | BN62: My Kingdom for a Horse - The Cavalier has a chance to be treated as mounted at the beginning of all turns. | BR62: Initial Corruption - The Black Knight begins battle with a certain amount of corruption. | BY62: Rainbow Spectrum – The Mercenary deals increased damage for each element she has used during her turn. | CE62: Swelling Enchantments – Until the first action of a unit after a Minstrel enchants them, the enchantment has an increased effect, based on this skill level. | CF62: Pratfalls – Whenever the Jester becomes prone, he quickens all allies. Whenever the Jester becomes disarmed, he deals ranged damage to a random enemy. Both are based on this skill level. | CG62: Mortal Harvest — Whenever the Dirge Singer kills an enemy with an instant kill effect (culling, ruthless, massive damage, or similar), he restores a percentage of his maximum health and a percentage of his maximum mana. | CH62: Extended Cuts — Whenever the Balladeer applies a condition that already exists on the target, the maximum duration of that condition is increased. This effect can apply multiple times to the same condition. | CI62: Favor of the Drum — Whenever the Drummer grants an elemental damage add to an ally, that ally also receives an additional untyped damage add. | CJ62: Initial Disguise - The Spy begins battle disguised. Higher levels of this skill allow more disguise options. | CK62: Elusive Rhythm — Whenever an enemy is prevented from targeting the Mountebank due to a condition, the Mountebank is quickened. | CL62: Dedicated Entourage — Whenever the Diva grants a provoke to an ally, that provoke lasts for one additional instance. | CM62: Encore — When the Muse is killed, he is granted one free resurrection on himself. | CN62: Constant Light – No units can gain hidden in battle. | CO62: Death Throes – When a companion of the Conjurer would die, it makes one last attack. | CP62: Initial Retaliation – The Occultist deals additional damage the first-time retaliation triggers each time she gains it. | CQ62: Critical Attendance – Whenever the Shaman scores a critical hit, her companion has an increased chance to critical during its turn. | CR62: Dualistic Power – Whenever the Medium increases one elemental power or resistance, she increases the opposed power by a percentage of that amount. | CS62: Animated Persistence – Animation abilities from the Animist have a chance not to be consumed when they trigger. | CT62: Endangered Awakening – Whenever the Spiritualist becomes endangered, she quickens and gains enhanced magic power with her next turn. | CU62: Sea of Stars – Whenever the Astrologer scores enough critical hits, she triggers a light magic attack against all enemies. | CV62: Dark Harvest – Whenever a unit with corruption on it dies, the Vizier restores mana based on the level of corruption. | CW62: Life of Insanity – The Alienist cannot die from illusory damage, but when illusory damage expires, it is converted into real damage based on the level of this passive. | CX62: Lifebond – Whenever the Pact Master would be dealt lethal damage while she has a companion, she survives with one health and all overflow damage is dealt to her companion. | CY62: Assisted Overheals – Overheals from the Acolyte include a percentage of all health restored, based on the level of this skill. | DA62: Reactive Resistance – The Disciple gains elemental resistance based on the last element that damaged him. | DC62: Conserve Vitality - The Combat Medic has a chance to keep vitality buffs when damaged based on this passive. | DD62: Exorcism – Attacks against intangible enemies have a chance to automatically kill them based on their low health and mana. | DG62: Plague Bearer - The Plague Doctor begins battle with contagion that has a chance to spread afflictions to enemies instead. | DI62: Enhanced Potential – Whenever the Buccaneer uses an ability that is based on the value of a damage affliction, the value is considered greater, based on this skill level. | DJ62: Critical Execution – The Executioner deals increased critical damage if the target has the lowest health. | DK62: Burial Proc – The modified skill has a chance to afflict the target with burial. | DM62: Constant Moon – Moon automatically appears in battle, determined by game calendar, at a lesser power. | DN62: Sinful Vapors - The Sin Eater gains mana whenever any affliction is purged. | DO62: Nightmare Manifest – Whenever incapacitated is removed from the Sandman, he deals illusory damage to all enemies based on the period he was incapacitated. | DP62: Whispering Maladies - The Whisperer has improved affliction power based on total number of enemies. | DS62: Greater Heights – Heightened abilities cost less mana for each extra cast. | DT62: Kinetic Control – The Kinetic gains kinetic bonuses from own physical damage. | DU62: Brainburning Strikes – Whenever the Amnesiac attacks an enemy with mana burn, she triggers that affliction on the target. | DV62: Lingering Patterns - Patterns remain active for a period after channeling starts. | DW62: Double Divination – The Diviner can maintain two divination effects at a time. | DX62: Haunted Spells - Spells have increased effect on low mana targets. | DZ62: Morbid Imagination – The Mindbleeder has increased illusory power the closer she is to death, based on the level of this skill. | EA62: Personal Time – The Chronomancer benefits when either slowed or hasted, with enchantments lasting longer while slower and afflictions fading quicker when hasted. | EB62: Broken Will – The Psychic lowers possession resistance and ignore possession by a percentage based on this skill level. | EC62: Double Defense Procs – Whenever a defense proc or runes triggers on the unit, it has a chance to trigger twice. | EE62: Know Your Master – Companions will not attack the Cabalist, and have a chance not to attack other party members. | EI62: Prismatic Magic – The Sage has a chance to create a random prism when this proc triggers. | EJ62: Double Attack Procs – Whenever an attack proc or rune triggers on the unit, it has a chance to trigger twice. | EK62: Remnants of Fate - Whenever a countdown triggers, the Cryptic gains mana. | EL62: Preemptive Preparation – The Sorcerer begins battle with one random ability prepared. | EM62: Share in Consumption – Whenever a drain ability benefits an ally, the Cultist gets a portion of the effect based on this skill level. | EN62: Whirlwind Targeting – The modified skill has a chance to target all enemies adjacent to the original target. | EO62: Personal Effigy – The Effigist gains increased magic damage for each damage affliction present on her. | EP62: Mana From Dust - Whenever the Dustbringer kills an enemy with corruption, she recovers mana based on that corruption. | EQ62: Chill to Frost - Whenever an enemy would be slowed enemy is slowed again, it is instead incapacitated. | ER62: Agnostic Afflictions – The Hedgemage ignores the opposing element penalty for vulnerability and exposure effects she applies. These effects retain full value even against resistances that would normally reduce them, as if the element were neutral. | ES62: Fetish Bag – The Witch Doctor gains increased mana generation for each fetish currently held and not yet deployed. The bonus scales with the number of undeployed fetishes. | ET62: Corpse Pile – Whenever another companion would be generated or would die, the Bokor's current zombie companion restores health and gains increased maximum health. | EU62: Expiration Surge – Whenever any affliction on any enemy expires naturally, the Hag generates mana. Criteria that complete their damage threshold generate a larger mana bonus. | EV62: Cursed Amplification – Increases the potency and power of all afflictions used against cursed enemies. This applies to afflictions used by any ally, not just the Malefax. | EW62: Elemental Momentum — Each time the Elementalist uses an ability with a different element than the previous elemental ability, she gains a stacking bonus to cast speed and reduced mana cost. The stack resets to zero when she repeats an element from her current set. | EX62: Kill Steal — The Necromancer's kill skills have a chance to activate when allied units kill enemies. | EY62: Water Mastery – Water spells cost less mana and cast quicker. | EZ62: Earth Mastery – Earth spells cost less mana and cast quicker. | FA62: Air Mastery – Air spells cost less mana and cast quicker. | FB62: Fire Mastery – Fire spells cost less mana and cast quicker. | FC62: Arcane Conversion – When the modified skill is triggered, the damage type has a chance to be converted to arcane. | FD62: Mana Disparity — Increases magic power based on the difference between the target's current mana and the Solomancer's current mana. Checked before the ability's mana cost is spent. | FE62: Reflected Counterspell — Prepared ability that counters an enemy spell and deals magic damage to the caster and random enemies based on the countered spell's mana cost. | FF62: Arcane Expenditure — Enhances the magic power of all abilities used on the next turn based on total mana spent on the current turn.
A63: Class Skill 1 | B63: =COUNTA(C63:FF63)/1.6 -> 0
A64: Class Skill 2 | B64: =COUNTA(C64:FF64)/1.6 -> 0
A65: Class Skill 3 | B65: =COUNTA(C65:FF65)/1.6 -> 0
A66: Class Skill 4 | B66: =COUNTA(C66:FF66)/1.6 -> 0
A67: Class Skill 5 | B67: =COUNTA(C67:FF67)/1.6 -> 0
A68: Class Skill 6 | B68: =COUNTA(C68:FF68)/1.6 -> 0
A69: Class Skill 7 | B69: =COUNTA(C69:FF69)/1.6 -> 0
A70: Class Skill 8 | B70: =COUNTA(C70:FF70)/1.6 -> 0
A71: Class Skill 9 | B71: =COUNTA(C71:FF71)/1.6 -> 0
A72: Class Skill 10 | B72: =COUNTA(C72:FF72)/1.6 -> 0
A73: Parent Skills | B73: =COUNTA(C73:FF73)/1.6 -> 0
A74: Effect Skills | B74: =COUNTA(C74:FF74)/1.6 -> 0
A75: Skill Mods | B75: =COUNTA(C75:FF75)/1.6 -> 0
A76: PassiveU | B76: =COUNTA(C76:FF76)/1.6 -> 100 | C76: Initiative | D76: Distant Damage | E76: Penetration | F76: Accuracy | G76: Accuracy | H76: Damage Versus Endangered | I76: Pinpoint | J76: Damage versus Endangered | K76: Critical Chance | L76: Distant Damage | M76: Speed | N76: Reduced Affliction Duration | O76: Damage versus Stunned | P76: Reaping | Q76: Glancing Damage Received | R76: Minimum Damage | S76: Earth Resistance | T76: Affliction Resistance | U76: Shattering | V76: Reduced Affliction Duration | W76: Alone Damage | X76: Bleed Damage | Y76: Damage while Hidden | Z76: Dualwield Speed | AA76: Dodge | AB76: Poison Damage | AC76: Damage versus Flanked | AD76: Damage versus Flanked | AE76: Penetration | AF76: Poison Damage | AG76: Mana Generation | AH76: Purge Power | AI76: Air Resistance | AJ76: Chaos Power | AK76: Companion Power | AL76: Area Damage | AM76: Ranged Damage | AN76: Enchant Power | AO76: Companion Health | AP76: Damage Shield | AQ76: Clobbering | AR76: Glancing Damage Dealt | AS76: Damage while Berserk | AT76: Dualwield Damage | AU76: Block Chance | AV76: Damage while Berserk | AW76: Endangered Damage | AX76: Healing Received | AY76: Critical Damage | AZ76: Melee Damage | BA76: Damage versus Stunned | BB76: Counter Damage | BC76: Block Amount | BD76: Dualwield Speed | BE76: Pinpoint | BF76: Two-handed Damage | BG76: Initiative | BH76: Movement Resist | BI76: Parry Chance | BJ76: Parry Chance | BK76: Health | BL76: Endangered Defense | BM76: Parry Chance | BN76: Mounted Damage | BO76: Defense | BP76: Mounted Damage | BQ76: Dualwield Speed | BR76: Corrupt Damage | BS76: Block Amount | BT76: Healing Received | BU76: Air Resistance | BV76: Fire Resist | BW76: Earth Resistance | BX76: Water Resistance | BY76: Dualwield Damage | BZ76: Enchant Potency | CA76: Arcane Power | CB76: Elemental Resistance | CC76: Dark Resistance | CD76: Light Resist | CE76: Regeneration | CF76: Fire Resist | CG76: Life Drain | CH76: Earth Resistance | CI76: Water Resistance | CJ76: Damage Resist | CK76: Dark Resistance | CL76: Maximum Mana | CM76: Retaliation | CN76: Dark Resistance | CO76: Summoning Speed | CP76: Retaliation | CQ76: Mana Reserved | CR76: Spell Critical | CS76: Mounted Damage | CT76: Endangered Damage | CU76: Light Resist | CV76: Companion Damage | CW76: Companion Damage | CX76: Area Damage | CY76: Regeneration | CZ76: Healing Power | DA76: Physical Resistance | DB76: Maximum Mana | DC76: Damage Resist | DD76: Light Power | DE76: Damage versus Incapacitated | DF76: Movement Resist | DG76: Affliction Resistance | DH76: Cast Speed | DI76: Reaping | DJ76: Damage versus Endangered | DK76: Elemental Resistance | DL76: Air Resistance | DM76: Speed | DN76: Disenchant Power | DO76: Damage versus Incapacitated | DP76: Retaliation | DQ76: Bleed Damage | DR76: Glancing Damage Dealt | DS76: Mana Cost Reduced | DT76: Delays | DU76: Mental Resistance | DV76: Delays | DW76: Spell Dodge | DX76: Possession Power | DY76: Quickens | DZ76: Illusory Damage | EA76: Quickens | EB76: Possession Power | EC76: Damage Shield | ED76: Proc Chance | EE76: Earth Power | EF76: Spell Critical | EG76: Disenchant Power | EH76: Cast Speed | EI76: Piercing | EJ76: Earth Power | EK76: Spell Critical | EL76: Area Damage | EM76: Starting Mana | EN76: Damage versus Maledicted | EO76: Fire Power | EP76: Magic Power | EQ76: Water Power | ER76: Mana Cost Reduced | ES76: Purge Power | ET76: Affliction Power | EU76: Affliction Power | EV76: Damage versus Maledicted | EW76: Elemental Damage | EX76: Dark Power | EY76: Water Power | EZ76: Earth Power | FA76: Air Power | FB76: Fire Power | FC76: Arcane Power | FD76: Light Power | FE76: Channeled Power | FF76: Magic Power
A77: PassiveG1 | B77: =COUNTA(C77:FF77)/1.6 -> 100 | C77: Initial Defense | D77: Glancing Damage Dealt | E77: Ranged Damage | F77: Penetration | G77: Companion Health | H77: Ranged Accuracy | I77: Damage while Hidden | J77: Pinpoint | K77: Ranged Accuracy | L77: Damage versus Full Health | M77: Percent Protection | N77: Damage versus Stunned | O77: Initial Damage | P77: Damage versus Stunned | Q77: Defense | R77: Penetration | S77: Poison Damage | T77: Stun Duration | U77: Air Power | V77: Dodge | W77: Initial Damage | X77: Hidden Critical Damage | Y77: Damage versus Full Health | Z77: Life Drain | AA77: Speed | AB77: Critical Chance | AC77: Critical Chance | AD77: Ignore Prone | AE77: Damage while Hidden | AF77: Maximum Damage | AG77: Full Health Defense | AH77: Distant Damage | AI77: Starting Mana | AJ77: Shattering | AK77: Ranged Damage | AL77: Area Dodge | AM77: Ranged Dodge | AN77: Air Piercing | AO77: Glancing Damage Received | AP77: Cast Speed | AQ77: Health | AR77: Shield Damage | AS77: Endangered Damage | AT77: Counter Damage | AU77: Shield Damage | AV77: Maximum Damage | AW77: Dualwield Speed | AX77: Endangered Damage | AY77: Weakness Power | AZ77: Alone Damage | BA77: Melee Damage | BB77: Parry Chance | BC77: Block Chance | BD77: Dualwield Damage | BE77: Parry Chance | BF77: Movement Resist | BG77: Dualwield Damage | BH77: Health | BI77: Accuracy | BJ77: Quickens | BK77: Full Health Defense | BL77: Healing Received | BM77: Purge Power | BN77: Mounted Defense | BO77: Block Chance | BP77: Elemental Resistance | BQ77: Parry Chance | BR77: Dark Power | BS77: Hex Power | BT77: Block Amount | BU77: Air Power | BV77: Fire Power | BW77: Earth Power | BX77: Water Power | BY77: Elemental Damage | BZ77: Enhance Power | CA77: Reaping | CB77: Alone Defense | CC77: Damage while Hidden | CD77: Counter Chance | CE77: Enhance Power | CF77: Chaos Power | CG77: Dark Piercing | CH77: Enchant Potency | CI77: Disruption Power | CJ77: Damage versus Flanked | CK77: Damage versus Flanked | CL77: Mana Generation | CM77: Quickens | CN77: Light Power | CO77: Companion Power | CP77: Water Power | CQ77: Percent Protection | CR77: Channeled Power | CS77: Death Protection | CT77: Retaliation | CU77: Light Power | CV77: Mana Reserved | CW77: Chaos Power | CX77: Corrupt Damage | CY77: Healing Power | CZ77: Maximum Mana | DA77: Purge Power | DB77: Damage Shield | DC77: Cast Speed | DD77: Affliction Resistance | DE77: Justice | DF77: Speed | DG77: Purge Power | DH77: Countdown Power | DI77: Water Power | DJ77: Critical Damage | DK77: Delays | DL77: Bleed Damage | DM77: Initiative | DN77: Full Health Damage | DO77: Reduced Affliction Duration | DP77: Possession Power | DQ77: Maximum Damage | DR77: Illusory Damage | DS77: Disruption Power | DT77: Magic Power | DU77: Disenchant Power | DV77: Channeled Power | DW77: Elemental Resistance | DX77: Alone Defense | DY77: Possession Power | DZ77: Bleed Damage | EA77: Delays | EB77: Mana Cost Reduced | EC77: Earth Power | ED77: Fire Power | EE77: Damage Shield | EF77: Affliction Power | EG77: Magic Resistance | EH77: Arcane Power | EI77: Area Damage | EJ77: Proc Power | EK77: Mental Resistance | EL77: Mana Generation | EM77: Affliction Duration | EN77: Bloodlust | EO77: Fire Piercing | EP77: Damage versus Maledicted | EQ77: Delays | ER77: Cast Speed | ES77: Life Drain | ET77: Damage versus Maledicted | EU77: Corrupt Damage | EV77: Hex Power | EW77: Elemental Resistance, Air and Fire | EX77: Companion Health | EY77: Water Piercing | EZ77: Earth Piercing | FA77: Air Piercing | FB77: Fire Piercing | FC77: Piercing | FD77: Light Piercing | FE77: Disruption Resist | FF77: Magic Resistance
A78: PassiveG2 | B78: =COUNTA(C78:FF78)/1.6 -> 100 | C78: Initial Damage | D78: Elemental Resistance, Air and Earth | E78: Glancing Damage Received | F78: Elemental Resistance, Air and Light | G78: Air Resistance | H78: Mental Resistance | I78: Bloodlust | J78: Air Resistance | K78: Penetration | L78: Accuracy | M78: Death Protection | N78: Elemental Resistance, Earth and Water | O78: Counter Chance | P78: Physical Resistance | Q78: Clobbering | R78: Water Resistance | S78: Critical Chance | T78: Tired Duration | U78: Elemental Resistance, Air and Water | V78: Ignore Prone | W78: Mana Damage | X78: Dualwield Speed | Y78: Damage Resist | Z78: Damage while Hidden | AA78: Area Dodge | AB78: Hidden Critical Damage | AC78: Hidden Critical Damage | AD78: Elemental Resistance, Fire and Water | AE78: Alone Defense | AF78: Elemental Resistance, Earth and Water | AG78: Chaos Power | AH78: Elemental Resistance, Earth and Fire | AI78: Air Power | AJ78: Summoning Speed | AK78: Summoning Speed | AL78: Initial Damage | AM78: Elemental Resistance, Air and Fire | AN78: Elemental Resistance, Air and Earth | AO78: Companion Damage | AP78: Elemental Resistance, Air and Dark | AQ78: Tired Duration | AR78: Elemental Resistance, Air and Water | AS78: Speed | AT78: Elemental Resistance, Light and Water | AU78: Damage while Berserk | AV78: Elemental Resistance, Fire and Light | AW78: Backbiting | AX78: Damage versus Endangered | AY78: Backbiting | AZ78: Damage while Berserk | BA78: Earth Resistance | BB78: Ignore Disarm | BC78: Full Health Damage | BD78: Elemental Resistance, Air and Fire | BE78: Elemental Resistance, Air and Water | BF78: Mounted Defense | BG78: Dualwield Speed | BH78: Earth Resistance | BI78: Ignore Prone | BJ78: Melee Damage | BK78: Healing Received | BL78: Disenchant Resist | BM78: Full Health Damage | BN78: Companion Defense | BO78: Full Health Defense | BP78: Two-handed Damage | BQ78: Justice | BR78: Reduced Affliction Duration | BS78: Elemental Resistance, Air and Dark | BT78: Minimum Damage | BU78: Storm Power | BV78: Retaliation | BW78: Block Amount | BX78: Delays | BY78: Ignore Disarm | BZ78: Melee Damage | CA78: Disenchant Resist | CB78: Damage versus Endangered | CC78: Dualwield Damage | CD78: Initiative | CE78: Elemental Resistance, Fire and Water | CF78: Percent Protection | CG78: Elemental Resistance, Light and Water | CH78: Piercing | CI78: Enchant Duration | CJ78: Ranged Dodge | CK78: Glancing Damage Dealt | CL78: Channeled Power | CM78: Elemental Resistance, Light and Water | CN78: Area Damage | CO78: Companion Defense | CP78: Water Resistance | CQ78: Magic Power | CR78: Elemental Resistance, Dark and Light | CS78: Companion Defense | CT78: Elemental Resistance, Air and Light | CU78: Lucky Bonus | CV78: Elemental Resistance, Air and Fire | CW78: Companion Power | CX78: Elemental Resistance, Dark and Light | CY78: Lucky Bonus | CZ78: Elemental Resistance, Dark and Water | DA78: Elemental Resistance, Air and Light | DB78: Light Piercing | DC78: Elemental Resistance, Dark and Water | DD78: Elemental Resistance, Dark and Light | DE78: Enchant Potency | DF78: Alone Damage | DG78: Healing Power | DH78: Purge Power | DI78: Water Piercing | DJ78: Elemental Resistance, Fire and Light | DK78: Elemental Resistance, Earth and Light | DL78: Reaping | DM78: Light Resist | DN78: Elemental Resistance, Dark and Fire | DO78: Illusory Damage | DP78: Dark Resistance | DQ78: Elemental Resistance, Earth and Light | DR78: Death Protection | DS78: Damage versus Incapacitated | DT78: Starting Mana | DU78: Magic Resistance | DV78: Elemental Resistance, Fire and Water | DW78: Magic Power | DX78: Elemental Resistance, Dark and Fire | DY78: Maximum Mana | DZ78: Affliction Potency | EA78: Mana Generation | EB78: Quickens | EC78: Defense | ED78: Disenchant Resist | EE78: Elemental Resistance, Dark and Earth | EF78: Elemental Resistance, Earth and Fire | EG78: Mana Damage | EH78: Mana Cost Reduced | EI78: Elemental Resistance, Air and Earth | EJ78: Earth Resistance | EK78: Elemental Resistance, Earth and Light | EL78: Proc Power | EM78: Affliction Power | EN78: Elemental Resistance, Air and Dark | EO78: Elemental Resistance, Dark and Fire | EP78: Earth Piercing | EQ78: Elemental Resistance, Dark and Water | ER78: Earth Resistance | ES78: Regeneration | ET78: Mana Damage | EU78: Maledicted Defense | EV78: Piercing | EW78: Elemental Resistance, Earth and Water | EX78: Companion Damage | EY78: Damage versus Incapacitated | EZ78: Damage Shield | FA78: Storm Power | FB78: Area Dodge | FC78: Maximum Mana | FD78: Area Damage | FE78: Water Piercing | FF78: Spell Critical
A79: PassiveS1 | B79: =COUNTA(C79:FF79)/1.6 -> 100 | C79: Initial Dodge | D79: Damage versus Endangered | E79: Defense while Fortified | F79: Initial Accuracy | G79: Ranged Damage | H79: Stun Duration | I79: Elemental Resistance, Fire and Water | J79: Poison Damage | K79: Accuracy | L79: Speed | M79: Elemental Resistance | N79: Ignore Counter | O79: Minimum Damage | P79: Ignore Prone | Q79: Ignore Glancing | R79: Ignore Avert | S79: Backbiting | T79: Damage versus Stunned | U79: Air Adds | V79: Ignore Flanked | W79: Ranged Damage | X79: Damage while Hidden | Y79: Initiative | Z79: Lucky Bonus | AA79: Damage versus Flanked | AB79: Critical Damage | AC79: Poison Damage | AD79: Poison Damage | AE79: Dodge | AF79: Conserve Poison | AG79: Ignore Mana Loss | AH79: Poison Damage | AI79: Chaos Power | AJ79: Affliction Duration | AK79: Enchant Power | AL79: Trap Damage | AM79: Critical Chance | AN79: Purge Power | AO79: Quickens | AP79: Quickens | AQ79: Ignore Critical | AR79: Block Chance | AS79: Glancing Damage Received | AT79: Bloodlust | AU79: Block Amount | AV79: Critical Damage | AW79: Tired Duration | AX79: Endangered Defense | AY79: Damage versus Full Health | AZ79: Health | BA79: Critical Chance | BB79: Ignore Flanked | BC79: Shield Damage | BD79: Speed | BE79: Accuracy | BF79: Mounted Damage | BG79: Initial Damage | BH79: Ignore Glancing | BI79: Initial Dodge | BJ79: Health | BK79: Defense | BL79: Damage versus Endangered | BM79: Purges Received | BN79: Momentum | BO79: Ignore Critical | BP79: Spell Dodge | BQ79: Dualwield Damage | BR79: Life Drain | BS79: Block Chance | BT79: Light Adds | BU79: Air Adds | BV79: Fire Adds | BW79: Earth Adds | BX79: Water Adds | BY79: Parry Chance | BZ79: Affliction Potency | CA79: Penetration | CB79: Shielded Power | CC79: Dark Adds | CD79: Light Adds | CE79: Weakness Power | CF79: Weakness Power | CG79: Death Protection | CH79: Earth Adds | CI79: Ignore Prone | CJ79: Damage versus Incapacitated | CK79: Avert Sustain | CL79: Damage Shield | CM79: Mana Generation | CN79: Accuracy | CO79: Companion Damage | CP79: Mana Reserved | CQ79: Purge Power | CR79: Dark Power | CS79: Damage versus Intangible | CT79: Empowered Power | CU79: Countdown Power | CV79: Proc Power | CW79: Illusory Damage | CX79: Magic Power | CY79: Starting Mana | CZ79: Endangered Healing | DA79: Corruption Resistance | DB79: Cast Speed | DC79: Healing Power | DD79: Damage versus Intangible | DE79: Healing Power | DF79: Light Adds | DG79: Purges Received | DH79: Lucky Bonus | DI79: Water Resistance | DJ79: Damage versus Incapacitated | DK79: Earth Power | DL79: Incapacitate Power | DM79: Initial Damage | DN79: Life Drain | DO79: Affliction Duration | DP79: Illusory Damage | DQ79: Poison Damage | DR79: Reaping | DS79: Damage versus Stunned | DT79: Arcane Power | DU79: Illusory Resistance | DV79: Maximum Mana | DW79: Dodge | DX79: Damage while Intangible | DY79: Defense versus Allies | DZ79: Purges Received | EA79: Reduced Delays | EB79: Mental Resistance | EC79: Enchant Potency | ED79: Fire Adds | EE79: Retaliation | EF79: Water Power | EG79: Ignore Mana Loss | EH79: Trap Damage | EI79: Elemental Damage | EJ79: Weakness Power | EK79: Countdown Power | EL79: Magic Power | EM79: Possession Power | EN79: Storm Power | EO79: Damage versus Maledicted | EP79: Delays | EQ79: Water Piercing | ER79: Affliction Duration | ES79: Light Power | ET79: Companion Health | EU79: Damage versus Maledicted | EV79: Ignore Mana Loss | EW79: Fire Power | EX79: Corrupt Damage | EY79: Affliction Power | EZ79: Weakness Power | FA79: Maximum Damage | FB79: Area Damage | FC79: Magic Resistance | FD79: Corruption Resistance | FE79: Cast Speed | FF79: Empowered Power
A80: PassiveS2 | B80: =COUNTA(C80:FF80)/1.6 -> 100 | C80: Quickens | D80: Critical Chance | E80: Glancing Damage Dealt | F80: Distant Damage | G80: Reaping | H80: Damage versus Incapacitated | I80: Ranged Accuracy | J80: Bloodlust | K80: Distant Damage | L80: Pinpoint | M80: Minimum Damage | N80: Ignore Disarm | O80: Dexterity Mastery | P80: Full Health Damage | Q80: Physical Resistance | R80: Damage while Hidden | S80: Damage Resist | T80: Conserve Focus | U80: Counter Damage | V80: Counter Chance | W80: Pinpoint | X80: Penetration | Y80: Initial Damage | Z80: Ignore Mana Loss | AA80: Air Resistance | AB80: Conserve Poison | AC80: Ranged Damage | AD80: Affliction Resistance | AE80: Spell Dodge | AF80: Hidden Critical Damage | AG80: Healing Received | AH80: Quickens | AI80: Trap Damage | AJ80: Companion Power | AK80: Trap Damage | AL80: Chaos Power | AM80: Distant Damage | AN80: Shielded Power | AO80: Defense while Fortified | AP80: Regeneration | AQ80: Critical Damage | AR80: Melee Damage | AS80: Two-handed Damage | AT80: Damage while Berserk | AU80: Bloodlust | AV80: Damage Resist | AW80: Death Protection | AX80: Damage while Berserk | AY80: Two-handed Damage | AZ80: Speed | BA80: Shattering | BB80: Counter Chance | BC80: Ignore Flanked | BD80: Damage while Hasted | BE80: Penetration | BF80: Momentum | BG80: Amplification | BH80: Reduced Delays | BI80: Dodge | BJ80: Defense | BK80: Disruption Power | BL80: Block Amount | BM80: Healing Received | BN80: Justice | BO80: Ignore Glancing | BP80: Mounted Defense | BQ80: Endangered Defense | BR80: Backbiting | BS80: Mounted Damage | BT80: Defense versus Compelled | BU80: Damage versus Stunned | BV80: Fire Piercing | BW80: Movement Resist | BX80: Reduced Delays | BY80: Chaos Power | BZ80: Disenchant Resist | CA80: Starting Mana | CB80: Full Health Defense | CC80: Reaping | CD80: Percent Protection | CE80: Corruption Resistance | CF80: Pinpoint | CG80: Endangered Damage | CH80: Enhance Power | CI80: Minimum Damage | CJ80: Avert Sustain | CK80: Enchant Duration | CL80: Reaping | CM80: Reduced Affliction Duration | CN80: Light Adds | CO80: Disruption Resist | CP80: Corrupt Damage | CQ80: Companion Damage | CR80: Dark Resistance | CS80: Ignore Possession | CT80: Shielded Power | CU80: Mental Resistance | CV80: Summoning Speed | CW80: Ignore Critical | CX80: Ignore Possession | CY80: Hex Power | CZ80: Purge Power | DA80: Minimum Damage | DB80: Initial Defense | DC80: Endangered Healing | DD80: Ignore Possession | DE80: Incapacitate Power | DF80: Quickens | DG80: Corruption Resistance | DH80: Initiative | DI80: Water Adds | DJ80: Shattering | DK80: Damage versus Incapacitated | DL80: Air Piercing | DM80: Damage versus Endangered | DN80: Purges Received | DO80: Dodge while Intangible | DP80: Channeled Power | DQ80: Bloodlust | DR80: Illusory Resistance | DS80: Illusory Resistance | DT80: Reduced Delays | DU80: Avert Sustain | DV80: Mana Generation | DW80: Possession Power | DX80: Ignore Possession | DY80: Delays | DZ80: Retaliation | EA80: Damage while Hasted | EB80: Channeled Power | EC80: Retaliation | ED80: Area Damage | EE80: Defense | EF80: Alone Defense | EG80: Amplification | EH80: Mana Generation | EI80: Elemental Resistance | EJ80: Proc Chance | EK80: Magic Resistance | EL80: Area Dodge | EM80: Dark Power | EN80: Air Piercing | EO80: Piercing | EP80: Earth Power | EQ80: Affliction Duration | ER80: Chaos Power | ES80: Damage Purge Power | ET80: Corrupt Damage | EU80: Dark Piercing | EV80: Affliction Power | EW80: Air Power | EX80: Dark Piercing | EY80: Water Resistance | EZ80: Initial Defense | FA80: Air Resistance | FB80: Disruption Resist | FC80: Spell Critical | FD80: Piercing | FE80: Melee Dodge | FF80: Maximum Mana
A81: PassiveS3 | B81: =COUNTA(C81:FF81)/1.6 -> 100 | C81: Momentum | D81: Physical Resistance | E81: Initial Defense | F81: Initial Damage | G81: Damage versus Endangered | H81: Movement Resist | I81: Bleed Damage | J81: Damage versus Incapacitated | K81: Pinpoint | L81: Ignore Avert | M81: Water Power | N81: Clobbering | O81: Dualwield Speed | P81: Health | Q81: Defense while Fortified | R81: Dodge | S81: Earth Power | T81: Damage while Focused | U81: Stun Duration | V81: Counter Damage | W81: Damage versus Endangered | X81: Alone Damage | Y81: Conserve Hidden | Z81: Dualwield Damage | AA81: Alone Damage | AB81: Damage versus Flanked | AC81: Initiative | AD81: Conserve Poison | AE81: Dualwield Speed | AF81: Dualwield Damage | AG81: Endangered Healing | AH81: Endangered Healing | AI81: Shielded Power | AJ81: Air Power | AK81: Air Resistance | AL81: Lucky Bonus | AM81: Air Piercing | AN81: Damage Shield | AO81: Area Damage | AP81: Healing Received | AQ81: Delays | AR81: Tired Duration | AS81: Backbiting | AT81: Clobbering | AU81: Water Adds | AV81: Fire Adds | AW81: Damage while Berserk | AX81: Endurance Mastery | AY81: Melee Damage | AZ81: Mounted Defense | BA81: Tired Duration | BB81: Speed | BC81: Ignore Critical | BD81: Momentum | BE81: Initial Accuracy | BF81: Shattering | BG81: Ignore Disarm | BH81: Defense | BI81: Initiative | BJ81: Strength Mastery | BK81: Defense versus Allies | BL81: Mounted Damage | BM81: Physical Purge Power | BN81: Initial Defense | BO81: Block Amount | BP81: Full Health Defense | BQ81: Melee Damage | BR81: Defense | BS81: Tired Duration | BT81: Shield Damage | BU81: Proc Chance | BV81: Proc Chance | BW81: Endangered Defense | BX81: Shattering | BY81: Dualwield Speed | BZ81: Elemental Resistance, Earth and Water | CA81: Stun Duration | CB81: Block Amount | CC81: Life Drain | CD81: Mana Defense | CE81: Water Power | CF81: Ignore Counter | CG81: Percent Protection | CH81: Regeneration | CI81: Disenchant Resist | CJ81: Initial Defense | CK81: Ignore Flanked | CL81: Regeneration | CM81: Enchant Duration | CN81: Enchant Potency | CO81: Starting Mana | CP81: Companion Power | CQ81: Channeled Power | CR81: Light Power | CS81: Health | CT81: Enhance Power | CU81: Companion Defense | CV81: Corrupt Damage | CW81: Affliction Resistance | CX81: Companion Power | CY81: Affliction Resistance | CZ81: Death Protection | DA81: Physical Purge Power | DB81: Wisdom Mastery | DC81: Tired Duration | DD81: Endangered Defense | DE81: Light Piercing | DF81: Damage while Hasted | DG81: Physical Purge Power | DH81: Damage Purge Power | DI81: Elemental Resistance, Air and Water | DJ81: Endangered Damage | DK81: Earth Piercing | DL81: Reduced Affliction Duration | DM81: Percent Protection | DN81: Dark Piercing | DO81: Incapacitate Power | DP81: Dark Piercing | DQ81: Percent Protection | DR81: Spell Dodge | DS81: Possession Power | DT81: Momentum | DU81: Mental Purge Power | DV81: Possession Power | DW81: Ranged Dodge | DX81: Channeled Power | DY81: Channeled Power | DZ81: Backbiting | EA81: Incapacitate Power | EB81: Healing Received | EC81: Shielded Power | ED81: Fire Piercing | EE81: Defense while Fortified | EF81: Alone Damage | EG81: Piercing | EH81: Earth Piercing | EI81: Arcane Power | EJ81: Elemental Resistance, Fire and Water | EK81: Mana Generation | EL81: Countdown Power | EM81: Elemental Resistance, Dark and Earth | EN81: Maledicted Defense | EO81: Fire Adds | EP81: Piercing | EQ81: Reduced Delays | ER81: Incapacitate Power | ES81: Physical Purge Power | ET81: Damage while Intangible | EU81: Mana Cost Reduced | EV81: Dark Piercing | EW81: Water Power | EX81: Dark Resistance | EY81: Delays | EZ81: Full Health Defense | FA81: Starting Mana | FB81: Fire Resist | FC81: Elemental Resistance | FD81: Dark Resistance | FE81: Spell Critical | FF81: Area Damage
A82: PassiveS4 | B82: =COUNTA(C82:FF82)/1.6 -> 100 | C82: Ranged Accuracy | D82: Elemental Resistance, Air and Fire | E82: Elemental Resistance, Fire and Water | F82: Glancing Damage Dealt | G82: Movement Resist | H82: Elemental Resistance, Air and Water | I82: Initial Accuracy | J82: Accuracy | K82: Air Piercing | L82: Air Adds | M82: Reduced Affliction Duration | N82: Water Adds | O82: Bleed Damage | P82: Elemental Resistance, Earth and Water | Q82: Glancing Damage Dealt | R82: Spell Dodge | S82: Elemental Resistance, Dark and Earth | T82: Mental Resistance | U82: Critical Chance | V82: Elemental Resistance, Air and Water | W82: Dodge | X82: Elemental Resistance, Dark and Water | Y82: Hidden Critical Damage | Z82: Conserve Poison | AA82: Critical Damage | AB82: Bloodlust | AC82: Area Dodge | AD82: Penetration | AE82: Earth Piercing | AF82: Melee Dodge | AG82: Damage Resist | AH82: Regeneration | AI82: Enchant Power | AJ82: Enchant Duration | AK82: Initial Defense | AL82: Elemental Resistance, Earth and Fire | AM82: Ranged Accuracy | AN82: Air Adds | AO82: Companion Defense | AP82: Companion Health | AQ82: Elemental Resistance, Air and Fire | AR82: Physical Resistance | AS82: Magic Resistance | AT82: Damage while Hasted | AU82: Ignore Prone | AV82: Elemental Resistance, Earth and Water | AW82: Damage while Hasted | AX82: Physical Resistance | AY82: Alone Defense | AZ82: Strength Mastery | BA82: Parry Chance | BB82: Penetration | BC82: Glancing Damage Received | BD82: Initial Dodge | BE82: Ignore Disarm | BF82: Defense versus Compelled | BG82: Damage versus Full Health | BH82: Two-Handed Damage | BI82: Penetration | BJ82: Ignore Disarm | BK82: Endangered Damage | BL82: Elemental Resistance, Earth and Light | BM82: Regeneration | BN82: Elemental Resistance, Dark and Earth | BO82: Shield Damage | BP82: Elemental Resistance, Earth and Light | BQ82: Full Health Damage | BR82: Death Protection | BS82: Movement Resist | BT82: Light Piercing | BU82: Initial Damage | BV82: Elemental Resistance, Air and Earth | BW82: Damage Shield | BX82: Elemental Resistance, Fire and Water | BY82: Disenchant Resist | BZ82: Affliction Resistance | CA82: Damage versus Intangible | CB82: Shield Damage | CC82: Ignore Compel | CD82: Amplification | CE82: Charm Mastery | CF82: Ignore Prone | CG82: Elemental Resistance, Dark and Water | CH82: Elemental Resistance, Air and Light | CI82: Glancing Damage Received | CJ82: Conserve Hidden | CK82: Elemental Resistance, Dark and Water | CL82: Starting Mana | CM82: Amplification | CN82: Maximum Mana | CO82: Elemental Resistance, Air and Dark | CP82: Water Piercing | CQ82: Mental Purge Power | CR82: Light Resist | CS82: Elemental Resistance, Earth and Light | CT82: Summoning Speed | CU82: Elemental Resistance, Air and Light | CV82: Companion Health | CW82: Starting Mana | CX82: Summoning Speed | CY82: Light Resist | CZ82: Elemental Resistance, Dark and Fire | DA82: Health | DB82: Elemental Resistance, Fire and Light | DC82: Regeneration | DD82: Full Health Damage | DE82: Elemental Resistance, Light and Water | DF82: Movement Purge Power | DG82: Elemental Resistance, Earth and Water | DH82: Spell Dodge | DI82: Elemental Resistance, Dark and Water | DJ82: Elemental Resistance, Air and Earth | DK82: Elemental Resistance, Dark and Earth | DL82: Elemental Resistance, Air and Dark | DM82: Movement Resist | DN82: Elemental Resistance, Earth and Light | DO82: Dark Power | DP82: Damage versus Intangible | DQ82: Dark Adds | DR82: Mental Resistance | DS82: Fire Piercing | DT82: Fire Power | DU82: Mana Damage | DV82: Avert Sustain | DW82: Mental Resistance | DX82: Dodge while Intangible | DY82: Ignore Possession | DZ82: Arcane Power | EA82: Elemental Resistance, Light and Water | EB82: Fire Piercing | EC82: Defense while Fortified | ED82: Mana Reserved | EE82: Elemental Resistance, Earth and Fire | EF82: Elemental Resistance, Earth and Water | EG82: Disruption Power | EH82: Ignore Mana Loss | EI82: Mana Reserved | EJ82: Elemental Resistance, Air and Earth | EK82: Earth Resistance | EL82: Magic Resistance | EM82: Elemental Resistance, Air and Fire | EN82: Mana Reserved | EO82: Fire Resist | EP82: Corrupt Damage | EQ82: Elemental Resistance, Light and Water | ER82: Elemental Resistance, Dark and Water | ES82: Light Resist | ET82: Elemental Resistance, Dark and Light | EU82: Elemental Resistance, Dark and Water | EV82: Mana Cost Reduced | EW82: Earth Power | EX82: Light Resist | EY82: Mana Reserved | EZ82: Earth Resistance | FA82: Maximum Mana | FB82: Spell Critical | FC82: Elemental Resistance, Air and Fire | FD82: Maximum Mana | FE82: Elemental Resistance, Air and Water | FF82: Will Mastery
A83: PassiveL1 | B83: =COUNTA(C83:FF83)/1.6 -> 100 | C83: Charm Mastery | D83: Charm Mastery | E83: Melee Dodge | F83: Ranged Critical Chance | G83: Summoning Speed | H83: Damage versus Stunned | I83: Ranged Damage | J83: Ranged Damage | K83: Break Limit Critical | L83: Break Limit Critical | M83: Dexterity Mastery | N83: Avoid Parry | O83: Damage while Hasted | P83: Ignore Flanked | Q83: Ignore Critical | R83: Dodge while Hasted | S83: Conserve Poison | T83: Corruption Regeneration | U83: Damage versus Stunned | V83: Clobbering | W83: Poison Damage | X83: Poison Damage | Y83: Conserve Poison | Z83: Dualwield Accuracy | AA83: Dodge while Hasted | AB83: Break Limit Critical | AC83: Break Limit Critical | AD83: Hidden Affliction Power | AE83: Poison Damage | AF83: Dodge while Hasted | AG83: Will Mastery | AH83: Overheal Effects | AI83: Conserve Trap | AJ83: Conserve Trap | AK83: Damage Shield | AL83: Conserve Trap | AM83: Ranged Critical Chance | AN83: Dexterity Mastery | AO83: Companion Speed | AP83: Damage Shield Regeneration | AQ83: Damage while Berserk | AR83: Damage while Berserk | AS83: Strength Mastery | AT83: Health | AU83: Break Limit Block | AV83: Melee Damage | AW83: Endangered Regeneration | AX83: Two-handed Damage | AY83: Overkill Effects | AZ83: Overkill Effects | BA83: Break Limit Parry | BB83: Break Limit Counter | BC83: Break Limit Block | BD83: Dodge while Hasted | BE83: Avoid Parry | BF83: Mounted Speed | BG83: Dualwield Accuracy | BH83: Two-handed Blocking | BI83: Break Limit Parry | BJ83: Break Limit Parry | BK83: Defense while Fortified | BL83: Overkill Effects | BM83: Break Limit Parry | BN83: Mounted Speed | BO83: Break Limit Block | BP83: Two-handed Blocking | BQ83: Break Limit Parry | BR83: Maledicted Defense | BS83: Shield Defense | BT83: Break Limit Block | BU83: Empowered Power | BV83: Countdown Power | BW83: Break Limit Block | BX83: Glancing Damage Received | BY83: Break Limit Parry | BZ83: Reduced Affliction Duration | CA83: Clobbering | CB83: Barrier Threshold | CC83: Dualwield Accuracy | CD83: Strength Mastery | CE83: Healing Power | CF83: Dodge while Hasted | CG83: Ignore Lifedrain | CH83: Corruption Resistance | CI83: Water Power | CJ83: Hidden Affliction Power | CK83: Poison Damage | CL83: Overheal Effects | CM83: Barrier Threshold | CN83: Corruption Regeneration | CO83: Break Limit Cast Speed | CP83: Shielded Power | CQ83: Damage versus Intangible | CR83: Mental Resistance | CS83: Corruption Regeneration | CT83: Endangered Regeneration | CU83: Wisdom Mastery | CV83: Wisdom Mastery | CW83: Companion Speed | CX83: Magic Resistance | CY83: Overheal Effects | CZ83: Overheal Effects | DA83: Corruption Regeneration | DB83: Purge Power | DC83: Break Limit Cast Speed | DD83: Ignore Lifedrain | DE83: Wisdom Mastery | DF83: Dodge while Hasted | DG83: Movement Purge Power | DH83: Break Limit Cast Speed | DI83: Luck Mastery | DJ83: Overkill Effects | DK83: Counter Damage | DL83: Air Power | DM83: Wisdom Mastery | DN83: Overheal Effects | DO83: Illusory Resistance | DP83: Disruption Power | DQ83: Damage versus Endangered | DR83: Damage versus Endangered | DS83: Illusory Damage | DT83: Spell Power while Focused | DU83: Illusory Regeneration | DV83: Incapacitate Power | DW83: Intelligence Mastery | DX83: Damage versus Intangible | DY83: Spell Power while Focused | DZ83: Illusory Regeneration | EA83: Dodge while Hasted | EB83: Spell Power while Focused | EC83: Barrier Threshold | ED83: Conserve Rune | EE83: Conserve Rune | EF83: Intelligence Mastery | EG83: Purge Power | EH83: Break Limit Cast Speed | EI83: Conserve Rune | EJ83: Air Adds | EK83: Conserve Rune | EL83: Conserve Rune | EM83: Damage versus Maledicted | EN83: Mana Cost Reduced | EO83: Maledicted Defense | EP83: Maledicted Defense | EQ83: Damage versus Maledicted | ER83: Break Limit Cast Speed | ES83: Illusory Damage | ET83: Hidden Affliction Power | EU83: Intelligence Mastery | EV83: Intelligence Mastery | EW83: Elemental Resistance | EX83: Companion Speed | EY83: Ignore Critical | EZ83: Damage Shield Regeneration | FA83: Stun Duration | FB83: Retaliation | FC83: Intelligence Mastery | FD83: Maximum Damage | FE83: Break Limit Cast Speed | FF83: Intelligence Mastery
A84: PassiveL2 | B84: =COUNTA(C84:FF84)/1.6 -> 100 | C84: Initial Accuracy | D84: Bloodlust | E84: Pinpoint | F84: Ranged Damage | G84: Dexterity Mastery | H84: Incapacitate Power | I84: Conserve Hidden | J84: Distant Damage | K84: Overkill Effects | L84: Dexterity Mastery | M84: Ignore Prone | N84: Dexterity Mastery | O84: Break Limit Counter | P84: Endurance Mastery | Q84: Endurance Mastery | R84: Conserve Hidden | S84: Bleed Damage | T84: Purges Received | U84: Ignore Prone | V84: Ignore Counter | W84: Critical Chance | X84: Dualwield Accuracy | Y84: Luck Mastery | Z84: Conserve Hidden | AA84: Dexterity Mastery | AB84: Overkill Effects | AC84: Ranged Critical Chance | AD84: Conserve Hidden | AE84: Dualwield Accuracy | AF84: Damage while Hidden | AG84: Purges Received | AH84: Healing Power | AI84: Will Mastery | AJ84: Trap Damage | AK84: Conserve Trap | AL84: Endangered Damage | AM84: Dexterity Mastery | AN84: Earth Power | AO84: Summoning Speed | AP84: Barrier Threshold | AQ84: Strength Mastery | AR84: Clobbering | AS84: Melee Damage | AT84: Break Limit Counter | AU84: Avoid Block | AV84: Two-handed Damage | AW84: Avoid Block | AX84: Life Drain | AY84: Disenchant Power | AZ84: Endurance Mastery | BA84: Strength Mastery | BB84: Luck Mastery | BC84: Shield Defense | BD84: Quickens | BE84: Critical Chance | BF84: Strength Mastery | BG84: Dodge | BH84: Defense versus Compelled | BI84: Luck Mastery | BJ84: Avoid Parry | BK84: Endangered Regeneration | BL84: Endangered Regeneration | BM84: Corruption Regeneration | BN84: Block Amount | BO84: Shield Defense | BP84: Mounted Speed | BQ84: Dualwield Accuracy | BR84: Avoid Block | BS84: Light Adds | BT84: Shield Defense | BU84: Speed | BV84: Corrupt Damage | BW84: Clobbering | BX84: Block Amount | BY84: Dualwield Accuracy | BZ84: Block Chance | CA84: Barrier Threshold | CB84: Defense versus Compelled | CC84: Conserve Hidden | CD84: Avoid Parry | CE84: Channeled Power | CF84: Charm Mastery | CG84: Corrupt Damage | CH84: Elemental Resistance, Air and Earth | CI84: Disruption Resist | CJ84: Trap Damage | CK84: Affliction Potency | CL84: Wisdom Mastery | CM84: Wisdom Mastery | CN84: Charm Mastery | CO84: Companion Speed | CP84: Damage versus Intangible | CQ84: Endurance Mastery | CR84: Companion Power | CS84: Summoning Speed | CT84: Damage versus Intangible | CU84: Companion Power | CV84: Companion Power | CW84: Summoning Speed | CX84: Companion Health | CY84: Physical Purge Power | CZ84: Damage Purge Power | DA84: Healing Power | DB84: Healing Power | DC84: Barrier Threshold | DD84: Light Adds | DE84: Illusory Resistance | DF84: Will Mastery | DG84: Percent Protection | DH84: Overheal Effects | DI84: Regeneration | DJ84: Damage while Hidden | DK84: Defense while Fortified | DL84: Tired Duration | DM84: Chaos Power | DN84: Light Resist | DO84: Dark Resistance | DP84: Wisdom Mastery | DQ84: Death Protection | DR84: Percent Protection | DS84: Defense versus Allies | DT84: Channeled Power | DU84: Damage versus Incapacitated | DV84: Illusory Damage | DW84: Mana Reserved | DX84: Charm Mastery | DY84: Intelligence Mastery | DZ84: Channeled Power | EA84: Initiative | EB84: Defense versus Allies | EC84: Damage Shield Regeneration | ED84: Conserve Trap | EE84: Damage Shield Regeneration | EF84: Water Adds | EG84: Mana Defense | EH84: Conserve Rune | EI84: Ignore Mana Loss | EJ84: Earth Adds | EK84: Amplification | EL84: Amplification | EM84: Maledicted Defense | EN84: Affliction Power | EO84: Elemental Resistance, Air and Earth | EP84: Elemental Resistance, Dark and Earth | EQ84: Maledicted Defense | ER84: Maledicted Defense | ES84: Ignore Lifedrain | ET84: Elemental Resistance, Dark and Water | EU84: Bleed Damage | EV84: Corrupt Damage | EW84: Companion Damage | EX84: Will Mastery | EY84: Water Adds | EZ84: Will Mastery | FA84: Distant Damage | FB84: Maximum Damage | FC84: Elemental Resistance, Earth and Water | FD84: Light Adds | FE84: Spell Power while Focused | FF84: Starting Mana
A85: PassiveL3 | B85: =COUNTA(C85:FF85)/1.6 -> 100 | C85: Damage versus Flanked | D85: Elemental Resistance, Air and Water | E85: Ignore Glancing | F85: Ranged Accuracy | G85: Companion Damage | H85: Critical Damage | I85: Hidden Critical Damage | J85: Disenchant Power | K85: Ranged Damage | L85: Ranged Accuracy | M85: Damage versus Flanked | N85: Stun Duration | O85: Momentum | P85: Movement Resist | Q85: Earth Piercing | R85: Avert Sustain | S85: Earth Adds | T85: Corruption Resistance | U85: Movement Resist | V85: Reduced Delays | W85: Hidden Critical Damage | X85: Conserve Poison | Y85: Dualwield Damage | Z85: Hidden Critical Damage | AA85: Dualwield Speed | AB85: Damage while Hidden | AC85: Conserve Hidden | AD85: Luck Mastery | AE85: Conserve Poison | AF85: Dexterity Mastery | AG85: Air Power | AH85: Chaos Power | AI85: Companion Damage | AJ85: Companion Damage | AK85: Companion Defense | AL85: Fire Piercing | AM85: Amplification | AN85: Empowered Power | AO85: Fire Adds | AP85: Trap Damage | AQ85: Endurance Mastery | AR85: Damage while Hasted | AS85: Movement Resist | AT85: Dualwield Speed | AU85: Bleed Damage | AV85: Momentum | AW85: Amplification | AX85: Elemental Resistance, Dark and Light | AY85: Corrupt Damage | AZ85: Two-handed Damage | BA85: Dualwield Speed | BB85: Ignore Prone | BC85: Initial Defense | BD85: Movement Resist | BE85: Alone Damage | BF85: Reduced Delays | BG85: Counter Chance | BH85: Shattering | BI85: Pinpoint | BJ85: Defense versus Compelled | BK85: Defense versus Compelled | BL85: Strength Mastery | BM85: Charm Mastery | BN85: Ignore Flanked | BO85: Defense versus Compelled | BP85: Momentum | BQ85: Strength Mastery | BR85: Shield Damage | BS85: Shield Damage | BT85: Charm Mastery | BU85: Parry Chance | BV85: Proc Power | BW85: Proc Power | BX85: Water Piercing | BY85: Strength Mastery | BZ85: Physical Purge Power | CA85: Will Mastery | CB85: Will Mastery | CC85: Damage while Intangible | CD85: Proc Power | CE85: Movement Purge Power | CF85: Air Power | CG85: Endangered Defense | CH85: Lucky Bonus | CI85: Elemental Resistance, Air and Water | CJ85: Movement Purge Power | CK85: Lucky Bonus | CL85: Quickens | CM85: Channeled Power | CN85: Mental Purge Power | CO85: Enhance Power | CP85: Companion Health | CQ85: Companion Defense | CR85: Ignore Possession | CS85: Endurance Mastery | CT85: Companion Damage | CU85: Companion Damage | CV85: Companion Defense | CW85: Ignore Glancing | CX85: Retaliation | CY85: Mental Purge Power | CZ85: Movement Purge Power | DA85: Mental Purge Power | DB85: Physical Purge Power | DC85: Purge Power | DD85: Will Mastery | DE85: Light Adds | DF85: Dualwield Damage | DG85: Corrupt Damage | DH85: Wisdom Mastery | DI85: Damage versus Endangered | DJ85: Alone Defense | DK85: Earth Resistance | DL85: Air Adds | DM85: Initial Defense | DN85: Justice | DO85: Dodge | DP85: Defense versus Allies | DQ85: Dark Piercing | DR85: Full Health Damage | DS85: Charm Mastery | DT85: Damage Shield | DU85: Weakness Power | DV85: Tired Duration | DW85: Arcane Power | DX85: Arcane Power | DY85: Retaliation | DZ85: Conserve Focus | EA85: Amplification | EB85: Ignore Possession | EC85: Endurance Mastery | ED85: Trap Damage | EE85: Summoning Speed | EF85: Earth Resistance | EG85: Weakness Power | EH85: Maximum Mana | EI85: Intelligence Mastery | EJ85: Fire Adds | EK85: Earth Piercing | EL85: Arcane Power | EM85: Luck Mastery | EN85: Mana Defense | EO85: Elemental Resistance, Fire and Light | EP85: Elemental Resistance, Earth and Light | EQ85: Fire Resist | ER85: Luck Mastery | ES85: Tired Duration | ET85: Dark Piercing | EU85: Light Resist | EV85: Bleed Damage | EW85: Air Resistance | EX85: Dark Adds | EY85: Storm Power | EZ85: Defense while Fortified | FA85: Damage versus Stunned | FB85: Countdown Power | FC85: Enchant Power | FD85: Justice | FE85: Possession Power | FF85: Elemental Damage
A86: PassiveL4 | B86: =COUNTA(C86:FF86)/1.6 -> 100 | C86: Alone Defense | D86: Pinpoint | E86: Reduced Delays | F86: Reaping | G86: Disruption Power | H86: Elemental Resistance, Air and Light | I86: Damage versus Flanked | J86: Bleed Damage | K86: Elemental Resistance, Air and Light | L86: Reduced Delays | M86: Tired Duration | N86: Elemental Resistance, Air and Fire | O86: Area Dodge | P86: Counter Damage | Q86: Elemental Resistance, Earth and Light | R86: Damage versus Flanked | S86: Damage versus Full Health | T86: Elemental Resistance, Fire and Water | U86: Proc Chance | V86: Minimum Damage | W86: Endangered Damage | X86: Conserve Hidden | Y86: Dualwield Speed | Z86: Avert Sustain | AA86: Avert Sustain | AB86: Earth Adds | AC86: Damage versus Full Health | AD86: Dualwield Damage | AE86: Dualwield Damage | AF86: Ignore Flanked | AG86: Air Piercing | AH86: Earth Power | AI86: Air Piercing | AJ86: Companion Health | AK86: Glancing Damage Dealt | AL86: Countdown Power | AM86: Damage while Hasted | AN86: Companion Defense | AO86: Companion Power | AP86: Shielded Power | AQ86: Two-handed Damage | AR86: Counter Chance | AS86: Bloodlust | AT86: Area Damage | AU86: Backbiting | AV86: Ignore Avert | AW86: Alone Defense | AX86: Damage versus Incapacitated | AY86: Alone Damage | AZ86: Backbiting | BA86: Reaping | BB86: Endangered Damage | BC86: Full Health Defense | BD86: Initial Damage | BE86: Alone Defense | BF86: Initial Damage | BG86: Melee Damage | BH86: Defense while Fortified | BI86: Damage versus Flanked | BJ86: Shattering | BK86: Block Chance | BL86: Block Chance | BM86: Mounted Damage | BN86: Minimum Damage | BO86: Mounted Defense | BP86: Magic Resistance | BQ86: Mounted Damage | BR86: Light Resist | BS86: Light Power | BT86: Block Chance | BU86: Maximum Damage | BV86: Backbiting | BW86: Earth Piercing | BX86: Tired Duration | BY86: Shattering | BZ86: Elemental Damage | CA86: Block Chance | CB86: Damage Shield | CC86: Hidden Critical Damage | CD86: Corruption Resistance | CE86: Damage Purge Power | CF86: Mana Damage | CG86: Affliction Duration | CH86: Mental Resistance | CI86: Reduced Delays | CJ86: Initiative | CK86: Disenchant Power | CL86: Percent Protection | CM86: Possession Power | CN86: Damage versus Intangible | CO86: Cast Speed | CP86: Elemental Resistance, Dark and Water | CQ86: Storm Power | CR86: Spell Dodge | CS86: Mounted Defense | CT86: Companion Health | CU86: Elemental Resistance, Dark and Light | CV86: Proc Chance | CW86: Affliction Duration | CX86: Mana Generation | CY86: Light Power | CZ86: Physical Purge Power | DA86: Affliction Resistance | DB86: Movement Purge Power | DC86: Block Amount | DD86: Mental Purge Power | DE86: Mental Purge Power | DF86: Dualwield Speed | DG86: Physical Resistance | DH86: Mental Purge Power | DI86: Ignore Flanked | DJ86: Luck Mastery | DK86: Glancing Damage Dealt | DL86: Elemental Resistance, Air and Light | DM86: Dark Power | DN86: Dark Power | DO86: Arcane Power | DP86: Life Drain | DQ86: Purges Received | DR86: Full Health Defense | DS86: Incapacitate Power | DT86: Movement Purge Power | DU86: Reduced Affliction Duration | DV86: Piercing | DW86: Spell Critical | DX86: Hex Power | DY86: Spell Critical | DZ86: Tired Duration | EA86: Arcane Power | EB86: Arcane Power | EC86: Enchant Duration | ED86: Chaos Power | EE86: Endurance Mastery | EF86: Water Piercing | EG86: Mental Resistance | EH86: Elemental Resistance, Light and Water | EI86: Earth Power | EJ86: Water Adds | EK86: Fire Piercing | EL86: Mana Cost Reduced | EM86: Dark Piercing | EN86: Air Power | EO86: Initiative | EP86: Water Resistance | EQ86: Water Adds | ER86: Water Power | ES86: Light Piercing | ET86: Dark Adds | EU86: Maximum Mana | EV86: Life Drain | EW86: Earth Resistance | EX86: Ignore Critical | EY86: Affliction Potency | EZ86: Enchant Power | FA86: Spell Critical | FB86: Fire Adds | FC86: Distant Damage | FD86: Hex Power | FE86: Ranged Dodge | FF86: Ignore Mana Loss
A87: PassiveL5 | B87: =COUNTA(C87:FF87)/1.6 -> 100 | C87: Reduced Delays | D87: Alone Damage | E87: Delays | F87: Lucky Bonus | G87: Pinpoint | H87: Pinpoint | I87: Damage versus Full Health | J87: Avert Sustain | K87: Damage while Focused | L87: Initial Accuracy | M87: Stun Duration | N87: Counter Damage | O87: Avert Sustain | P87: Disruption Power | Q87: Stun Duration | R87: Initiative | S87: Spell Dodge | T87: Full Health Damage | U87: Quickens | V87: Parry Chance | W87: Ignore Flanked | X87: Critical Damage | Y87: Disenchant Power | Z87: Earth Resistance | AA87: Pinpoint | AB87: Damage versus Endangered | AC87: Full Health Damage | AD87: Avert Sustain | AE87: Avert Sustain | AF87: Critical Chance | AG87: Physical Resistance | AH87: Earth Piercing | AI87: Enchant Duration | AJ87: Damage Shield | AK87: Air Piercing | AL87: Fire Power | AM87: Storm Power | AN87: Endangered Healing | AO87: Amplification | AP87: Companion Damage | AQ87: Damage versus Full Health | AR87: Water Resistance | AS87: Enhance Power | AT87: Damage Resist | AU87: Elemental Resistance, Dark and Light | AV87: Ignore Compel | AW87: Speed | AX87: Affliction Resistance | AY87: Fire Resist | AZ87: Healing Received | BA87: Elemental Resistance, Earth and Water | BB87: Elemental Resistance, Air and Water | BC87: Ignore Glancing | BD87: Retaliation | BE87: Damage while Focused | BF87: Initial Defense | BG87: Physical Resistance | BH87: Damage Resist | BI87: Endangered Damage | BJ87: Ignore Counter | BK87: Damage Shield | BL87: Shield Damage | BM87: Affliction Resistance | BN87: Movement Resist | BO87: Damage Shield | BP87: Mental Resistance | BQ87: Elemental Resistance, Air and Light | BR87: Damage versus Incapacitated | BS87: Reduced Affliction Duration | BT87: Mounted Defense | BU87: Elemental Resistance, Air and Water | BV87: Ignore Avert | BW87: Defense while Fortified | BX87: Minimum Damage | BY87: Water Adds | BZ87: Initial Defense | CA87: Shield Damage | CB87: Block Chance | CC87: Dodge while Intangible | CD87: Light Piercing | CE87: Water Resistance | CF87: Melee Dodge | CG87: Dodge while Intangible | CH87: Empowered Power | CI87: Regeneration | CJ87: Initial Dodge | CK87: Weakness Power | CL87: Purges Received | CM87: Lucky Bonus | CN87: Justice | CO87: Magic Resistance | CP87: Affliction Duration | CQ87: Elemental Resistance, Earth and Light | CR87: Death Protection | CS87: Possession Power | CT87: Possession Power | CU87: Endangered Defense | CV87: Quickens | CW87: Physical Resistance | CX87: Conserve Focus | CY87: Initial Dodge | CZ87: Cast Speed | DA87: Enhance Power | DB87: Light Power | DC87: Disruption Resist | DD87: Disenchant Power | DE87: Mana Reserved | DF87: Physical Purge Power | DG87: Healing Received | DH87: Regeneration | DI87: Ignore Prone | DJ87: Reaping | DK87: Reduced Delays | DL87: Purges Received | DM87: Dark Adds | DN87: Ignore Glancing | DO87: Damage while Intangible | DP87: Dark Power | DQ87: Initial Defense | DR87: Ignore Avert | DS87: Channeled Power | DT87: Movement Resist | DU87: Cast Speed | DV87: Affliction Duration | DW87: Piercing | DX87: Affliction Potency | DY87: Starting Mana | DZ87: Affliction Power | EA87: Mana Defense | EB87: Maximum Mana | EC87: Enchant Power | ED87: Mana Defense | EE87: Companion Defense | EF87: Elemental Damage | EG87: Mana Cost Reduced | EH87: Percent Protection | EI87: Air Power | EJ87: Conserve Rune | EK87: Air Piercing | EL87: Elemental Damage | EM87: Damage versus Incapacitated | EN87: Alone Defense | EO87: Magic Power | EP87: Glancing Damage Received | EQ87: Affliction Potency | ER87: Ignore Critical | ES87: Water Resistance | ET87: Area Damage | EU87: Magic Power | EV87: Dark Power | EW87: Fire Resist | EX87: Elemental Resistance, Air and Dark | EY87: Fire Resist | EZ87: Damage versus Stunned | FA87: Earth Resistance | FB87: Affliction Power | FC87: Storm Power | FD87: Percent Protection | FE87: Reduced Affliction Duration | FF87: Piercing
A88: PassiveL6 | B88: =COUNTA(C88:FF88)/1.6 -> 100 | C88: Speed | D88: Momentum | E88: Percent Protection | F88: Air Adds | G88: Elemental Resistance, Air and Water | H88: Bloodlust | I88: Ranged Dodge | J88: Elemental Resistance, Air and Dark | K88: Ranged Dodge | L88: Physical Resistance | M88: Spell Dodge | N88: Disruption Power | O88: Speed | P88: Damage versus Incapacitated | Q88: Percent Protection | R88: Ranged Dodge | S88: Speed | T88: Full Health Defense | U88: Reduced Affliction Duration | V88: Glancing Damage Received | W88: Initiative | X88: Ignore Avert | Y88: Initial Accuracy | Z88: Damage versus Flanked | AA88: Proc Chance | AB88: Damage versus Full Health | AC88: Initial Damage | AD88: Hidden Critical Damage | AE88: Hidden Critical Damage | AF88: Area Dodge | AG88: Air Resistance | AH88: Fire Piercing | AI88: Enhance Power | AJ88: Regeneration | AK88: Distant Damage | AL88: Fire Resist | AM88: Critical Damage | AN88: Enchant Potency | AO88: Initial Defense | AP88: Amplification | AQ88: Full Health Damage | AR88: Reaping | AS88: Ignore Compel | AT88: Ignore Prone | AU88: Elemental Resistance, Fire and Water | AV88: Backbiting | AW88: Critical Chance | AX88: Maximum Damage | AY88: Maximum Damage | AZ88: Ignore Critical | BA88: Ignore Avert | BB88: Glancing Damage Dealt | BC88: Defense | BD88: Reduced Delays | BE88: Ignore Flanked | BF88: Glancing Damage Dealt | BG88: Elemental Resistance | BH88: Full Health Defense | BI88: Initial Accuracy | BJ88: Critical Chance | BK88: Clobbering | BL88: Justice | BM88: Physical Resistance | BN88: Full Health Damage | BO88: Clobbering | BP88: Melee Damage | BQ88: Ignore Counter | BR88: Damage Resist | BS88: Elemental Resistance, Dark and Fire | BT88: Mounted Damage | BU88: Elemental Resistance, Air and Fire | BV88: Starting Mana | BW88: Full Health Defense | BX88: Ignore Glancing | BY88: Air Adds | BZ88: Defense | CA88: Shattering | CB88: Shattering | CC88: Avert Sustain | CD88: Parry Chance | CE88: Enchant Potency | CF88: Elemental Resistance, Air and Fire | CG88: Dark Resistance | CH88: Ignore Mana Loss | CI88: Storm Power | CJ88: Ranged Accuracy | CK88: Alone Defense | CL88: Reduced Affliction Duration | CM88: Water Power | CN88: Light Resist | CO88: Mental Resistance | CP88: Corruption Resistance | CQ88: Hex Power | CR88: Magic Power | CS88: Corruption Resistance | CT88: Hex Power | CU88: Ignore Mana Loss | CV88: Elemental Resistance, Dark and Fire | CW88: Corruption Resistance | CX88: Piercing | CY88: Elemental Resistance | CZ88: Damage Resist | DA88: Dark Resistance | DB88: Elemental Resistance | DC88: Defense | DD88: Death Protection | DE88: Glancing Damage Received | DF88: Ignore Avert | DG88: Damage Resist | DH88: Dark Resistance | DI88: Ignore Disarm | DJ88: Alone Damage | DK88: Ignore Compel | DL88: Alone Defense | DM88: Elemental Resistance, Air and Dark | DN88: Elemental Resistance, Dark and Earth | DO88: Mana Damage | DP88: Damage versus Incapacitated | DQ88: Glancing Damage Dealt | DR88: Ignore Glancing | DS88: Ignore Compel | DT88: Damage while Focused | DU88: Disruption Resist | DV88: Disruption Resist | DW88: Elemental Resistance, Fire and Light | DX88: Fire Piercing | DY88: Spell Dodge | DZ88: Spell Critical | EA88: Reduced Affliction Duration | EB88: Magic Resistance | EC88: Elemental Resistance, Earth and Water | ED88: Elemental Resistance, Earth and Fire | EE88: Companion Health | EF88: Elemental Resistance, Dark and Earth | EG88: Damage Resist | EH88: Elemental Resistance, Earth and Light | EI88: Elemental Resistance, Fire and Water | EJ88: Disenchant Resist | EK88: Water Piercing | EL88: Enchant Potency | EM88: Endangered Defense | EN88: Air Resistance | EO88: Critical Damage | EP88: Initial Dodge | EQ88: Elemental Resistance, Fire and Light | ER88: Damage versus Maledicted | ES88: Magic Power | ET88: Mana Reserved | EU88: Ignore Critical | EV88: Affliction Duration | EW88: Water Resistance | EX88: Physical Resistance | EY88: Spell Critical | EZ88: Glancing Damage Received | FA88: Elemental Resistance, Air and Earth | FB88: Starting Mana | FC88: Area Damage | FD88: Mana Cost Reduced | FE88: Mana Generation | FF88: Cast Speed

Sheet Sheet5
A2: Name | B2: Archer | C2: Barbarian | D2: Bard | E2: Binder | F2: Cleric | G2: Fighter | H2: Knight | I2: Monk | J2: Psychic | K2: Reaper | L2: Rogue | M2: Runemage | N2: Spellsword | O2: Teknixian | P2: Witch | Q2: Wizard
A3: Code
A4: Tier
A5: Base Class
A6: Gender
A7: Associated Demon
A8: Quote
A9: Description
A10: Mechanic
A11: Lore
A12: Appearance
A13: Req Dex
A14: Req Int
... A20: Req Wil
A21: Weapon Name | E21: Whip
A22: Weapon Mech | E22: companion quicken on turn
A23: Weapon Stats
A24: Armor Name
A25: Armor Stats
A26: Major 1
A27: Major 2
A28: Major 3
A29: Major 4
A30: Major 5
A31: Major 6
A32: Major 7
A33: Major 8
A34: Major 9
... A87: PassiveL6

Sheet Sheet2
B1: Healing Belt | C1: Lightning Belt | D1: Acid Belt | E1: Purge Belt | F1: Damage Add Belt | G1: Grenade Belt | H1: Tangle Belt | I1: Teknos Armor | J1: Teknos Weapon | K1: Ramshackle Shot | L1: Teknos Shielding | M1: Grenade | N1: Teknos Shot | O1: Amplifying Shot | P1: Timebomb
A2: Air | B2: Air retaliation | C2: 3 Random Attacks | M2: Multiple storm instead | N2: Chance for multipe storm attacks | O2: Storms per amplification | P2: Storm against 2 others
A3: Earth | B3: Fortification | C3: Clobbering | M3: Defense weakness | N3: Clobbering attack | O3: Increased clobbering per amplification | P3: Defense weakness
A4: Fire | B4: Chance to heal all | C4: Chance to damage all | M4: Fire bleed | N4: Pierces fire resistance | O4: Increased damage to all per amplification | P4: Lesser damage against all others
A5: Water | B5: Regeneration | C5: Generate mana | M5: Dodge weakness | N5: Chance for incapacitate | O5: Greater damage and reduced range | P5: Chance to cause brittle
A6: Light | B6: Heal target and teknixian | C6: 2 Attacks against same target | M6: Justice | N6: Chance to disenchant | O6: Doubles amplify stacking | P6: Chance to blind all
A7: Dark | B7: Provides death protection | C7: Culling | M7: Bloodlust | N7: Life drain | O7: Stacking cull chance | P7: Culling
A8: Mana | B8: Restores target mana | C8: Consumes mana for more damage | M8: Damages mana | N8: Damage scales with mana | O8: Drains mana | P8: Damage scales with mana
A9: Delay | B9: Quickens target | C9: Delays target | M9: Delays all | N9: Delay | O9: Chance for prone | P9: Delays target
A10: Penetration | B10: Purges damage affliction | C10: Penetrate | M10: Penetrates defense | N10: Penetration | O10: Penetration | P10: Causes bleed
A11: Corruption | B11: Cleanses corruption | C11: Corruption | M11: Corrupt damage | N11: Corruption | O11: Corrupt damage | P11: Corrupt damage
A12: Illusory | B12: Cleanses illusory | C12: Illusory | M12: Illusory damage | N12: Illusory | O12: Chance to possess | P12: Illusory damage
A13: Flechette | B13: Storm heal | C13: Damage based on consumption | M13: Wild damage | N13: Chance to use all ammo | O13: Conserves ammo per amplification | P13: Damage based on remaining ammo

Sheet Dualclass Aspects
AV1: Psychologist | AW1: Spellthief | BA1: Kaoteknixian | BC1: Shadow Dancer | CE1: Bone Archer
